Workbook

Sheet Start Here
A1: Canadian Budget & Cash-Flow Tracker
A2: Built by a Canadian personal banker. Track every dollar, see your real savings rate.
B4: WHAT'S INSIDE
B5: • Start Here — this page.
B6: • Categories — 38 Canadian budget categories plus 12 spare slots, all pre-wired.
B7: • Transactions — 1,200-row logbook with a drop-down category picker.
B8: • Budget vs Actual — 12-month plan against real spending, filtered to one budget year.
B9: • Dashboard — income, spending, net cash flow, savings rate and a monthly chart.
B11: HOW TO USE IT
B12: 1. Open the Categories tab and rename anything that does not fit your life. Spare blank rows are waiting at the bottom.
B13: 2. Go to Budget vs Actual, set the budget year in the yellow cell at the top, and type what you PLAN to spend each month.
B14: 3. Log spending on the Transactions tab — date, category, money in or money out.
B15: 4. The Dashboard and the Actual columns update themselves. Nothing else to do.
B16: 5. Keep several years in the same file: change the budget year and every total follows it.
... B26: Questions or a problem with the file? Message me through Etsy and I will help.

Sheet Categories
A1: Categories
A2: Rename any row to match your life, or fill in the spare rows at the bottom.
A4: Group | B4: Category | C4: Type
A5: Income | B5: Employment income | C5: Income
A6: Income | B6: Self-employment / side income | C6: Income
A7: Income | B7: Government benefits (CCB, GST/HST credit) | C7: Income
A8: Income | B8: Investment / other income | C8: Income
A9: Housing | B9: Rent or mortgage payment | C9: Expense
A10: Housing | B10: Property tax | C10: Expense
A11: Housing | B11: Home / tenant insurance | C11: Expense
A12: Housing | B12: Utilities (hydro, gas, water) | C12: Expense
A13: Housing | B13: Internet / phone | C13: Expense
A14: Housing | B14: Maintenance & repairs | C14: Expense
A15: Living | B15: Groceries | C15: Expense
... A42: Other | B42: Miscellaneous | C42: Expense
A56: The last 12 rows are deliberately blank. They are already inside the drop-down, the Budget vs Actual table and every dashboard formula — type a category into one and it works immediately.
A57: Do not insert or delete rows. Rename what you do not need, or leave it blank.
A58: Keep category names unique — the Budget and Dashboard tabs match on the exact text.

Sheet Transactions
A1: Transactions
A2: Log every dollar in and out. Paste from your bank export or type as you go.
A4: Date | B4: Month | C4: Year | D4: Category | E4: Description | F4: Money In | G4: Money Out | H4: Net
B5: =IF($A5="","",TEXT($A5,"mmm")) | C5: =IF($A5="","",YEAR($A5)) | H5: =IF(AND($F5="",$G5=""),"",N($F5)-N($G5))
B6: =IF($A6="","",TEXT($A6,"mmm")) | C6: =IF($A6="","",YEAR($A6)) | H6: =IF(AND($F6="",$G6=""),"",N($F6)-N($G6))
B7: =IF($A7="","",TEXT($A7,"mmm")) | C7: =IF($A7="","",YEAR($A7)) | H7: =IF(AND($F7="",$G7=""),"",N($F7)-N($G7))
B8: =IF($A8="","",TEXT($A8,"mmm")) | C8: =IF($A8="","",YEAR($A8)) | H8: =IF(AND($F8="",$G8=""),"",N($F8)-N($G8))
B9: =IF($A9="","",TEXT($A9,"mmm")) | C9: =IF($A9="","",YEAR($A9)) | H9: =IF(AND($F9="",$G9=""),"",N($F9)-N($G9))
B10: =IF($A10="","",TEXT($A10,"mmm")) | C10: =IF($A10="","",YEAR($A10)) | H10: =IF(AND($F10="",$G10=""),"",N($F10)-N($G10))
B11: =IF($A11="","",TEXT($A11,"mmm")) | C11: =IF($A11="","",YEAR($A11)) | H11: =IF(AND($F11="",$G11=""),"",N($F11)-N($G11))
B12: =IF($A12="","",TEXT($A12,"mmm")) | C12: =IF($A12="","",YEAR($A12)) | H12: =IF(AND($F12="",$G12=""),"",N($F12)-N($G12))
B13: =IF($A13="","",TEXT($A13,"mmm")) | C13: =IF($A13="","",YEAR($A13)) | H13: =IF(AND($F13="",$G13=""),"",N($F13)-N($G13))
B14: =IF($A14="","",TEXT($A14,"mmm")) | C14: =IF($A14="","",YEAR($A14)) | H14: =IF(AND($F14="",$G14=""),"",N($F14)-N($G14))
B15: =IF($A15="","",TEXT($A15,"mmm")) | C15: =IF($A15="","",YEAR($A15)) | H15: =IF(AND($F15="",$G15=""),"",N($F15)-N($G15))
B16: =IF($A16="","",TEXT($A16,"mmm")) | C16: =IF($A16="","",YEAR($A16)) | H16: =IF(AND($F16="",$G16=""),"",N($F16)-N($G16))
... B1204: =IF($A1204="","",TEXT($A1204,"mmm")) | C1204: =IF($A1204="","",YEAR($A1204)) | H1204: =IF(AND($F1204="",$G1204=""),"",N($F1204)-N($G1204))
A1206: Year is filled in for you from the date. It is what keeps one year's totals separate from the next.

Sheet Budget vs Actual
A1: Budget vs Actual
A2: Type your monthly plan. Actuals pull from the Transactions tab for the year you choose.
A3: Budget year → | B3: 2026 | C3: Only transactions dated in this year are counted. Change it and every actual updates.
A4: Category | B4: Jan | C4: Feb | D4: Mar | E4: Apr | F4: May | G4: Jun | H4: Jul | I4: Aug | J4: Sep | K4: Oct | L4: Nov | M4: Dec | N4: Budget Total | O4: Actual Total | P4: Variance
A5: =Categories!B5 | B5: 0 | C5: 0 | D5: 0 | E5: 0 | F5: 0 | G5: 0 | H5: 0 | I5: 0 | J5: 0 | K5: 0 | L5: 0 | M5: 0 | N5: =SUM(B5:M5) | O5: =IF($A5="","",SUMIFS(Transactions!$F$5:$F$1204,Transactions!$D$5:$D$1204,$A5,Transactions!$C$5:$C$1204,$B$3)+SUMIFS(Transactions!$G$5:$G$1204,Transactions!$D$5:$D$1204,$A5,Transactions!$C$5:$C$1204,$B$3)) | P5: =IF($A5="","",N5-O5)
A6: =Categories!B6 | B6: 0 | C6: 0 | D6: 0 | E6: 0 | F6: 0 | G6: 0 | H6: 0 | I6: 0 | J6: 0 | K6: 0 | L6: 0 | M6: 0 | N6: =SUM(B6:M6) | O6: =IF($A6="","",SUMIFS(Transactions!$F$5:$F$1204,Transactions!$D$5:$D$1204,$A6,Transactions!$C$5:$C$1204,$B$3)+SUMIFS(Transactions!$G$5:$G$1204,Transactions!$D$5:$D$1204,$A6,Transactions!$C$5:$C$1204,$B$3)) | P6: =IF($A6="","",N6-O6)
A7: =Categories!B7 | B7: 0 | C7: 0 | D7: 0 | E7: 0 | F7: 0 | G7: 0 | H7: 0 | I7: 0 | J7: 0 | K7: 0 | L7: 0 | M7: 0 | N7: =SUM(B7:M7) | O7: =IF($A7="","",SUMIFS(Transactions!$F$5:$F$1204,Transactions!$D$5:$D$1204,$A7,Transactions!$C$5:$C$1204,$B$3)+SUMIFS(Transactions!$G$5:$G$1204,Transactions!$D$5:$D$1204,$A7,Transactions!$C$5:$C$1204,$B$3)) | P7: =IF($A7="","",N7-O7)
A8: =Categories!B8 | B8: 0 | C8: 0 | D8: 0 | E8: 0 | F8: 0 | G8: 0 | H8: 0 | I8: 0 | J8: 0 | K8: 0 | L8: 0 | M8: 0 | N8: =SUM(B8:M8) | O8: =IF($A8="","",SUMIFS(Transactions!$F$5:$F$1204,Transactions!$D$5:$D$1204,$A8,Transactions!$C$5:$C$1204,$B$3)+SUMIFS(Transactions!$G$5:$G$1204,Transactions!$D$5:$D$1204,$A8,Transactions!$C$5:$C$1204,$B$3)) | P8: =IF($A8="","",N8-O8)
A9: =Categories!B9 | B9: 0 | C9: 0 | D9: 0 | E9: 0 | F9: 0 | G9: 0 | H9: 0 | I9: 0 | J9: 0 | K9: 0 | L9: 0 | M9: 0 | N9: =SUM(B9:M9) | O9: =IF($A9="","",SUMIFS(Transactions!$F$5:$F$1204,Transactions!$D$5:$D$1204,$A9,Transactions!$C$5:$C$1204,$B$3)+SUMIFS(Transactions!$G$5:$G$1204,Transactions!$D$5:$D$1204,$A9,Transactions!$C$5:$C$1204,$B$3)) | P9: =IF($A9="","",N9-O9)
A10: =Categories!B10 | B10: 0 | C10: 0 | D10: 0 | E10: 0 | F10: 0 | G10: 0 | H10: 0 | I10: 0 | J10: 0 | K10: 0 | L10: 0 | M10: 0 | N10: =SUM(B10:M10) | O10: =IF($A10="","",SUMIFS(Transactions!$F$5:$F$1204,Transactions!$D$5:$D$1204,$A10,Transactions!$C$5:$C$1204,$B$3)+SUMIFS(Transactions!$G$5:$G$1204,Transactions!$D$5:$D$1204,$A10,Transactions!$C$5:$C$1204,$B$3)) | P10: =IF($A10="","",N10-O10)
A11: =Categories!B11 | B11: 0 | C11: 0 | D11: 0 | E11: 0 | F11: 0 | G11: 0 | H11: 0 | I11: 0 | J11: 0 | K11: 0 | L11: 0 | M11: 0 | N11: =SUM(B11:M11) | O11: =IF($A11="","",SUMIFS(Transactions!$F$5:$F$1204,Transactions!$D$5:$D$1204,$A11,Transactions!$C$5:$C$1204,$B$3)+SUMIFS(Transactions!$G$5:$G$1204,Transactions!$D$5:$D$1204,$A11,Transactions!$C$5:$C$1204,$B$3)) | P11: =IF($A11="","",N11-O11)
A12: =Categories!B12 | B12: 0 | C12: 0 | D12: 0 | E12: 0 | F12: 0 | G12: 0 | H12: 0 | I12: 0 | J12: 0 | K12: 0 | L12: 0 | M12: 0 | N12: =SUM(B12:M12) | O12: =IF($A12="","",SUMIFS(Transactions!$F$5:$F$1204,Transactions!$D$5:$D$1204,$A12,Transactions!$C$5:$C$1204,$B$3)+SUMIFS(Transactions!$G$5:$G$1204,Transactions!$D$5:$D$1204,$A12,Transactions!$C$5:$C$1204,$B$3)) | P12: =IF($A12="","",N12-O12)
A13: =Categories!B13 | B13: 0 | C13: 0 | D13: 0 | E13: 0 | F13: 0 | G13: 0 | H13: 0 | I13: 0 | J13: 0 | K13: 0 | L13: 0 | M13: 0 | N13: =SUM(B13:M13) | O13: =IF($A13="","",SUMIFS(Transactions!$F$5:$F$1204,Transactions!$D$5:$D$1204,$A13,Transactions!$C$5:$C$1204,$B$3)+SUMIFS(Transactions!$G$5:$G$1204,Transactions!$D$5:$D$1204,$A13,Transactions!$C$5:$C$1204,$B$3)) | P13: =IF($A13="","",N13-O13)
A14: =Categories!B14 | B14: 0 | C14: 0 | D14: 0 | E14: 0 | F14: 0 | G14: 0 | H14: 0 | I14: 0 | J14: 0 | K14: 0 | L14: 0 | M14: 0 | N14: =SUM(B14:M14) | O14: =IF($A14="","",SUMIFS(Transactions!$F$5:$F$1204,Transactions!$D$5:$D$1204,$A14,Transactions!$C$5:$C$1204,$B$3)+SUMIFS(Transactions!$G$5:$G$1204,Transactions!$D$5:$D$1204,$A14,Transactions!$C$5:$C$1204,$B$3)) | P14: =IF($A14="","",N14-O14)
A15: =Categories!B15 | B15: 0 | C15: 0 | D15: 0 | E15: 0 | F15: 0 | G15: 0 | H15: 0 | I15: 0 | J15: 0 | K15: 0 | L15: 0 | M15: 0 | N15: =SUM(B15:M15) | O15: =IF($A15="","",SUMIFS(Transactions!$F$5:$F$1204,Transactions!$D$5:$D$1204,$A15,Transactions!$C$5:$C$1204,$B$3)+SUMIFS(Transactions!$G$5:$G$1204,Transactions!$D$5:$D$1204,$A15,Transactions!$C$5:$C$1204,$B$3)) | P15: =IF($A15="","",N15-O15)
A16: =Categories!B16 | B16: 0 | C16: 0 | D16: 0 | E16: 0 | F16: 0 | G16: 0 | H16: 0 | I16: 0 | J16: 0 | K16: 0 | L16: 0 | M16: 0 | N16: =SUM(B16:M16) | O16: =IF($A16="","",SUMIFS(Transactions!$F$5:$F$1204,Transactions!$D$5:$D$1204,$A16,Transactions!$C$5:$C$1204,$B$3)+SUMIFS(Transactions!$G$5:$G$1204,Transactions!$D$5:$D$1204,$A16,Transactions!$C$5:$C$1204,$B$3)) | P16: =IF($A16="","",N16-O16)
... A54: =Categories!B54 | B54: 0 | C54: 0 | D54: 0 | E54: 0 | F54: 0 | G54: 0 | H54: 0 | I54: 0 | J54: 0 | K54: 0 | L54: 0 | M54: 0 | N54: =SUM(B54:M54) | O54: =IF($A54="","",SUMIFS(Transactions!$F$5:$F$1204,Transactions!$D$5:$D$1204,$A54,Transactions!$C$5:$C$1204,$B$3)+SUMIFS(Transactions!$G$5:$G$1204,Transactions!$D$5:$D$1204,$A54,Transactions!$C$5:$C$1204,$B$3)) | P54: =IF($A54="","",N54-O54)
A55: TOTAL | B55: =SUM(B5:B54) | C55: =SUM(C5:C54) | D55: =SUM(D5:D54) | E55: =SUM(E5:E54) | F55: =SUM(F5:F54) | G55: =SUM(G5:G54) | H55: =SUM(H5:H54) | I55: =SUM(I5:I54) | ... P55: =SUM(P5:P54)

Sheet Dashboard
A1: Dashboard
A2: Your year at a glance — updates itself as you log transactions.
A3: Showing budget year | B3: ='Budget vs Actual'!$B$3
A4: THE HEADLINE NUMBERS
A6: Total money in | B6: =SUMIFS(Transactions!$F$5:$F$1204,Transactions!$C$5:$C$1204,$B$3)
A7: Total money out | B7: =SUMIFS(Transactions!$G$5:$G$1204,Transactions!$C$5:$C$1204,$B$3)
A8: Net cash flow | B8: =B6-B7
A9: Total saved / invested | B9: =SUMIFS(Transactions!$G$5:$G$1204,Transactions!$D$5:$D$1204,"TFSA contribution",Transactions!$C$5:$C$1204,$B$3)+SUMIFS(Transactions!$G$5:$G$1204,Transactions!$D$5:$D$1204,"RRSP contribution",Transactions!$C$5:$C$1204,$B$3)+SUMIFS(Transactions!$G$5:$G$1204,Transactions!$D$5:$D$1204,"RESP contribution",Transactions!$C$5:$C$1204,$B$3)+SUMIFS(Transactions!$G$5:$G$1204,Transactions!$D$5:$D$1204,"Emergency fund",Transactions!$C$5:$C$1204,$B$3)
A10: Savings rate | B10: =IF(B6=0,"—",B9/B6)
A11: Budgeted total | B11: ='Budget vs Actual'!N55
A12: Actual total | B12: ='Budget vs Actual'!O55
A14: MONTH BY MONTH
A15: Month | B15: In | C15: Out | D15: Net
A16: Jan | B16: =SUMIFS(Transactions!$F$5:$F$1204,Transactions!$B$5:$B$1204,$A16,Transactions!$C$5:$C$1204,$B$3) | C16: =SUMIFS(Transactions!$G$5:$G$1204,Transactions!$B$5:$B$1204,$A16,Transactions!$C$5:$C$1204,$B$3) | D16: =B16-C16
A17: Feb | B17: =SUMIFS(Transactions!$F$5:$F$1204,Transactions!$B$5:$B$1204,$A17,Transactions!$C$5:$C$1204,$B$3) | C17: =SUMIFS(Transactions!$G$5:$G$1204,Transactions!$B$5:$B$1204,$A17,Transactions!$C$5:$C$1204,$B$3) | D17: =B17-C17
A18: Mar | B18: =SUMIFS(Transactions!$F$5:$F$1204,Transactions!$B$5:$B$1204,$A18,Transactions!$C$5:$C$1204,$B$3) | C18: =SUMIFS(Transactions!$G$5:$G$1204,Transactions!$B$5:$B$1204,$A18,Transactions!$C$5:$C$1204,$B$3) | D18: =B18-C18
A19: Apr | B19: =SUMIFS(Transactions!$F$5:$F$1204,Transactions!$B$5:$B$1204,$A19,Transactions!$C$5:$C$1204,$B$3) | C19: =SUMIFS(Transactions!$G$5:$G$1204,Transactions!$B$5:$B$1204,$A19,Transactions!$C$5:$C$1204,$B$3) | D19: =B19-C19
A20: May | B20: =SUMIFS(Transactions!$F$5:$F$1204,Transactions!$B$5:$B$1204,$A20,Transactions!$C$5:$C$1204,$B$3) | C20: =SUMIFS(Transactions!$G$5:$G$1204,Transactions!$B$5:$B$1204,$A20,Transactions!$C$5:$C$1204,$B$3) | D20: =B20-C20
A21: Jun | B21: =SUMIFS(Transactions!$F$5:$F$1204,Transactions!$B$5:$B$1204,$A21,Transactions!$C$5:$C$1204,$B$3) | C21: =SUMIFS(Transactions!$G$5:$G$1204,Transactions!$B$5:$B$1204,$A21,Transactions!$C$5:$C$1204,$B$3) | D21: =B21-C21
A22: Jul | B22: =SUMIFS(Transactions!$F$5:$F$1204,Transactions!$B$5:$B$1204,$A22,Transactions!$C$5:$C$1204,$B$3) | C22: =SUMIFS(Transactions!$G$5:$G$1204,Transactions!$B$5:$B$1204,$A22,Transactions!$C$5:$C$1204,$B$3) | D22: =B22-C22
A23: Aug | B23: =SUMIFS(Transactions!$F$5:$F$1204,Transactions!$B$5:$B$1204,$A23,Transactions!$C$5:$C$1204,$B$3) | C23: =SUMIFS(Transactions!$G$5:$G$1204,Transactions!$B$5:$B$1204,$A23,Transactions!$C$5:$C$1204,$B$3) | D23: =B23-C23
A24: Sep | B24: =SUMIFS(Transactions!$F$5:$F$1204,Transactions!$B$5:$B$1204,$A24,Transactions!$C$5:$C$1204,$B$3) | C24: =SUMIFS(Transactions!$G$5:$G$1204,Transactions!$B$5:$B$1204,$A24,Transactions!$C$5:$C$1204,$B$3) | D24: =B24-C24
A25: Oct | B25: =SUMIFS(Transactions!$F$5:$F$1204,Transactions!$B$5:$B$1204,$A25,Transactions!$C$5:$C$1204,$B$3) | C25: =SUMIFS(Transactions!$G$5:$G$1204,Transactions!$B$5:$B$1204,$A25,Transactions!$C$5:$C$1204,$B$3) | D25: =B25-C25
A26: Nov | B26: =SUMIFS(Transactions!$F$5:$F$1204,Transactions!$B$5:$B$1204,$A26,Transactions!$C$5:$C$1204,$B$3) | C26: =SUMIFS(Transactions!$G$5:$G$1204,Transactions!$B$5:$B$1204,$A26,Transactions!$C$5:$C$1204,$B$3) | D26: =B26-C26
A27: Dec | B27: =SUMIFS(Transactions!$F$5:$F$1204,Transactions!$B$5:$B$1204,$A27,Transactions!$C$5:$C$1204,$B$3) | C27: =SUMIFS(Transactions!$G$5:$G$1204,Transactions!$B$5:$B$1204,$A27,Transactions!$C$5:$C$1204,$B$3) | D27: =B27-C27
