Workbook

Sheet Start Here
A1: TFSA vs RRSP Contribution Planner (Canada)
A2: Know your real room, and know which account to fill first.
B4: WHAT'S INSIDE
B5: • Your Numbers — every input in one place.
B6: • TFSA Room — 2009-2026 limits, counted from age 18 AND Canadian residency.
B7: • RRSP Room — today's room from your CRA notice, and next year's earned room.
B8: • TFSA vs RRSP — after-tax comparison capped at your real room, with a plain-English verdict.
B9: • Projection — 30-year contribution and growth schedule with a chart.
B11: HOW TO USE IT
B12: 1. Fill in the yellow cells on the Your Numbers tab — that is the only typing you do.
B13: 2. Open TFSA Room: room builds from the later of the year you turned 18 and the year you became a resident.
B14: 3. Open RRSP Room: today's room comes straight off your CRA notice; next year's is 18% of last year's income.
B15: 4. Open TFSA vs RRSP for the after-tax answer — capped at the room you actually have.
B16: 5. Use Projection to see what steady contributions turn into over your time horizon.
... B26: Questions or a problem with the file? Message me through Etsy and I will help.

Sheet Your Numbers
A1: Your Numbers
A2: Fill in the yellow cells. Everything else calculates.
A4: ABOUT YOU
A5: Your name
A6: Current age | B6: 30
A7: Year you turned 18 | B7: 2013
A8: Year you became a Canadian resident | B8: 2013
A9: Planning year | B9: 2026
A10: Province / territory | B10: Ontario
A11: TFSA room starts in the LATER of the year you turned 18 and the year you became a Canadian resident.
A12: If you were born in Canada, put the same year in both boxes.
A14: INCOME & TAX
A15: Earned income LAST year (employment + net self-employment) | B15: 78000
A16: Marginal tax rate NOW (combined fed + prov) | B16: 0.2965
A17: Expected marginal tax rate IN RETIREMENT | B17: 0.2005
A18: Pension adjustment last year (box 52 of your T4) | B18: 0
A19: RRSP room is earned on LAST year's income and becomes available THIS year — that is why last year's figure is what belongs here.
A20: Marginal rate = the tax you pay on your NEXT dollar of income, not your average rate.
A22: WHAT YOU HAVE ALREADY
A23: Total TFSA contributions made to date | B23: 21000
A24: Total TFSA withdrawals in PREVIOUS years | B24: 0
A25: RRSP deduction limit for this year (from your CRA notice) | B25: 44000
A26: RRSP contributions already made this year | B26: 3000
A27: Your CRA My Account notice of assessment is the authoritative source. The RRSP deduction limit it shows ALREADY includes your carry-forward — do not add anything to it.
A30: PLANNING ASSUMPTIONS
A31: Amount you can save per year | B31: 12000
A32: Expected annual investment return | B32: 0.06
A33: Years until you draw the money | B33: 25

Sheet TFSA Room
A1: TFSA Room
A2: Year-by-year room, counted from the later of age 18 and Canadian residency.
A4: Year | B4: Annual TFSA limit | C4: Counts for you? | D4: Room earned
A5: 2009 | B5: 5000 | C5: =IF(AND(A5>=MAX('Your Numbers'!$B$7,'Your Numbers'!$B$8),A5<='Your Numbers'!$B$9),"Yes","No") | D5: =IF(C5="Yes",B5,0)
A6: 2010 | B6: 5000 | C6: =IF(AND(A6>=MAX('Your Numbers'!$B$7,'Your Numbers'!$B$8),A6<='Your Numbers'!$B$9),"Yes","No") | D6: =IF(C6="Yes",B6,0)
A7: 2011 | B7: 5000 | C7: =IF(AND(A7>=MAX('Your Numbers'!$B$7,'Your Numbers'!$B$8),A7<='Your Numbers'!$B$9),"Yes","No") | D7: =IF(C7="Yes",B7,0)
A8: 2012 | B8: 5000 | C8: =IF(AND(A8>=MAX('Your Numbers'!$B$7,'Your Numbers'!$B$8),A8<='Your Numbers'!$B$9),"Yes","No") | D8: =IF(C8="Yes",B8,0)
A9: 2013 | B9: 5500 | C9: =IF(AND(A9>=MAX('Your Numbers'!$B$7,'Your Numbers'!$B$8),A9<='Your Numbers'!$B$9),"Yes","No") | D9: =IF(C9="Yes",B9,0)
A10: 2014 | B10: 5500 | C10: =IF(AND(A10>=MAX('Your Numbers'!$B$7,'Your Numbers'!$B$8),A10<='Your Numbers'!$B$9),"Yes","No") | D10: =IF(C10="Yes",B10,0)
A11: 2015 | B11: 10000 | C11: =IF(AND(A11>=MAX('Your Numbers'!$B$7,'Your Numbers'!$B$8),A11<='Your Numbers'!$B$9),"Yes","No") | D11: =IF(C11="Yes",B11,0)
A12: 2016 | B12: 5500 | C12: =IF(AND(A12>=MAX('Your Numbers'!$B$7,'Your Numbers'!$B$8),A12<='Your Numbers'!$B$9),"Yes","No") | D12: =IF(C12="Yes",B12,0)
A13: 2017 | B13: 5500 | C13: =IF(AND(A13>=MAX('Your Numbers'!$B$7,'Your Numbers'!$B$8),A13<='Your Numbers'!$B$9),"Yes","No") | D13: =IF(C13="Yes",B13,0)
A14: 2018 | B14: 5500 | C14: =IF(AND(A14>=MAX('Your Numbers'!$B$7,'Your Numbers'!$B$8),A14<='Your Numbers'!$B$9),"Yes","No") | D14: =IF(C14="Yes",B14,0)
A15: 2019 | B15: 6000 | C15: =IF(AND(A15>=MAX('Your Numbers'!$B$7,'Your Numbers'!$B$8),A15<='Your Numbers'!$B$9),"Yes","No") | D15: =IF(C15="Yes",B15,0)
A16: 2020 | B16: 6000 | C16: =IF(AND(A16>=MAX('Your Numbers'!$B$7,'Your Numbers'!$B$8),A16<='Your Numbers'!$B$9),"Yes","No") | D16: =IF(C16="Yes",B16,0)
... A22: 2026 | B22: 7000 | C22: =IF(AND(A22>=MAX('Your Numbers'!$B$7,'Your Numbers'!$B$8),A22<='Your Numbers'!$B$9),"Yes","No") | D22: =IF(C22="Yes",B22,0)
A24: Total room earned | B24: =SUM(D5:D22)
A25: Less: contributions made | B25: ='Your Numbers'!$B$23
A26: Add back: prior-year withdrawals | B26: ='Your Numbers'!$B$24
A27: ROOM AVAILABLE TODAY | B27: =MAX(0,B24-B25+B26)
A29: 2026 limit shown as $7,000 — confirm on canada.ca before you rely on it; the limit is indexed each year.
A30: Money withdrawn from a TFSA comes back as room on January 1 of the FOLLOWING year, never the same year.
A31: Over-contributing costs 1% of the excess per month. Check CRA My Account if you are close to the line.
A32: Newcomers: room does NOT build for years you were not a Canadian resident, even if you were over 18.

Sheet RRSP Room
A1: RRSP Room
A2: What you can contribute today, and what next year's room will be.
A4: Year | B4: Annual RRSP dollar limit
A5: 2019 | B5: 26500
A6: 2020 | B6: 27230
A7: 2021 | B7: 27830
A8: 2022 | B8: 29210
A9: 2023 | B9: 30780
A10: 2024 | B10: 31560
A11: 2025 | B11: 32490
A12: 2026 | B12: 33810
A13: 2027 | B13: 35130
A15: ROOM AVAILABLE TO YOU TODAY
A16: RRSP deduction limit for this year (from your CRA notice) | B16: ='Your Numbers'!$B$25
A17: Less: contributions already made this year | B17: ='Your Numbers'!$B$26
A18: ROOM AVAILABLE TODAY | B18: =MAX(0,B16-B17)
A19: Tax refund if you contribute it all | B19: =B18*'Your Numbers'!$B$16
A21: The deduction limit on your notice of assessment ALREADY includes every unused dollar carried forward. Adding this year's new room to it would double-count.
A23: ROOM YOU WILL EARN FOR NEXT YEAR
A24: 18% of last year's earned income | B24: =0.18*'Your Numbers'!$B$15
A25: Dollar limit for next year | B25: =IFERROR(VLOOKUP('Your Numbers'!$B$9+1,A5:B13,2,FALSE),MAX(B5:B13))
A26: New room earned (lesser of the two) | B26: =MIN(B24,B25)
A27: Less: pension adjustment | B27: ='Your Numbers'!$B$18
A28: ROOM ADDED FOR NEXT YEAR | B28: =MAX(0,B26-B27)
A30: Contributions earn room on the PREVIOUS year's income: 18% of what you earned last year is what became available this year.
A31: Dollar limits are as published by CRA; later years are indexed — verify before filing.
A32: You have a $2,000 lifetime over-contribution cushion, but it is not deductible. Do not lean on it.

Sheet TFSA vs RRSP
A1: TFSA vs RRSP
A2: Same dollars, both accounts, side by side after tax — capped at the room you actually have.
A4: IF YOU PUT THIS YEAR'S SAVINGS IN ONE ACCOUNT
B5: TFSA route | C5: RRSP route | D5: What this line means
A6: Amount you want to save | B6: ='Your Numbers'!$B$31 | C6: ='Your Numbers'!$B$31 | D6: What you told the Your Numbers tab you can put away.
A7: Room available in this account | B7: ='TFSA Room'!$B$27 | C7: ='RRSP Room'!$B$18 | D7: Pulled from the two room tabs. This is the ceiling.
A8: Amount actually contributed | B8: =MIN(B6,B7) | C8: =MIN(C6,C7) | D8: Capped at your room — the planner will not model an over-contribution.
A9: Immediate tax refund | B9: 0 | C9: =C8*'Your Numbers'!$B$16 | D9: RRSP contributions are deductible; TFSA contributions are not.
A10: Refund reinvested at the same return | B10: 0 | C10: =C9*(1+'Your Numbers'!$B$32)^'Your Numbers'!$B$33 | D10: Only counts if you actually invest the refund.
A11: Value at the end of the horizon | B11: =B8*(1+'Your Numbers'!$B$32)^'Your Numbers'!$B$33 | C11: =C8*(1+'Your Numbers'!$B$32)^'Your Numbers'!$B$33 | D11: Growth before any tax on withdrawal.
A12: Tax on withdrawal | B12: 0 | C12: =-C11*'Your Numbers'!$B$17 | D12: RRSP/RRIF withdrawals are fully taxable as income.
A13: Refund pot after tax (non-registered, simplified) | B13: 0 | C13: =C10*(1-'Your Numbers'!$B$17*0.5) | D13: Assumes the refund grows in a taxable account.
A14: AFTER-TAX VALUE | B14: =B11 | C14: =C11+C12+C13 | D14: The number that actually matters.
A16: WHICH ONE WINS FOR YOU
A17: =IF(AND('TFSA Room'!$B$27<=0,'RRSP Room'!$B$18<=0),"You have no room left in either account this year. Anything more goes to a non-registered account, or waits for January.",IF('RRSP Room'!$B$18<=0,"TFSA — you have no RRSP room left this year.",IF('TFSA Room'!$B$27<=0,"RRSP — you have no TFSA room left this year.",IF('Your Numbers'!$B$16>'Your Numbers'!$B$17,"RRSP first — you deduct at a higher rate than you will pay on withdrawal."&IF('RRSP Room'!$B$18<'Your Numbers'!$B$31," Your RRSP room runs out before your savings do, so put the remainder in your TFSA.",""),IF('Your Numbers'!$B$16<'Your Numbers'!$B$17,"TFSA first — you would deduct at a low rate now and pay tax at a higher one later."&IF('TFSA Room'!$B$27<'Your Numbers'!$B$31," Your TFSA room runs out before your savings do, so put the remainder in your RRSP.",""),"Close call — your rate now equals your expected rate later, so use the TFSA for its flexibility.")))))
A19: YOUR ROOM, PULLED FROM THE OTHER TABS
A20: TFSA room available | B20: ='TFSA Room'!$B$27
A21: RRSP room available | B21: ='RRSP Room'!$B$18
A22: Total room available | B22: =B20+B21
A23: Savings with nowhere registered to go | B23: =MAX(0,'Your Numbers'!$B$31-B22)

Sheet Projection
A1: Projection
A2: What steady contributions look like over time.
A4: Year | B4: Contributed this year | C4: Cumulative contributed | D4: Growth | E4: Balance
A5: 1 | B5: =IF(A5<='Your Numbers'!$B$33,'Your Numbers'!$B$31,0) | C5: =B5 | D5: =(0+B5)*'Your Numbers'!$B$32 | E5: =0+B5+D5
A6: 2 | B6: =IF(A6<='Your Numbers'!$B$33,'Your Numbers'!$B$31,0) | C6: =C5+B6 | D6: =(E5+B6)*'Your Numbers'!$B$32 | E6: =E5+B6+D6
A7: 3 | B7: =IF(A7<='Your Numbers'!$B$33,'Your Numbers'!$B$31,0) | C7: =C6+B7 | D7: =(E6+B7)*'Your Numbers'!$B$32 | E7: =E6+B7+D7
A8: 4 | B8: =IF(A8<='Your Numbers'!$B$33,'Your Numbers'!$B$31,0) | C8: =C7+B8 | D8: =(E7+B8)*'Your Numbers'!$B$32 | E8: =E7+B8+D8
A9: 5 | B9: =IF(A9<='Your Numbers'!$B$33,'Your Numbers'!$B$31,0) | C9: =C8+B9 | D9: =(E8+B9)*'Your Numbers'!$B$32 | E9: =E8+B9+D9
A10: 6 | B10: =IF(A10<='Your Numbers'!$B$33,'Your Numbers'!$B$31,0) | C10: =C9+B10 | D10: =(E9+B10)*'Your Numbers'!$B$32 | E10: =E9+B10+D10
A11: 7 | B11: =IF(A11<='Your Numbers'!$B$33,'Your Numbers'!$B$31,0) | C11: =C10+B11 | D11: =(E10+B11)*'Your Numbers'!$B$32 | E11: =E10+B11+D11
A12: 8 | B12: =IF(A12<='Your Numbers'!$B$33,'Your Numbers'!$B$31,0) | C12: =C11+B12 | D12: =(E11+B12)*'Your Numbers'!$B$32 | E12: =E11+B12+D12
A13: 9 | B13: =IF(A13<='Your Numbers'!$B$33,'Your Numbers'!$B$31,0) | C13: =C12+B13 | D13: =(E12+B13)*'Your Numbers'!$B$32 | E13: =E12+B13+D13
A14: 10 | B14: =IF(A14<='Your Numbers'!$B$33,'Your Numbers'!$B$31,0) | C14: =C13+B14 | D14: =(E13+B14)*'Your Numbers'!$B$32 | E14: =E13+B14+D14
A15: 11 | B15: =IF(A15<='Your Numbers'!$B$33,'Your Numbers'!$B$31,0) | C15: =C14+B15 | D15: =(E14+B15)*'Your Numbers'!$B$32 | E15: =E14+B15+D15
A16: 12 | B16: =IF(A16<='Your Numbers'!$B$33,'Your Numbers'!$B$31,0) | C16: =C15+B16 | D16: =(E15+B16)*'Your Numbers'!$B$32 | E16: =E15+B16+D16
A17: 13 | B17: =IF(A17<='Your Numbers'!$B$33,'Your Numbers'!$B$31,0) | C17: =C16+B17 | D17: =(E16+B17)*'Your Numbers'!$B$32 | E17: =E16+B17+D17
... A34: 30 | B34: =IF(A34<='Your Numbers'!$B$33,'Your Numbers'!$B$31,0) | C34: =C33+B34 | D34: =(E33+B34)*'Your Numbers'!$B$32 | E34: =E33+B34+D34
