Workbook

Sheet Start Here
A1: Debt Payoff Planner — Snowball & Avalanche
A2: Put your debts in, pick a method, get a real payoff date.
B4: WHAT'S INSIDE
B5: • Start Here — this page.
B6: • Your Debts — up to 8 debts, with automatic payoff ordering.
B7: • Payoff Plan — 180-month schedule with rollover payments built in.
B8: • Summary — debt-free date, total interest, total repaid, and a balance chart.
B10: HOW TO USE IT
B11: 1. List your debts on the Your Debts tab — name, balance, rate and minimum payment.
B12: 2. Pick Snowball (smallest balance first) or Avalanche (highest rate first) from the drop-down.
B13: 3. Enter any extra amount you can pay each month on top of the minimums.
B14: 4. Read the Summary tab: your debt-free date and total interest.
B15: 5. Open Payoff Plan for the month-by-month schedule you can actually follow.
B17: COLOUR KEY
... B25: Questions or a problem with the file? Message me through Etsy and I will help.

Sheet Your Debts
A1: Your Debts
A2: List up to 8 debts. Order does not matter — the plan sorts them for you.
A4: Debt name | B4: Balance owing | C4: Interest rate (APR) | D4: Minimum payment | E4: Sort key | F4: Payoff order | G4: Position
A5: Visa credit card | B5: 6400 | C5: 0.1999 | D5: 160 | E5: =IF(OR($A5="",N($B5)<=0),9999999,IF($B$16="Snowball",$B5,1000000-N($C5)*1000000)) | F5: =IF(E5=9999999,"—",RANK.EQ(E5,$E$5:$E$12,1)+COUNTIF($E$5:E5,E5)-1) | G5: =IFERROR(MATCH(1,$F$5:$F$12,0),0)
A6: Store card | B6: 1850 | C6: 0.2799 | D6: 60 | E6: =IF(OR($A6="",N($B6)<=0),9999999,IF($B$16="Snowball",$B6,1000000-N($C6)*1000000)) | F6: =IF(E6=9999999,"—",RANK.EQ(E6,$E$5:$E$12,1)+COUNTIF($E$5:E6,E6)-1) | G6: =IFERROR(MATCH(2,$F$5:$F$12,0),0)
A7: Car loan | B7: 14200 | C7: 0.0689 | D7: 385 | E7: =IF(OR($A7="",N($B7)<=0),9999999,IF($B$16="Snowball",$B7,1000000-N($C7)*1000000)) | F7: =IF(E7=9999999,"—",RANK.EQ(E7,$E$5:$E$12,1)+COUNTIF($E$5:E7,E7)-1) | G7: =IFERROR(MATCH(3,$F$5:$F$12,0),0)
A8: Student loan | B8: 9800 | C8: 0.0545 | D8: 210 | E8: =IF(OR($A8="",N($B8)<=0),9999999,IF($B$16="Snowball",$B8,1000000-N($C8)*1000000)) | F8: =IF(E8=9999999,"—",RANK.EQ(E8,$E$5:$E$12,1)+COUNTIF($E$5:E8,E8)-1) | G8: =IFERROR(MATCH(4,$F$5:$F$12,0),0)
A9: Line of credit | B9: 5200 | C9: 0.1145 | D9: 130 | E9: =IF(OR($A9="",N($B9)<=0),9999999,IF($B$16="Snowball",$B9,1000000-N($C9)*1000000)) | F9: =IF(E9=9999999,"—",RANK.EQ(E9,$E$5:$E$12,1)+COUNTIF($E$5:E9,E9)-1) | G9: =IFERROR(MATCH(5,$F$5:$F$12,0),0)
E10: =IF(OR($A10="",N($B10)<=0),9999999,IF($B$16="Snowball",$B10,1000000-N($C10)*1000000)) | F10: =IF(E10=9999999,"—",RANK.EQ(E10,$E$5:$E$12,1)+COUNTIF($E$5:E10,E10)-1) | G10: =IFERROR(MATCH(6,$F$5:$F$12,0),0)
E11: =IF(OR($A11="",N($B11)<=0),9999999,IF($B$16="Snowball",$B11,1000000-N($C11)*1000000)) | F11: =IF(E11=9999999,"—",RANK.EQ(E11,$E$5:$E$12,1)+COUNTIF($E$5:E11,E11)-1) | G11: =IFERROR(MATCH(7,$F$5:$F$12,0),0)
E12: =IF(OR($A12="",N($B12)<=0),9999999,IF($B$16="Snowball",$B12,1000000-N($C12)*1000000)) | F12: =IF(E12=9999999,"—",RANK.EQ(E12,$E$5:$E$12,1)+COUNTIF($E$5:E12,E12)-1) | G12: =IFERROR(MATCH(8,$F$5:$F$12,0),0)
A13: Total owing | B13: =SUM(B5:B12) | C13: Total minimums | D13: =SUM(D5:D12)
A15: YOUR PLAN
A16: Method | B16: Snowball | C16: Snowball = smallest balance first (fastest wins). Avalanche = highest rate first (cheapest).
A17: Extra payment per month | B17: 250
A18: Total monthly budget | B18: =D13+B17
A19: First payment month | B19: 2026-01-01
A21: Type the method exactly as Snowball or Avalanche — the drop-down keeps it clean.
A22: Extra payment is anything you can add on top of the minimums. Try changing it and watch the payoff date move.

Sheet Payoff Plan
A1: Payoff Plan
A2: Month-by-month. Freed-up minimums roll onto the next debt automatically.
A4: Payoff order → | D4: =IF('Your Debts'!$G$5=0,"—",INDEX('Your Debts'!$A$5:$A$12,'Your Debts'!$G$5)) | G4: =IF('Your Debts'!$G$6=0,"—",INDEX('Your Debts'!$A$5:$A$12,'Your Debts'!$G$6)) | J4: =IF('Your Debts'!$G$7=0,"—",INDEX('Your Debts'!$A$5:$A$12,'Your Debts'!$G$7)) | M4: =IF('Your Debts'!$G$8=0,"—",INDEX('Your Debts'!$A$5:$A$12,'Your Debts'!$G$8)) | P4: =IF('Your Debts'!$G$9=0,"—",INDEX('Your Debts'!$A$5:$A$12,'Your Debts'!$G$9)) | S4: =IF('Your Debts'!$G$10=0,"—",INDEX('Your Debts'!$A$5:$A$12,'Your Debts'!$G$10)) | V4: =IF('Your Debts'!$G$11=0,"—",INDEX('Your Debts'!$A$5:$A$12,'Your Debts'!$G$11)) | Y4: =IF('Your Debts'!$G$12=0,"—",INDEX('Your Debts'!$A$5:$A$12,'Your Debts'!$G$12))
A5: Month | B5: Date | C5: Budget | D5: Interest | E5: Payment | F5: Balance | G5: Interest | H5: Payment | I5: Balance | J5: Interest | K5: Payment | L5: Balance | M5: Interest | N5: Payment | O5: Balance | P5: Interest | Q5: Payment | R5: Balance | S5: Interest | T5: Payment | U5: Balance | V5: Interest | W5: Payment | X5: Balance | Y5: Interest | Z5: Payment | AA5: Balance | AB5: Total balance | AC5: Interest paid to date
A6: 1 | B6: =EDATE('Your Debts'!$B$19,0) | C6: ='Your Debts'!$B$18 | D6: =ROUND((IF('Your Debts'!$G$5=0,0,INDEX('Your Debts'!$B$5:$B$12,'Your Debts'!$G$5)))*(IF('Your Debts'!$G$5=0,0,INDEX('Your Debts'!$C$5:$C$12,'Your Debts'!$G$5)/12)),2) | E6: =MIN((IF('Your Debts'!$G$5=0,0,INDEX('Your Debts'!$B$5:$B$12,'Your Debts'!$G$5)))+D6,MAX(0,$C6-(0))) | F6: =ROUND(MAX(0,(IF('Your Debts'!$G$5=0,0,INDEX('Your Debts'!$B$5:$B$12,'Your Debts'!$G$5)))+D6-E6),2) | G6: =ROUND((IF('Your Debts'!$G$6=0,0,INDEX('Your Debts'!$B$5:$B$12,'Your Debts'!$G$6)))*(IF('Your Debts'!$G$6=0,0,INDEX('Your Debts'!$C$5:$C$12,'Your Debts'!$G$6)/12)),2) | H6: =MIN((IF('Your Debts'!$G$6=0,0,INDEX('Your Debts'!$B$5:$B$12,'Your Debts'!$G$6)))+G6,MAX(0,$C6-(E6))) | I6: =ROUND(MAX(0,(IF('Your Debts'!$G$6=0,0,INDEX('Your Debts'!$B$5:$B$12,'Your Debts'!$G$6)))+G6-H6),2) | J6: =ROUND((IF('Your Debts'!$G$7=0,0,INDEX('Your Debts'!$B$5:$B$12,'Your Debts'!$G$7)))*(IF('Your Debts'!$G$7=0,0,INDEX('Your Debts'!$C$5:$C$12,'Your Debts'!$G$7)/12)),2) | K6: =MIN((IF('Your Debts'!$G$7=0,0,INDEX('Your Debts'!$B$5:$B$12,'Your Debts'!$G$7)))+J6,MAX(0,$C6-(E6+H6))) | L6: =ROUND(MAX(0,(IF('Your Debts'!$G$7=0,0,INDEX('Your Debts'!$B$5:$B$12,'Your Debts'!$G$7)))+J6-K6),2) | M6: =ROUND((IF('Your Debts'!$G$8=0,0,INDEX('Your Debts'!$B$5:$B$12,'Your Debts'!$G$8)))*(IF('Your Debts'!$G$8=0,0,INDEX('Your Debts'!$C$5:$C$12,'Your Debts'!$G$8)/12)),2) | N6: =MIN((IF('Your Debts'!$G$8=0,0,INDEX('Your Debts'!$B$5:$B$12,'Your Debts'!$G$8)))+M6,MAX(0,$C6-(E6+H6+K6))) | O6: =ROUND(MAX(0,(IF('Your Debts'!$G$8=0,0,INDEX('Your Debts'!$B$5:$B$12,'Your Debts'!$G$8)))+M6-N6),2) | P6: =ROUND((IF('Your Debts'!$G$9=0,0,INDEX('Your Debts'!$B$5:$B$12,'Your Debts'!$G$9)))*(IF('Your Debts'!$G$9=0,0,INDEX('Your Debts'!$C$5:$C$12,'Your Debts'!$G$9)/12)),2) | Q6: =MIN((IF('Your Debts'!$G$9=0,0,INDEX('Your Debts'!$B$5:$B$12,'Your Debts'!$G$9)))+P6,MAX(0,$C6-(E6+H6+K6+N6))) | R6: =ROUND(MAX(0,(IF('Your Debts'!$G$9=0,0,INDEX('Your Debts'!$B$5:$B$12,'Your Debts'!$G$9)))+P6-Q6),2) | S6: =ROUND((IF('Your Debts'!$G$10=0,0,INDEX('Your Debts'!$B$5:$B$12,'Your Debts'!$G$10)))*(IF('Your Debts'!$G$10=0,0,INDEX('Your Debts'!$C$5:$C$12,'Your Debts'!$G$10)/12)),2) | T6: =MIN((IF('Your Debts'!$G$10=0,0,INDEX('Your Debts'!$B$5:$B$12,'Your Debts'!$G$10)))+S6,MAX(0,$C6-(E6+H6+K6+N6+Q6))) | U6: =ROUND(MAX(0,(IF('Your Debts'!$G$10=0,0,INDEX('Your Debts'!$B$5:$B$12,'Your Debts'!$G$10)))+S6-T6),2) | V6: =ROUND((IF('Your Debts'!$G$11=0,0,INDEX('Your Debts'!$B$5:$B$12,'Your Debts'!$G$11)))*(IF('Your Debts'!$G$11=0,0,INDEX('Your Debts'!$C$5:$C$12,'Your Debts'!$G$11)/12)),2) | W6: =MIN((IF('Your Debts'!$G$11=0,0,INDEX('Your Debts'!$B$5:$B$12,'Your Debts'!$G$11)))+V6,MAX(0,$C6-(E6+H6+K6+N6+Q6+T6))) | X6: =ROUND(MAX(0,(IF('Your Debts'!$G$11=0,0,INDEX('Your Debts'!$B$5:$B$12,'Your Debts'!$G$11)))+V6-W6),2) | Y6: =ROUND((IF('Your Debts'!$G$12=0,0,INDEX('Your Debts'!$B$5:$B$12,'Your Debts'!$G$12)))*(IF('Your Debts'!$G$12=0,0,INDEX('Your Debts'!$C$5:$C$12,'Your Debts'!$G$12)/12)),2) | Z6: =MIN((IF('Your Debts'!$G$12=0,0,INDEX('Your Debts'!$B$5:$B$12,'Your Debts'!$G$12)))+Y6,MAX(0,$C6-(E6+H6+K6+N6+Q6+T6+W6))) | AA6: =ROUND(MAX(0,(IF('Your Debts'!$G$12=0,0,INDEX('Your Debts'!$B$5:$B$12,'Your Debts'!$G$12)))+Y6-Z6),2) | AB6: =F6+I6+L6+O6+R6+U6+X6+AA6 | AC6: =0+D6+G6+J6+M6+P6+S6+V6+Y6
A7: 2 | B7: =EDATE('Your Debts'!$B$19,1) | C7: ='Your Debts'!$B$18 | D7: =ROUND((F6)*(IF('Your Debts'!$G$5=0,0,INDEX('Your Debts'!$C$5:$C$12,'Your Debts'!$G$5)/12)),2) | E7: =MIN((F6)+D7,MAX(0,$C7-(0))) | F7: =ROUND(MAX(0,(F6)+D7-E7),2) | G7: =ROUND((I6)*(IF('Your Debts'!$G$6=0,0,INDEX('Your Debts'!$C$5:$C$12,'Your Debts'!$G$6)/12)),2) | H7: =MIN((I6)+G7,MAX(0,$C7-(E7))) | I7: =ROUND(MAX(0,(I6)+G7-H7),2) | J7: =ROUND((L6)*(IF('Your Debts'!$G$7=0,0,INDEX('Your Debts'!$C$5:$C$12,'Your Debts'!$G$7)/12)),2) | K7: =MIN((L6)+J7,MAX(0,$C7-(E7+H7))) | L7: =ROUND(MAX(0,(L6)+J7-K7),2) | M7: =ROUND((O6)*(IF('Your Debts'!$G$8=0,0,INDEX('Your Debts'!$C$5:$C$12,'Your Debts'!$G$8)/12)),2) | N7: =MIN((O6)+M7,MAX(0,$C7-(E7+H7+K7))) | O7: =ROUND(MAX(0,(O6)+M7-N7),2) | P7: =ROUND((R6)*(IF('Your Debts'!$G$9=0,0,INDEX('Your Debts'!$C$5:$C$12,'Your Debts'!$G$9)/12)),2) | Q7: =MIN((R6)+P7,MAX(0,$C7-(E7+H7+K7+N7))) | R7: =ROUND(MAX(0,(R6)+P7-Q7),2) | S7: =ROUND((U6)*(IF('Your Debts'!$G$10=0,0,INDEX('Your Debts'!$C$5:$C$12,'Your Debts'!$G$10)/12)),2) | T7: =MIN((U6)+S7,MAX(0,$C7-(E7+H7+K7+N7+Q7))) | U7: =ROUND(MAX(0,(U6)+S7-T7),2) | V7: =ROUND((X6)*(IF('Your Debts'!$G$11=0,0,INDEX('Your Debts'!$C$5:$C$12,'Your Debts'!$G$11)/12)),2) | W7: =MIN((X6)+V7,MAX(0,$C7-(E7+H7+K7+N7+Q7+T7))) | X7: =ROUND(MAX(0,(X6)+V7-W7),2) | Y7: =ROUND((AA6)*(IF('Your Debts'!$G$12=0,0,INDEX('Your Debts'!$C$5:$C$12,'Your Debts'!$G$12)/12)),2) | Z7: =MIN((AA6)+Y7,MAX(0,$C7-(E7+H7+K7+N7+Q7+T7+W7))) | AA7: =ROUND(MAX(0,(AA6)+Y7-Z7),2) | AB7: =F7+I7+L7+O7+R7+U7+X7+AA7 | AC7: =AC6+D7+G7+J7+M7+P7+S7+V7+Y7
A8: 3 | B8: =EDATE('Your Debts'!$B$19,2) | C8: ='Your Debts'!$B$18 | D8: =ROUND((F7)*(IF('Your Debts'!$G$5=0,0,INDEX('Your Debts'!$C$5:$C$12,'Your Debts'!$G$5)/12)),2) | E8: =MIN((F7)+D8,MAX(0,$C8-(0))) | F8: =ROUND(MAX(0,(F7)+D8-E8),2) | G8: =ROUND((I7)*(IF('Your Debts'!$G$6=0,0,INDEX('Your Debts'!$C$5:$C$12,'Your Debts'!$G$6)/12)),2) | H8: =MIN((I7)+G8,MAX(0,$C8-(E8))) | I8: =ROUND(MAX(0,(I7)+G8-H8),2) | J8: =ROUND((L7)*(IF('Your Debts'!$G$7=0,0,INDEX('Your Debts'!$C$5:$C$12,'Your Debts'!$G$7)/12)),2) | K8: =MIN((L7)+J8,MAX(0,$C8-(E8+H8))) | L8: =ROUND(MAX(0,(L7)+J8-K8),2) | M8: =ROUND((O7)*(IF('Your Debts'!$G$8=0,0,INDEX('Your Debts'!$C$5:$C$12,'Your Debts'!$G$8)/12)),2) | N8: =MIN((O7)+M8,MAX(0,$C8-(E8+H8+K8))) | O8: =ROUND(MAX(0,(O7)+M8-N8),2) | P8: =ROUND((R7)*(IF('Your Debts'!$G$9=0,0,INDEX('Your Debts'!$C$5:$C$12,'Your Debts'!$G$9)/12)),2) | Q8: =MIN((R7)+P8,MAX(0,$C8-(E8+H8+K8+N8))) | R8: =ROUND(MAX(0,(R7)+P8-Q8),2) | S8: =ROUND((U7)*(IF('Your Debts'!$G$10=0,0,INDEX('Your Debts'!$C$5:$C$12,'Your Debts'!$G$10)/12)),2) | T8: =MIN((U7)+S8,MAX(0,$C8-(E8+H8+K8+N8+Q8))) | U8: =ROUND(MAX(0,(U7)+S8-T8),2) | V8: =ROUND((X7)*(IF('Your Debts'!$G$11=0,0,INDEX('Your Debts'!$C$5:$C$12,'Your Debts'!$G$11)/12)),2) | W8: =MIN((X7)+V8,MAX(0,$C8-(E8+H8+K8+N8+Q8+T8))) | X8: =ROUND(MAX(0,(X7)+V8-W8),2) | Y8: =ROUND((AA7)*(IF('Your Debts'!$G$12=0,0,INDEX('Your Debts'!$C$5:$C$12,'Your Debts'!$G$12)/12)),2) | Z8: =MIN((AA7)+Y8,MAX(0,$C8-(E8+H8+K8+N8+Q8+T8+W8))) | AA8: =ROUND(MAX(0,(AA7)+Y8-Z8),2) | AB8: =F8+I8+L8+O8+R8+U8+X8+AA8 | AC8: =AC7+D8+G8+J8+M8+P8+S8+V8+Y8
A9: 4 | B9: =EDATE('Your Debts'!$B$19,3) | C9: ='Your Debts'!$B$18 | D9: =ROUND((F8)*(IF('Your Debts'!$G$5=0,0,INDEX('Your Debts'!$C$5:$C$12,'Your Debts'!$G$5)/12)),2) | E9: =MIN((F8)+D9,MAX(0,$C9-(0))) | F9: =ROUND(MAX(0,(F8)+D9-E9),2) | G9: =ROUND((I8)*(IF('Your Debts'!$G$6=0,0,INDEX('Your Debts'!$C$5:$C$12,'Your Debts'!$G$6)/12)),2) | H9: =MIN((I8)+G9,MAX(0,$C9-(E9))) | I9: =ROUND(MAX(0,(I8)+G9-H9),2) | J9: =ROUND((L8)*(IF('Your Debts'!$G$7=0,0,INDEX('Your Debts'!$C$5:$C$12,'Your Debts'!$G$7)/12)),2) | K9: =MIN((L8)+J9,MAX(0,$C9-(E9+H9))) | L9: =ROUND(MAX(0,(L8)+J9-K9),2) | M9: =ROUND((O8)*(IF('Your Debts'!$G$8=0,0,INDEX('Your Debts'!$C$5:$C$12,'Your Debts'!$G$8)/12)),2) | N9: =MIN((O8)+M9,MAX(0,$C9-(E9+H9+K9))) | O9: =ROUND(MAX(0,(O8)+M9-N9),2) | P9: =ROUND((R8)*(IF('Your Debts'!$G$9=0,0,INDEX('Your Debts'!$C$5:$C$12,'Your Debts'!$G$9)/12)),2) | Q9: =MIN((R8)+P9,MAX(0,$C9-(E9+H9+K9+N9))) | R9: =ROUND(MAX(0,(R8)+P9-Q9),2) | S9: =ROUND((U8)*(IF('Your Debts'!$G$10=0,0,INDEX('Your Debts'!$C$5:$C$12,'Your Debts'!$G$10)/12)),2) | T9: =MIN((U8)+S9,MAX(0,$C9-(E9+H9+K9+N9+Q9))) | U9: =ROUND(MAX(0,(U8)+S9-T9),2) | V9: =ROUND((X8)*(IF('Your Debts'!$G$11=0,0,INDEX('Your Debts'!$C$5:$C$12,'Your Debts'!$G$11)/12)),2) | W9: =MIN((X8)+V9,MAX(0,$C9-(E9+H9+K9+N9+Q9+T9))) | X9: =ROUND(MAX(0,(X8)+V9-W9),2) | Y9: =ROUND((AA8)*(IF('Your Debts'!$G$12=0,0,INDEX('Your Debts'!$C$5:$C$12,'Your Debts'!$G$12)/12)),2) | Z9: =MIN((AA8)+Y9,MAX(0,$C9-(E9+H9+K9+N9+Q9+T9+W9))) | AA9: =ROUND(MAX(0,(AA8)+Y9-Z9),2) | AB9: =F9+I9+L9+O9+R9+U9+X9+AA9 | AC9: =AC8+D9+G9+J9+M9+P9+S9+V9+Y9
A10: 5 | B10: =EDATE('Your Debts'!$B$19,4) | C10: ='Your Debts'!$B$18 | D10: =ROUND((F9)*(IF('Your Debts'!$G$5=0,0,INDEX('Your Debts'!$C$5:$C$12,'Your Debts'!$G$5)/12)),2) | E10: =MIN((F9)+D10,MAX(0,$C10-(0))) | F10: =ROUND(MAX(0,(F9)+D10-E10),2) | G10: =ROUND((I9)*(IF('Your Debts'!$G$6=0,0,INDEX('Your Debts'!$C$5:$C$12,'Your Debts'!$G$6)/12)),2) | H10: =MIN((I9)+G10,MAX(0,$C10-(E10))) | I10: =ROUND(MAX(0,(I9)+G10-H10),2) | J10: =ROUND((L9)*(IF('Your Debts'!$G$7=0,0,INDEX('Your Debts'!$C$5:$C$12,'Your Debts'!$G$7)/12)),2) | K10: =MIN((L9)+J10,MAX(0,$C10-(E10+H10))) | L10: =ROUND(MAX(0,(L9)+J10-K10),2) | M10: =ROUND((O9)*(IF('Your Debts'!$G$8=0,0,INDEX('Your Debts'!$C$5:$C$12,'Your Debts'!$G$8)/12)),2) | N10: =MIN((O9)+M10,MAX(0,$C10-(E10+H10+K10))) | O10: =ROUND(MAX(0,(O9)+M10-N10),2) | P10: =ROUND((R9)*(IF('Your Debts'!$G$9=0,0,INDEX('Your Debts'!$C$5:$C$12,'Your Debts'!$G$9)/12)),2) | Q10: =MIN((R9)+P10,MAX(0,$C10-(E10+H10+K10+N10))) | R10: =ROUND(MAX(0,(R9)+P10-Q10),2) | S10: =ROUND((U9)*(IF('Your Debts'!$G$10=0,0,INDEX('Your Debts'!$C$5:$C$12,'Your Debts'!$G$10)/12)),2) | T10: =MIN((U9)+S10,MAX(0,$C10-(E10+H10+K10+N10+Q10))) | U10: =ROUND(MAX(0,(U9)+S10-T10),2) | V10: =ROUND((X9)*(IF('Your Debts'!$G$11=0,0,INDEX('Your Debts'!$C$5:$C$12,'Your Debts'!$G$11)/12)),2) | W10: =MIN((X9)+V10,MAX(0,$C10-(E10+H10+K10+N10+Q10+T10))) | X10: =ROUND(MAX(0,(X9)+V10-W10),2) | Y10: =ROUND((AA9)*(IF('Your Debts'!$G$12=0,0,INDEX('Your Debts'!$C$5:$C$12,'Your Debts'!$G$12)/12)),2) | Z10: =MIN((AA9)+Y10,MAX(0,$C10-(E10+H10+K10+N10+Q10+T10+W10))) | AA10: =ROUND(MAX(0,(AA9)+Y10-Z10),2) | AB10: =F10+I10+L10+O10+R10+U10+X10+AA10 | AC10: =AC9+D10+G10+J10+M10+P10+S10+V10+Y10
A11: 6 | B11: =EDATE('Your Debts'!$B$19,5) | C11: ='Your Debts'!$B$18 | D11: =ROUND((F10)*(IF('Your Debts'!$G$5=0,0,INDEX('Your Debts'!$C$5:$C$12,'Your Debts'!$G$5)/12)),2) | E11: =MIN((F10)+D11,MAX(0,$C11-(0))) | F11: =ROUND(MAX(0,(F10)+D11-E11),2) | G11: =ROUND((I10)*(IF('Your Debts'!$G$6=0,0,INDEX('Your Debts'!$C$5:$C$12,'Your Debts'!$G$6)/12)),2) | H11: =MIN((I10)+G11,MAX(0,$C11-(E11))) | I11: =ROUND(MAX(0,(I10)+G11-H11),2) | J11: =ROUND((L10)*(IF('Your Debts'!$G$7=0,0,INDEX('Your Debts'!$C$5:$C$12,'Your Debts'!$G$7)/12)),2) | K11: =MIN((L10)+J11,MAX(0,$C11-(E11+H11))) | L11: =ROUND(MAX(0,(L10)+J11-K11),2) | M11: =ROUND((O10)*(IF('Your Debts'!$G$8=0,0,INDEX('Your Debts'!$C$5:$C$12,'Your Debts'!$G$8)/12)),2) | N11: =MIN((O10)+M11,MAX(0,$C11-(E11+H11+K11))) | O11: =ROUND(MAX(0,(O10)+M11-N11),2) | P11: =ROUND((R10)*(IF('Your Debts'!$G$9=0,0,INDEX('Your Debts'!$C$5:$C$12,'Your Debts'!$G$9)/12)),2) | Q11: =MIN((R10)+P11,MAX(0,$C11-(E11+H11+K11+N11))) | R11: =ROUND(MAX(0,(R10)+P11-Q11),2) | S11: =ROUND((U10)*(IF('Your Debts'!$G$10=0,0,INDEX('Your Debts'!$C$5:$C$12,'Your Debts'!$G$10)/12)),2) | T11: =MIN((U10)+S11,MAX(0,$C11-(E11+H11+K11+N11+Q11))) | U11: =ROUND(MAX(0,(U10)+S11-T11),2) | V11: =ROUND((X10)*(IF('Your Debts'!$G$11=0,0,INDEX('Your Debts'!$C$5:$C$12,'Your Debts'!$G$11)/12)),2) | W11: =MIN((X10)+V11,MAX(0,$C11-(E11+H11+K11+N11+Q11+T11))) | X11: =ROUND(MAX(0,(X10)+V11-W11),2) | Y11: =ROUND((AA10)*(IF('Your Debts'!$G$12=0,0,INDEX('Your Debts'!$C$5:$C$12,'Your Debts'!$G$12)/12)),2) | Z11: =MIN((AA10)+Y11,MAX(0,$C11-(E11+H11+K11+N11+Q11+T11+W11))) | AA11: =ROUND(MAX(0,(AA10)+Y11-Z11),2) | AB11: =F11+I11+L11+O11+R11+U11+X11+AA11 | AC11: =AC10+D11+G11+J11+M11+P11+S11+V11+Y11
A12: 7 | B12: =EDATE('Your Debts'!$B$19,6) | C12: ='Your Debts'!$B$18 | D12: =ROUND((F11)*(IF('Your Debts'!$G$5=0,0,INDEX('Your Debts'!$C$5:$C$12,'Your Debts'!$G$5)/12)),2) | E12: =MIN((F11)+D12,MAX(0,$C12-(0))) | F12: =ROUND(MAX(0,(F11)+D12-E12),2) | G12: =ROUND((I11)*(IF('Your Debts'!$G$6=0,0,INDEX('Your Debts'!$C$5:$C$12,'Your Debts'!$G$6)/12)),2) | H12: =MIN((I11)+G12,MAX(0,$C12-(E12))) | I12: =ROUND(MAX(0,(I11)+G12-H12),2) | J12: =ROUND((L11)*(IF('Your Debts'!$G$7=0,0,INDEX('Your Debts'!$C$5:$C$12,'Your Debts'!$G$7)/12)),2) | K12: =MIN((L11)+J12,MAX(0,$C12-(E12+H12))) | L12: =ROUND(MAX(0,(L11)+J12-K12),2) | M12: =ROUND((O11)*(IF('Your Debts'!$G$8=0,0,INDEX('Your Debts'!$C$5:$C$12,'Your Debts'!$G$8)/12)),2) | N12: =MIN((O11)+M12,MAX(0,$C12-(E12+H12+K12))) | O12: =ROUND(MAX(0,(O11)+M12-N12),2) | P12: =ROUND((R11)*(IF('Your Debts'!$G$9=0,0,INDEX('Your Debts'!$C$5:$C$12,'Your Debts'!$G$9)/12)),2) | Q12: =MIN((R11)+P12,MAX(0,$C12-(E12+H12+K12+N12))) | R12: =ROUND(MAX(0,(R11)+P12-Q12),2) | S12: =ROUND((U11)*(IF('Your Debts'!$G$10=0,0,INDEX('Your Debts'!$C$5:$C$12,'Your Debts'!$G$10)/12)),2) | T12: =MIN((U11)+S12,MAX(0,$C12-(E12+H12+K12+N12+Q12))) | U12: =ROUND(MAX(0,(U11)+S12-T12),2) | V12: =ROUND((X11)*(IF('Your Debts'!$G$11=0,0,INDEX('Your Debts'!$C$5:$C$12,'Your Debts'!$G$11)/12)),2) | W12: =MIN((X11)+V12,MAX(0,$C12-(E12+H12+K12+N12+Q12+T12))) | X12: =ROUND(MAX(0,(X11)+V12-W12),2) | Y12: =ROUND((AA11)*(IF('Your Debts'!$G$12=0,0,INDEX('Your Debts'!$C$5:$C$12,'Your Debts'!$G$12)/12)),2) | Z12: =MIN((AA11)+Y12,MAX(0,$C12-(E12+H12+K12+N12+Q12+T12+W12))) | AA12: =ROUND(MAX(0,(AA11)+Y12-Z12),2) | AB12: =F12+I12+L12+O12+R12+U12+X12+AA12 | AC12: =AC11+D12+G12+J12+M12+P12+S12+V12+Y12
A13: 8 | B13: =EDATE('Your Debts'!$B$19,7) | C13: ='Your Debts'!$B$18 | D13: =ROUND((F12)*(IF('Your Debts'!$G$5=0,0,INDEX('Your Debts'!$C$5:$C$12,'Your Debts'!$G$5)/12)),2) | E13: =MIN((F12)+D13,MAX(0,$C13-(0))) | F13: =ROUND(MAX(0,(F12)+D13-E13),2) | G13: =ROUND((I12)*(IF('Your Debts'!$G$6=0,0,INDEX('Your Debts'!$C$5:$C$12,'Your Debts'!$G$6)/12)),2) | H13: =MIN((I12)+G13,MAX(0,$C13-(E13))) | I13: =ROUND(MAX(0,(I12)+G13-H13),2) | J13: =ROUND((L12)*(IF('Your Debts'!$G$7=0,0,INDEX('Your Debts'!$C$5:$C$12,'Your Debts'!$G$7)/12)),2) | K13: =MIN((L12)+J13,MAX(0,$C13-(E13+H13))) | L13: =ROUND(MAX(0,(L12)+J13-K13),2) | M13: =ROUND((O12)*(IF('Your Debts'!$G$8=0,0,INDEX('Your Debts'!$C$5:$C$12,'Your Debts'!$G$8)/12)),2) | N13: =MIN((O12)+M13,MAX(0,$C13-(E13+H13+K13))) | O13: =ROUND(MAX(0,(O12)+M13-N13),2) | P13: =ROUND((R12)*(IF('Your Debts'!$G$9=0,0,INDEX('Your Debts'!$C$5:$C$12,'Your Debts'!$G$9)/12)),2) | Q13: =MIN((R12)+P13,MAX(0,$C13-(E13+H13+K13+N13))) | R13: =ROUND(MAX(0,(R12)+P13-Q13),2) | S13: =ROUND((U12)*(IF('Your Debts'!$G$10=0,0,INDEX('Your Debts'!$C$5:$C$12,'Your Debts'!$G$10)/12)),2) | T13: =MIN((U12)+S13,MAX(0,$C13-(E13+H13+K13+N13+Q13))) | U13: =ROUND(MAX(0,(U12)+S13-T13),2) | V13: =ROUND((X12)*(IF('Your Debts'!$G$11=0,0,INDEX('Your Debts'!$C$5:$C$12,'Your Debts'!$G$11)/12)),2) | W13: =MIN((X12)+V13,MAX(0,$C13-(E13+H13+K13+N13+Q13+T13))) | X13: =ROUND(MAX(0,(X12)+V13-W13),2) | Y13: =ROUND((AA12)*(IF('Your Debts'!$G$12=0,0,INDEX('Your Debts'!$C$5:$C$12,'Your Debts'!$G$12)/12)),2) | Z13: =MIN((AA12)+Y13,MAX(0,$C13-(E13+H13+K13+N13+Q13+T13+W13))) | AA13: =ROUND(MAX(0,(AA12)+Y13-Z13),2) | AB13: =F13+I13+L13+O13+R13+U13+X13+AA13 | AC13: =AC12+D13+G13+J13+M13+P13+S13+V13+Y13
A14: 9 | B14: =EDATE('Your Debts'!$B$19,8) | C14: ='Your Debts'!$B$18 | D14: =ROUND((F13)*(IF('Your Debts'!$G$5=0,0,INDEX('Your Debts'!$C$5:$C$12,'Your Debts'!$G$5)/12)),2) | E14: =MIN((F13)+D14,MAX(0,$C14-(0))) | F14: =ROUND(MAX(0,(F13)+D14-E14),2) | G14: =ROUND((I13)*(IF('Your Debts'!$G$6=0,0,INDEX('Your Debts'!$C$5:$C$12,'Your Debts'!$G$6)/12)),2) | H14: =MIN((I13)+G14,MAX(0,$C14-(E14))) | I14: =ROUND(MAX(0,(I13)+G14-H14),2) | J14: =ROUND((L13)*(IF('Your Debts'!$G$7=0,0,INDEX('Your Debts'!$C$5:$C$12,'Your Debts'!$G$7)/12)),2) | K14: =MIN((L13)+J14,MAX(0,$C14-(E14+H14))) | L14: =ROUND(MAX(0,(L13)+J14-K14),2) | M14: =ROUND((O13)*(IF('Your Debts'!$G$8=0,0,INDEX('Your Debts'!$C$5:$C$12,'Your Debts'!$G$8)/12)),2) | N14: =MIN((O13)+M14,MAX(0,$C14-(E14+H14+K14))) | O14: =ROUND(MAX(0,(O13)+M14-N14),2) | P14: =ROUND((R13)*(IF('Your Debts'!$G$9=0,0,INDEX('Your Debts'!$C$5:$C$12,'Your Debts'!$G$9)/12)),2) | Q14: =MIN((R13)+P14,MAX(0,$C14-(E14+H14+K14+N14))) | R14: =ROUND(MAX(0,(R13)+P14-Q14),2) | S14: =ROUND((U13)*(IF('Your Debts'!$G$10=0,0,INDEX('Your Debts'!$C$5:$C$12,'Your Debts'!$G$10)/12)),2) | T14: =MIN((U13)+S14,MAX(0,$C14-(E14+H14+K14+N14+Q14))) | U14: =ROUND(MAX(0,(U13)+S14-T14),2) | V14: =ROUND((X13)*(IF('Your Debts'!$G$11=0,0,INDEX('Your Debts'!$C$5:$C$12,'Your Debts'!$G$11)/12)),2) | W14: =MIN((X13)+V14,MAX(0,$C14-(E14+H14+K14+N14+Q14+T14))) | X14: =ROUND(MAX(0,(X13)+V14-W14),2) | Y14: =ROUND((AA13)*(IF('Your Debts'!$G$12=0,0,INDEX('Your Debts'!$C$5:$C$12,'Your Debts'!$G$12)/12)),2) | Z14: =MIN((AA13)+Y14,MAX(0,$C14-(E14+H14+K14+N14+Q14+T14+W14))) | AA14: =ROUND(MAX(0,(AA13)+Y14-Z14),2) | AB14: =F14+I14+L14+O14+R14+U14+X14+AA14 | AC14: =AC13+D14+G14+J14+M14+P14+S14+V14+Y14
A15: 10 | B15: =EDATE('Your Debts'!$B$19,9) | C15: ='Your Debts'!$B$18 | D15: =ROUND((F14)*(IF('Your Debts'!$G$5=0,0,INDEX('Your Debts'!$C$5:$C$12,'Your Debts'!$G$5)/12)),2) | E15: =MIN((F14)+D15,MAX(0,$C15-(0))) | F15: =ROUND(MAX(0,(F14)+D15-E15),2) | G15: =ROUND((I14)*(IF('Your Debts'!$G$6=0,0,INDEX('Your Debts'!$C$5:$C$12,'Your Debts'!$G$6)/12)),2) | H15: =MIN((I14)+G15,MAX(0,$C15-(E15))) | I15: =ROUND(MAX(0,(I14)+G15-H15),2) | J15: =ROUND((L14)*(IF('Your Debts'!$G$7=0,0,INDEX('Your Debts'!$C$5:$C$12,'Your Debts'!$G$7)/12)),2) | K15: =MIN((L14)+J15,MAX(0,$C15-(E15+H15))) | L15: =ROUND(MAX(0,(L14)+J15-K15),2) | M15: =ROUND((O14)*(IF('Your Debts'!$G$8=0,0,INDEX('Your Debts'!$C$5:$C$12,'Your Debts'!$G$8)/12)),2) | N15: =MIN((O14)+M15,MAX(0,$C15-(E15+H15+K15))) | O15: =ROUND(MAX(0,(O14)+M15-N15),2) | P15: =ROUND((R14)*(IF('Your Debts'!$G$9=0,0,INDEX('Your Debts'!$C$5:$C$12,'Your Debts'!$G$9)/12)),2) | Q15: =MIN((R14)+P15,MAX(0,$C15-(E15+H15+K15+N15))) | R15: =ROUND(MAX(0,(R14)+P15-Q15),2) | S15: =ROUND((U14)*(IF('Your Debts'!$G$10=0,0,INDEX('Your Debts'!$C$5:$C$12,'Your Debts'!$G$10)/12)),2) | T15: =MIN((U14)+S15,MAX(0,$C15-(E15+H15+K15+N15+Q15))) | U15: =ROUND(MAX(0,(U14)+S15-T15),2) | V15: =ROUND((X14)*(IF('Your Debts'!$G$11=0,0,INDEX('Your Debts'!$C$5:$C$12,'Your Debts'!$G$11)/12)),2) | W15: =MIN((X14)+V15,MAX(0,$C15-(E15+H15+K15+N15+Q15+T15))) | X15: =ROUND(MAX(0,(X14)+V15-W15),2) | Y15: =ROUND((AA14)*(IF('Your Debts'!$G$12=0,0,INDEX('Your Debts'!$C$5:$C$12,'Your Debts'!$G$12)/12)),2) | Z15: =MIN((AA14)+Y15,MAX(0,$C15-(E15+H15+K15+N15+Q15+T15+W15))) | AA15: =ROUND(MAX(0,(AA14)+Y15-Z15),2) | AB15: =F15+I15+L15+O15+R15+U15+X15+AA15 | AC15: =AC14+D15+G15+J15+M15+P15+S15+V15+Y15
A16: 11 | B16: =EDATE('Your Debts'!$B$19,10) | C16: ='Your Debts'!$B$18 | D16: =ROUND((F15)*(IF('Your Debts'!$G$5=0,0,INDEX('Your Debts'!$C$5:$C$12,'Your Debts'!$G$5)/12)),2) | E16: =MIN((F15)+D16,MAX(0,$C16-(0))) | F16: =ROUND(MAX(0,(F15)+D16-E16),2) | G16: =ROUND((I15)*(IF('Your Debts'!$G$6=0,0,INDEX('Your Debts'!$C$5:$C$12,'Your Debts'!$G$6)/12)),2) | H16: =MIN((I15)+G16,MAX(0,$C16-(E16))) | I16: =ROUND(MAX(0,(I15)+G16-H16),2) | J16: =ROUND((L15)*(IF('Your Debts'!$G$7=0,0,INDEX('Your Debts'!$C$5:$C$12,'Your Debts'!$G$7)/12)),2) | K16: =MIN((L15)+J16,MAX(0,$C16-(E16+H16))) | L16: =ROUND(MAX(0,(L15)+J16-K16),2) | M16: =ROUND((O15)*(IF('Your Debts'!$G$8=0,0,INDEX('Your Debts'!$C$5:$C$12,'Your Debts'!$G$8)/12)),2) | N16: =MIN((O15)+M16,MAX(0,$C16-(E16+H16+K16))) | O16: =ROUND(MAX(0,(O15)+M16-N16),2) | P16: =ROUND((R15)*(IF('Your Debts'!$G$9=0,0,INDEX('Your Debts'!$C$5:$C$12,'Your Debts'!$G$9)/12)),2) | Q16: =MIN((R15)+P16,MAX(0,$C16-(E16+H16+K16+N16))) | R16: =ROUND(MAX(0,(R15)+P16-Q16),2) | S16: =ROUND((U15)*(IF('Your Debts'!$G$10=0,0,INDEX('Your Debts'!$C$5:$C$12,'Your Debts'!$G$10)/12)),2) | T16: =MIN((U15)+S16,MAX(0,$C16-(E16+H16+K16+N16+Q16))) | U16: =ROUND(MAX(0,(U15)+S16-T16),2) | V16: =ROUND((X15)*(IF('Your Debts'!$G$11=0,0,INDEX('Your Debts'!$C$5:$C$12,'Your Debts'!$G$11)/12)),2) | W16: =MIN((X15)+V16,MAX(0,$C16-(E16+H16+K16+N16+Q16+T16))) | X16: =ROUND(MAX(0,(X15)+V16-W16),2) | Y16: =ROUND((AA15)*(IF('Your Debts'!$G$12=0,0,INDEX('Your Debts'!$C$5:$C$12,'Your Debts'!$G$12)/12)),2) | Z16: =MIN((AA15)+Y16,MAX(0,$C16-(E16+H16+K16+N16+Q16+T16+W16))) | AA16: =ROUND(MAX(0,(AA15)+Y16-Z16),2) | AB16: =F16+I16+L16+O16+R16+U16+X16+AA16 | AC16: =AC15+D16+G16+J16+M16+P16+S16+V16+Y16
A17: 12 | B17: =EDATE('Your Debts'!$B$19,11) | C17: ='Your Debts'!$B$18 | D17: =ROUND((F16)*(IF('Your Debts'!$G$5=0,0,INDEX('Your Debts'!$C$5:$C$12,'Your Debts'!$G$5)/12)),2) | E17: =MIN((F16)+D17,MAX(0,$C17-(0))) | F17: =ROUND(MAX(0,(F16)+D17-E17),2) | G17: =ROUND((I16)*(IF('Your Debts'!$G$6=0,0,INDEX('Your Debts'!$C$5:$C$12,'Your Debts'!$G$6)/12)),2) | H17: =MIN((I16)+G17,MAX(0,$C17-(E17))) | I17: =ROUND(MAX(0,(I16)+G17-H17),2) | J17: =ROUND((L16)*(IF('Your Debts'!$G$7=0,0,INDEX('Your Debts'!$C$5:$C$12,'Your Debts'!$G$7)/12)),2) | K17: =MIN((L16)+J17,MAX(0,$C17-(E17+H17))) | L17: =ROUND(MAX(0,(L16)+J17-K17),2) | M17: =ROUND((O16)*(IF('Your Debts'!$G$8=0,0,INDEX('Your Debts'!$C$5:$C$12,'Your Debts'!$G$8)/12)),2) | N17: =MIN((O16)+M17,MAX(0,$C17-(E17+H17+K17))) | O17: =ROUND(MAX(0,(O16)+M17-N17),2) | P17: =ROUND((R16)*(IF('Your Debts'!$G$9=0,0,INDEX('Your Debts'!$C$5:$C$12,'Your Debts'!$G$9)/12)),2) | Q17: =MIN((R16)+P17,MAX(0,$C17-(E17+H17+K17+N17))) | R17: =ROUND(MAX(0,(R16)+P17-Q17),2) | S17: =ROUND((U16)*(IF('Your Debts'!$G$10=0,0,INDEX('Your Debts'!$C$5:$C$12,'Your Debts'!$G$10)/12)),2) | T17: =MIN((U16)+S17,MAX(0,$C17-(E17+H17+K17+N17+Q17))) | U17: =ROUND(MAX(0,(U16)+S17-T17),2) | V17: =ROUND((X16)*(IF('Your Debts'!$G$11=0,0,INDEX('Your Debts'!$C$5:$C$12,'Your Debts'!$G$11)/12)),2) | W17: =MIN((X16)+V17,MAX(0,$C17-(E17+H17+K17+N17+Q17+T17))) | X17: =ROUND(MAX(0,(X16)+V17-W17),2) | Y17: =ROUND((AA16)*(IF('Your Debts'!$G$12=0,0,INDEX('Your Debts'!$C$5:$C$12,'Your Debts'!$G$12)/12)),2) | Z17: =MIN((AA16)+Y17,MAX(0,$C17-(E17+H17+K17+N17+Q17+T17+W17))) | AA17: =ROUND(MAX(0,(AA16)+Y17-Z17),2) | AB17: =F17+I17+L17+O17+R17+U17+X17+AA17 | AC17: =AC16+D17+G17+J17+M17+P17+S17+V17+Y17
A18: 13 | B18: =EDATE('Your Debts'!$B$19,12) | C18: ='Your Debts'!$B$18 | D18: =ROUND((F17)*(IF('Your Debts'!$G$5=0,0,INDEX('Your Debts'!$C$5:$C$12,'Your Debts'!$G$5)/12)),2) | E18: =MIN((F17)+D18,MAX(0,$C18-(0))) | F18: =ROUND(MAX(0,(F17)+D18-E18),2) | G18: =ROUND((I17)*(IF('Your Debts'!$G$6=0,0,INDEX('Your Debts'!$C$5:$C$12,'Your Debts'!$G$6)/12)),2) | H18: =MIN((I17)+G18,MAX(0,$C18-(E18))) | I18: =ROUND(MAX(0,(I17)+G18-H18),2) | J18: =ROUND((L17)*(IF('Your Debts'!$G$7=0,0,INDEX('Your Debts'!$C$5:$C$12,'Your Debts'!$G$7)/12)),2) | K18: =MIN((L17)+J18,MAX(0,$C18-(E18+H18))) | L18: =ROUND(MAX(0,(L17)+J18-K18),2) | M18: =ROUND((O17)*(IF('Your Debts'!$G$8=0,0,INDEX('Your Debts'!$C$5:$C$12,'Your Debts'!$G$8)/12)),2) | N18: =MIN((O17)+M18,MAX(0,$C18-(E18+H18+K18))) | O18: =ROUND(MAX(0,(O17)+M18-N18),2) | P18: =ROUND((R17)*(IF('Your Debts'!$G$9=0,0,INDEX('Your Debts'!$C$5:$C$12,'Your Debts'!$G$9)/12)),2) | Q18: =MIN((R17)+P18,MAX(0,$C18-(E18+H18+K18+N18))) | R18: =ROUND(MAX(0,(R17)+P18-Q18),2) | S18: =ROUND((U17)*(IF('Your Debts'!$G$10=0,0,INDEX('Your Debts'!$C$5:$C$12,'Your Debts'!$G$10)/12)),2) | T18: =MIN((U17)+S18,MAX(0,$C18-(E18+H18+K18+N18+Q18))) | U18: =ROUND(MAX(0,(U17)+S18-T18),2) | V18: =ROUND((X17)*(IF('Your Debts'!$G$11=0,0,INDEX('Your Debts'!$C$5:$C$12,'Your Debts'!$G$11)/12)),2) | W18: =MIN((X17)+V18,MAX(0,$C18-(E18+H18+K18+N18+Q18+T18))) | X18: =ROUND(MAX(0,(X17)+V18-W18),2) | Y18: =ROUND((AA17)*(IF('Your Debts'!$G$12=0,0,INDEX('Your Debts'!$C$5:$C$12,'Your Debts'!$G$12)/12)),2) | Z18: =MIN((AA17)+Y18,MAX(0,$C18-(E18+H18+K18+N18+Q18+T18+W18))) | AA18: =ROUND(MAX(0,(AA17)+Y18-Z18),2) | AB18: =F18+I18+L18+O18+R18+U18+X18+AA18 | AC18: =AC17+D18+G18+J18+M18+P18+S18+V18+Y18
A19: 14 | B19: =EDATE('Your Debts'!$B$19,13) | C19: ='Your Debts'!$B$18 | D19: =ROUND((F18)*(IF('Your Debts'!$G$5=0,0,INDEX('Your Debts'!$C$5:$C$12,'Your Debts'!$G$5)/12)),2) | E19: =MIN((F18)+D19,MAX(0,$C19-(0))) | F19: =ROUND(MAX(0,(F18)+D19-E19),2) | G19: =ROUND((I18)*(IF('Your Debts'!$G$6=0,0,INDEX('Your Debts'!$C$5:$C$12,'Your Debts'!$G$6)/12)),2) | H19: =MIN((I18)+G19,MAX(0,$C19-(E19))) | I19: =ROUND(MAX(0,(I18)+G19-H19),2) | J19: =ROUND((L18)*(IF('Your Debts'!$G$7=0,0,INDEX('Your Debts'!$C$5:$C$12,'Your Debts'!$G$7)/12)),2) | K19: =MIN((L18)+J19,MAX(0,$C19-(E19+H19))) | L19: =ROUND(MAX(0,(L18)+J19-K19),2) | M19: =ROUND((O18)*(IF('Your Debts'!$G$8=0,0,INDEX('Your Debts'!$C$5:$C$12,'Your Debts'!$G$8)/12)),2) | N19: =MIN((O18)+M19,MAX(0,$C19-(E19+H19+K19))) | O19: =ROUND(MAX(0,(O18)+M19-N19),2) | P19: =ROUND((R18)*(IF('Your Debts'!$G$9=0,0,INDEX('Your Debts'!$C$5:$C$12,'Your Debts'!$G$9)/12)),2) | Q19: =MIN((R18)+P19,MAX(0,$C19-(E19+H19+K19+N19))) | R19: =ROUND(MAX(0,(R18)+P19-Q19),2) | S19: =ROUND((U18)*(IF('Your Debts'!$G$10=0,0,INDEX('Your Debts'!$C$5:$C$12,'Your Debts'!$G$10)/12)),2) | T19: =MIN((U18)+S19,MAX(0,$C19-(E19+H19+K19+N19+Q19))) | U19: =ROUND(MAX(0,(U18)+S19-T19),2) | V19: =ROUND((X18)*(IF('Your Debts'!$G$11=0,0,INDEX('Your Debts'!$C$5:$C$12,'Your Debts'!$G$11)/12)),2) | W19: =MIN((X18)+V19,MAX(0,$C19-(E19+H19+K19+N19+Q19+T19))) | X19: =ROUND(MAX(0,(X18)+V19-W19),2) | Y19: =ROUND((AA18)*(IF('Your Debts'!$G$12=0,0,INDEX('Your Debts'!$C$5:$C$12,'Your Debts'!$G$12)/12)),2) | Z19: =MIN((AA18)+Y19,MAX(0,$C19-(E19+H19+K19+N19+Q19+T19+W19))) | AA19: =ROUND(MAX(0,(AA18)+Y19-Z19),2) | AB19: =F19+I19+L19+O19+R19+U19+X19+AA19 | AC19: =AC18+D19+G19+J19+M19+P19+S19+V19+Y19
A20: 15 | B20: =EDATE('Your Debts'!$B$19,14) | C20: ='Your Debts'!$B$18 | D20: =ROUND((F19)*(IF('Your Debts'!$G$5=0,0,INDEX('Your Debts'!$C$5:$C$12,'Your Debts'!$G$5)/12)),2) | E20: =MIN((F19)+D20,MAX(0,$C20-(0))) | F20: =ROUND(MAX(0,(F19)+D20-E20),2) | G20: =ROUND((I19)*(IF('Your Debts'!$G$6=0,0,INDEX('Your Debts'!$C$5:$C$12,'Your Debts'!$G$6)/12)),2) | H20: =MIN((I19)+G20,MAX(0,$C20-(E20))) | I20: =ROUND(MAX(0,(I19)+G20-H20),2) | J20: =ROUND((L19)*(IF('Your Debts'!$G$7=0,0,INDEX('Your Debts'!$C$5:$C$12,'Your Debts'!$G$7)/12)),2) | K20: =MIN((L19)+J20,MAX(0,$C20-(E20+H20))) | L20: =ROUND(MAX(0,(L19)+J20-K20),2) | M20: =ROUND((O19)*(IF('Your Debts'!$G$8=0,0,INDEX('Your Debts'!$C$5:$C$12,'Your Debts'!$G$8)/12)),2) | N20: =MIN((O19)+M20,MAX(0,$C20-(E20+H20+K20))) | O20: =ROUND(MAX(0,(O19)+M20-N20),2) | P20: =ROUND((R19)*(IF('Your Debts'!$G$9=0,0,INDEX('Your Debts'!$C$5:$C$12,'Your Debts'!$G$9)/12)),2) | Q20: =MIN((R19)+P20,MAX(0,$C20-(E20+H20+K20+N20))) | R20: =ROUND(MAX(0,(R19)+P20-Q20),2) | S20: =ROUND((U19)*(IF('Your Debts'!$G$10=0,0,INDEX('Your Debts'!$C$5:$C$12,'Your Debts'!$G$10)/12)),2) | T20: =MIN((U19)+S20,MAX(0,$C20-(E20+H20+K20+N20+Q20))) | U20: =ROUND(MAX(0,(U19)+S20-T20),2) | V20: =ROUND((X19)*(IF('Your Debts'!$G$11=0,0,INDEX('Your Debts'!$C$5:$C$12,'Your Debts'!$G$11)/12)),2) | W20: =MIN((X19)+V20,MAX(0,$C20-(E20+H20+K20+N20+Q20+T20))) | X20: =ROUND(MAX(0,(X19)+V20-W20),2) | Y20: =ROUND((AA19)*(IF('Your Debts'!$G$12=0,0,INDEX('Your Debts'!$C$5:$C$12,'Your Debts'!$G$12)/12)),2) | Z20: =MIN((AA19)+Y20,MAX(0,$C20-(E20+H20+K20+N20+Q20+T20+W20))) | AA20: =ROUND(MAX(0,(AA19)+Y20-Z20),2) | AB20: =F20+I20+L20+O20+R20+U20+X20+AA20 | AC20: =AC19+D20+G20+J20+M20+P20+S20+V20+Y20
A21: 16 | B21: =EDATE('Your Debts'!$B$19,15) | C21: ='Your Debts'!$B$18 | D21: =ROUND((F20)*(IF('Your Debts'!$G$5=0,0,INDEX('Your Debts'!$C$5:$C$12,'Your Debts'!$G$5)/12)),2) | E21: =MIN((F20)+D21,MAX(0,$C21-(0))) | F21: =ROUND(MAX(0,(F20)+D21-E21),2) | G21: =ROUND((I20)*(IF('Your Debts'!$G$6=0,0,INDEX('Your Debts'!$C$5:$C$12,'Your Debts'!$G$6)/12)),2) | H21: =MIN((I20)+G21,MAX(0,$C21-(E21))) | I21: =ROUND(MAX(0,(I20)+G21-H21),2) | J21: =ROUND((L20)*(IF('Your Debts'!$G$7=0,0,INDEX('Your Debts'!$C$5:$C$12,'Your Debts'!$G$7)/12)),2) | K21: =MIN((L20)+J21,MAX(0,$C21-(E21+H21))) | L21: =ROUND(MAX(0,(L20)+J21-K21),2) | M21: =ROUND((O20)*(IF('Your Debts'!$G$8=0,0,INDEX('Your Debts'!$C$5:$C$12,'Your Debts'!$G$8)/12)),2) | N21: =MIN((O20)+M21,MAX(0,$C21-(E21+H21+K21))) | O21: =ROUND(MAX(0,(O20)+M21-N21),2) | P21: =ROUND((R20)*(IF('Your Debts'!$G$9=0,0,INDEX('Your Debts'!$C$5:$C$12,'Your Debts'!$G$9)/12)),2) | Q21: =MIN((R20)+P21,MAX(0,$C21-(E21+H21+K21+N21))) | R21: =ROUND(MAX(0,(R20)+P21-Q21),2) | S21: =ROUND((U20)*(IF('Your Debts'!$G$10=0,0,INDEX('Your Debts'!$C$5:$C$12,'Your Debts'!$G$10)/12)),2) | T21: =MIN((U20)+S21,MAX(0,$C21-(E21+H21+K21+N21+Q21))) | U21: =ROUND(MAX(0,(U20)+S21-T21),2) | V21: =ROUND((X20)*(IF('Your Debts'!$G$11=0,0,INDEX('Your Debts'!$C$5:$C$12,'Your Debts'!$G$11)/12)),2) | W21: =MIN((X20)+V21,MAX(0,$C21-(E21+H21+K21+N21+Q21+T21))) | X21: =ROUND(MAX(0,(X20)+V21-W21),2) | Y21: =ROUND((AA20)*(IF('Your Debts'!$G$12=0,0,INDEX('Your Debts'!$C$5:$C$12,'Your Debts'!$G$12)/12)),2) | Z21: =MIN((AA20)+Y21,MAX(0,$C21-(E21+H21+K21+N21+Q21+T21+W21))) | AA21: =ROUND(MAX(0,(AA20)+Y21-Z21),2) | AB21: =F21+I21+L21+O21+R21+U21+X21+AA21 | AC21: =AC20+D21+G21+J21+M21+P21+S21+V21+Y21
A22: 17 | B22: =EDATE('Your Debts'!$B$19,16) | C22: ='Your Debts'!$B$18 | D22: =ROUND((F21)*(IF('Your Debts'!$G$5=0,0,INDEX('Your Debts'!$C$5:$C$12,'Your Debts'!$G$5)/12)),2) | E22: =MIN((F21)+D22,MAX(0,$C22-(0))) | F22: =ROUND(MAX(0,(F21)+D22-E22),2) | G22: =ROUND((I21)*(IF('Your Debts'!$G$6=0,0,INDEX('Your Debts'!$C$5:$C$12,'Your Debts'!$G$6)/12)),2) | H22: =MIN((I21)+G22,MAX(0,$C22-(E22))) | I22: =ROUND(MAX(0,(I21)+G22-H22),2) | J22: =ROUND((L21)*(IF('Your Debts'!$G$7=0,0,INDEX('Your Debts'!$C$5:$C$12,'Your Debts'!$G$7)/12)),2) | K22: =MIN((L21)+J22,MAX(0,$C22-(E22+H22))) | L22: =ROUND(MAX(0,(L21)+J22-K22),2) | M22: =ROUND((O21)*(IF('Your Debts'!$G$8=0,0,INDEX('Your Debts'!$C$5:$C$12,'Your Debts'!$G$8)/12)),2) | N22: =MIN((O21)+M22,MAX(0,$C22-(E22+H22+K22))) | O22: =ROUND(MAX(0,(O21)+M22-N22),2) | P22: =ROUND((R21)*(IF('Your Debts'!$G$9=0,0,INDEX('Your Debts'!$C$5:$C$12,'Your Debts'!$G$9)/12)),2) | Q22: =MIN((R21)+P22,MAX(0,$C22-(E22+H22+K22+N22))) | R22: =ROUND(MAX(0,(R21)+P22-Q22),2) | S22: =ROUND((U21)*(IF('Your Debts'!$G$10=0,0,INDEX('Your Debts'!$C$5:$C$12,'Your Debts'!$G$10)/12)),2) | T22: =MIN((U21)+S22,MAX(0,$C22-(E22+H22+K22+N22+Q22))) | U22: =ROUND(MAX(0,(U21)+S22-T22),2) | V22: =ROUND((X21)*(IF('Your Debts'!$G$11=0,0,INDEX('Your Debts'!$C$5:$C$12,'Your Debts'!$G$11)/12)),2) | W22: =MIN((X21)+V22,MAX(0,$C22-(E22+H22+K22+N22+Q22+T22))) | X22: =ROUND(MAX(0,(X21)+V22-W22),2) | Y22: =ROUND((AA21)*(IF('Your Debts'!$G$12=0,0,INDEX('Your Debts'!$C$5:$C$12,'Your Debts'!$G$12)/12)),2) | Z22: =MIN((AA21)+Y22,MAX(0,$C22-(E22+H22+K22+N22+Q22+T22+W22))) | AA22: =ROUND(MAX(0,(AA21)+Y22-Z22),2) | AB22: =F22+I22+L22+O22+R22+U22+X22+AA22 | AC22: =AC21+D22+G22+J22+M22+P22+S22+V22+Y22
A23: 18 | B23: =EDATE('Your Debts'!$B$19,17) | C23: ='Your Debts'!$B$18 | D23: =ROUND((F22)*(IF('Your Debts'!$G$5=0,0,INDEX('Your Debts'!$C$5:$C$12,'Your Debts'!$G$5)/12)),2) | E23: =MIN((F22)+D23,MAX(0,$C23-(0))) | F23: =ROUND(MAX(0,(F22)+D23-E23),2) | G23: =ROUND((I22)*(IF('Your Debts'!$G$6=0,0,INDEX('Your Debts'!$C$5:$C$12,'Your Debts'!$G$6)/12)),2) | H23: =MIN((I22)+G23,MAX(0,$C23-(E23))) | I23: =ROUND(MAX(0,(I22)+G23-H23),2) | J23: =ROUND((L22)*(IF('Your Debts'!$G$7=0,0,INDEX('Your Debts'!$C$5:$C$12,'Your Debts'!$G$7)/12)),2) | K23: =MIN((L22)+J23,MAX(0,$C23-(E23+H23))) | L23: =ROUND(MAX(0,(L22)+J23-K23),2) | M23: =ROUND((O22)*(IF('Your Debts'!$G$8=0,0,INDEX('Your Debts'!$C$5:$C$12,'Your Debts'!$G$8)/12)),2) | N23: =MIN((O22)+M23,MAX(0,$C23-(E23+H23+K23))) | O23: =ROUND(MAX(0,(O22)+M23-N23),2) | P23: =ROUND((R22)*(IF('Your Debts'!$G$9=0,0,INDEX('Your Debts'!$C$5:$C$12,'Your Debts'!$G$9)/12)),2) | Q23: =MIN((R22)+P23,MAX(0,$C23-(E23+H23+K23+N23))) | R23: =ROUND(MAX(0,(R22)+P23-Q23),2) | S23: =ROUND((U22)*(IF('Your Debts'!$G$10=0,0,INDEX('Your Debts'!$C$5:$C$12,'Your Debts'!$G$10)/12)),2) | T23: =MIN((U22)+S23,MAX(0,$C23-(E23+H23+K23+N23+Q23))) | U23: =ROUND(MAX(0,(U22)+S23-T23),2) | V23: =ROUND((X22)*(IF('Your Debts'!$G$11=0,0,INDEX('Your Debts'!$C$5:$C$12,'Your Debts'!$G$11)/12)),2) | W23: =MIN((X22)+V23,MAX(0,$C23-(E23+H23+K23+N23+Q23+T23))) | X23: =ROUND(MAX(0,(X22)+V23-W23),2) | Y23: =ROUND((AA22)*(IF('Your Debts'!$G$12=0,0,INDEX('Your Debts'!$C$5:$C$12,'Your Debts'!$G$12)/12)),2) | Z23: =MIN((AA22)+Y23,MAX(0,$C23-(E23+H23+K23+N23+Q23+T23+W23))) | AA23: =ROUND(MAX(0,(AA22)+Y23-Z23),2) | AB23: =F23+I23+L23+O23+R23+U23+X23+AA23 | AC23: =AC22+D23+G23+J23+M23+P23+S23+V23+Y23
A24: 19 | B24: =EDATE('Your Debts'!$B$19,18) | C24: ='Your Debts'!$B$18 | D24: =ROUND((F23)*(IF('Your Debts'!$G$5=0,0,INDEX('Your Debts'!$C$5:$C$12,'Your Debts'!$G$5)/12)),2) | E24: =MIN((F23)+D24,MAX(0,$C24-(0))) | F24: =ROUND(MAX(0,(F23)+D24-E24),2) | G24: =ROUND((I23)*(IF('Your Debts'!$G$6=0,0,INDEX('Your Debts'!$C$5:$C$12,'Your Debts'!$G$6)/12)),2) | H24: =MIN((I23)+G24,MAX(0,$C24-(E24))) | I24: =ROUND(MAX(0,(I23)+G24-H24),2) | J24: =ROUND((L23)*(IF('Your Debts'!$G$7=0,0,INDEX('Your Debts'!$C$5:$C$12,'Your Debts'!$G$7)/12)),2) | K24: =MIN((L23)+J24,MAX(0,$C24-(E24+H24))) | L24: =ROUND(MAX(0,(L23)+J24-K24),2) | M24: =ROUND((O23)*(IF('Your Debts'!$G$8=0,0,INDEX('Your Debts'!$C$5:$C$12,'Your Debts'!$G$8)/12)),2) | N24: =MIN((O23)+M24,MAX(0,$C24-(E24+H24+K24))) | O24: =ROUND(MAX(0,(O23)+M24-N24),2) | P24: =ROUND((R23)*(IF('Your Debts'!$G$9=0,0,INDEX('Your Debts'!$C$5:$C$12,'Your Debts'!$G$9)/12)),2) | Q24: =MIN((R23)+P24,MAX(0,$C24-(E24+H24+K24+N24))) | R24: =ROUND(MAX(0,(R23)+P24-Q24),2) | S24: =ROUND((U23)*(IF('Your Debts'!$G$10=0,0,INDEX('Your Debts'!$C$5:$C$12,'Your Debts'!$G$10)/12)),2) | T24: =MIN((U23)+S24,MAX(0,$C24-(E24+H24+K24+N24+Q24))) | U24: =ROUND(MAX(0,(U23)+S24-T24),2) | V24: =ROUND((X23)*(IF('Your Debts'!$G$11=0,0,INDEX('Your Debts'!$C$5:$C$12,'Your Debts'!$G$11)/12)),2) | W24: =MIN((X23)+V24,MAX(0,$C24-(E24+H24+K24+N24+Q24+T24))) | X24: =ROUND(MAX(0,(X23)+V24-W24),2) | Y24: =ROUND((AA23)*(IF('Your Debts'!$G$12=0,0,INDEX('Your Debts'!$C$5:$C$12,'Your Debts'!$G$12)/12)),2) | Z24: =MIN((AA23)+Y24,MAX(0,$C24-(E24+H24+K24+N24+Q24+T24+W24))) | AA24: =ROUND(MAX(0,(AA23)+Y24-Z24),2) | AB24: =F24+I24+L24+O24+R24+U24+X24+AA24 | AC24: =AC23+D24+G24+J24+M24+P24+S24+V24+Y24
A25: 20 | B25: =EDATE('Your Debts'!$B$19,19) | C25: ='Your Debts'!$B$18 | D25: =ROUND((F24)*(IF('Your Debts'!$G$5=0,0,INDEX('Your Debts'!$C$5:$C$12,'Your Debts'!$G$5)/12)),2) | E25: =MIN((F24)+D25,MAX(0,$C25-(0))) | F25: =ROUND(MAX(0,(F24)+D25-E25),2) | G25: =ROUND((I24)*(IF('Your Debts'!$G$6=0,0,INDEX('Your Debts'!$C$5:$C$12,'Your Debts'!$G$6)/12)),2) | H25: =MIN((I24)+G25,MAX(0,$C25-(E25))) | I25: =ROUND(MAX(0,(I24)+G25-H25),2) | J25: =ROUND((L24)*(IF('Your Debts'!$G$7=0,0,INDEX('Your Debts'!$C$5:$C$12,'Your Debts'!$G$7)/12)),2) | K25: =MIN((L24)+J25,MAX(0,$C25-(E25+H25))) | L25: =ROUND(MAX(0,(L24)+J25-K25),2) | M25: =ROUND((O24)*(IF('Your Debts'!$G$8=0,0,INDEX('Your Debts'!$C$5:$C$12,'Your Debts'!$G$8)/12)),2) | N25: =MIN((O24)+M25,MAX(0,$C25-(E25+H25+K25))) | O25: =ROUND(MAX(0,(O24)+M25-N25),2) | P25: =ROUND((R24)*(IF('Your Debts'!$G$9=0,0,INDEX('Your Debts'!$C$5:$C$12,'Your Debts'!$G$9)/12)),2) | Q25: =MIN((R24)+P25,MAX(0,$C25-(E25+H25+K25+N25))) | R25: =ROUND(MAX(0,(R24)+P25-Q25),2) | S25: =ROUND((U24)*(IF('Your Debts'!$G$10=0,0,INDEX('Your Debts'!$C$5:$C$12,'Your Debts'!$G$10)/12)),2) | T25: =MIN((U24)+S25,MAX(0,$C25-(E25+H25+K25+N25+Q25))) | U25: =ROUND(MAX(0,(U24)+S25-T25),2) | V25: =ROUND((X24)*(IF('Your Debts'!$G$11=0,0,INDEX('Your Debts'!$C$5:$C$12,'Your Debts'!$G$11)/12)),2) | W25: =MIN((X24)+V25,MAX(0,$C25-(E25+H25+K25+N25+Q25+T25))) | X25: =ROUND(MAX(0,(X24)+V25-W25),2) | Y25: =ROUND((AA24)*(IF('Your Debts'!$G$12=0,0,INDEX('Your Debts'!$C$5:$C$12,'Your Debts'!$G$12)/12)),2) | Z25: =MIN((AA24)+Y25,MAX(0,$C25-(E25+H25+K25+N25+Q25+T25+W25))) | AA25: =ROUND(MAX(0,(AA24)+Y25-Z25),2) | AB25: =F25+I25+L25+O25+R25+U25+X25+AA25 | AC25: =AC24+D25+G25+J25+M25+P25+S25+V25+Y25
A26: 21 | B26: =EDATE('Your Debts'!$B$19,20) | C26: ='Your Debts'!$B$18 | D26: =ROUND((F25)*(IF('Your Debts'!$G$5=0,0,INDEX('Your Debts'!$C$5:$C$12,'Your Debts'!$G$5)/12)),2) | E26: =MIN((F25)+D26,MAX(0,$C26-(0))) | F26: =ROUND(MAX(0,(F25)+D26-E26),2) | G26: =ROUND((I25)*(IF('Your Debts'!$G$6=0,0,INDEX('Your Debts'!$C$5:$C$12,'Your Debts'!$G$6)/12)),2) | H26: =MIN((I25)+G26,MAX(0,$C26-(E26))) | I26: =ROUND(MAX(0,(I25)+G26-H26),2) | J26: =ROUND((L25)*(IF('Your Debts'!$G$7=0,0,INDEX('Your Debts'!$C$5:$C$12,'Your Debts'!$G$7)/12)),2) | K26: =MIN((L25)+J26,MAX(0,$C26-(E26+H26))) | L26: =ROUND(MAX(0,(L25)+J26-K26),2) | M26: =ROUND((O25)*(IF('Your Debts'!$G$8=0,0,INDEX('Your Debts'!$C$5:$C$12,'Your Debts'!$G$8)/12)),2) | N26: =MIN((O25)+M26,MAX(0,$C26-(E26+H26+K26))) | O26: =ROUND(MAX(0,(O25)+M26-N26),2) | P26: =ROUND((R25)*(IF('Your Debts'!$G$9=0,0,INDEX('Your Debts'!$C$5:$C$12,'Your Debts'!$G$9)/12)),2) | Q26: =MIN((R25)+P26,MAX(0,$C26-(E26+H26+K26+N26))) | R26: =ROUND(MAX(0,(R25)+P26-Q26),2) | S26: =ROUND((U25)*(IF('Your Debts'!$G$10=0,0,INDEX('Your Debts'!$C$5:$C$12,'Your Debts'!$G$10)/12)),2) | T26: =MIN((U25)+S26,MAX(0,$C26-(E26+H26+K26+N26+Q26))) | U26: =ROUND(MAX(0,(U25)+S26-T26),2) | V26: =ROUND((X25)*(IF('Your Debts'!$G$11=0,0,INDEX('Your Debts'!$C$5:$C$12,'Your Debts'!$G$11)/12)),2) | W26: =MIN((X25)+V26,MAX(0,$C26-(E26+H26+K26+N26+Q26+T26))) | X26: =ROUND(MAX(0,(X25)+V26-W26),2) | Y26: =ROUND((AA25)*(IF('Your Debts'!$G$12=0,0,INDEX('Your Debts'!$C$5:$C$12,'Your Debts'!$G$12)/12)),2) | Z26: =MIN((AA25)+Y26,MAX(0,$C26-(E26+H26+K26+N26+Q26+T26+W26))) | AA26: =ROUND(MAX(0,(AA25)+Y26-Z26),2) | AB26: =F26+I26+L26+O26+R26+U26+X26+AA26 | AC26: =AC25+D26+G26+J26+M26+P26+S26+V26+Y26
A27: 22 | B27: =EDATE('Your Debts'!$B$19,21) | C27: ='Your Debts'!$B$18 | D27: =ROUND((F26)*(IF('Your Debts'!$G$5=0,0,INDEX('Your Debts'!$C$5:$C$12,'Your Debts'!$G$5)/12)),2) | E27: =MIN((F26)+D27,MAX(0,$C27-(0))) | F27: =ROUND(MAX(0,(F26)+D27-E27),2) | G27: =ROUND((I26)*(IF('Your Debts'!$G$6=0,0,INDEX('Your Debts'!$C$5:$C$12,'Your Debts'!$G$6)/12)),2) | H27: =MIN((I26)+G27,MAX(0,$C27-(E27))) | I27: =ROUND(MAX(0,(I26)+G27-H27),2) | J27: =ROUND((L26)*(IF('Your Debts'!$G$7=0,0,INDEX('Your Debts'!$C$5:$C$12,'Your Debts'!$G$7)/12)),2) | K27: =MIN((L26)+J27,MAX(0,$C27-(E27+H27))) | L27: =ROUND(MAX(0,(L26)+J27-K27),2) | M27: =ROUND((O26)*(IF('Your Debts'!$G$8=0,0,INDEX('Your Debts'!$C$5:$C$12,'Your Debts'!$G$8)/12)),2) | N27: =MIN((O26)+M27,MAX(0,$C27-(E27+H27+K27))) | O27: =ROUND(MAX(0,(O26)+M27-N27),2) | P27: =ROUND((R26)*(IF('Your Debts'!$G$9=0,0,INDEX('Your Debts'!$C$5:$C$12,'Your Debts'!$G$9)/12)),2) | Q27: =MIN((R26)+P27,MAX(0,$C27-(E27+H27+K27+N27))) | R27: =ROUND(MAX(0,(R26)+P27-Q27),2) | S27: =ROUND((U26)*(IF('Your Debts'!$G$10=0,0,INDEX('Your Debts'!$C$5:$C$12,'Your Debts'!$G$10)/12)),2) | T27: =MIN((U26)+S27,MAX(0,$C27-(E27+H27+K27+N27+Q27))) | U27: =ROUND(MAX(0,(U26)+S27-T27),2) | V27: =ROUND((X26)*(IF('Your Debts'!$G$11=0,0,INDEX('Your Debts'!$C$5:$C$12,'Your Debts'!$G$11)/12)),2) | W27: =MIN((X26)+V27,MAX(0,$C27-(E27+H27+K27+N27+Q27+T27))) | X27: =ROUND(MAX(0,(X26)+V27-W27),2) | Y27: =ROUND((AA26)*(IF('Your Debts'!$G$12=0,0,INDEX('Your Debts'!$C$5:$C$12,'Your Debts'!$G$12)/12)),2) | Z27: =MIN((AA26)+Y27,MAX(0,$C27-(E27+H27+K27+N27+Q27+T27+W27))) | AA27: =ROUND(MAX(0,(AA26)+Y27-Z27),2) | AB27: =F27+I27+L27+O27+R27+U27+X27+AA27 | AC27: =AC26+D27+G27+J27+M27+P27+S27+V27+Y27
A28: 23 | B28: =EDATE('Your Debts'!$B$19,22) | C28: ='Your Debts'!$B$18 | D28: =ROUND((F27)*(IF('Your Debts'!$G$5=0,0,INDEX('Your Debts'!$C$5:$C$12,'Your Debts'!$G$5)/12)),2) | E28: =MIN((F27)+D28,MAX(0,$C28-(0))) | F28: =ROUND(MAX(0,(F27)+D28-E28),2) | G28: =ROUND((I27)*(IF('Your Debts'!$G$6=0,0,INDEX('Your Debts'!$C$5:$C$12,'Your Debts'!$G$6)/12)),2) | H28: =MIN((I27)+G28,MAX(0,$C28-(E28))) | I28: =ROUND(MAX(0,(I27)+G28-H28),2) | J28: =ROUND((L27)*(IF('Your Debts'!$G$7=0,0,INDEX('Your Debts'!$C$5:$C$12,'Your Debts'!$G$7)/12)),2) | K28: =MIN((L27)+J28,MAX(0,$C28-(E28+H28))) | L28: =ROUND(MAX(0,(L27)+J28-K28),2) | M28: =ROUND((O27)*(IF('Your Debts'!$G$8=0,0,INDEX('Your Debts'!$C$5:$C$12,'Your Debts'!$G$8)/12)),2) | N28: =MIN((O27)+M28,MAX(0,$C28-(E28+H28+K28))) | O28: =ROUND(MAX(0,(O27)+M28-N28),2) | P28: =ROUND((R27)*(IF('Your Debts'!$G$9=0,0,INDEX('Your Debts'!$C$5:$C$12,'Your Debts'!$G$9)/12)),2) | Q28: =MIN((R27)+P28,MAX(0,$C28-(E28+H28+K28+N28))) | R28: =ROUND(MAX(0,(R27)+P28-Q28),2) | S28: =ROUND((U27)*(IF('Your Debts'!$G$10=0,0,INDEX('Your Debts'!$C$5:$C$12,'Your Debts'!$G$10)/12)),2) | T28: =MIN((U27)+S28,MAX(0,$C28-(E28+H28+K28+N28+Q28))) | U28: =ROUND(MAX(0,(U27)+S28-T28),2) | V28: =ROUND((X27)*(IF('Your Debts'!$G$11=0,0,INDEX('Your Debts'!$C$5:$C$12,'Your Debts'!$G$11)/12)),2) | W28: =MIN((X27)+V28,MAX(0,$C28-(E28+H28+K28+N28+Q28+T28))) | X28: =ROUND(MAX(0,(X27)+V28-W28),2) | Y28: =ROUND((AA27)*(IF('Your Debts'!$G$12=0,0,INDEX('Your Debts'!$C$5:$C$12,'Your Debts'!$G$12)/12)),2) | Z28: =MIN((AA27)+Y28,MAX(0,$C28-(E28+H28+K28+N28+Q28+T28+W28))) | AA28: =ROUND(MAX(0,(AA27)+Y28-Z28),2) | AB28: =F28+I28+L28+O28+R28+U28+X28+AA28 | AC28: =AC27+D28+G28+J28+M28+P28+S28+V28+Y28
A29: 24 | B29: =EDATE('Your Debts'!$B$19,23) | C29: ='Your Debts'!$B$18 | D29: =ROUND((F28)*(IF('Your Debts'!$G$5=0,0,INDEX('Your Debts'!$C$5:$C$12,'Your Debts'!$G$5)/12)),2) | E29: =MIN((F28)+D29,MAX(0,$C29-(0))) | F29: =ROUND(MAX(0,(F28)+D29-E29),2) | G29: =ROUND((I28)*(IF('Your Debts'!$G$6=0,0,INDEX('Your Debts'!$C$5:$C$12,'Your Debts'!$G$6)/12)),2) | H29: =MIN((I28)+G29,MAX(0,$C29-(E29))) | I29: =ROUND(MAX(0,(I28)+G29-H29),2) | J29: =ROUND((L28)*(IF('Your Debts'!$G$7=0,0,INDEX('Your Debts'!$C$5:$C$12,'Your Debts'!$G$7)/12)),2) | K29: =MIN((L28)+J29,MAX(0,$C29-(E29+H29))) | L29: =ROUND(MAX(0,(L28)+J29-K29),2) | M29: =ROUND((O28)*(IF('Your Debts'!$G$8=0,0,INDEX('Your Debts'!$C$5:$C$12,'Your Debts'!$G$8)/12)),2) | N29: =MIN((O28)+M29,MAX(0,$C29-(E29+H29+K29))) | O29: =ROUND(MAX(0,(O28)+M29-N29),2) | P29: =ROUND((R28)*(IF('Your Debts'!$G$9=0,0,INDEX('Your Debts'!$C$5:$C$12,'Your Debts'!$G$9)/12)),2) | Q29: =MIN((R28)+P29,MAX(0,$C29-(E29+H29+K29+N29))) | R29: =ROUND(MAX(0,(R28)+P29-Q29),2) | S29: =ROUND((U28)*(IF('Your Debts'!$G$10=0,0,INDEX('Your Debts'!$C$5:$C$12,'Your Debts'!$G$10)/12)),2) | T29: =MIN((U28)+S29,MAX(0,$C29-(E29+H29+K29+N29+Q29))) | U29: =ROUND(MAX(0,(U28)+S29-T29),2) | V29: =ROUND((X28)*(IF('Your Debts'!$G$11=0,0,INDEX('Your Debts'!$C$5:$C$12,'Your Debts'!$G$11)/12)),2) | W29: =MIN((X28)+V29,MAX(0,$C29-(E29+H29+K29+N29+Q29+T29))) | X29: =ROUND(MAX(0,(X28)+V29-W29),2) | Y29: =ROUND((AA28)*(IF('Your Debts'!$G$12=0,0,INDEX('Your Debts'!$C$5:$C$12,'Your Debts'!$G$12)/12)),2) | Z29: =MIN((AA28)+Y29,MAX(0,$C29-(E29+H29+K29+N29+Q29+T29+W29))) | AA29: =ROUND(MAX(0,(AA28)+Y29-Z29),2) | AB29: =F29+I29+L29+O29+R29+U29+X29+AA29 | AC29: =AC28+D29+G29+J29+M29+P29+S29+V29+Y29
A30: 25 | B30: =EDATE('Your Debts'!$B$19,24) | C30: ='Your Debts'!$B$18 | D30: =ROUND((F29)*(IF('Your Debts'!$G$5=0,0,INDEX('Your Debts'!$C$5:$C$12,'Your Debts'!$G$5)/12)),2) | E30: =MIN((F29)+D30,MAX(0,$C30-(0))) | F30: =ROUND(MAX(0,(F29)+D30-E30),2) | G30: =ROUND((I29)*(IF('Your Debts'!$G$6=0,0,INDEX('Your Debts'!$C$5:$C$12,'Your Debts'!$G$6)/12)),2) | H30: =MIN((I29)+G30,MAX(0,$C30-(E30))) | I30: =ROUND(MAX(0,(I29)+G30-H30),2) | J30: =ROUND((L29)*(IF('Your Debts'!$G$7=0,0,INDEX('Your Debts'!$C$5:$C$12,'Your Debts'!$G$7)/12)),2) | K30: =MIN((L29)+J30,MAX(0,$C30-(E30+H30))) | L30: =ROUND(MAX(0,(L29)+J30-K30),2) | M30: =ROUND((O29)*(IF('Your Debts'!$G$8=0,0,INDEX('Your Debts'!$C$5:$C$12,'Your Debts'!$G$8)/12)),2) | N30: =MIN((O29)+M30,MAX(0,$C30-(E30+H30+K30))) | O30: =ROUND(MAX(0,(O29)+M30-N30),2) | P30: =ROUND((R29)*(IF('Your Debts'!$G$9=0,0,INDEX('Your Debts'!$C$5:$C$12,'Your Debts'!$G$9)/12)),2) | Q30: =MIN((R29)+P30,MAX(0,$C30-(E30+H30+K30+N30))) | R30: =ROUND(MAX(0,(R29)+P30-Q30),2) | S30: =ROUND((U29)*(IF('Your Debts'!$G$10=0,0,INDEX('Your Debts'!$C$5:$C$12,'Your Debts'!$G$10)/12)),2) | T30: =MIN((U29)+S30,MAX(0,$C30-(E30+H30+K30+N30+Q30))) | U30: =ROUND(MAX(0,(U29)+S30-T30),2) | V30: =ROUND((X29)*(IF('Your Debts'!$G$11=0,0,INDEX('Your Debts'!$C$5:$C$12,'Your Debts'!$G$11)/12)),2) | W30: =MIN((X29)+V30,MAX(0,$C30-(E30+H30+K30+N30+Q30+T30))) | X30: =ROUND(MAX(0,(X29)+V30-W30),2) | Y30: =ROUND((AA29)*(IF('Your Debts'!$G$12=0,0,INDEX('Your Debts'!$C$5:$C$12,'Your Debts'!$G$12)/12)),2) | Z30: =MIN((AA29)+Y30,MAX(0,$C30-(E30+H30+K30+N30+Q30+T30+W30))) | AA30: =ROUND(MAX(0,(AA29)+Y30-Z30),2) | AB30: =F30+I30+L30+O30+R30+U30+X30+AA30 | AC30: =AC29+D30+G30+J30+M30+P30+S30+V30+Y30
A31: 26 | B31: =EDATE('Your Debts'!$B$19,25) | C31: ='Your Debts'!$B$18 | D31: =ROUND((F30)*(IF('Your Debts'!$G$5=0,0,INDEX('Your Debts'!$C$5:$C$12,'Your Debts'!$G$5)/12)),2) | E31: =MIN((F30)+D31,MAX(0,$C31-(0))) | F31: =ROUND(MAX(0,(F30)+D31-E31),2) | G31: =ROUND((I30)*(IF('Your Debts'!$G$6=0,0,INDEX('Your Debts'!$C$5:$C$12,'Your Debts'!$G$6)/12)),2) | H31: =MIN((I30)+G31,MAX(0,$C31-(E31))) | I31: =ROUND(MAX(0,(I30)+G31-H31),2) | J31: =ROUND((L30)*(IF('Your Debts'!$G$7=0,0,INDEX('Your Debts'!$C$5:$C$12,'Your Debts'!$G$7)/12)),2) | K31: =MIN((L30)+J31,MAX(0,$C31-(E31+H31))) | L31: =ROUND(MAX(0,(L30)+J31-K31),2) | M31: =ROUND((O30)*(IF('Your Debts'!$G$8=0,0,INDEX('Your Debts'!$C$5:$C$12,'Your Debts'!$G$8)/12)),2) | N31: =MIN((O30)+M31,MAX(0,$C31-(E31+H31+K31))) | O31: =ROUND(MAX(0,(O30)+M31-N31),2) | P31: =ROUND((R30)*(IF('Your Debts'!$G$9=0,0,INDEX('Your Debts'!$C$5:$C$12,'Your Debts'!$G$9)/12)),2) | Q31: =MIN((R30)+P31,MAX(0,$C31-(E31+H31+K31+N31))) | R31: =ROUND(MAX(0,(R30)+P31-Q31),2) | S31: =ROUND((U30)*(IF('Your Debts'!$G$10=0,0,INDEX('Your Debts'!$C$5:$C$12,'Your Debts'!$G$10)/12)),2) | T31: =MIN((U30)+S31,MAX(0,$C31-(E31+H31+K31+N31+Q31))) | U31: =ROUND(MAX(0,(U30)+S31-T31),2) | V31: =ROUND((X30)*(IF('Your Debts'!$G$11=0,0,INDEX('Your Debts'!$C$5:$C$12,'Your Debts'!$G$11)/12)),2) | W31: =MIN((X30)+V31,MAX(0,$C31-(E31+H31+K31+N31+Q31+T31))) | X31: =ROUND(MAX(0,(X30)+V31-W31),2) | Y31: =ROUND((AA30)*(IF('Your Debts'!$G$12=0,0,INDEX('Your Debts'!$C$5:$C$12,'Your Debts'!$G$12)/12)),2) | Z31: =MIN((AA30)+Y31,MAX(0,$C31-(E31+H31+K31+N31+Q31+T31+W31))) | AA31: =ROUND(MAX(0,(AA30)+Y31-Z31),2) | AB31: =F31+I31+L31+O31+R31+U31+X31+AA31 | AC31: =AC30+D31+G31+J31+M31+P31+S31+V31+Y31
A32: 27 | B32: =EDATE('Your Debts'!$B$19,26) | C32: ='Your Debts'!$B$18 | D32: =ROUND((F31)*(IF('Your Debts'!$G$5=0,0,INDEX('Your Debts'!$C$5:$C$12,'Your Debts'!$G$5)/12)),2) | E32: =MIN((F31)+D32,MAX(0,$C32-(0))) | F32: =ROUND(MAX(0,(F31)+D32-E32),2) | G32: =ROUND((I31)*(IF('Your Debts'!$G$6=0,0,INDEX('Your Debts'!$C$5:$C$12,'Your Debts'!$G$6)/12)),2) | H32: =MIN((I31)+G32,MAX(0,$C32-(E32))) | I32: =ROUND(MAX(0,(I31)+G32-H32),2) | J32: =ROUND((L31)*(IF('Your Debts'!$G$7=0,0,INDEX('Your Debts'!$C$5:$C$12,'Your Debts'!$G$7)/12)),2) | K32: =MIN((L31)+J32,MAX(0,$C32-(E32+H32))) | L32: =ROUND(MAX(0,(L31)+J32-K32),2) | M32: =ROUND((O31)*(IF('Your Debts'!$G$8=0,0,INDEX('Your Debts'!$C$5:$C$12,'Your Debts'!$G$8)/12)),2) | N32: =MIN((O31)+M32,MAX(0,$C32-(E32+H32+K32))) | O32: =ROUND(MAX(0,(O31)+M32-N32),2) | P32: =ROUND((R31)*(IF('Your Debts'!$G$9=0,0,INDEX('Your Debts'!$C$5:$C$12,'Your Debts'!$G$9)/12)),2) | Q32: =MIN((R31)+P32,MAX(0,$C32-(E32+H32+K32+N32))) | R32: =ROUND(MAX(0,(R31)+P32-Q32),2) | S32: =ROUND((U31)*(IF('Your Debts'!$G$10=0,0,INDEX('Your Debts'!$C$5:$C$12,'Your Debts'!$G$10)/12)),2) | T32: =MIN((U31)+S32,MAX(0,$C32-(E32+H32+K32+N32+Q32))) | U32: =ROUND(MAX(0,(U31)+S32-T32),2) | V32: =ROUND((X31)*(IF('Your Debts'!$G$11=0,0,INDEX('Your Debts'!$C$5:$C$12,'Your Debts'!$G$11)/12)),2) | W32: =MIN((X31)+V32,MAX(0,$C32-(E32+H32+K32+N32+Q32+T32))) | X32: =ROUND(MAX(0,(X31)+V32-W32),2) | Y32: =ROUND((AA31)*(IF('Your Debts'!$G$12=0,0,INDEX('Your Debts'!$C$5:$C$12,'Your Debts'!$G$12)/12)),2) | Z32: =MIN((AA31)+Y32,MAX(0,$C32-(E32+H32+K32+N32+Q32+T32+W32))) | AA32: =ROUND(MAX(0,(AA31)+Y32-Z32),2) | AB32: =F32+I32+L32+O32+R32+U32+X32+AA32 | AC32: =AC31+D32+G32+J32+M32+P32+S32+V32+Y32
A33: 28 | B33: =EDATE('Your Debts'!$B$19,27) | C33: ='Your Debts'!$B$18 | D33: =ROUND((F32)*(IF('Your Debts'!$G$5=0,0,INDEX('Your Debts'!$C$5:$C$12,'Your Debts'!$G$5)/12)),2) | E33: =MIN((F32)+D33,MAX(0,$C33-(0))) | F33: =ROUND(MAX(0,(F32)+D33-E33),2) | G33: =ROUND((I32)*(IF('Your Debts'!$G$6=0,0,INDEX('Your Debts'!$C$5:$C$12,'Your Debts'!$G$6)/12)),2) | H33: =MIN((I32)+G33,MAX(0,$C33-(E33))) | I33: =ROUND(MAX(0,(I32)+G33-H33),2) | J33: =ROUND((L32)*(IF('Your Debts'!$G$7=0,0,INDEX('Your Debts'!$C$5:$C$12,'Your Debts'!$G$7)/12)),2) | K33: =MIN((L32)+J33,MAX(0,$C33-(E33+H33))) | L33: =ROUND(MAX(0,(L32)+J33-K33),2) | M33: =ROUND((O32)*(IF('Your Debts'!$G$8=0,0,INDEX('Your Debts'!$C$5:$C$12,'Your Debts'!$G$8)/12)),2) | N33: =MIN((O32)+M33,MAX(0,$C33-(E33+H33+K33))) | O33: =ROUND(MAX(0,(O32)+M33-N33),2) | P33: =ROUND((R32)*(IF('Your Debts'!$G$9=0,0,INDEX('Your Debts'!$C$5:$C$12,'Your Debts'!$G$9)/12)),2) | Q33: =MIN((R32)+P33,MAX(0,$C33-(E33+H33+K33+N33))) | R33: =ROUND(MAX(0,(R32)+P33-Q33),2) | S33: =ROUND((U32)*(IF('Your Debts'!$G$10=0,0,INDEX('Your Debts'!$C$5:$C$12,'Your Debts'!$G$10)/12)),2) | T33: =MIN((U32)+S33,MAX(0,$C33-(E33+H33+K33+N33+Q33))) | U33: =ROUND(MAX(0,(U32)+S33-T33),2) | V33: =ROUND((X32)*(IF('Your Debts'!$G$11=0,0,INDEX('Your Debts'!$C$5:$C$12,'Your Debts'!$G$11)/12)),2) | W33: =MIN((X32)+V33,MAX(0,$C33-(E33+H33+K33+N33+Q33+T33))) | X33: =ROUND(MAX(0,(X32)+V33-W33),2) | Y33: =ROUND((AA32)*(IF('Your Debts'!$G$12=0,0,INDEX('Your Debts'!$C$5:$C$12,'Your Debts'!$G$12)/12)),2) | Z33: =MIN((AA32)+Y33,MAX(0,$C33-(E33+H33+K33+N33+Q33+T33+W33))) | AA33: =ROUND(MAX(0,(AA32)+Y33-Z33),2) | AB33: =F33+I33+L33+O33+R33+U33+X33+AA33 | AC33: =AC32+D33+G33+J33+M33+P33+S33+V33+Y33
A34: 29 | B34: =EDATE('Your Debts'!$B$19,28) | C34: ='Your Debts'!$B$18 | D34: =ROUND((F33)*(IF('Your Debts'!$G$5=0,0,INDEX('Your Debts'!$C$5:$C$12,'Your Debts'!$G$5)/12)),2) | E34: =MIN((F33)+D34,MAX(0,$C34-(0))) | F34: =ROUND(MAX(0,(F33)+D34-E34),2) | G34: =ROUND((I33)*(IF('Your Debts'!$G$6=0,0,INDEX('Your Debts'!$C$5:$C$12,'Your Debts'!$G$6)/12)),2) | H34: =MIN((I33)+G34,MAX(0,$C34-(E34))) | I34: =ROUND(MAX(0,(I33)+G34-H34),2) | J34: =ROUND((L33)*(IF('Your Debts'!$G$7=0,0,INDEX('Your Debts'!$C$5:$C$12,'Your Debts'!$G$7)/12)),2) | K34: =MIN((L33)+J34,MAX(0,$C34-(E34+H34))) | L34: =ROUND(MAX(0,(L33)+J34-K34),2) | M34: =ROUND((O33)*(IF('Your Debts'!$G$8=0,0,INDEX('Your Debts'!$C$5:$C$12,'Your Debts'!$G$8)/12)),2) | N34: =MIN((O33)+M34,MAX(0,$C34-(E34+H34+K34))) | O34: =ROUND(MAX(0,(O33)+M34-N34),2) | P34: =ROUND((R33)*(IF('Your Debts'!$G$9=0,0,INDEX('Your Debts'!$C$5:$C$12,'Your Debts'!$G$9)/12)),2) | Q34: =MIN((R33)+P34,MAX(0,$C34-(E34+H34+K34+N34))) | R34: =ROUND(MAX(0,(R33)+P34-Q34),2) | S34: =ROUND((U33)*(IF('Your Debts'!$G$10=0,0,INDEX('Your Debts'!$C$5:$C$12,'Your Debts'!$G$10)/12)),2) | T34: =MIN((U33)+S34,MAX(0,$C34-(E34+H34+K34+N34+Q34))) | U34: =ROUND(MAX(0,(U33)+S34-T34),2) | V34: =ROUND((X33)*(IF('Your Debts'!$G$11=0,0,INDEX('Your Debts'!$C$5:$C$12,'Your Debts'!$G$11)/12)),2) | W34: =MIN((X33)+V34,MAX(0,$C34-(E34+H34+K34+N34+Q34+T34))) | X34: =ROUND(MAX(0,(X33)+V34-W34),2) | Y34: =ROUND((AA33)*(IF('Your Debts'!$G$12=0,0,INDEX('Your Debts'!$C$5:$C$12,'Your Debts'!$G$12)/12)),2) | Z34: =MIN((AA33)+Y34,MAX(0,$C34-(E34+H34+K34+N34+Q34+T34+W34))) | AA34: =ROUND(MAX(0,(AA33)+Y34-Z34),2) | AB34: =F34+I34+L34+O34+R34+U34+X34+AA34 | AC34: =AC33+D34+G34+J34+M34+P34+S34+V34+Y34
A35: 30 | B35: =EDATE('Your Debts'!$B$19,29) | C35: ='Your Debts'!$B$18 | D35: =ROUND((F34)*(IF('Your Debts'!$G$5=0,0,INDEX('Your Debts'!$C$5:$C$12,'Your Debts'!$G$5)/12)),2) | E35: =MIN((F34)+D35,MAX(0,$C35-(0))) | F35: =ROUND(MAX(0,(F34)+D35-E35),2) | G35: =ROUND((I34)*(IF('Your Debts'!$G$6=0,0,INDEX('Your Debts'!$C$5:$C$12,'Your Debts'!$G$6)/12)),2) | H35: =MIN((I34)+G35,MAX(0,$C35-(E35))) | I35: =ROUND(MAX(0,(I34)+G35-H35),2) | J35: =ROUND((L34)*(IF('Your Debts'!$G$7=0,0,INDEX('Your Debts'!$C$5:$C$12,'Your Debts'!$G$7)/12)),2) | K35: =MIN((L34)+J35,MAX(0,$C35-(E35+H35))) | L35: =ROUND(MAX(0,(L34)+J35-K35),2) | M35: =ROUND((O34)*(IF('Your Debts'!$G$8=0,0,INDEX('Your Debts'!$C$5:$C$12,'Your Debts'!$G$8)/12)),2) | N35: =MIN((O34)+M35,MAX(0,$C35-(E35+H35+K35))) | O35: =ROUND(MAX(0,(O34)+M35-N35),2) | P35: =ROUND((R34)*(IF('Your Debts'!$G$9=0,0,INDEX('Your Debts'!$C$5:$C$12,'Your Debts'!$G$9)/12)),2) | Q35: =MIN((R34)+P35,MAX(0,$C35-(E35+H35+K35+N35))) | R35: =ROUND(MAX(0,(R34)+P35-Q35),2) | S35: =ROUND((U34)*(IF('Your Debts'!$G$10=0,0,INDEX('Your Debts'!$C$5:$C$12,'Your Debts'!$G$10)/12)),2) | T35: =MIN((U34)+S35,MAX(0,$C35-(E35+H35+K35+N35+Q35))) | U35: =ROUND(MAX(0,(U34)+S35-T35),2) | V35: =ROUND((X34)*(IF('Your Debts'!$G$11=0,0,INDEX('Your Debts'!$C$5:$C$12,'Your Debts'!$G$11)/12)),2) | W35: =MIN((X34)+V35,MAX(0,$C35-(E35+H35+K35+N35+Q35+T35))) | X35: =ROUND(MAX(0,(X34)+V35-W35),2) | Y35: =ROUND((AA34)*(IF('Your Debts'!$G$12=0,0,INDEX('Your Debts'!$C$5:$C$12,'Your Debts'!$G$12)/12)),2) | Z35: =MIN((AA34)+Y35,MAX(0,$C35-(E35+H35+K35+N35+Q35+T35+W35))) | AA35: =ROUND(MAX(0,(AA34)+Y35-Z35),2) | AB35: =F35+I35+L35+O35+R35+U35+X35+AA35 | AC35: =AC34+D35+G35+J35+M35+P35+S35+V35+Y35
A36: 31 | B36: =EDATE('Your Debts'!$B$19,30) | C36: ='Your Debts'!$B$18 | D36: =ROUND((F35)*(IF('Your Debts'!$G$5=0,0,INDEX('Your Debts'!$C$5:$C$12,'Your Debts'!$G$5)/12)),2) | E36: =MIN((F35)+D36,MAX(0,$C36-(0))) | F36: =ROUND(MAX(0,(F35)+D36-E36),2) | G36: =ROUND((I35)*(IF('Your Debts'!$G$6=0,0,INDEX('Your Debts'!$C$5:$C$12,'Your Debts'!$G$6)/12)),2) | H36: =MIN((I35)+G36,MAX(0,$C36-(E36))) | I36: =ROUND(MAX(0,(I35)+G36-H36),2) | J36: =ROUND((L35)*(IF('Your Debts'!$G$7=0,0,INDEX('Your Debts'!$C$5:$C$12,'Your Debts'!$G$7)/12)),2) | K36: =MIN((L35)+J36,MAX(0,$C36-(E36+H36))) | L36: =ROUND(MAX(0,(L35)+J36-K36),2) | M36: =ROUND((O35)*(IF('Your Debts'!$G$8=0,0,INDEX('Your Debts'!$C$5:$C$12,'Your Debts'!$G$8)/12)),2) | N36: =MIN((O35)+M36,MAX(0,$C36-(E36+H36+K36))) | O36: =ROUND(MAX(0,(O35)+M36-N36),2) | P36: =ROUND((R35)*(IF('Your Debts'!$G$9=0,0,INDEX('Your Debts'!$C$5:$C$12,'Your Debts'!$G$9)/12)),2) | Q36: =MIN((R35)+P36,MAX(0,$C36-(E36+H36+K36+N36))) | R36: =ROUND(MAX(0,(R35)+P36-Q36),2) | S36: =ROUND((U35)*(IF('Your Debts'!$G$10=0,0,INDEX('Your Debts'!$C$5:$C$12,'Your Debts'!$G$10)/12)),2) | T36: =MIN((U35)+S36,MAX(0,$C36-(E36+H36+K36+N36+Q36))) | U36: =ROUND(MAX(0,(U35)+S36-T36),2) | V36: =ROUND((X35)*(IF('Your Debts'!$G$11=0,0,INDEX('Your Debts'!$C$5:$C$12,'Your Debts'!$G$11)/12)),2) | W36: =MIN((X35)+V36,MAX(0,$C36-(E36+H36+K36+N36+Q36+T36))) | X36: =ROUND(MAX(0,(X35)+V36-W36),2) | Y36: =ROUND((AA35)*(IF('Your Debts'!$G$12=0,0,INDEX('Your Debts'!$C$5:$C$12,'Your Debts'!$G$12)/12)),2) | Z36: =MIN((AA35)+Y36,MAX(0,$C36-(E36+H36+K36+N36+Q36+T36+W36))) | AA36: =ROUND(MAX(0,(AA35)+Y36-Z36),2) | AB36: =F36+I36+L36+O36+R36+U36+X36+AA36 | AC36: =AC35+D36+G36+J36+M36+P36+S36+V36+Y36
A37: 32 | B37: =EDATE('Your Debts'!$B$19,31) | C37: ='Your Debts'!$B$18 | D37: =ROUND((F36)*(IF('Your Debts'!$G$5=0,0,INDEX('Your Debts'!$C$5:$C$12,'Your Debts'!$G$5)/12)),2) | E37: =MIN((F36)+D37,MAX(0,$C37-(0))) | F37: =ROUND(MAX(0,(F36)+D37-E37),2) | G37: =ROUND((I36)*(IF('Your Debts'!$G$6=0,0,INDEX('Your Debts'!$C$5:$C$12,'Your Debts'!$G$6)/12)),2) | H37: =MIN((I36)+G37,MAX(0,$C37-(E37))) | I37: =ROUND(MAX(0,(I36)+G37-H37),2) | J37: =ROUND((L36)*(IF('Your Debts'!$G$7=0,0,INDEX('Your Debts'!$C$5:$C$12,'Your Debts'!$G$7)/12)),2) | K37: =MIN((L36)+J37,MAX(0,$C37-(E37+H37))) | L37: =ROUND(MAX(0,(L36)+J37-K37),2) | M37: =ROUND((O36)*(IF('Your Debts'!$G$8=0,0,INDEX('Your Debts'!$C$5:$C$12,'Your Debts'!$G$8)/12)),2) | N37: =MIN((O36)+M37,MAX(0,$C37-(E37+H37+K37))) | O37: =ROUND(MAX(0,(O36)+M37-N37),2) | P37: =ROUND((R36)*(IF('Your Debts'!$G$9=0,0,INDEX('Your Debts'!$C$5:$C$12,'Your Debts'!$G$9)/12)),2) | Q37: =MIN((R36)+P37,MAX(0,$C37-(E37+H37+K37+N37))) | R37: =ROUND(MAX(0,(R36)+P37-Q37),2) | S37: =ROUND((U36)*(IF('Your Debts'!$G$10=0,0,INDEX('Your Debts'!$C$5:$C$12,'Your Debts'!$G$10)/12)),2) | T37: =MIN((U36)+S37,MAX(0,$C37-(E37+H37+K37+N37+Q37))) | U37: =ROUND(MAX(0,(U36)+S37-T37),2) | V37: =ROUND((X36)*(IF('Your Debts'!$G$11=0,0,INDEX('Your Debts'!$C$5:$C$12,'Your Debts'!$G$11)/12)),2) | W37: =MIN((X36)+V37,MAX(0,$C37-(E37+H37+K37+N37+Q37+T37))) | X37: =ROUND(MAX(0,(X36)+V37-W37),2) | Y37: =ROUND((AA36)*(IF('Your Debts'!$G$12=0,0,INDEX('Your Debts'!$C$5:$C$12,'Your Debts'!$G$12)/12)),2) | Z37: =MIN((AA36)+Y37,MAX(0,$C37-(E37+H37+K37+N37+Q37+T37+W37))) | AA37: =ROUND(MAX(0,(AA36)+Y37-Z37),2) | AB37: =F37+I37+L37+O37+R37+U37+X37+AA37 | AC37: =AC36+D37+G37+J37+M37+P37+S37+V37+Y37
A38: 33 | B38: =EDATE('Your Debts'!$B$19,32) | C38: ='Your Debts'!$B$18 | D38: =ROUND((F37)*(IF('Your Debts'!$G$5=0,0,INDEX('Your Debts'!$C$5:$C$12,'Your Debts'!$G$5)/12)),2) | E38: =MIN((F37)+D38,MAX(0,$C38-(0))) | F38: =ROUND(MAX(0,(F37)+D38-E38),2) | G38: =ROUND((I37)*(IF('Your Debts'!$G$6=0,0,INDEX('Your Debts'!$C$5:$C$12,'Your Debts'!$G$6)/12)),2) | H38: =MIN((I37)+G38,MAX(0,$C38-(E38))) | I38: =ROUND(MAX(0,(I37)+G38-H38),2) | J38: =ROUND((L37)*(IF('Your Debts'!$G$7=0,0,INDEX('Your Debts'!$C$5:$C$12,'Your Debts'!$G$7)/12)),2) | K38: =MIN((L37)+J38,MAX(0,$C38-(E38+H38))) | L38: =ROUND(MAX(0,(L37)+J38-K38),2) | M38: =ROUND((O37)*(IF('Your Debts'!$G$8=0,0,INDEX('Your Debts'!$C$5:$C$12,'Your Debts'!$G$8)/12)),2) | N38: =MIN((O37)+M38,MAX(0,$C38-(E38+H38+K38))) | O38: =ROUND(MAX(0,(O37)+M38-N38),2) | P38: =ROUND((R37)*(IF('Your Debts'!$G$9=0,0,INDEX('Your Debts'!$C$5:$C$12,'Your Debts'!$G$9)/12)),2) | Q38: =MIN((R37)+P38,MAX(0,$C38-(E38+H38+K38+N38))) | R38: =ROUND(MAX(0,(R37)+P38-Q38),2) | S38: =ROUND((U37)*(IF('Your Debts'!$G$10=0,0,INDEX('Your Debts'!$C$5:$C$12,'Your Debts'!$G$10)/12)),2) | T38: =MIN((U37)+S38,MAX(0,$C38-(E38+H38+K38+N38+Q38))) | U38: =ROUND(MAX(0,(U37)+S38-T38),2) | V38: =ROUND((X37)*(IF('Your Debts'!$G$11=0,0,INDEX('Your Debts'!$C$5:$C$12,'Your Debts'!$G$11)/12)),2) | W38: =MIN((X37)+V38,MAX(0,$C38-(E38+H38+K38+N38+Q38+T38))) | X38: =ROUND(MAX(0,(X37)+V38-W38),2) | Y38: =ROUND((AA37)*(IF('Your Debts'!$G$12=0,0,INDEX('Your Debts'!$C$5:$C$12,'Your Debts'!$G$12)/12)),2) | Z38: =MIN((AA37)+Y38,MAX(0,$C38-(E38+H38+K38+N38+Q38+T38+W38))) | AA38: =ROUND(MAX(0,(AA37)+Y38-Z38),2) | AB38: =F38+I38+L38+O38+R38+U38+X38+AA38 | AC38: =AC37+D38+G38+J38+M38+P38+S38+V38+Y38
A39: 34 | B39: =EDATE('Your Debts'!$B$19,33) | C39: ='Your Debts'!$B$18 | D39: =ROUND((F38)*(IF('Your Debts'!$G$5=0,0,INDEX('Your Debts'!$C$5:$C$12,'Your Debts'!$G$5)/12)),2) | E39: =MIN((F38)+D39,MAX(0,$C39-(0))) | F39: =ROUND(MAX(0,(F38)+D39-E39),2) | G39: =ROUND((I38)*(IF('Your Debts'!$G$6=0,0,INDEX('Your Debts'!$C$5:$C$12,'Your Debts'!$G$6)/12)),2) | H39: =MIN((I38)+G39,MAX(0,$C39-(E39))) | I39: =ROUND(MAX(0,(I38)+G39-H39),2) | J39: =ROUND((L38)*(IF('Your Debts'!$G$7=0,0,INDEX('Your Debts'!$C$5:$C$12,'Your Debts'!$G$7)/12)),2) | K39: =MIN((L38)+J39,MAX(0,$C39-(E39+H39))) | L39: =ROUND(MAX(0,(L38)+J39-K39),2) | M39: =ROUND((O38)*(IF('Your Debts'!$G$8=0,0,INDEX('Your Debts'!$C$5:$C$12,'Your Debts'!$G$8)/12)),2) | N39: =MIN((O38)+M39,MAX(0,$C39-(E39+H39+K39))) | O39: =ROUND(MAX(0,(O38)+M39-N39),2) | P39: =ROUND((R38)*(IF('Your Debts'!$G$9=0,0,INDEX('Your Debts'!$C$5:$C$12,'Your Debts'!$G$9)/12)),2) | Q39: =MIN((R38)+P39,MAX(0,$C39-(E39+H39+K39+N39))) | R39: =ROUND(MAX(0,(R38)+P39-Q39),2) | S39: =ROUND((U38)*(IF('Your Debts'!$G$10=0,0,INDEX('Your Debts'!$C$5:$C$12,'Your Debts'!$G$10)/12)),2) | T39: =MIN((U38)+S39,MAX(0,$C39-(E39+H39+K39+N39+Q39))) | U39: =ROUND(MAX(0,(U38)+S39-T39),2) | V39: =ROUND((X38)*(IF('Your Debts'!$G$11=0,0,INDEX('Your Debts'!$C$5:$C$12,'Your Debts'!$G$11)/12)),2) | W39: =MIN((X38)+V39,MAX(0,$C39-(E39+H39+K39+N39+Q39+T39))) | X39: =ROUND(MAX(0,(X38)+V39-W39),2) | Y39: =ROUND((AA38)*(IF('Your Debts'!$G$12=0,0,INDEX('Your Debts'!$C$5:$C$12,'Your Debts'!$G$12)/12)),2) | Z39: =MIN((AA38)+Y39,MAX(0,$C39-(E39+H39+K39+N39+Q39+T39+W39))) | AA39: =ROUND(MAX(0,(AA38)+Y39-Z39),2) | AB39: =F39+I39+L39+O39+R39+U39+X39+AA39 | AC39: =AC38+D39+G39+J39+M39+P39+S39+V39+Y39
A40: 35 | B40: =EDATE('Your Debts'!$B$19,34) | C40: ='Your Debts'!$B$18 | D40: =ROUND((F39)*(IF('Your Debts'!$G$5=0,0,INDEX('Your Debts'!$C$5:$C$12,'Your Debts'!$G$5)/12)),2) | E40: =MIN((F39)+D40,MAX(0,$C40-(0))) | F40: =ROUND(MAX(0,(F39)+D40-E40),2) | G40: =ROUND((I39)*(IF('Your Debts'!$G$6=0,0,INDEX('Your Debts'!$C$5:$C$12,'Your Debts'!$G$6)/12)),2) | H40: =MIN((I39)+G40,MAX(0,$C40-(E40))) | I40: =ROUND(MAX(0,(I39)+G40-H40),2) | J40: =ROUND((L39)*(IF('Your Debts'!$G$7=0,0,INDEX('Your Debts'!$C$5:$C$12,'Your Debts'!$G$7)/12)),2) | K40: =MIN((L39)+J40,MAX(0,$C40-(E40+H40))) | L40: =ROUND(MAX(0,(L39)+J40-K40),2) | M40: =ROUND((O39)*(IF('Your Debts'!$G$8=0,0,INDEX('Your Debts'!$C$5:$C$12,'Your Debts'!$G$8)/12)),2) | N40: =MIN((O39)+M40,MAX(0,$C40-(E40+H40+K40))) | O40: =ROUND(MAX(0,(O39)+M40-N40),2) | P40: =ROUND((R39)*(IF('Your Debts'!$G$9=0,0,INDEX('Your Debts'!$C$5:$C$12,'Your Debts'!$G$9)/12)),2) | Q40: =MIN((R39)+P40,MAX(0,$C40-(E40+H40+K40+N40))) | R40: =ROUND(MAX(0,(R39)+P40-Q40),2) | S40: =ROUND((U39)*(IF('Your Debts'!$G$10=0,0,INDEX('Your Debts'!$C$5:$C$12,'Your Debts'!$G$10)/12)),2) | T40: =MIN((U39)+S40,MAX(0,$C40-(E40+H40+K40+N40+Q40))) | U40: =ROUND(MAX(0,(U39)+S40-T40),2) | V40: =ROUND((X39)*(IF('Your Debts'!$G$11=0,0,INDEX('Your Debts'!$C$5:$C$12,'Your Debts'!$G$11)/12)),2) | W40: =MIN((X39)+V40,MAX(0,$C40-(E40+H40+K40+N40+Q40+T40))) | X40: =ROUND(MAX(0,(X39)+V40-W40),2) | Y40: =ROUND((AA39)*(IF('Your Debts'!$G$12=0,0,INDEX('Your Debts'!$C$5:$C$12,'Your Debts'!$G$12)/12)),2) | Z40: =MIN((AA39)+Y40,MAX(0,$C40-(E40+H40+K40+N40+Q40+T40+W40))) | AA40: =ROUND(MAX(0,(AA39)+Y40-Z40),2) | AB40: =F40+I40+L40+O40+R40+U40+X40+AA40 | AC40: =AC39+D40+G40+J40+M40+P40+S40+V40+Y40
A41: 36 | B41: =EDATE('Your Debts'!$B$19,35) | C41: ='Your Debts'!$B$18 | D41: =ROUND((F40)*(IF('Your Debts'!$G$5=0,0,INDEX('Your Debts'!$C$5:$C$12,'Your Debts'!$G$5)/12)),2) | E41: =MIN((F40)+D41,MAX(0,$C41-(0))) | F41: =ROUND(MAX(0,(F40)+D41-E41),2) | G41: =ROUND((I40)*(IF('Your Debts'!$G$6=0,0,INDEX('Your Debts'!$C$5:$C$12,'Your Debts'!$G$6)/12)),2) | H41: =MIN((I40)+G41,MAX(0,$C41-(E41))) | I41: =ROUND(MAX(0,(I40)+G41-H41),2) | J41: =ROUND((L40)*(IF('Your Debts'!$G$7=0,0,INDEX('Your Debts'!$C$5:$C$12,'Your Debts'!$G$7)/12)),2) | K41: =MIN((L40)+J41,MAX(0,$C41-(E41+H41))) | L41: =ROUND(MAX(0,(L40)+J41-K41),2) | M41: =ROUND((O40)*(IF('Your Debts'!$G$8=0,0,INDEX('Your Debts'!$C$5:$C$12,'Your Debts'!$G$8)/12)),2) | N41: =MIN((O40)+M41,MAX(0,$C41-(E41+H41+K41))) | O41: =ROUND(MAX(0,(O40)+M41-N41),2) | P41: =ROUND((R40)*(IF('Your Debts'!$G$9=0,0,INDEX('Your Debts'!$C$5:$C$12,'Your Debts'!$G$9)/12)),2) | Q41: =MIN((R40)+P41,MAX(0,$C41-(E41+H41+K41+N41))) | R41: =ROUND(MAX(0,(R40)+P41-Q41),2) | S41: =ROUND((U40)*(IF('Your Debts'!$G$10=0,0,INDEX('Your Debts'!$C$5:$C$12,'Your Debts'!$G$10)/12)),2) | T41: =MIN((U40)+S41,MAX(0,$C41-(E41+H41+K41+N41+Q41))) | U41: =ROUND(MAX(0,(U40)+S41-T41),2) | V41: =ROUND((X40)*(IF('Your Debts'!$G$11=0,0,INDEX('Your Debts'!$C$5:$C$12,'Your Debts'!$G$11)/12)),2) | W41: =MIN((X40)+V41,MAX(0,$C41-(E41+H41+K41+N41+Q41+T41))) | X41: =ROUND(MAX(0,(X40)+V41-W41),2) | Y41: =ROUND((AA40)*(IF('Your Debts'!$G$12=0,0,INDEX('Your Debts'!$C$5:$C$12,'Your Debts'!$G$12)/12)),2) | Z41: =MIN((AA40)+Y41,MAX(0,$C41-(E41+H41+K41+N41+Q41+T41+W41))) | AA41: =ROUND(MAX(0,(AA40)+Y41-Z41),2) | AB41: =F41+I41+L41+O41+R41+U41+X41+AA41 | AC41: =AC40+D41+G41+J41+M41+P41+S41+V41+Y41
A42: 37 | B42: =EDATE('Your Debts'!$B$19,36) | C42: ='Your Debts'!$B$18 | D42: =ROUND((F41)*(IF('Your Debts'!$G$5=0,0,INDEX('Your Debts'!$C$5:$C$12,'Your Debts'!$G$5)/12)),2) | E42: =MIN((F41)+D42,MAX(0,$C42-(0))) | F42: =ROUND(MAX(0,(F41)+D42-E42),2) | G42: =ROUND((I41)*(IF('Your Debts'!$G$6=0,0,INDEX('Your Debts'!$C$5:$C$12,'Your Debts'!$G$6)/12)),2) | H42: =MIN((I41)+G42,MAX(0,$C42-(E42))) | I42: =ROUND(MAX(0,(I41)+G42-H42),2) | J42: =ROUND((L41)*(IF('Your Debts'!$G$7=0,0,INDEX('Your Debts'!$C$5:$C$12,'Your Debts'!$G$7)/12)),2) | K42: =MIN((L41)+J42,MAX(0,$C42-(E42+H42))) | L42: =ROUND(MAX(0,(L41)+J42-K42),2) | M42: =ROUND((O41)*(IF('Your Debts'!$G$8=0,0,INDEX('Your Debts'!$C$5:$C$12,'Your Debts'!$G$8)/12)),2) | N42: =MIN((O41)+M42,MAX(0,$C42-(E42+H42+K42))) | O42: =ROUND(MAX(0,(O41)+M42-N42),2) | P42: =ROUND((R41)*(IF('Your Debts'!$G$9=0,0,INDEX('Your Debts'!$C$5:$C$12,'Your Debts'!$G$9)/12)),2) | Q42: =MIN((R41)+P42,MAX(0,$C42-(E42+H42+K42+N42))) | R42: =ROUND(MAX(0,(R41)+P42-Q42),2) | S42: =ROUND((U41)*(IF('Your Debts'!$G$10=0,0,INDEX('Your Debts'!$C$5:$C$12,'Your Debts'!$G$10)/12)),2) | T42: =MIN((U41)+S42,MAX(0,$C42-(E42+H42+K42+N42+Q42))) | U42: =ROUND(MAX(0,(U41)+S42-T42),2) | V42: =ROUND((X41)*(IF('Your Debts'!$G$11=0,0,INDEX('Your Debts'!$C$5:$C$12,'Your Debts'!$G$11)/12)),2) | W42: =MIN((X41)+V42,MAX(0,$C42-(E42+H42+K42+N42+Q42+T42))) | X42: =ROUND(MAX(0,(X41)+V42-W42),2) | Y42: =ROUND((AA41)*(IF('Your Debts'!$G$12=0,0,INDEX('Your Debts'!$C$5:$C$12,'Your Debts'!$G$12)/12)),2) | Z42: =MIN((AA41)+Y42,MAX(0,$C42-(E42+H42+K42+N42+Q42+T42+W42))) | AA42: =ROUND(MAX(0,(AA41)+Y42-Z42),2) | AB42: =F42+I42+L42+O42+R42+U42+X42+AA42 | AC42: =AC41+D42+G42+J42+M42+P42+S42+V42+Y42
A43: 38 | B43: =EDATE('Your Debts'!$B$19,37) | C43: ='Your Debts'!$B$18 | D43: =ROUND((F42)*(IF('Your Debts'!$G$5=0,0,INDEX('Your Debts'!$C$5:$C$12,'Your Debts'!$G$5)/12)),2) | E43: =MIN((F42)+D43,MAX(0,$C43-(0))) | F43: =ROUND(MAX(0,(F42)+D43-E43),2) | G43: =ROUND((I42)*(IF('Your Debts'!$G$6=0,0,INDEX('Your Debts'!$C$5:$C$12,'Your Debts'!$G$6)/12)),2) | H43: =MIN((I42)+G43,MAX(0,$C43-(E43))) | I43: =ROUND(MAX(0,(I42)+G43-H43),2) | J43: =ROUND((L42)*(IF('Your Debts'!$G$7=0,0,INDEX('Your Debts'!$C$5:$C$12,'Your Debts'!$G$7)/12)),2) | K43: =MIN((L42)+J43,MAX(0,$C43-(E43+H43))) | L43: =ROUND(MAX(0,(L42)+J43-K43),2) | M43: =ROUND((O42)*(IF('Your Debts'!$G$8=0,0,INDEX('Your Debts'!$C$5:$C$12,'Your Debts'!$G$8)/12)),2) | N43: =MIN((O42)+M43,MAX(0,$C43-(E43+H43+K43))) | O43: =ROUND(MAX(0,(O42)+M43-N43),2) | P43: =ROUND((R42)*(IF('Your Debts'!$G$9=0,0,INDEX('Your Debts'!$C$5:$C$12,'Your Debts'!$G$9)/12)),2) | Q43: =MIN((R42)+P43,MAX(0,$C43-(E43+H43+K43+N43))) | R43: =ROUND(MAX(0,(R42)+P43-Q43),2) | S43: =ROUND((U42)*(IF('Your Debts'!$G$10=0,0,INDEX('Your Debts'!$C$5:$C$12,'Your Debts'!$G$10)/12)),2) | T43: =MIN((U42)+S43,MAX(0,$C43-(E43+H43+K43+N43+Q43))) | U43: =ROUND(MAX(0,(U42)+S43-T43),2) | V43: =ROUND((X42)*(IF('Your Debts'!$G$11=0,0,INDEX('Your Debts'!$C$5:$C$12,'Your Debts'!$G$11)/12)),2) | W43: =MIN((X42)+V43,MAX(0,$C43-(E43+H43+K43+N43+Q43+T43))) | X43: =ROUND(MAX(0,(X42)+V43-W43),2) | Y43: =ROUND((AA42)*(IF('Your Debts'!$G$12=0,0,INDEX('Your Debts'!$C$5:$C$12,'Your Debts'!$G$12)/12)),2) | Z43: =MIN((AA42)+Y43,MAX(0,$C43-(E43+H43+K43+N43+Q43+T43+W43))) | AA43: =ROUND(MAX(0,(AA42)+Y43-Z43),2) | AB43: =F43+I43+L43+O43+R43+U43+X43+AA43 | AC43: =AC42+D43+G43+J43+M43+P43+S43+V43+Y43
A44: 39 | B44: =EDATE('Your Debts'!$B$19,38) | C44: ='Your Debts'!$B$18 | D44: =ROUND((F43)*(IF('Your Debts'!$G$5=0,0,INDEX('Your Debts'!$C$5:$C$12,'Your Debts'!$G$5)/12)),2) | E44: =MIN((F43)+D44,MAX(0,$C44-(0))) | F44: =ROUND(MAX(0,(F43)+D44-E44),2) | G44: =ROUND((I43)*(IF('Your Debts'!$G$6=0,0,INDEX('Your Debts'!$C$5:$C$12,'Your Debts'!$G$6)/12)),2) | H44: =MIN((I43)+G44,MAX(0,$C44-(E44))) | I44: =ROUND(MAX(0,(I43)+G44-H44),2) | J44: =ROUND((L43)*(IF('Your Debts'!$G$7=0,0,INDEX('Your Debts'!$C$5:$C$12,'Your Debts'!$G$7)/12)),2) | K44: =MIN((L43)+J44,MAX(0,$C44-(E44+H44))) | L44: =ROUND(MAX(0,(L43)+J44-K44),2) | M44: =ROUND((O43)*(IF('Your Debts'!$G$8=0,0,INDEX('Your Debts'!$C$5:$C$12,'Your Debts'!$G$8)/12)),2) | N44: =MIN((O43)+M44,MAX(0,$C44-(E44+H44+K44))) | O44: =ROUND(MAX(0,(O43)+M44-N44),2) | P44: =ROUND((R43)*(IF('Your Debts'!$G$9=0,0,INDEX('Your Debts'!$C$5:$C$12,'Your Debts'!$G$9)/12)),2) | Q44: =MIN((R43)+P44,MAX(0,$C44-(E44+H44+K44+N44))) | R44: =ROUND(MAX(0,(R43)+P44-Q44),2) | S44: =ROUND((U43)*(IF('Your Debts'!$G$10=0,0,INDEX('Your Debts'!$C$5:$C$12,'Your Debts'!$G$10)/12)),2) | T44: =MIN((U43)+S44,MAX(0,$C44-(E44+H44+K44+N44+Q44))) | U44: =ROUND(MAX(0,(U43)+S44-T44),2) | V44: =ROUND((X43)*(IF('Your Debts'!$G$11=0,0,INDEX('Your Debts'!$C$5:$C$12,'Your Debts'!$G$11)/12)),2) | W44: =MIN((X43)+V44,MAX(0,$C44-(E44+H44+K44+N44+Q44+T44))) | X44: =ROUND(MAX(0,(X43)+V44-W44),2) | Y44: =ROUND((AA43)*(IF('Your Debts'!$G$12=0,0,INDEX('Your Debts'!$C$5:$C$12,'Your Debts'!$G$12)/12)),2) | Z44: =MIN((AA43)+Y44,MAX(0,$C44-(E44+H44+K44+N44+Q44+T44+W44))) | AA44: =ROUND(MAX(0,(AA43)+Y44-Z44),2) | AB44: =F44+I44+L44+O44+R44+U44+X44+AA44 | AC44: =AC43+D44+G44+J44+M44+P44+S44+V44+Y44
A45: 40 | B45: =EDATE('Your Debts'!$B$19,39) | C45: ='Your Debts'!$B$18 | D45: =ROUND((F44)*(IF('Your Debts'!$G$5=0,0,INDEX('Your Debts'!$C$5:$C$12,'Your Debts'!$G$5)/12)),2) | E45: =MIN((F44)+D45,MAX(0,$C45-(0))) | F45: =ROUND(MAX(0,(F44)+D45-E45),2) | G45: =ROUND((I44)*(IF('Your Debts'!$G$6=0,0,INDEX('Your Debts'!$C$5:$C$12,'Your Debts'!$G$6)/12)),2) | H45: =MIN((I44)+G45,MAX(0,$C45-(E45))) | I45: =ROUND(MAX(0,(I44)+G45-H45),2) | J45: =ROUND((L44)*(IF('Your Debts'!$G$7=0,0,INDEX('Your Debts'!$C$5:$C$12,'Your Debts'!$G$7)/12)),2) | K45: =MIN((L44)+J45,MAX(0,$C45-(E45+H45))) | L45: =ROUND(MAX(0,(L44)+J45-K45),2) | M45: =ROUND((O44)*(IF('Your Debts'!$G$8=0,0,INDEX('Your Debts'!$C$5:$C$12,'Your Debts'!$G$8)/12)),2) | N45: =MIN((O44)+M45,MAX(0,$C45-(E45+H45+K45))) | O45: =ROUND(MAX(0,(O44)+M45-N45),2) | P45: =ROUND((R44)*(IF('Your Debts'!$G$9=0,0,INDEX('Your Debts'!$C$5:$C$12,'Your Debts'!$G$9)/12)),2) | Q45: =MIN((R44)+P45,MAX(0,$C45-(E45+H45+K45+N45))) | R45: =ROUND(MAX(0,(R44)+P45-Q45),2) | S45: =ROUND((U44)*(IF('Your Debts'!$G$10=0,0,INDEX('Your Debts'!$C$5:$C$12,'Your Debts'!$G$10)/12)),2) | T45: =MIN((U44)+S45,MAX(0,$C45-(E45+H45+K45+N45+Q45))) | U45: =ROUND(MAX(0,(U44)+S45-T45),2) | V45: =ROUND((X44)*(IF('Your Debts'!$G$11=0,0,INDEX('Your Debts'!$C$5:$C$12,'Your Debts'!$G$11)/12)),2) | W45: =MIN((X44)+V45,MAX(0,$C45-(E45+H45+K45+N45+Q45+T45))) | X45: =ROUND(MAX(0,(X44)+V45-W45),2) | Y45: =ROUND((AA44)*(IF('Your Debts'!$G$12=0,0,INDEX('Your Debts'!$C$5:$C$12,'Your Debts'!$G$12)/12)),2) | Z45: =MIN((AA44)+Y45,MAX(0,$C45-(E45+H45+K45+N45+Q45+T45+W45))) | AA45: =ROUND(MAX(0,(AA44)+Y45-Z45),2) | AB45: =F45+I45+L45+O45+R45+U45+X45+AA45 | AC45: =AC44+D45+G45+J45+M45+P45+S45+V45+Y45
A46: 41 | B46: =EDATE('Your Debts'!$B$19,40) | C46: ='Your Debts'!$B$18 | D46: =ROUND((F45)*(IF('Your Debts'!$G$5=0,0,INDEX('Your Debts'!$C$5:$C$12,'Your Debts'!$G$5)/12)),2) | E46: =MIN((F45)+D46,MAX(0,$C46-(0))) | F46: =ROUND(MAX(0,(F45)+D46-E46),2) | G46: =ROUND((I45)*(IF('Your Debts'!$G$6=0,0,INDEX('Your Debts'!$C$5:$C$12,'Your Debts'!$G$6)/12)),2) | H46: =MIN((I45)+G46,MAX(0,$C46-(E46))) | I46: =ROUND(MAX(0,(I45)+G46-H46),2) | J46: =ROUND((L45)*(IF('Your Debts'!$G$7=0,0,INDEX('Your Debts'!$C$5:$C$12,'Your Debts'!$G$7)/12)),2) | K46: =MIN((L45)+J46,MAX(0,$C46-(E46+H46))) | L46: =ROUND(MAX(0,(L45)+J46-K46),2) | M46: =ROUND((O45)*(IF('Your Debts'!$G$8=0,0,INDEX('Your Debts'!$C$5:$C$12,'Your Debts'!$G$8)/12)),2) | N46: =MIN((O45)+M46,MAX(0,$C46-(E46+H46+K46))) | O46: =ROUND(MAX(0,(O45)+M46-N46),2) | P46: =ROUND((R45)*(IF('Your Debts'!$G$9=0,0,INDEX('Your Debts'!$C$5:$C$12,'Your Debts'!$G$9)/12)),2) | Q46: =MIN((R45)+P46,MAX(0,$C46-(E46+H46+K46+N46))) | R46: =ROUND(MAX(0,(R45)+P46-Q46),2) | S46: =ROUND((U45)*(IF('Your Debts'!$G$10=0,0,INDEX('Your Debts'!$C$5:$C$12,'Your Debts'!$G$10)/12)),2) | T46: =MIN((U45)+S46,MAX(0,$C46-(E46+H46+K46+N46+Q46))) | U46: =ROUND(MAX(0,(U45)+S46-T46),2) | V46: =ROUND((X45)*(IF('Your Debts'!$G$11=0,0,INDEX('Your Debts'!$C$5:$C$12,'Your Debts'!$G$11)/12)),2) | W46: =MIN((X45)+V46,MAX(0,$C46-(E46+H46+K46+N46+Q46+T46))) | X46: =ROUND(MAX(0,(X45)+V46-W46),2) | Y46: =ROUND((AA45)*(IF('Your Debts'!$G$12=0,0,INDEX('Your Debts'!$C$5:$C$12,'Your Debts'!$G$12)/12)),2) | Z46: =MIN((AA45)+Y46,MAX(0,$C46-(E46+H46+K46+N46+Q46+T46+W46))) | AA46: =ROUND(MAX(0,(AA45)+Y46-Z46),2) | AB46: =F46+I46+L46+O46+R46+U46+X46+AA46 | AC46: =AC45+D46+G46+J46+M46+P46+S46+V46+Y46
A47: 42 | B47: =EDATE('Your Debts'!$B$19,41) | C47: ='Your Debts'!$B$18 | D47: =ROUND((F46)*(IF('Your Debts'!$G$5=0,0,INDEX('Your Debts'!$C$5:$C$12,'Your Debts'!$G$5)/12)),2) | E47: =MIN((F46)+D47,MAX(0,$C47-(0))) | F47: =ROUND(MAX(0,(F46)+D47-E47),2) | G47: =ROUND((I46)*(IF('Your Debts'!$G$6=0,0,INDEX('Your Debts'!$C$5:$C$12,'Your Debts'!$G$6)/12)),2) | H47: =MIN((I46)+G47,MAX(0,$C47-(E47))) | I47: =ROUND(MAX(0,(I46)+G47-H47),2) | J47: =ROUND((L46)*(IF('Your Debts'!$G$7=0,0,INDEX('Your Debts'!$C$5:$C$12,'Your Debts'!$G$7)/12)),2) | K47: =MIN((L46)+J47,MAX(0,$C47-(E47+H47))) | L47: =ROUND(MAX(0,(L46)+J47-K47),2) | M47: =ROUND((O46)*(IF('Your Debts'!$G$8=0,0,INDEX('Your Debts'!$C$5:$C$12,'Your Debts'!$G$8)/12)),2) | N47: =MIN((O46)+M47,MAX(0,$C47-(E47+H47+K47))) | O47: =ROUND(MAX(0,(O46)+M47-N47),2) | P47: =ROUND((R46)*(IF('Your Debts'!$G$9=0,0,INDEX('Your Debts'!$C$5:$C$12,'Your Debts'!$G$9)/12)),2) | Q47: =MIN((R46)+P47,MAX(0,$C47-(E47+H47+K47+N47))) | R47: =ROUND(MAX(0,(R46)+P47-Q47),2) | S47: =ROUND((U46)*(IF('Your Debts'!$G$10=0,0,INDEX('Your Debts'!$C$5:$C$12,'Your Debts'!$G$10)/12)),2) | T47: =MIN((U46)+S47,MAX(0,$C47-(E47+H47+K47+N47+Q47))) | U47: =ROUND(MAX(0,(U46)+S47-T47),2) | V47: =ROUND((X46)*(IF('Your Debts'!$G$11=0,0,INDEX('Your Debts'!$C$5:$C$12,'Your Debts'!$G$11)/12)),2) | W47: =MIN((X46)+V47,MAX(0,$C47-(E47+H47+K47+N47+Q47+T47))) | X47: =ROUND(MAX(0,(X46)+V47-W47),2) | Y47: =ROUND((AA46)*(IF('Your Debts'!$G$12=0,0,INDEX('Your Debts'!$C$5:$C$12,'Your Debts'!$G$12)/12)),2) | Z47: =MIN((AA46)+Y47,MAX(0,$C47-(E47+H47+K47+N47+Q47+T47+W47))) | AA47: =ROUND(MAX(0,(AA46)+Y47-Z47),2) | AB47: =F47+I47+L47+O47+R47+U47+X47+AA47 | AC47: =AC46+D47+G47+J47+M47+P47+S47+V47+Y47
A48: 43 | B48: =EDATE('Your Debts'!$B$19,42) | C48: ='Your Debts'!$B$18 | D48: =ROUND((F47)*(IF('Your Debts'!$G$5=0,0,INDEX('Your Debts'!$C$5:$C$12,'Your Debts'!$G$5)/12)),2) | E48: =MIN((F47)+D48,MAX(0,$C48-(0))) | F48: =ROUND(MAX(0,(F47)+D48-E48),2) | G48: =ROUND((I47)*(IF('Your Debts'!$G$6=0,0,INDEX('Your Debts'!$C$5:$C$12,'Your Debts'!$G$6)/12)),2) | H48: =MIN((I47)+G48,MAX(0,$C48-(E48))) | I48: =ROUND(MAX(0,(I47)+G48-H48),2) | J48: =ROUND((L47)*(IF('Your Debts'!$G$7=0,0,INDEX('Your Debts'!$C$5:$C$12,'Your Debts'!$G$7)/12)),2) | K48: =MIN((L47)+J48,MAX(0,$C48-(E48+H48))) | L48: =ROUND(MAX(0,(L47)+J48-K48),2) | M48: =ROUND((O47)*(IF('Your Debts'!$G$8=0,0,INDEX('Your Debts'!$C$5:$C$12,'Your Debts'!$G$8)/12)),2) | N48: =MIN((O47)+M48,MAX(0,$C48-(E48+H48+K48))) | O48: =ROUND(MAX(0,(O47)+M48-N48),2) | P48: =ROUND((R47)*(IF('Your Debts'!$G$9=0,0,INDEX('Your Debts'!$C$5:$C$12,'Your Debts'!$G$9)/12)),2) | Q48: =MIN((R47)+P48,MAX(0,$C48-(E48+H48+K48+N48))) | R48: =ROUND(MAX(0,(R47)+P48-Q48),2) | S48: =ROUND((U47)*(IF('Your Debts'!$G$10=0,0,INDEX('Your Debts'!$C$5:$C$12,'Your Debts'!$G$10)/12)),2) | T48: =MIN((U47)+S48,MAX(0,$C48-(E48+H48+K48+N48+Q48))) | U48: =ROUND(MAX(0,(U47)+S48-T48),2) | V48: =ROUND((X47)*(IF('Your Debts'!$G$11=0,0,INDEX('Your Debts'!$C$5:$C$12,'Your Debts'!$G$11)/12)),2) | W48: =MIN((X47)+V48,MAX(0,$C48-(E48+H48+K48+N48+Q48+T48))) | X48: =ROUND(MAX(0,(X47)+V48-W48),2) | Y48: =ROUND((AA47)*(IF('Your Debts'!$G$12=0,0,INDEX('Your Debts'!$C$5:$C$12,'Your Debts'!$G$12)/12)),2) | Z48: =MIN((AA47)+Y48,MAX(0,$C48-(E48+H48+K48+N48+Q48+T48+W48))) | AA48: =ROUND(MAX(0,(AA47)+Y48-Z48),2) | AB48: =F48+I48+L48+O48+R48+U48+X48+AA48 | AC48: =AC47+D48+G48+J48+M48+P48+S48+V48+Y48
A49: 44 | B49: =EDATE('Your Debts'!$B$19,43) | C49: ='Your Debts'!$B$18 | D49: =ROUND((F48)*(IF('Your Debts'!$G$5=0,0,INDEX('Your Debts'!$C$5:$C$12,'Your Debts'!$G$5)/12)),2) | E49: =MIN((F48)+D49,MAX(0,$C49-(0))) | F49: =ROUND(MAX(0,(F48)+D49-E49),2) | G49: =ROUND((I48)*(IF('Your Debts'!$G$6=0,0,INDEX('Your Debts'!$C$5:$C$12,'Your Debts'!$G$6)/12)),2) | H49: =MIN((I48)+G49,MAX(0,$C49-(E49))) | I49: =ROUND(MAX(0,(I48)+G49-H49),2) | J49: =ROUND((L48)*(IF('Your Debts'!$G$7=0,0,INDEX('Your Debts'!$C$5:$C$12,'Your Debts'!$G$7)/12)),2) | K49: =MIN((L48)+J49,MAX(0,$C49-(E49+H49))) | L49: =ROUND(MAX(0,(L48)+J49-K49),2) | M49: =ROUND((O48)*(IF('Your Debts'!$G$8=0,0,INDEX('Your Debts'!$C$5:$C$12,'Your Debts'!$G$8)/12)),2) | N49: =MIN((O48)+M49,MAX(0,$C49-(E49+H49+K49))) | O49: =ROUND(MAX(0,(O48)+M49-N49),2) | P49: =ROUND((R48)*(IF('Your Debts'!$G$9=0,0,INDEX('Your Debts'!$C$5:$C$12,'Your Debts'!$G$9)/12)),2) | Q49: =MIN((R48)+P49,MAX(0,$C49-(E49+H49+K49+N49))) | R49: =ROUND(MAX(0,(R48)+P49-Q49),2) | S49: =ROUND((U48)*(IF('Your Debts'!$G$10=0,0,INDEX('Your Debts'!$C$5:$C$12,'Your Debts'!$G$10)/12)),2) | T49: =MIN((U48)+S49,MAX(0,$C49-(E49+H49+K49+N49+Q49))) | U49: =ROUND(MAX(0,(U48)+S49-T49),2) | V49: =ROUND((X48)*(IF('Your Debts'!$G$11=0,0,INDEX('Your Debts'!$C$5:$C$12,'Your Debts'!$G$11)/12)),2) | W49: =MIN((X48)+V49,MAX(0,$C49-(E49+H49+K49+N49+Q49+T49))) | X49: =ROUND(MAX(0,(X48)+V49-W49),2) | Y49: =ROUND((AA48)*(IF('Your Debts'!$G$12=0,0,INDEX('Your Debts'!$C$5:$C$12,'Your Debts'!$G$12)/12)),2) | Z49: =MIN((AA48)+Y49,MAX(0,$C49-(E49+H49+K49+N49+Q49+T49+W49))) | AA49: =ROUND(MAX(0,(AA48)+Y49-Z49),2) | AB49: =F49+I49+L49+O49+R49+U49+X49+AA49 | AC49: =AC48+D49+G49+J49+M49+P49+S49+V49+Y49
A50: 45 | B50: =EDATE('Your Debts'!$B$19,44) | C50: ='Your Debts'!$B$18 | D50: =ROUND((F49)*(IF('Your Debts'!$G$5=0,0,INDEX('Your Debts'!$C$5:$C$12,'Your Debts'!$G$5)/12)),2) | E50: =MIN((F49)+D50,MAX(0,$C50-(0))) | F50: =ROUND(MAX(0,(F49)+D50-E50),2) | G50: =ROUND((I49)*(IF('Your Debts'!$G$6=0,0,INDEX('Your Debts'!$C$5:$C$12,'Your Debts'!$G$6)/12)),2) | H50: =MIN((I49)+G50,MAX(0,$C50-(E50))) | I50: =ROUND(MAX(0,(I49)+G50-H50),2) | J50: =ROUND((L49)*(IF('Your Debts'!$G$7=0,0,INDEX('Your Debts'!$C$5:$C$12,'Your Debts'!$G$7)/12)),2) | K50: =MIN((L49)+J50,MAX(0,$C50-(E50+H50))) | L50: =ROUND(MAX(0,(L49)+J50-K50),2) | M50: =ROUND((O49)*(IF('Your Debts'!$G$8=0,0,INDEX('Your Debts'!$C$5:$C$12,'Your Debts'!$G$8)/12)),2) | N50: =MIN((O49)+M50,MAX(0,$C50-(E50+H50+K50))) | O50: =ROUND(MAX(0,(O49)+M50-N50),2) | P50: =ROUND((R49)*(IF('Your Debts'!$G$9=0,0,INDEX('Your Debts'!$C$5:$C$12,'Your Debts'!$G$9)/12)),2) | Q50: =MIN((R49)+P50,MAX(0,$C50-(E50+H50+K50+N50))) | R50: =ROUND(MAX(0,(R49)+P50-Q50),2) | S50: =ROUND((U49)*(IF('Your Debts'!$G$10=0,0,INDEX('Your Debts'!$C$5:$C$12,'Your Debts'!$G$10)/12)),2) | T50: =MIN((U49)+S50,MAX(0,$C50-(E50+H50+K50+N50+Q50))) | U50: =ROUND(MAX(0,(U49)+S50-T50),2) | V50: =ROUND((X49)*(IF('Your Debts'!$G$11=0,0,INDEX('Your Debts'!$C$5:$C$12,'Your Debts'!$G$11)/12)),2) | W50: =MIN((X49)+V50,MAX(0,$C50-(E50+H50+K50+N50+Q50+T50))) | X50: =ROUND(MAX(0,(X49)+V50-W50),2) | Y50: =ROUND((AA49)*(IF('Your Debts'!$G$12=0,0,INDEX('Your Debts'!$C$5:$C$12,'Your Debts'!$G$12)/12)),2) | Z50: =MIN((AA49)+Y50,MAX(0,$C50-(E50+H50+K50+N50+Q50+T50+W50))) | AA50: =ROUND(MAX(0,(AA49)+Y50-Z50),2) | AB50: =F50+I50+L50+O50+R50+U50+X50+AA50 | AC50: =AC49+D50+G50+J50+M50+P50+S50+V50+Y50
A51: 46 | B51: =EDATE('Your Debts'!$B$19,45) | C51: ='Your Debts'!$B$18 | D51: =ROUND((F50)*(IF('Your Debts'!$G$5=0,0,INDEX('Your Debts'!$C$5:$C$12,'Your Debts'!$G$5)/12)),2) | E51: =MIN((F50)+D51,MAX(0,$C51-(0))) | F51: =ROUND(MAX(0,(F50)+D51-E51),2) | G51: =ROUND((I50)*(IF('Your Debts'!$G$6=0,0,INDEX('Your Debts'!$C$5:$C$12,'Your Debts'!$G$6)/12)),2) | H51: =MIN((I50)+G51,MAX(0,$C51-(E51))) | I51: =ROUND(MAX(0,(I50)+G51-H51),2) | J51: =ROUND((L50)*(IF('Your Debts'!$G$7=0,0,INDEX('Your Debts'!$C$5:$C$12,'Your Debts'!$G$7)/12)),2) | K51: =MIN((L50)+J51,MAX(0,$C51-(E51+H51))) | L51: =ROUND(MAX(0,(L50)+J51-K51),2) | M51: =ROUND((O50)*(IF('Your Debts'!$G$8=0,0,INDEX('Your Debts'!$C$5:$C$12,'Your Debts'!$G$8)/12)),2) | N51: =MIN((O50)+M51,MAX(0,$C51-(E51+H51+K51))) | O51: =ROUND(MAX(0,(O50)+M51-N51),2) | P51: =ROUND((R50)*(IF('Your Debts'!$G$9=0,0,INDEX('Your Debts'!$C$5:$C$12,'Your Debts'!$G$9)/12)),2) | Q51: =MIN((R50)+P51,MAX(0,$C51-(E51+H51+K51+N51))) | R51: =ROUND(MAX(0,(R50)+P51-Q51),2) | S51: =ROUND((U50)*(IF('Your Debts'!$G$10=0,0,INDEX('Your Debts'!$C$5:$C$12,'Your Debts'!$G$10)/12)),2) | T51: =MIN((U50)+S51,MAX(0,$C51-(E51+H51+K51+N51+Q51))) | U51: =ROUND(MAX(0,(U50)+S51-T51),2) | V51: =ROUND((X50)*(IF('Your Debts'!$G$11=0,0,INDEX('Your Debts'!$C$5:$C$12,'Your Debts'!$G$11)/12)),2) | W51: =MIN((X50)+V51,MAX(0,$C51-(E51+H51+K51+N51+Q51+T51))) | X51: =ROUND(MAX(0,(X50)+V51-W51),2) | Y51: =ROUND((AA50)*(IF('Your Debts'!$G$12=0,0,INDEX('Your Debts'!$C$5:$C$12,'Your Debts'!$G$12)/12)),2) | Z51: =MIN((AA50)+Y51,MAX(0,$C51-(E51+H51+K51+N51+Q51+T51+W51))) | AA51: =ROUND(MAX(0,(AA50)+Y51-Z51),2) | AB51: =F51+I51+L51+O51+R51+U51+X51+AA51 | AC51: =AC50+D51+G51+J51+M51+P51+S51+V51+Y51
A52: 47 | B52: =EDATE('Your Debts'!$B$19,46) | C52: ='Your Debts'!$B$18 | D52: =ROUND((F51)*(IF('Your Debts'!$G$5=0,0,INDEX('Your Debts'!$C$5:$C$12,'Your Debts'!$G$5)/12)),2) | E52: =MIN((F51)+D52,MAX(0,$C52-(0))) | F52: =ROUND(MAX(0,(F51)+D52-E52),2) | G52: =ROUND((I51)*(IF('Your Debts'!$G$6=0,0,INDEX('Your Debts'!$C$5:$C$12,'Your Debts'!$G$6)/12)),2) | H52: =MIN((I51)+G52,MAX(0,$C52-(E52))) | I52: =ROUND(MAX(0,(I51)+G52-H52),2) | J52: =ROUND((L51)*(IF('Your Debts'!$G$7=0,0,INDEX('Your Debts'!$C$5:$C$12,'Your Debts'!$G$7)/12)),2) | K52: =MIN((L51)+J52,MAX(0,$C52-(E52+H52))) | L52: =ROUND(MAX(0,(L51)+J52-K52),2) | M52: =ROUND((O51)*(IF('Your Debts'!$G$8=0,0,INDEX('Your Debts'!$C$5:$C$12,'Your Debts'!$G$8)/12)),2) | N52: =MIN((O51)+M52,MAX(0,$C52-(E52+H52+K52))) | O52: =ROUND(MAX(0,(O51)+M52-N52),2) | P52: =ROUND((R51)*(IF('Your Debts'!$G$9=0,0,INDEX('Your Debts'!$C$5:$C$12,'Your Debts'!$G$9)/12)),2) | Q52: =MIN((R51)+P52,MAX(0,$C52-(E52+H52+K52+N52))) | R52: =ROUND(MAX(0,(R51)+P52-Q52),2) | S52: =ROUND((U51)*(IF('Your Debts'!$G$10=0,0,INDEX('Your Debts'!$C$5:$C$12,'Your Debts'!$G$10)/12)),2) | T52: =MIN((U51)+S52,MAX(0,$C52-(E52+H52+K52+N52+Q52))) | U52: =ROUND(MAX(0,(U51)+S52-T52),2) | V52: =ROUND((X51)*(IF('Your Debts'!$G$11=0,0,INDEX('Your Debts'!$C$5:$C$12,'Your Debts'!$G$11)/12)),2) | W52: =MIN((X51)+V52,MAX(0,$C52-(E52+H52+K52+N52+Q52+T52))) | X52: =ROUND(MAX(0,(X51)+V52-W52),2) | Y52: =ROUND((AA51)*(IF('Your Debts'!$G$12=0,0,INDEX('Your Debts'!$C$5:$C$12,'Your Debts'!$G$12)/12)),2) | Z52: =MIN((AA51)+Y52,MAX(0,$C52-(E52+H52+K52+N52+Q52+T52+W52))) | AA52: =ROUND(MAX(0,(AA51)+Y52-Z52),2) | AB52: =F52+I52+L52+O52+R52+U52+X52+AA52 | AC52: =AC51+D52+G52+J52+M52+P52+S52+V52+Y52
A53: 48 | B53: =EDATE('Your Debts'!$B$19,47) | C53: ='Your Debts'!$B$18 | D53: =ROUND((F52)*(IF('Your Debts'!$G$5=0,0,INDEX('Your Debts'!$C$5:$C$12,'Your Debts'!$G$5)/12)),2) | E53: =MIN((F52)+D53,MAX(0,$C53-(0))) | F53: =ROUND(MAX(0,(F52)+D53-E53),2) | G53: =ROUND((I52)*(IF('Your Debts'!$G$6=0,0,INDEX('Your Debts'!$C$5:$C$12,'Your Debts'!$G$6)/12)),2) | H53: =MIN((I52)+G53,MAX(0,$C53-(E53))) | I53: =ROUND(MAX(0,(I52)+G53-H53),2) | J53: =ROUND((L52)*(IF('Your Debts'!$G$7=0,0,INDEX('Your Debts'!$C$5:$C$12,'Your Debts'!$G$7)/12)),2) | K53: =MIN((L52)+J53,MAX(0,$C53-(E53+H53))) | L53: =ROUND(MAX(0,(L52)+J53-K53),2) | M53: =ROUND((O52)*(IF('Your Debts'!$G$8=0,0,INDEX('Your Debts'!$C$5:$C$12,'Your Debts'!$G$8)/12)),2) | N53: =MIN((O52)+M53,MAX(0,$C53-(E53+H53+K53))) | O53: =ROUND(MAX(0,(O52)+M53-N53),2) | P53: =ROUND((R52)*(IF('Your Debts'!$G$9=0,0,INDEX('Your Debts'!$C$5:$C$12,'Your Debts'!$G$9)/12)),2) | Q53: =MIN((R52)+P53,MAX(0,$C53-(E53+H53+K53+N53))) | R53: =ROUND(MAX(0,(R52)+P53-Q53),2) | S53: =ROUND((U52)*(IF('Your Debts'!$G$10=0,0,INDEX('Your Debts'!$C$5:$C$12,'Your Debts'!$G$10)/12)),2) | T53: =MIN((U52)+S53,MAX(0,$C53-(E53+H53+K53+N53+Q53))) | U53: =ROUND(MAX(0,(U52)+S53-T53),2) | V53: =ROUND((X52)*(IF('Your Debts'!$G$11=0,0,INDEX('Your Debts'!$C$5:$C$12,'Your Debts'!$G$11)/12)),2) | W53: =MIN((X52)+V53,MAX(0,$C53-(E53+H53+K53+N53+Q53+T53))) | X53: =ROUND(MAX(0,(X52)+V53-W53),2) | Y53: =ROUND((AA52)*(IF('Your Debts'!$G$12=0,0,INDEX('Your Debts'!$C$5:$C$12,'Your Debts'!$G$12)/12)),2) | Z53: =MIN((AA52)+Y53,MAX(0,$C53-(E53+H53+K53+N53+Q53+T53+W53))) | AA53: =ROUND(MAX(0,(AA52)+Y53-Z53),2) | AB53: =F53+I53+L53+O53+R53+U53+X53+AA53 | AC53: =AC52+D53+G53+J53+M53+P53+S53+V53+Y53
A54: 49 | B54: =EDATE('Your Debts'!$B$19,48) | C54: ='Your Debts'!$B$18 | D54: =ROUND((F53)*(IF('Your Debts'!$G$5=0,0,INDEX('Your Debts'!$C$5:$C$12,'Your Debts'!$G$5)/12)),2) | E54: =MIN((F53)+D54,MAX(0,$C54-(0))) | F54: =ROUND(MAX(0,(F53)+D54-E54),2) | G54: =ROUND((I53)*(IF('Your Debts'!$G$6=0,0,INDEX('Your Debts'!$C$5:$C$12,'Your Debts'!$G$6)/12)),2) | H54: =MIN((I53)+G54,MAX(0,$C54-(E54))) | I54: =ROUND(MAX(0,(I53)+G54-H54),2) | J54: =ROUND((L53)*(IF('Your Debts'!$G$7=0,0,INDEX('Your Debts'!$C$5:$C$12,'Your Debts'!$G$7)/12)),2) | K54: =MIN((L53)+J54,MAX(0,$C54-(E54+H54))) | L54: =ROUND(MAX(0,(L53)+J54-K54),2) | M54: =ROUND((O53)*(IF('Your Debts'!$G$8=0,0,INDEX('Your Debts'!$C$5:$C$12,'Your Debts'!$G$8)/12)),2) | N54: =MIN((O53)+M54,MAX(0,$C54-(E54+H54+K54))) | O54: =ROUND(MAX(0,(O53)+M54-N54),2) | P54: =ROUND((R53)*(IF('Your Debts'!$G$9=0,0,INDEX('Your Debts'!$C$5:$C$12,'Your Debts'!$G$9)/12)),2) | Q54: =MIN((R53)+P54,MAX(0,$C54-(E54+H54+K54+N54))) | R54: =ROUND(MAX(0,(R53)+P54-Q54),2) | S54: =ROUND((U53)*(IF('Your Debts'!$G$10=0,0,INDEX('Your Debts'!$C$5:$C$12,'Your Debts'!$G$10)/12)),2) | T54: =MIN((U53)+S54,MAX(0,$C54-(E54+H54+K54+N54+Q54))) | U54: =ROUND(MAX(0,(U53)+S54-T54),2) | V54: =ROUND((X53)*(IF('Your Debts'!$G$11=0,0,INDEX('Your Debts'!$C$5:$C$12,'Your Debts'!$G$11)/12)),2) | W54: =MIN((X53)+V54,MAX(0,$C54-(E54+H54+K54+N54+Q54+T54))) | X54: =ROUND(MAX(0,(X53)+V54-W54),2) | Y54: =ROUND((AA53)*(IF('Your Debts'!$G$12=0,0,INDEX('Your Debts'!$C$5:$C$12,'Your Debts'!$G$12)/12)),2) | Z54: =MIN((AA53)+Y54,MAX(0,$C54-(E54+H54+K54+N54+Q54+T54+W54))) | AA54: =ROUND(MAX(0,(AA53)+Y54-Z54),2) | AB54: =F54+I54+L54+O54+R54+U54+X54+AA54 | AC54: =AC53+D54+G54+J54+M54+P54+S54+V54+Y54
A55: 50 | B55: =EDATE('Your Debts'!$B$19,49) | C55: ='Your Debts'!$B$18 | D55: =ROUND((F54)*(IF('Your Debts'!$G$5=0,0,INDEX('Your Debts'!$C$5:$C$12,'Your Debts'!$G$5)/12)),2) | E55: =MIN((F54)+D55,MAX(0,$C55-(0))) | F55: =ROUND(MAX(0,(F54)+D55-E55),2) | G55: =ROUND((I54)*(IF('Your Debts'!$G$6=0,0,INDEX('Your Debts'!$C$5:$C$12,'Your Debts'!$G$6)/12)),2) | H55: =MIN((I54)+G55,MAX(0,$C55-(E55))) | I55: =ROUND(MAX(0,(I54)+G55-H55),2) | J55: =ROUND((L54)*(IF('Your Debts'!$G$7=0,0,INDEX('Your Debts'!$C$5:$C$12,'Your Debts'!$G$7)/12)),2) | K55: =MIN((L54)+J55,MAX(0,$C55-(E55+H55))) | L55: =ROUND(MAX(0,(L54)+J55-K55),2) | M55: =ROUND((O54)*(IF('Your Debts'!$G$8=0,0,INDEX('Your Debts'!$C$5:$C$12,'Your Debts'!$G$8)/12)),2) | N55: =MIN((O54)+M55,MAX(0,$C55-(E55+H55+K55))) | O55: =ROUND(MAX(0,(O54)+M55-N55),2) | P55: =ROUND((R54)*(IF('Your Debts'!$G$9=0,0,INDEX('Your Debts'!$C$5:$C$12,'Your Debts'!$G$9)/12)),2) | Q55: =MIN((R54)+P55,MAX(0,$C55-(E55+H55+K55+N55))) | R55: =ROUND(MAX(0,(R54)+P55-Q55),2) | S55: =ROUND((U54)*(IF('Your Debts'!$G$10=0,0,INDEX('Your Debts'!$C$5:$C$12,'Your Debts'!$G$10)/12)),2) | T55: =MIN((U54)+S55,MAX(0,$C55-(E55+H55+K55+N55+Q55))) | U55: =ROUND(MAX(0,(U54)+S55-T55),2) | V55: =ROUND((X54)*(IF('Your Debts'!$G$11=0,0,INDEX('Your Debts'!$C$5:$C$12,'Your Debts'!$G$11)/12)),2) | W55: =MIN((X54)+V55,MAX(0,$C55-(E55+H55+K55+N55+Q55+T55))) | X55: =ROUND(MAX(0,(X54)+V55-W55),2) | Y55: =ROUND((AA54)*(IF('Your Debts'!$G$12=0,0,INDEX('Your Debts'!$C$5:$C$12,'Your Debts'!$G$12)/12)),2) | Z55: =MIN((AA54)+Y55,MAX(0,$C55-(E55+H55+K55+N55+Q55+T55+W55))) | AA55: =ROUND(MAX(0,(AA54)+Y55-Z55),2) | AB55: =F55+I55+L55+O55+R55+U55+X55+AA55 | AC55: =AC54+D55+G55+J55+M55+P55+S55+V55+Y55
A56: 51 | B56: =EDATE('Your Debts'!$B$19,50) | C56: ='Your Debts'!$B$18 | D56: =ROUND((F55)*(IF('Your Debts'!$G$5=0,0,INDEX('Your Debts'!$C$5:$C$12,'Your Debts'!$G$5)/12)),2) | E56: =MIN((F55)+D56,MAX(0,$C56-(0))) | F56: =ROUND(MAX(0,(F55)+D56-E56),2) | G56: =ROUND((I55)*(IF('Your Debts'!$G$6=0,0,INDEX('Your Debts'!$C$5:$C$12,'Your Debts'!$G$6)/12)),2) | H56: =MIN((I55)+G56,MAX(0,$C56-(E56))) | I56: =ROUND(MAX(0,(I55)+G56-H56),2) | J56: =ROUND((L55)*(IF('Your Debts'!$G$7=0,0,INDEX('Your Debts'!$C$5:$C$12,'Your Debts'!$G$7)/12)),2) | K56: =MIN((L55)+J56,MAX(0,$C56-(E56+H56))) | L56: =ROUND(MAX(0,(L55)+J56-K56),2) | M56: =ROUND((O55)*(IF('Your Debts'!$G$8=0,0,INDEX('Your Debts'!$C$5:$C$12,'Your Debts'!$G$8)/12)),2) | N56: =MIN((O55)+M56,MAX(0,$C56-(E56+H56+K56))) | O56: =ROUND(MAX(0,(O55)+M56-N56),2) | P56: =ROUND((R55)*(IF('Your Debts'!$G$9=0,0,INDEX('Your Debts'!$C$5:$C$12,'Your Debts'!$G$9)/12)),2) | Q56: =MIN((R55)+P56,MAX(0,$C56-(E56+H56+K56+N56))) | R56: =ROUND(MAX(0,(R55)+P56-Q56),2) | S56: =ROUND((U55)*(IF('Your Debts'!$G$10=0,0,INDEX('Your Debts'!$C$5:$C$12,'Your Debts'!$G$10)/12)),2) | T56: =MIN((U55)+S56,MAX(0,$C56-(E56+H56+K56+N56+Q56))) | U56: =ROUND(MAX(0,(U55)+S56-T56),2) | V56: =ROUND((X55)*(IF('Your Debts'!$G$11=0,0,INDEX('Your Debts'!$C$5:$C$12,'Your Debts'!$G$11)/12)),2) | W56: =MIN((X55)+V56,MAX(0,$C56-(E56+H56+K56+N56+Q56+T56))) | X56: =ROUND(MAX(0,(X55)+V56-W56),2) | Y56: =ROUND((AA55)*(IF('Your Debts'!$G$12=0,0,INDEX('Your Debts'!$C$5:$C$12,'Your Debts'!$G$12)/12)),2) | Z56: =MIN((AA55)+Y56,MAX(0,$C56-(E56+H56+K56+N56+Q56+T56+W56))) | AA56: =ROUND(MAX(0,(AA55)+Y56-Z56),2) | AB56: =F56+I56+L56+O56+R56+U56+X56+AA56 | AC56: =AC55+D56+G56+J56+M56+P56+S56+V56+Y56
A57: 52 | B57: =EDATE('Your Debts'!$B$19,51) | C57: ='Your Debts'!$B$18 | D57: =ROUND((F56)*(IF('Your Debts'!$G$5=0,0,INDEX('Your Debts'!$C$5:$C$12,'Your Debts'!$G$5)/12)),2) | E57: =MIN((F56)+D57,MAX(0,$C57-(0))) | F57: =ROUND(MAX(0,(F56)+D57-E57),2) | G57: =ROUND((I56)*(IF('Your Debts'!$G$6=0,0,INDEX('Your Debts'!$C$5:$C$12,'Your Debts'!$G$6)/12)),2) | H57: =MIN((I56)+G57,MAX(0,$C57-(E57))) | I57: =ROUND(MAX(0,(I56)+G57-H57),2) | J57: =ROUND((L56)*(IF('Your Debts'!$G$7=0,0,INDEX('Your Debts'!$C$5:$C$12,'Your Debts'!$G$7)/12)),2) | K57: =MIN((L56)+J57,MAX(0,$C57-(E57+H57))) | L57: =ROUND(MAX(0,(L56)+J57-K57),2) | M57: =ROUND((O56)*(IF('Your Debts'!$G$8=0,0,INDEX('Your Debts'!$C$5:$C$12,'Your Debts'!$G$8)/12)),2) | N57: =MIN((O56)+M57,MAX(0,$C57-(E57+H57+K57))) | O57: =ROUND(MAX(0,(O56)+M57-N57),2) | P57: =ROUND((R56)*(IF('Your Debts'!$G$9=0,0,INDEX('Your Debts'!$C$5:$C$12,'Your Debts'!$G$9)/12)),2) | Q57: =MIN((R56)+P57,MAX(0,$C57-(E57+H57+K57+N57))) | R57: =ROUND(MAX(0,(R56)+P57-Q57),2) | S57: =ROUND((U56)*(IF('Your Debts'!$G$10=0,0,INDEX('Your Debts'!$C$5:$C$12,'Your Debts'!$G$10)/12)),2) | T57: =MIN((U56)+S57,MAX(0,$C57-(E57+H57+K57+N57+Q57))) | U57: =ROUND(MAX(0,(U56)+S57-T57),2) | V57: =ROUND((X56)*(IF('Your Debts'!$G$11=0,0,INDEX('Your Debts'!$C$5:$C$12,'Your Debts'!$G$11)/12)),2) | W57: =MIN((X56)+V57,MAX(0,$C57-(E57+H57+K57+N57+Q57+T57))) | X57: =ROUND(MAX(0,(X56)+V57-W57),2) | Y57: =ROUND((AA56)*(IF('Your Debts'!$G$12=0,0,INDEX('Your Debts'!$C$5:$C$12,'Your Debts'!$G$12)/12)),2) | Z57: =MIN((AA56)+Y57,MAX(0,$C57-(E57+H57+K57+N57+Q57+T57+W57))) | AA57: =ROUND(MAX(0,(AA56)+Y57-Z57),2) | AB57: =F57+I57+L57+O57+R57+U57+X57+AA57 | AC57: =AC56+D57+G57+J57+M57+P57+S57+V57+Y57
A58: 53 | B58: =EDATE('Your Debts'!$B$19,52) | C58: ='Your Debts'!$B$18 | D58: =ROUND((F57)*(IF('Your Debts'!$G$5=0,0,INDEX('Your Debts'!$C$5:$C$12,'Your Debts'!$G$5)/12)),2) | E58: =MIN((F57)+D58,MAX(0,$C58-(0))) | F58: =ROUND(MAX(0,(F57)+D58-E58),2) | G58: =ROUND((I57)*(IF('Your Debts'!$G$6=0,0,INDEX('Your Debts'!$C$5:$C$12,'Your Debts'!$G$6)/12)),2) | H58: =MIN((I57)+G58,MAX(0,$C58-(E58))) | I58: =ROUND(MAX(0,(I57)+G58-H58),2) | J58: =ROUND((L57)*(IF('Your Debts'!$G$7=0,0,INDEX('Your Debts'!$C$5:$C$12,'Your Debts'!$G$7)/12)),2) | K58: =MIN((L57)+J58,MAX(0,$C58-(E58+H58))) | L58: =ROUND(MAX(0,(L57)+J58-K58),2) | M58: =ROUND((O57)*(IF('Your Debts'!$G$8=0,0,INDEX('Your Debts'!$C$5:$C$12,'Your Debts'!$G$8)/12)),2) | N58: =MIN((O57)+M58,MAX(0,$C58-(E58+H58+K58))) | O58: =ROUND(MAX(0,(O57)+M58-N58),2) | P58: =ROUND((R57)*(IF('Your Debts'!$G$9=0,0,INDEX('Your Debts'!$C$5:$C$12,'Your Debts'!$G$9)/12)),2) | Q58: =MIN((R57)+P58,MAX(0,$C58-(E58+H58+K58+N58))) | R58: =ROUND(MAX(0,(R57)+P58-Q58),2) | S58: =ROUND((U57)*(IF('Your Debts'!$G$10=0,0,INDEX('Your Debts'!$C$5:$C$12,'Your Debts'!$G$10)/12)),2) | T58: =MIN((U57)+S58,MAX(0,$C58-(E58+H58+K58+N58+Q58))) | U58: =ROUND(MAX(0,(U57)+S58-T58),2) | V58: =ROUND((X57)*(IF('Your Debts'!$G$11=0,0,INDEX('Your Debts'!$C$5:$C$12,'Your Debts'!$G$11)/12)),2) | W58: =MIN((X57)+V58,MAX(0,$C58-(E58+H58+K58+N58+Q58+T58))) | X58: =ROUND(MAX(0,(X57)+V58-W58),2) | Y58: =ROUND((AA57)*(IF('Your Debts'!$G$12=0,0,INDEX('Your Debts'!$C$5:$C$12,'Your Debts'!$G$12)/12)),2) | Z58: =MIN((AA57)+Y58,MAX(0,$C58-(E58+H58+K58+N58+Q58+T58+W58))) | AA58: =ROUND(MAX(0,(AA57)+Y58-Z58),2) | AB58: =F58+I58+L58+O58+R58+U58+X58+AA58 | AC58: =AC57+D58+G58+J58+M58+P58+S58+V58+Y58
A59: 54 | B59: =EDATE('Your Debts'!$B$19,53) | C59: ='Your Debts'!$B$18 | D59: =ROUND((F58)*(IF('Your Debts'!$G$5=0,0,INDEX('Your Debts'!$C$5:$C$12,'Your Debts'!$G$5)/12)),2) | E59: =MIN((F58)+D59,MAX(0,$C59-(0))) | F59: =ROUND(MAX(0,(F58)+D59-E59),2) | G59: =ROUND((I58)*(IF('Your Debts'!$G$6=0,0,INDEX('Your Debts'!$C$5:$C$12,'Your Debts'!$G$6)/12)),2) | H59: =MIN((I58)+G59,MAX(0,$C59-(E59))) | I59: =ROUND(MAX(0,(I58)+G59-H59),2) | J59: =ROUND((L58)*(IF('Your Debts'!$G$7=0,0,INDEX('Your Debts'!$C$5:$C$12,'Your Debts'!$G$7)/12)),2) | K59: =MIN((L58)+J59,MAX(0,$C59-(E59+H59))) | L59: =ROUND(MAX(0,(L58)+J59-K59),2) | M59: =ROUND((O58)*(IF('Your Debts'!$G$8=0,0,INDEX('Your Debts'!$C$5:$C$12,'Your Debts'!$G$8)/12)),2) | N59: =MIN((O58)+M59,MAX(0,$C59-(E59+H59+K59))) | O59: =ROUND(MAX(0,(O58)+M59-N59),2) | P59: =ROUND((R58)*(IF('Your Debts'!$G$9=0,0,INDEX('Your Debts'!$C$5:$C$12,'Your Debts'!$G$9)/12)),2) | Q59: =MIN((R58)+P59,MAX(0,$C59-(E59+H59+K59+N59))) | R59: =ROUND(MAX(0,(R58)+P59-Q59),2) | S59: =ROUND((U58)*(IF('Your Debts'!$G$10=0,0,INDEX('Your Debts'!$C$5:$C$12,'Your Debts'!$G$10)/12)),2) | T59: =MIN((U58)+S59,MAX(0,$C59-(E59+H59+K59+N59+Q59))) | U59: =ROUND(MAX(0,(U58)+S59-T59),2) | V59: =ROUND((X58)*(IF('Your Debts'!$G$11=0,0,INDEX('Your Debts'!$C$5:$C$12,'Your Debts'!$G$11)/12)),2) | W59: =MIN((X58)+V59,MAX(0,$C59-(E59+H59+K59+N59+Q59+T59))) | X59: =ROUND(MAX(0,(X58)+V59-W59),2) | Y59: =ROUND((AA58)*(IF('Your Debts'!$G$12=0,0,INDEX('Your Debts'!$C$5:$C$12,'Your Debts'!$G$12)/12)),2) | Z59: =MIN((AA58)+Y59,MAX(0,$C59-(E59+H59+K59+N59+Q59+T59+W59))) | AA59: =ROUND(MAX(0,(AA58)+Y59-Z59),2) | AB59: =F59+I59+L59+O59+R59+U59+X59+AA59 | AC59: =AC58+D59+G59+J59+M59+P59+S59+V59+Y59
A60: 55 | B60: =EDATE('Your Debts'!$B$19,54) | C60: ='Your Debts'!$B$18 | D60: =ROUND((F59)*(IF('Your Debts'!$G$5=0,0,INDEX('Your Debts'!$C$5:$C$12,'Your Debts'!$G$5)/12)),2) | E60: =MIN((F59)+D60,MAX(0,$C60-(0))) | F60: =ROUND(MAX(0,(F59)+D60-E60),2) | G60: =ROUND((I59)*(IF('Your Debts'!$G$6=0,0,INDEX('Your Debts'!$C$5:$C$12,'Your Debts'!$G$6)/12)),2) | H60: =MIN((I59)+G60,MAX(0,$C60-(E60))) | I60: =ROUND(MAX(0,(I59)+G60-H60),2) | J60: =ROUND((L59)*(IF('Your Debts'!$G$7=0,0,INDEX('Your Debts'!$C$5:$C$12,'Your Debts'!$G$7)/12)),2) | K60: =MIN((L59)+J60,MAX(0,$C60-(E60+H60))) | L60: =ROUND(MAX(0,(L59)+J60-K60),2) | M60: =ROUND((O59)*(IF('Your Debts'!$G$8=0,0,INDEX('Your Debts'!$C$5:$C$12,'Your Debts'!$G$8)/12)),2) | N60: =MIN((O59)+M60,MAX(0,$C60-(E60+H60+K60))) | O60: =ROUND(MAX(0,(O59)+M60-N60),2) | P60: =ROUND((R59)*(IF('Your Debts'!$G$9=0,0,INDEX('Your Debts'!$C$5:$C$12,'Your Debts'!$G$9)/12)),2) | Q60: =MIN((R59)+P60,MAX(0,$C60-(E60+H60+K60+N60))) | R60: =ROUND(MAX(0,(R59)+P60-Q60),2) | S60: =ROUND((U59)*(IF('Your Debts'!$G$10=0,0,INDEX('Your Debts'!$C$5:$C$12,'Your Debts'!$G$10)/12)),2) | T60: =MIN((U59)+S60,MAX(0,$C60-(E60+H60+K60+N60+Q60))) | U60: =ROUND(MAX(0,(U59)+S60-T60),2) | V60: =ROUND((X59)*(IF('Your Debts'!$G$11=0,0,INDEX('Your Debts'!$C$5:$C$12,'Your Debts'!$G$11)/12)),2) | W60: =MIN((X59)+V60,MAX(0,$C60-(E60+H60+K60+N60+Q60+T60))) | X60: =ROUND(MAX(0,(X59)+V60-W60),2) | Y60: =ROUND((AA59)*(IF('Your Debts'!$G$12=0,0,INDEX('Your Debts'!$C$5:$C$12,'Your Debts'!$G$12)/12)),2) | Z60: =MIN((AA59)+Y60,MAX(0,$C60-(E60+H60+K60+N60+Q60+T60+W60))) | AA60: =ROUND(MAX(0,(AA59)+Y60-Z60),2) | AB60: =F60+I60+L60+O60+R60+U60+X60+AA60 | AC60: =AC59+D60+G60+J60+M60+P60+S60+V60+Y60
A61: 56 | B61: =EDATE('Your Debts'!$B$19,55) | C61: ='Your Debts'!$B$18 | D61: =ROUND((F60)*(IF('Your Debts'!$G$5=0,0,INDEX('Your Debts'!$C$5:$C$12,'Your Debts'!$G$5)/12)),2) | E61: =MIN((F60)+D61,MAX(0,$C61-(0))) | F61: =ROUND(MAX(0,(F60)+D61-E61),2) | G61: =ROUND((I60)*(IF('Your Debts'!$G$6=0,0,INDEX('Your Debts'!$C$5:$C$12,'Your Debts'!$G$6)/12)),2) | H61: =MIN((I60)+G61,MAX(0,$C61-(E61))) | I61: =ROUND(MAX(0,(I60)+G61-H61),2) | J61: =ROUND((L60)*(IF('Your Debts'!$G$7=0,0,INDEX('Your Debts'!$C$5:$C$12,'Your Debts'!$G$7)/12)),2) | K61: =MIN((L60)+J61,MAX(0,$C61-(E61+H61))) | L61: =ROUND(MAX(0,(L60)+J61-K61),2) | M61: =ROUND((O60)*(IF('Your Debts'!$G$8=0,0,INDEX('Your Debts'!$C$5:$C$12,'Your Debts'!$G$8)/12)),2) | N61: =MIN((O60)+M61,MAX(0,$C61-(E61+H61+K61))) | O61: =ROUND(MAX(0,(O60)+M61-N61),2) | P61: =ROUND((R60)*(IF('Your Debts'!$G$9=0,0,INDEX('Your Debts'!$C$5:$C$12,'Your Debts'!$G$9)/12)),2) | Q61: =MIN((R60)+P61,MAX(0,$C61-(E61+H61+K61+N61))) | R61: =ROUND(MAX(0,(R60)+P61-Q61),2) | S61: =ROUND((U60)*(IF('Your Debts'!$G$10=0,0,INDEX('Your Debts'!$C$5:$C$12,'Your Debts'!$G$10)/12)),2) | T61: =MIN((U60)+S61,MAX(0,$C61-(E61+H61+K61+N61+Q61))) | U61: =ROUND(MAX(0,(U60)+S61-T61),2) | V61: =ROUND((X60)*(IF('Your Debts'!$G$11=0,0,INDEX('Your Debts'!$C$5:$C$12,'Your Debts'!$G$11)/12)),2) | W61: =MIN((X60)+V61,MAX(0,$C61-(E61+H61+K61+N61+Q61+T61))) | X61: =ROUND(MAX(0,(X60)+V61-W61),2) | Y61: =ROUND((AA60)*(IF('Your Debts'!$G$12=0,0,INDEX('Your Debts'!$C$5:$C$12,'Your Debts'!$G$12)/12)),2) | Z61: =MIN((AA60)+Y61,MAX(0,$C61-(E61+H61+K61+N61+Q61+T61+W61))) | AA61: =ROUND(MAX(0,(AA60)+Y61-Z61),2) | AB61: =F61+I61+L61+O61+R61+U61+X61+AA61 | AC61: =AC60+D61+G61+J61+M61+P61+S61+V61+Y61
A62: 57 | B62: =EDATE('Your Debts'!$B$19,56) | C62: ='Your Debts'!$B$18 | D62: =ROUND((F61)*(IF('Your Debts'!$G$5=0,0,INDEX('Your Debts'!$C$5:$C$12,'Your Debts'!$G$5)/12)),2) | E62: =MIN((F61)+D62,MAX(0,$C62-(0))) | F62: =ROUND(MAX(0,(F61)+D62-E62),2) | G62: =ROUND((I61)*(IF('Your Debts'!$G$6=0,0,INDEX('Your Debts'!$C$5:$C$12,'Your Debts'!$G$6)/12)),2) | H62: =MIN((I61)+G62,MAX(0,$C62-(E62))) | I62: =ROUND(MAX(0,(I61)+G62-H62),2) | J62: =ROUND((L61)*(IF('Your Debts'!$G$7=0,0,INDEX('Your Debts'!$C$5:$C$12,'Your Debts'!$G$7)/12)),2) | K62: =MIN((L61)+J62,MAX(0,$C62-(E62+H62))) | L62: =ROUND(MAX(0,(L61)+J62-K62),2) | M62: =ROUND((O61)*(IF('Your Debts'!$G$8=0,0,INDEX('Your Debts'!$C$5:$C$12,'Your Debts'!$G$8)/12)),2) | N62: =MIN((O61)+M62,MAX(0,$C62-(E62+H62+K62))) | O62: =ROUND(MAX(0,(O61)+M62-N62),2) | P62: =ROUND((R61)*(IF('Your Debts'!$G$9=0,0,INDEX('Your Debts'!$C$5:$C$12,'Your Debts'!$G$9)/12)),2) | Q62: =MIN((R61)+P62,MAX(0,$C62-(E62+H62+K62+N62))) | R62: =ROUND(MAX(0,(R61)+P62-Q62),2) | S62: =ROUND((U61)*(IF('Your Debts'!$G$10=0,0,INDEX('Your Debts'!$C$5:$C$12,'Your Debts'!$G$10)/12)),2) | T62: =MIN((U61)+S62,MAX(0,$C62-(E62+H62+K62+N62+Q62))) | U62: =ROUND(MAX(0,(U61)+S62-T62),2) | V62: =ROUND((X61)*(IF('Your Debts'!$G$11=0,0,INDEX('Your Debts'!$C$5:$C$12,'Your Debts'!$G$11)/12)),2) | W62: =MIN((X61)+V62,MAX(0,$C62-(E62+H62+K62+N62+Q62+T62))) | X62: =ROUND(MAX(0,(X61)+V62-W62),2) | Y62: =ROUND((AA61)*(IF('Your Debts'!$G$12=0,0,INDEX('Your Debts'!$C$5:$C$12,'Your Debts'!$G$12)/12)),2) | Z62: =MIN((AA61)+Y62,MAX(0,$C62-(E62+H62+K62+N62+Q62+T62+W62))) | AA62: =ROUND(MAX(0,(AA61)+Y62-Z62),2) | AB62: =F62+I62+L62+O62+R62+U62+X62+AA62 | AC62: =AC61+D62+G62+J62+M62+P62+S62+V62+Y62
A63: 58 | B63: =EDATE('Your Debts'!$B$19,57) | C63: ='Your Debts'!$B$18 | D63: =ROUND((F62)*(IF('Your Debts'!$G$5=0,0,INDEX('Your Debts'!$C$5:$C$12,'Your Debts'!$G$5)/12)),2) | E63: =MIN((F62)+D63,MAX(0,$C63-(0))) | F63: =ROUND(MAX(0,(F62)+D63-E63),2) | G63: =ROUND((I62)*(IF('Your Debts'!$G$6=0,0,INDEX('Your Debts'!$C$5:$C$12,'Your Debts'!$G$6)/12)),2) | H63: =MIN((I62)+G63,MAX(0,$C63-(E63))) | I63: =ROUND(MAX(0,(I62)+G63-H63),2) | J63: =ROUND((L62)*(IF('Your Debts'!$G$7=0,0,INDEX('Your Debts'!$C$5:$C$12,'Your Debts'!$G$7)/12)),2) | K63: =MIN((L62)+J63,MAX(0,$C63-(E63+H63))) | L63: =ROUND(MAX(0,(L62)+J63-K63),2) | M63: =ROUND((O62)*(IF('Your Debts'!$G$8=0,0,INDEX('Your Debts'!$C$5:$C$12,'Your Debts'!$G$8)/12)),2) | N63: =MIN((O62)+M63,MAX(0,$C63-(E63+H63+K63))) | O63: =ROUND(MAX(0,(O62)+M63-N63),2) | P63: =ROUND((R62)*(IF('Your Debts'!$G$9=0,0,INDEX('Your Debts'!$C$5:$C$12,'Your Debts'!$G$9)/12)),2) | Q63: =MIN((R62)+P63,MAX(0,$C63-(E63+H63+K63+N63))) | R63: =ROUND(MAX(0,(R62)+P63-Q63),2) | S63: =ROUND((U62)*(IF('Your Debts'!$G$10=0,0,INDEX('Your Debts'!$C$5:$C$12,'Your Debts'!$G$10)/12)),2) | T63: =MIN((U62)+S63,MAX(0,$C63-(E63+H63+K63+N63+Q63))) | U63: =ROUND(MAX(0,(U62)+S63-T63),2) | V63: =ROUND((X62)*(IF('Your Debts'!$G$11=0,0,INDEX('Your Debts'!$C$5:$C$12,'Your Debts'!$G$11)/12)),2) | W63: =MIN((X62)+V63,MAX(0,$C63-(E63+H63+K63+N63+Q63+T63))) | X63: =ROUND(MAX(0,(X62)+V63-W63),2) | Y63: =ROUND((AA62)*(IF('Your Debts'!$G$12=0,0,INDEX('Your Debts'!$C$5:$C$12,'Your Debts'!$G$12)/12)),2) | Z63: =MIN((AA62)+Y63,MAX(0,$C63-(E63+H63+K63+N63+Q63+T63+W63))) | AA63: =ROUND(MAX(0,(AA62)+Y63-Z63),2) | AB63: =F63+I63+L63+O63+R63+U63+X63+AA63 | AC63: =AC62+D63+G63+J63+M63+P63+S63+V63+Y63
A64: 59 | B64: =EDATE('Your Debts'!$B$19,58) | C64: ='Your Debts'!$B$18 | D64: =ROUND((F63)*(IF('Your Debts'!$G$5=0,0,INDEX('Your Debts'!$C$5:$C$12,'Your Debts'!$G$5)/12)),2) | E64: =MIN((F63)+D64,MAX(0,$C64-(0))) | F64: =ROUND(MAX(0,(F63)+D64-E64),2) | G64: =ROUND((I63)*(IF('Your Debts'!$G$6=0,0,INDEX('Your Debts'!$C$5:$C$12,'Your Debts'!$G$6)/12)),2) | H64: =MIN((I63)+G64,MAX(0,$C64-(E64))) | I64: =ROUND(MAX(0,(I63)+G64-H64),2) | J64: =ROUND((L63)*(IF('Your Debts'!$G$7=0,0,INDEX('Your Debts'!$C$5:$C$12,'Your Debts'!$G$7)/12)),2) | K64: =MIN((L63)+J64,MAX(0,$C64-(E64+H64))) | L64: =ROUND(MAX(0,(L63)+J64-K64),2) | M64: =ROUND((O63)*(IF('Your Debts'!$G$8=0,0,INDEX('Your Debts'!$C$5:$C$12,'Your Debts'!$G$8)/12)),2) | N64: =MIN((O63)+M64,MAX(0,$C64-(E64+H64+K64))) | O64: =ROUND(MAX(0,(O63)+M64-N64),2) | P64: =ROUND((R63)*(IF('Your Debts'!$G$9=0,0,INDEX('Your Debts'!$C$5:$C$12,'Your Debts'!$G$9)/12)),2) | Q64: =MIN((R63)+P64,MAX(0,$C64-(E64+H64+K64+N64))) | R64: =ROUND(MAX(0,(R63)+P64-Q64),2) | S64: =ROUND((U63)*(IF('Your Debts'!$G$10=0,0,INDEX('Your Debts'!$C$5:$C$12,'Your Debts'!$G$10)/12)),2) | T64: =MIN((U63)+S64,MAX(0,$C64-(E64+H64+K64+N64+Q64))) | U64: =ROUND(MAX(0,(U63)+S64-T64),2) | V64: =ROUND((X63)*(IF('Your Debts'!$G$11=0,0,INDEX('Your Debts'!$C$5:$C$12,'Your Debts'!$G$11)/12)),2) | W64: =MIN((X63)+V64,MAX(0,$C64-(E64+H64+K64+N64+Q64+T64))) | X64: =ROUND(MAX(0,(X63)+V64-W64),2) | Y64: =ROUND((AA63)*(IF('Your Debts'!$G$12=0,0,INDEX('Your Debts'!$C$5:$C$12,'Your Debts'!$G$12)/12)),2) | Z64: =MIN((AA63)+Y64,MAX(0,$C64-(E64+H64+K64+N64+Q64+T64+W64))) | AA64: =ROUND(MAX(0,(AA63)+Y64-Z64),2) | AB64: =F64+I64+L64+O64+R64+U64+X64+AA64 | AC64: =AC63+D64+G64+J64+M64+P64+S64+V64+Y64
A65: 60 | B65: =EDATE('Your Debts'!$B$19,59) | C65: ='Your Debts'!$B$18 | D65: =ROUND((F64)*(IF('Your Debts'!$G$5=0,0,INDEX('Your Debts'!$C$5:$C$12,'Your Debts'!$G$5)/12)),2) | E65: =MIN((F64)+D65,MAX(0,$C65-(0))) | F65: =ROUND(MAX(0,(F64)+D65-E65),2) | G65: =ROUND((I64)*(IF('Your Debts'!$G$6=0,0,INDEX('Your Debts'!$C$5:$C$12,'Your Debts'!$G$6)/12)),2) | H65: =MIN((I64)+G65,MAX(0,$C65-(E65))) | I65: =ROUND(MAX(0,(I64)+G65-H65),2) | J65: =ROUND((L64)*(IF('Your Debts'!$G$7=0,0,INDEX('Your Debts'!$C$5:$C$12,'Your Debts'!$G$7)/12)),2) | K65: =MIN((L64)+J65,MAX(0,$C65-(E65+H65))) | L65: =ROUND(MAX(0,(L64)+J65-K65),2) | M65: =ROUND((O64)*(IF('Your Debts'!$G$8=0,0,INDEX('Your Debts'!$C$5:$C$12,'Your Debts'!$G$8)/12)),2) | N65: =MIN((O64)+M65,MAX(0,$C65-(E65+H65+K65))) | O65: =ROUND(MAX(0,(O64)+M65-N65),2) | P65: =ROUND((R64)*(IF('Your Debts'!$G$9=0,0,INDEX('Your Debts'!$C$5:$C$12,'Your Debts'!$G$9)/12)),2) | Q65: =MIN((R64)+P65,MAX(0,$C65-(E65+H65+K65+N65))) | R65: =ROUND(MAX(0,(R64)+P65-Q65),2) | S65: =ROUND((U64)*(IF('Your Debts'!$G$10=0,0,INDEX('Your Debts'!$C$5:$C$12,'Your Debts'!$G$10)/12)),2) | T65: =MIN((U64)+S65,MAX(0,$C65-(E65+H65+K65+N65+Q65))) | U65: =ROUND(MAX(0,(U64)+S65-T65),2) | V65: =ROUND((X64)*(IF('Your Debts'!$G$11=0,0,INDEX('Your Debts'!$C$5:$C$12,'Your Debts'!$G$11)/12)),2) | W65: =MIN((X64)+V65,MAX(0,$C65-(E65+H65+K65+N65+Q65+T65))) | X65: =ROUND(MAX(0,(X64)+V65-W65),2) | Y65: =ROUND((AA64)*(IF('Your Debts'!$G$12=0,0,INDEX('Your Debts'!$C$5:$C$12,'Your Debts'!$G$12)/12)),2) | Z65: =MIN((AA64)+Y65,MAX(0,$C65-(E65+H65+K65+N65+Q65+T65+W65))) | AA65: =ROUND(MAX(0,(AA64)+Y65-Z65),2) | AB65: =F65+I65+L65+O65+R65+U65+X65+AA65 | AC65: =AC64+D65+G65+J65+M65+P65+S65+V65+Y65
A66: 61 | B66: =EDATE('Your Debts'!$B$19,60) | C66: ='Your Debts'!$B$18 | D66: =ROUND((F65)*(IF('Your Debts'!$G$5=0,0,INDEX('Your Debts'!$C$5:$C$12,'Your Debts'!$G$5)/12)),2) | E66: =MIN((F65)+D66,MAX(0,$C66-(0))) | F66: =ROUND(MAX(0,(F65)+D66-E66),2) | G66: =ROUND((I65)*(IF('Your Debts'!$G$6=0,0,INDEX('Your Debts'!$C$5:$C$12,'Your Debts'!$G$6)/12)),2) | H66: =MIN((I65)+G66,MAX(0,$C66-(E66))) | I66: =ROUND(MAX(0,(I65)+G66-H66),2) | J66: =ROUND((L65)*(IF('Your Debts'!$G$7=0,0,INDEX('Your Debts'!$C$5:$C$12,'Your Debts'!$G$7)/12)),2) | K66: =MIN((L65)+J66,MAX(0,$C66-(E66+H66))) | L66: =ROUND(MAX(0,(L65)+J66-K66),2) | M66: =ROUND((O65)*(IF('Your Debts'!$G$8=0,0,INDEX('Your Debts'!$C$5:$C$12,'Your Debts'!$G$8)/12)),2) | N66: =MIN((O65)+M66,MAX(0,$C66-(E66+H66+K66))) | O66: =ROUND(MAX(0,(O65)+M66-N66),2) | P66: =ROUND((R65)*(IF('Your Debts'!$G$9=0,0,INDEX('Your Debts'!$C$5:$C$12,'Your Debts'!$G$9)/12)),2) | Q66: =MIN((R65)+P66,MAX(0,$C66-(E66+H66+K66+N66))) | R66: =ROUND(MAX(0,(R65)+P66-Q66),2) | S66: =ROUND((U65)*(IF('Your Debts'!$G$10=0,0,INDEX('Your Debts'!$C$5:$C$12,'Your Debts'!$G$10)/12)),2) | T66: =MIN((U65)+S66,MAX(0,$C66-(E66+H66+K66+N66+Q66))) | U66: =ROUND(MAX(0,(U65)+S66-T66),2) | V66: =ROUND((X65)*(IF('Your Debts'!$G$11=0,0,INDEX('Your Debts'!$C$5:$C$12,'Your Debts'!$G$11)/12)),2) | W66: =MIN((X65)+V66,MAX(0,$C66-(E66+H66+K66+N66+Q66+T66))) | X66: =ROUND(MAX(0,(X65)+V66-W66),2) | Y66: =ROUND((AA65)*(IF('Your Debts'!$G$12=0,0,INDEX('Your Debts'!$C$5:$C$12,'Your Debts'!$G$12)/12)),2) | Z66: =MIN((AA65)+Y66,MAX(0,$C66-(E66+H66+K66+N66+Q66+T66+W66))) | AA66: =ROUND(MAX(0,(AA65)+Y66-Z66),2) | AB66: =F66+I66+L66+O66+R66+U66+X66+AA66 | AC66: =AC65+D66+G66+J66+M66+P66+S66+V66+Y66
A67: 62 | B67: =EDATE('Your Debts'!$B$19,61) | C67: ='Your Debts'!$B$18 | D67: =ROUND((F66)*(IF('Your Debts'!$G$5=0,0,INDEX('Your Debts'!$C$5:$C$12,'Your Debts'!$G$5)/12)),2) | E67: =MIN((F66)+D67,MAX(0,$C67-(0))) | F67: =ROUND(MAX(0,(F66)+D67-E67),2) | G67: =ROUND((I66)*(IF('Your Debts'!$G$6=0,0,INDEX('Your Debts'!$C$5:$C$12,'Your Debts'!$G$6)/12)),2) | H67: =MIN((I66)+G67,MAX(0,$C67-(E67))) | I67: =ROUND(MAX(0,(I66)+G67-H67),2) | J67: =ROUND((L66)*(IF('Your Debts'!$G$7=0,0,INDEX('Your Debts'!$C$5:$C$12,'Your Debts'!$G$7)/12)),2) | K67: =MIN((L66)+J67,MAX(0,$C67-(E67+H67))) | L67: =ROUND(MAX(0,(L66)+J67-K67),2) | M67: =ROUND((O66)*(IF('Your Debts'!$G$8=0,0,INDEX('Your Debts'!$C$5:$C$12,'Your Debts'!$G$8)/12)),2) | N67: =MIN((O66)+M67,MAX(0,$C67-(E67+H67+K67))) | O67: =ROUND(MAX(0,(O66)+M67-N67),2) | P67: =ROUND((R66)*(IF('Your Debts'!$G$9=0,0,INDEX('Your Debts'!$C$5:$C$12,'Your Debts'!$G$9)/12)),2) | Q67: =MIN((R66)+P67,MAX(0,$C67-(E67+H67+K67+N67))) | R67: =ROUND(MAX(0,(R66)+P67-Q67),2) | S67: =ROUND((U66)*(IF('Your Debts'!$G$10=0,0,INDEX('Your Debts'!$C$5:$C$12,'Your Debts'!$G$10)/12)),2) | T67: =MIN((U66)+S67,MAX(0,$C67-(E67+H67+K67+N67+Q67))) | U67: =ROUND(MAX(0,(U66)+S67-T67),2) | V67: =ROUND((X66)*(IF('Your Debts'!$G$11=0,0,INDEX('Your Debts'!$C$5:$C$12,'Your Debts'!$G$11)/12)),2) | W67: =MIN((X66)+V67,MAX(0,$C67-(E67+H67+K67+N67+Q67+T67))) | X67: =ROUND(MAX(0,(X66)+V67-W67),2) | Y67: =ROUND((AA66)*(IF('Your Debts'!$G$12=0,0,INDEX('Your Debts'!$C$5:$C$12,'Your Debts'!$G$12)/12)),2) | Z67: =MIN((AA66)+Y67,MAX(0,$C67-(E67+H67+K67+N67+Q67+T67+W67))) | AA67: =ROUND(MAX(0,(AA66)+Y67-Z67),2) | AB67: =F67+I67+L67+O67+R67+U67+X67+AA67 | AC67: =AC66+D67+G67+J67+M67+P67+S67+V67+Y67
A68: 63 | B68: =EDATE('Your Debts'!$B$19,62) | C68: ='Your Debts'!$B$18 | D68: =ROUND((F67)*(IF('Your Debts'!$G$5=0,0,INDEX('Your Debts'!$C$5:$C$12,'Your Debts'!$G$5)/12)),2) | E68: =MIN((F67)+D68,MAX(0,$C68-(0))) | F68: =ROUND(MAX(0,(F67)+D68-E68),2) | G68: =ROUND((I67)*(IF('Your Debts'!$G$6=0,0,INDEX('Your Debts'!$C$5:$C$12,'Your Debts'!$G$6)/12)),2) | H68: =MIN((I67)+G68,MAX(0,$C68-(E68))) | I68: =ROUND(MAX(0,(I67)+G68-H68),2) | J68: =ROUND((L67)*(IF('Your Debts'!$G$7=0,0,INDEX('Your Debts'!$C$5:$C$12,'Your Debts'!$G$7)/12)),2) | K68: =MIN((L67)+J68,MAX(0,$C68-(E68+H68))) | L68: =ROUND(MAX(0,(L67)+J68-K68),2) | M68: =ROUND((O67)*(IF('Your Debts'!$G$8=0,0,INDEX('Your Debts'!$C$5:$C$12,'Your Debts'!$G$8)/12)),2) | N68: =MIN((O67)+M68,MAX(0,$C68-(E68+H68+K68))) | O68: =ROUND(MAX(0,(O67)+M68-N68),2) | P68: =ROUND((R67)*(IF('Your Debts'!$G$9=0,0,INDEX('Your Debts'!$C$5:$C$12,'Your Debts'!$G$9)/12)),2) | Q68: =MIN((R67)+P68,MAX(0,$C68-(E68+H68+K68+N68))) | R68: =ROUND(MAX(0,(R67)+P68-Q68),2) | S68: =ROUND((U67)*(IF('Your Debts'!$G$10=0,0,INDEX('Your Debts'!$C$5:$C$12,'Your Debts'!$G$10)/12)),2) | T68: =MIN((U67)+S68,MAX(0,$C68-(E68+H68+K68+N68+Q68))) | U68: =ROUND(MAX(0,(U67)+S68-T68),2) | V68: =ROUND((X67)*(IF('Your Debts'!$G$11=0,0,INDEX('Your Debts'!$C$5:$C$12,'Your Debts'!$G$11)/12)),2) | W68: =MIN((X67)+V68,MAX(0,$C68-(E68+H68+K68+N68+Q68+T68))) | X68: =ROUND(MAX(0,(X67)+V68-W68),2) | Y68: =ROUND((AA67)*(IF('Your Debts'!$G$12=0,0,INDEX('Your Debts'!$C$5:$C$12,'Your Debts'!$G$12)/12)),2) | Z68: =MIN((AA67)+Y68,MAX(0,$C68-(E68+H68+K68+N68+Q68+T68+W68))) | AA68: =ROUND(MAX(0,(AA67)+Y68-Z68),2) | AB68: =F68+I68+L68+O68+R68+U68+X68+AA68 | AC68: =AC67+D68+G68+J68+M68+P68+S68+V68+Y68
A69: 64 | B69: =EDATE('Your Debts'!$B$19,63) | C69: ='Your Debts'!$B$18 | D69: =ROUND((F68)*(IF('Your Debts'!$G$5=0,0,INDEX('Your Debts'!$C$5:$C$12,'Your Debts'!$G$5)/12)),2) | E69: =MIN((F68)+D69,MAX(0,$C69-(0))) | F69: =ROUND(MAX(0,(F68)+D69-E69),2) | G69: =ROUND((I68)*(IF('Your Debts'!$G$6=0,0,INDEX('Your Debts'!$C$5:$C$12,'Your Debts'!$G$6)/12)),2) | H69: =MIN((I68)+G69,MAX(0,$C69-(E69))) | I69: =ROUND(MAX(0,(I68)+G69-H69),2) | J69: =ROUND((L68)*(IF('Your Debts'!$G$7=0,0,INDEX('Your Debts'!$C$5:$C$12,'Your Debts'!$G$7)/12)),2) | K69: =MIN((L68)+J69,MAX(0,$C69-(E69+H69))) | L69: =ROUND(MAX(0,(L68)+J69-K69),2) | M69: =ROUND((O68)*(IF('Your Debts'!$G$8=0,0,INDEX('Your Debts'!$C$5:$C$12,'Your Debts'!$G$8)/12)),2) | N69: =MIN((O68)+M69,MAX(0,$C69-(E69+H69+K69))) | O69: =ROUND(MAX(0,(O68)+M69-N69),2) | P69: =ROUND((R68)*(IF('Your Debts'!$G$9=0,0,INDEX('Your Debts'!$C$5:$C$12,'Your Debts'!$G$9)/12)),2) | Q69: =MIN((R68)+P69,MAX(0,$C69-(E69+H69+K69+N69))) | R69: =ROUND(MAX(0,(R68)+P69-Q69),2) | S69: =ROUND((U68)*(IF('Your Debts'!$G$10=0,0,INDEX('Your Debts'!$C$5:$C$12,'Your Debts'!$G$10)/12)),2) | T69: =MIN((U68)+S69,MAX(0,$C69-(E69+H69+K69+N69+Q69))) | U69: =ROUND(MAX(0,(U68)+S69-T69),2) | V69: =ROUND((X68)*(IF('Your Debts'!$G$11=0,0,INDEX('Your Debts'!$C$5:$C$12,'Your Debts'!$G$11)/12)),2) | W69: =MIN((X68)+V69,MAX(0,$C69-(E69+H69+K69+N69+Q69+T69))) | X69: =ROUND(MAX(0,(X68)+V69-W69),2) | Y69: =ROUND((AA68)*(IF('Your Debts'!$G$12=0,0,INDEX('Your Debts'!$C$5:$C$12,'Your Debts'!$G$12)/12)),2) | Z69: =MIN((AA68)+Y69,MAX(0,$C69-(E69+H69+K69+N69+Q69+T69+W69))) | AA69: =ROUND(MAX(0,(AA68)+Y69-Z69),2) | AB69: =F69+I69+L69+O69+R69+U69+X69+AA69 | AC69: =AC68+D69+G69+J69+M69+P69+S69+V69+Y69
A70: 65 | B70: =EDATE('Your Debts'!$B$19,64) | C70: ='Your Debts'!$B$18 | D70: =ROUND((F69)*(IF('Your Debts'!$G$5=0,0,INDEX('Your Debts'!$C$5:$C$12,'Your Debts'!$G$5)/12)),2) | E70: =MIN((F69)+D70,MAX(0,$C70-(0))) | F70: =ROUND(MAX(0,(F69)+D70-E70),2) | G70: =ROUND((I69)*(IF('Your Debts'!$G$6=0,0,INDEX('Your Debts'!$C$5:$C$12,'Your Debts'!$G$6)/12)),2) | H70: =MIN((I69)+G70,MAX(0,$C70-(E70))) | I70: =ROUND(MAX(0,(I69)+G70-H70),2) | J70: =ROUND((L69)*(IF('Your Debts'!$G$7=0,0,INDEX('Your Debts'!$C$5:$C$12,'Your Debts'!$G$7)/12)),2) | K70: =MIN((L69)+J70,MAX(0,$C70-(E70+H70))) | L70: =ROUND(MAX(0,(L69)+J70-K70),2) | M70: =ROUND((O69)*(IF('Your Debts'!$G$8=0,0,INDEX('Your Debts'!$C$5:$C$12,'Your Debts'!$G$8)/12)),2) | N70: =MIN((O69)+M70,MAX(0,$C70-(E70+H70+K70))) | O70: =ROUND(MAX(0,(O69)+M70-N70),2) | P70: =ROUND((R69)*(IF('Your Debts'!$G$9=0,0,INDEX('Your Debts'!$C$5:$C$12,'Your Debts'!$G$9)/12)),2) | Q70: =MIN((R69)+P70,MAX(0,$C70-(E70+H70+K70+N70))) | R70: =ROUND(MAX(0,(R69)+P70-Q70),2) | S70: =ROUND((U69)*(IF('Your Debts'!$G$10=0,0,INDEX('Your Debts'!$C$5:$C$12,'Your Debts'!$G$10)/12)),2) | T70: =MIN((U69)+S70,MAX(0,$C70-(E70+H70+K70+N70+Q70))) | U70: =ROUND(MAX(0,(U69)+S70-T70),2) | V70: =ROUND((X69)*(IF('Your Debts'!$G$11=0,0,INDEX('Your Debts'!$C$5:$C$12,'Your Debts'!$G$11)/12)),2) | W70: =MIN((X69)+V70,MAX(0,$C70-(E70+H70+K70+N70+Q70+T70))) | X70: =ROUND(MAX(0,(X69)+V70-W70),2) | Y70: =ROUND((AA69)*(IF('Your Debts'!$G$12=0,0,INDEX('Your Debts'!$C$5:$C$12,'Your Debts'!$G$12)/12)),2) | Z70: =MIN((AA69)+Y70,MAX(0,$C70-(E70+H70+K70+N70+Q70+T70+W70))) | AA70: =ROUND(MAX(0,(AA69)+Y70-Z70),2) | AB70: =F70+I70+L70+O70+R70+U70+X70+AA70 | AC70: =AC69+D70+G70+J70+M70+P70+S70+V70+Y70
A71: 66 | B71: =EDATE('Your Debts'!$B$19,65) | C71: ='Your Debts'!$B$18 | D71: =ROUND((F70)*(IF('Your Debts'!$G$5=0,0,INDEX('Your Debts'!$C$5:$C$12,'Your Debts'!$G$5)/12)),2) | E71: =MIN((F70)+D71,MAX(0,$C71-(0))) | F71: =ROUND(MAX(0,(F70)+D71-E71),2) | G71: =ROUND((I70)*(IF('Your Debts'!$G$6=0,0,INDEX('Your Debts'!$C$5:$C$12,'Your Debts'!$G$6)/12)),2) | H71: =MIN((I70)+G71,MAX(0,$C71-(E71))) | I71: =ROUND(MAX(0,(I70)+G71-H71),2) | J71: =ROUND((L70)*(IF('Your Debts'!$G$7=0,0,INDEX('Your Debts'!$C$5:$C$12,'Your Debts'!$G$7)/12)),2) | K71: =MIN((L70)+J71,MAX(0,$C71-(E71+H71))) | L71: =ROUND(MAX(0,(L70)+J71-K71),2) | M71: =ROUND((O70)*(IF('Your Debts'!$G$8=0,0,INDEX('Your Debts'!$C$5:$C$12,'Your Debts'!$G$8)/12)),2) | N71: =MIN((O70)+M71,MAX(0,$C71-(E71+H71+K71))) | O71: =ROUND(MAX(0,(O70)+M71-N71),2) | P71: =ROUND((R70)*(IF('Your Debts'!$G$9=0,0,INDEX('Your Debts'!$C$5:$C$12,'Your Debts'!$G$9)/12)),2) | Q71: =MIN((R70)+P71,MAX(0,$C71-(E71+H71+K71+N71))) | R71: =ROUND(MAX(0,(R70)+P71-Q71),2) | S71: =ROUND((U70)*(IF('Your Debts'!$G$10=0,0,INDEX('Your Debts'!$C$5:$C$12,'Your Debts'!$G$10)/12)),2) | T71: =MIN((U70)+S71,MAX(0,$C71-(E71+H71+K71+N71+Q71))) | U71: =ROUND(MAX(0,(U70)+S71-T71),2) | V71: =ROUND((X70)*(IF('Your Debts'!$G$11=0,0,INDEX('Your Debts'!$C$5:$C$12,'Your Debts'!$G$11)/12)),2) | W71: =MIN((X70)+V71,MAX(0,$C71-(E71+H71+K71+N71+Q71+T71))) | X71: =ROUND(MAX(0,(X70)+V71-W71),2) | Y71: =ROUND((AA70)*(IF('Your Debts'!$G$12=0,0,INDEX('Your Debts'!$C$5:$C$12,'Your Debts'!$G$12)/12)),2) | Z71: =MIN((AA70)+Y71,MAX(0,$C71-(E71+H71+K71+N71+Q71+T71+W71))) | AA71: =ROUND(MAX(0,(AA70)+Y71-Z71),2) | AB71: =F71+I71+L71+O71+R71+U71+X71+AA71 | AC71: =AC70+D71+G71+J71+M71+P71+S71+V71+Y71
A72: 67 | B72: =EDATE('Your Debts'!$B$19,66) | C72: ='Your Debts'!$B$18 | D72: =ROUND((F71)*(IF('Your Debts'!$G$5=0,0,INDEX('Your Debts'!$C$5:$C$12,'Your Debts'!$G$5)/12)),2) | E72: =MIN((F71)+D72,MAX(0,$C72-(0))) | F72: =ROUND(MAX(0,(F71)+D72-E72),2) | G72: =ROUND((I71)*(IF('Your Debts'!$G$6=0,0,INDEX('Your Debts'!$C$5:$C$12,'Your Debts'!$G$6)/12)),2) | H72: =MIN((I71)+G72,MAX(0,$C72-(E72))) | I72: =ROUND(MAX(0,(I71)+G72-H72),2) | J72: =ROUND((L71)*(IF('Your Debts'!$G$7=0,0,INDEX('Your Debts'!$C$5:$C$12,'Your Debts'!$G$7)/12)),2) | K72: =MIN((L71)+J72,MAX(0,$C72-(E72+H72))) | L72: =ROUND(MAX(0,(L71)+J72-K72),2) | M72: =ROUND((O71)*(IF('Your Debts'!$G$8=0,0,INDEX('Your Debts'!$C$5:$C$12,'Your Debts'!$G$8)/12)),2) | N72: =MIN((O71)+M72,MAX(0,$C72-(E72+H72+K72))) | O72: =ROUND(MAX(0,(O71)+M72-N72),2) | P72: =ROUND((R71)*(IF('Your Debts'!$G$9=0,0,INDEX('Your Debts'!$C$5:$C$12,'Your Debts'!$G$9)/12)),2) | Q72: =MIN((R71)+P72,MAX(0,$C72-(E72+H72+K72+N72))) | R72: =ROUND(MAX(0,(R71)+P72-Q72),2) | S72: =ROUND((U71)*(IF('Your Debts'!$G$10=0,0,INDEX('Your Debts'!$C$5:$C$12,'Your Debts'!$G$10)/12)),2) | T72: =MIN((U71)+S72,MAX(0,$C72-(E72+H72+K72+N72+Q72))) | U72: =ROUND(MAX(0,(U71)+S72-T72),2) | V72: =ROUND((X71)*(IF('Your Debts'!$G$11=0,0,INDEX('Your Debts'!$C$5:$C$12,'Your Debts'!$G$11)/12)),2) | W72: =MIN((X71)+V72,MAX(0,$C72-(E72+H72+K72+N72+Q72+T72))) | X72: =ROUND(MAX(0,(X71)+V72-W72),2) | Y72: =ROUND((AA71)*(IF('Your Debts'!$G$12=0,0,INDEX('Your Debts'!$C$5:$C$12,'Your Debts'!$G$12)/12)),2) | Z72: =MIN((AA71)+Y72,MAX(0,$C72-(E72+H72+K72+N72+Q72+T72+W72))) | AA72: =ROUND(MAX(0,(AA71)+Y72-Z72),2) | AB72: =F72+I72+L72+O72+R72+U72+X72+AA72 | AC72: =AC71+D72+G72+J72+M72+P72+S72+V72+Y72
A73: 68 | B73: =EDATE('Your Debts'!$B$19,67) | C73: ='Your Debts'!$B$18 | D73: =ROUND((F72)*(IF('Your Debts'!$G$5=0,0,INDEX('Your Debts'!$C$5:$C$12,'Your Debts'!$G$5)/12)),2) | E73: =MIN((F72)+D73,MAX(0,$C73-(0))) | F73: =ROUND(MAX(0,(F72)+D73-E73),2) | G73: =ROUND((I72)*(IF('Your Debts'!$G$6=0,0,INDEX('Your Debts'!$C$5:$C$12,'Your Debts'!$G$6)/12)),2) | H73: =MIN((I72)+G73,MAX(0,$C73-(E73))) | I73: =ROUND(MAX(0,(I72)+G73-H73),2) | J73: =ROUND((L72)*(IF('Your Debts'!$G$7=0,0,INDEX('Your Debts'!$C$5:$C$12,'Your Debts'!$G$7)/12)),2) | K73: =MIN((L72)+J73,MAX(0,$C73-(E73+H73))) | L73: =ROUND(MAX(0,(L72)+J73-K73),2) | M73: =ROUND((O72)*(IF('Your Debts'!$G$8=0,0,INDEX('Your Debts'!$C$5:$C$12,'Your Debts'!$G$8)/12)),2) | N73: =MIN((O72)+M73,MAX(0,$C73-(E73+H73+K73))) | O73: =ROUND(MAX(0,(O72)+M73-N73),2) | P73: =ROUND((R72)*(IF('Your Debts'!$G$9=0,0,INDEX('Your Debts'!$C$5:$C$12,'Your Debts'!$G$9)/12)),2) | Q73: =MIN((R72)+P73,MAX(0,$C73-(E73+H73+K73+N73))) | R73: =ROUND(MAX(0,(R72)+P73-Q73),2) | S73: =ROUND((U72)*(IF('Your Debts'!$G$10=0,0,INDEX('Your Debts'!$C$5:$C$12,'Your Debts'!$G$10)/12)),2) | T73: =MIN((U72)+S73,MAX(0,$C73-(E73+H73+K73+N73+Q73))) | U73: =ROUND(MAX(0,(U72)+S73-T73),2) | V73: =ROUND((X72)*(IF('Your Debts'!$G$11=0,0,INDEX('Your Debts'!$C$5:$C$12,'Your Debts'!$G$11)/12)),2) | W73: =MIN((X72)+V73,MAX(0,$C73-(E73+H73+K73+N73+Q73+T73))) | X73: =ROUND(MAX(0,(X72)+V73-W73),2) | Y73: =ROUND((AA72)*(IF('Your Debts'!$G$12=0,0,INDEX('Your Debts'!$C$5:$C$12,'Your Debts'!$G$12)/12)),2) | Z73: =MIN((AA72)+Y73,MAX(0,$C73-(E73+H73+K73+N73+Q73+T73+W73))) | AA73: =ROUND(MAX(0,(AA72)+Y73-Z73),2) | AB73: =F73+I73+L73+O73+R73+U73+X73+AA73 | AC73: =AC72+D73+G73+J73+M73+P73+S73+V73+Y73
A74: 69 | B74: =EDATE('Your Debts'!$B$19,68) | C74: ='Your Debts'!$B$18 | D74: =ROUND((F73)*(IF('Your Debts'!$G$5=0,0,INDEX('Your Debts'!$C$5:$C$12,'Your Debts'!$G$5)/12)),2) | E74: =MIN((F73)+D74,MAX(0,$C74-(0))) | F74: =ROUND(MAX(0,(F73)+D74-E74),2) | G74: =ROUND((I73)*(IF('Your Debts'!$G$6=0,0,INDEX('Your Debts'!$C$5:$C$12,'Your Debts'!$G$6)/12)),2) | H74: =MIN((I73)+G74,MAX(0,$C74-(E74))) | I74: =ROUND(MAX(0,(I73)+G74-H74),2) | J74: =ROUND((L73)*(IF('Your Debts'!$G$7=0,0,INDEX('Your Debts'!$C$5:$C$12,'Your Debts'!$G$7)/12)),2) | K74: =MIN((L73)+J74,MAX(0,$C74-(E74+H74))) | L74: =ROUND(MAX(0,(L73)+J74-K74),2) | M74: =ROUND((O73)*(IF('Your Debts'!$G$8=0,0,INDEX('Your Debts'!$C$5:$C$12,'Your Debts'!$G$8)/12)),2) | N74: =MIN((O73)+M74,MAX(0,$C74-(E74+H74+K74))) | O74: =ROUND(MAX(0,(O73)+M74-N74),2) | P74: =ROUND((R73)*(IF('Your Debts'!$G$9=0,0,INDEX('Your Debts'!$C$5:$C$12,'Your Debts'!$G$9)/12)),2) | Q74: =MIN((R73)+P74,MAX(0,$C74-(E74+H74+K74+N74))) | R74: =ROUND(MAX(0,(R73)+P74-Q74),2) | S74: =ROUND((U73)*(IF('Your Debts'!$G$10=0,0,INDEX('Your Debts'!$C$5:$C$12,'Your Debts'!$G$10)/12)),2) | T74: =MIN((U73)+S74,MAX(0,$C74-(E74+H74+K74+N74+Q74))) | U74: =ROUND(MAX(0,(U73)+S74-T74),2) | V74: =ROUND((X73)*(IF('Your Debts'!$G$11=0,0,INDEX('Your Debts'!$C$5:$C$12,'Your Debts'!$G$11)/12)),2) | W74: =MIN((X73)+V74,MAX(0,$C74-(E74+H74+K74+N74+Q74+T74))) | X74: =ROUND(MAX(0,(X73)+V74-W74),2) | Y74: =ROUND((AA73)*(IF('Your Debts'!$G$12=0,0,INDEX('Your Debts'!$C$5:$C$12,'Your Debts'!$G$12)/12)),2) | Z74: =MIN((AA73)+Y74,MAX(0,$C74-(E74+H74+K74+N74+Q74+T74+W74))) | AA74: =ROUND(MAX(0,(AA73)+Y74-Z74),2) | AB74: =F74+I74+L74+O74+R74+U74+X74+AA74 | AC74: =AC73+D74+G74+J74+M74+P74+S74+V74+Y74
A75: 70 | B75: =EDATE('Your Debts'!$B$19,69) | C75: ='Your Debts'!$B$18 | D75: =ROUND((F74)*(IF('Your Debts'!$G$5=0,0,INDEX('Your Debts'!$C$5:$C$12,'Your Debts'!$G$5)/12)),2) | E75: =MIN((F74)+D75,MAX(0,$C75-(0))) | F75: =ROUND(MAX(0,(F74)+D75-E75),2) | G75: =ROUND((I74)*(IF('Your Debts'!$G$6=0,0,INDEX('Your Debts'!$C$5:$C$12,'Your Debts'!$G$6)/12)),2) | H75: =MIN((I74)+G75,MAX(0,$C75-(E75))) | I75: =ROUND(MAX(0,(I74)+G75-H75),2) | J75: =ROUND((L74)*(IF('Your Debts'!$G$7=0,0,INDEX('Your Debts'!$C$5:$C$12,'Your Debts'!$G$7)/12)),2) | K75: =MIN((L74)+J75,MAX(0,$C75-(E75+H75))) | L75: =ROUND(MAX(0,(L74)+J75-K75),2) | M75: =ROUND((O74)*(IF('Your Debts'!$G$8=0,0,INDEX('Your Debts'!$C$5:$C$12,'Your Debts'!$G$8)/12)),2) | N75: =MIN((O74)+M75,MAX(0,$C75-(E75+H75+K75))) | O75: =ROUND(MAX(0,(O74)+M75-N75),2) | P75: =ROUND((R74)*(IF('Your Debts'!$G$9=0,0,INDEX('Your Debts'!$C$5:$C$12,'Your Debts'!$G$9)/12)),2) | Q75: =MIN((R74)+P75,MAX(0,$C75-(E75+H75+K75+N75))) | R75: =ROUND(MAX(0,(R74)+P75-Q75),2) | S75: =ROUND((U74)*(IF('Your Debts'!$G$10=0,0,INDEX('Your Debts'!$C$5:$C$12,'Your Debts'!$G$10)/12)),2) | T75: =MIN((U74)+S75,MAX(0,$C75-(E75+H75+K75+N75+Q75))) | U75: =ROUND(MAX(0,(U74)+S75-T75),2) | V75: =ROUND((X74)*(IF('Your Debts'!$G$11=0,0,INDEX('Your Debts'!$C$5:$C$12,'Your Debts'!$G$11)/12)),2) | W75: =MIN((X74)+V75,MAX(0,$C75-(E75+H75+K75+N75+Q75+T75))) | X75: =ROUND(MAX(0,(X74)+V75-W75),2) | Y75: =ROUND((AA74)*(IF('Your Debts'!$G$12=0,0,INDEX('Your Debts'!$C$5:$C$12,'Your Debts'!$G$12)/12)),2) | Z75: =MIN((AA74)+Y75,MAX(0,$C75-(E75+H75+K75+N75+Q75+T75+W75))) | AA75: =ROUND(MAX(0,(AA74)+Y75-Z75),2) | AB75: =F75+I75+L75+O75+R75+U75+X75+AA75 | AC75: =AC74+D75+G75+J75+M75+P75+S75+V75+Y75
A76: 71 | B76: =EDATE('Your Debts'!$B$19,70) | C76: ='Your Debts'!$B$18 | D76: =ROUND((F75)*(IF('Your Debts'!$G$5=0,0,INDEX('Your Debts'!$C$5:$C$12,'Your Debts'!$G$5)/12)),2) | E76: =MIN((F75)+D76,MAX(0,$C76-(0))) | F76: =ROUND(MAX(0,(F75)+D76-E76),2) | G76: =ROUND((I75)*(IF('Your Debts'!$G$6=0,0,INDEX('Your Debts'!$C$5:$C$12,'Your Debts'!$G$6)/12)),2) | H76: =MIN((I75)+G76,MAX(0,$C76-(E76))) | I76: =ROUND(MAX(0,(I75)+G76-H76),2) | J76: =ROUND((L75)*(IF('Your Debts'!$G$7=0,0,INDEX('Your Debts'!$C$5:$C$12,'Your Debts'!$G$7)/12)),2) | K76: =MIN((L75)+J76,MAX(0,$C76-(E76+H76))) | L76: =ROUND(MAX(0,(L75)+J76-K76),2) | M76: =ROUND((O75)*(IF('Your Debts'!$G$8=0,0,INDEX('Your Debts'!$C$5:$C$12,'Your Debts'!$G$8)/12)),2) | N76: =MIN((O75)+M76,MAX(0,$C76-(E76+H76+K76))) | O76: =ROUND(MAX(0,(O75)+M76-N76),2) | P76: =ROUND((R75)*(IF('Your Debts'!$G$9=0,0,INDEX('Your Debts'!$C$5:$C$12,'Your Debts'!$G$9)/12)),2) | Q76: =MIN((R75)+P76,MAX(0,$C76-(E76+H76+K76+N76))) | R76: =ROUND(MAX(0,(R75)+P76-Q76),2) | S76: =ROUND((U75)*(IF('Your Debts'!$G$10=0,0,INDEX('Your Debts'!$C$5:$C$12,'Your Debts'!$G$10)/12)),2) | T76: =MIN((U75)+S76,MAX(0,$C76-(E76+H76+K76+N76+Q76))) | U76: =ROUND(MAX(0,(U75)+S76-T76),2) | V76: =ROUND((X75)*(IF('Your Debts'!$G$11=0,0,INDEX('Your Debts'!$C$5:$C$12,'Your Debts'!$G$11)/12)),2) | W76: =MIN((X75)+V76,MAX(0,$C76-(E76+H76+K76+N76+Q76+T76))) | X76: =ROUND(MAX(0,(X75)+V76-W76),2) | Y76: =ROUND((AA75)*(IF('Your Debts'!$G$12=0,0,INDEX('Your Debts'!$C$5:$C$12,'Your Debts'!$G$12)/12)),2) | Z76: =MIN((AA75)+Y76,MAX(0,$C76-(E76+H76+K76+N76+Q76+T76+W76))) | AA76: =ROUND(MAX(0,(AA75)+Y76-Z76),2) | AB76: =F76+I76+L76+O76+R76+U76+X76+AA76 | AC76: =AC75+D76+G76+J76+M76+P76+S76+V76+Y76
A77: 72 | B77: =EDATE('Your Debts'!$B$19,71) | C77: ='Your Debts'!$B$18 | D77: =ROUND((F76)*(IF('Your Debts'!$G$5=0,0,INDEX('Your Debts'!$C$5:$C$12,'Your Debts'!$G$5)/12)),2) | E77: =MIN((F76)+D77,MAX(0,$C77-(0))) | F77: =ROUND(MAX(0,(F76)+D77-E77),2) | G77: =ROUND((I76)*(IF('Your Debts'!$G$6=0,0,INDEX('Your Debts'!$C$5:$C$12,'Your Debts'!$G$6)/12)),2) | H77: =MIN((I76)+G77,MAX(0,$C77-(E77))) | I77: =ROUND(MAX(0,(I76)+G77-H77),2) | J77: =ROUND((L76)*(IF('Your Debts'!$G$7=0,0,INDEX('Your Debts'!$C$5:$C$12,'Your Debts'!$G$7)/12)),2) | K77: =MIN((L76)+J77,MAX(0,$C77-(E77+H77))) | L77: =ROUND(MAX(0,(L76)+J77-K77),2) | M77: =ROUND((O76)*(IF('Your Debts'!$G$8=0,0,INDEX('Your Debts'!$C$5:$C$12,'Your Debts'!$G$8)/12)),2) | N77: =MIN((O76)+M77,MAX(0,$C77-(E77+H77+K77))) | O77: =ROUND(MAX(0,(O76)+M77-N77),2) | P77: =ROUND((R76)*(IF('Your Debts'!$G$9=0,0,INDEX('Your Debts'!$C$5:$C$12,'Your Debts'!$G$9)/12)),2) | Q77: =MIN((R76)+P77,MAX(0,$C77-(E77+H77+K77+N77))) | R77: =ROUND(MAX(0,(R76)+P77-Q77),2) | S77: =ROUND((U76)*(IF('Your Debts'!$G$10=0,0,INDEX('Your Debts'!$C$5:$C$12,'Your Debts'!$G$10)/12)),2) | T77: =MIN((U76)+S77,MAX(0,$C77-(E77+H77+K77+N77+Q77))) | U77: =ROUND(MAX(0,(U76)+S77-T77),2) | V77: =ROUND((X76)*(IF('Your Debts'!$G$11=0,0,INDEX('Your Debts'!$C$5:$C$12,'Your Debts'!$G$11)/12)),2) | W77: =MIN((X76)+V77,MAX(0,$C77-(E77+H77+K77+N77+Q77+T77))) | X77: =ROUND(MAX(0,(X76)+V77-W77),2) | Y77: =ROUND((AA76)*(IF('Your Debts'!$G$12=0,0,INDEX('Your Debts'!$C$5:$C$12,'Your Debts'!$G$12)/12)),2) | Z77: =MIN((AA76)+Y77,MAX(0,$C77-(E77+H77+K77+N77+Q77+T77+W77))) | AA77: =ROUND(MAX(0,(AA76)+Y77-Z77),2) | AB77: =F77+I77+L77+O77+R77+U77+X77+AA77 | AC77: =AC76+D77+G77+J77+M77+P77+S77+V77+Y77
A78: 73 | B78: =EDATE('Your Debts'!$B$19,72) | C78: ='Your Debts'!$B$18 | D78: =ROUND((F77)*(IF('Your Debts'!$G$5=0,0,INDEX('Your Debts'!$C$5:$C$12,'Your Debts'!$G$5)/12)),2) | E78: =MIN((F77)+D78,MAX(0,$C78-(0))) | F78: =ROUND(MAX(0,(F77)+D78-E78),2) | G78: =ROUND((I77)*(IF('Your Debts'!$G$6=0,0,INDEX('Your Debts'!$C$5:$C$12,'Your Debts'!$G$6)/12)),2) | H78: =MIN((I77)+G78,MAX(0,$C78-(E78))) | I78: =ROUND(MAX(0,(I77)+G78-H78),2) | J78: =ROUND((L77)*(IF('Your Debts'!$G$7=0,0,INDEX('Your Debts'!$C$5:$C$12,'Your Debts'!$G$7)/12)),2) | K78: =MIN((L77)+J78,MAX(0,$C78-(E78+H78))) | L78: =ROUND(MAX(0,(L77)+J78-K78),2) | M78: =ROUND((O77)*(IF('Your Debts'!$G$8=0,0,INDEX('Your Debts'!$C$5:$C$12,'Your Debts'!$G$8)/12)),2) | N78: =MIN((O77)+M78,MAX(0,$C78-(E78+H78+K78))) | O78: =ROUND(MAX(0,(O77)+M78-N78),2) | P78: =ROUND((R77)*(IF('Your Debts'!$G$9=0,0,INDEX('Your Debts'!$C$5:$C$12,'Your Debts'!$G$9)/12)),2) | Q78: =MIN((R77)+P78,MAX(0,$C78-(E78+H78+K78+N78))) | R78: =ROUND(MAX(0,(R77)+P78-Q78),2) | S78: =ROUND((U77)*(IF('Your Debts'!$G$10=0,0,INDEX('Your Debts'!$C$5:$C$12,'Your Debts'!$G$10)/12)),2) | T78: =MIN((U77)+S78,MAX(0,$C78-(E78+H78+K78+N78+Q78))) | U78: =ROUND(MAX(0,(U77)+S78-T78),2) | V78: =ROUND((X77)*(IF('Your Debts'!$G$11=0,0,INDEX('Your Debts'!$C$5:$C$12,'Your Debts'!$G$11)/12)),2) | W78: =MIN((X77)+V78,MAX(0,$C78-(E78+H78+K78+N78+Q78+T78))) | X78: =ROUND(MAX(0,(X77)+V78-W78),2) | Y78: =ROUND((AA77)*(IF('Your Debts'!$G$12=0,0,INDEX('Your Debts'!$C$5:$C$12,'Your Debts'!$G$12)/12)),2) | Z78: =MIN((AA77)+Y78,MAX(0,$C78-(E78+H78+K78+N78+Q78+T78+W78))) | AA78: =ROUND(MAX(0,(AA77)+Y78-Z78),2) | AB78: =F78+I78+L78+O78+R78+U78+X78+AA78 | AC78: =AC77+D78+G78+J78+M78+P78+S78+V78+Y78
A79: 74 | B79: =EDATE('Your Debts'!$B$19,73) | C79: ='Your Debts'!$B$18 | D79: =ROUND((F78)*(IF('Your Debts'!$G$5=0,0,INDEX('Your Debts'!$C$5:$C$12,'Your Debts'!$G$5)/12)),2) | E79: =MIN((F78)+D79,MAX(0,$C79-(0))) | F79: =ROUND(MAX(0,(F78)+D79-E79),2) | G79: =ROUND((I78)*(IF('Your Debts'!$G$6=0,0,INDEX('Your Debts'!$C$5:$C$12,'Your Debts'!$G$6)/12)),2) | H79: =MIN((I78)+G79,MAX(0,$C79-(E79))) | I79: =ROUND(MAX(0,(I78)+G79-H79),2) | J79: =ROUND((L78)*(IF('Your Debts'!$G$7=0,0,INDEX('Your Debts'!$C$5:$C$12,'Your Debts'!$G$7)/12)),2) | K79: =MIN((L78)+J79,MAX(0,$C79-(E79+H79))) | L79: =ROUND(MAX(0,(L78)+J79-K79),2) | M79: =ROUND((O78)*(IF('Your Debts'!$G$8=0,0,INDEX('Your Debts'!$C$5:$C$12,'Your Debts'!$G$8)/12)),2) | N79: =MIN((O78)+M79,MAX(0,$C79-(E79+H79+K79))) | O79: =ROUND(MAX(0,(O78)+M79-N79),2) | P79: =ROUND((R78)*(IF('Your Debts'!$G$9=0,0,INDEX('Your Debts'!$C$5:$C$12,'Your Debts'!$G$9)/12)),2) | Q79: =MIN((R78)+P79,MAX(0,$C79-(E79+H79+K79+N79))) | R79: =ROUND(MAX(0,(R78)+P79-Q79),2) | S79: =ROUND((U78)*(IF('Your Debts'!$G$10=0,0,INDEX('Your Debts'!$C$5:$C$12,'Your Debts'!$G$10)/12)),2) | T79: =MIN((U78)+S79,MAX(0,$C79-(E79+H79+K79+N79+Q79))) | U79: =ROUND(MAX(0,(U78)+S79-T79),2) | V79: =ROUND((X78)*(IF('Your Debts'!$G$11=0,0,INDEX('Your Debts'!$C$5:$C$12,'Your Debts'!$G$11)/12)),2) | W79: =MIN((X78)+V79,MAX(0,$C79-(E79+H79+K79+N79+Q79+T79))) | X79: =ROUND(MAX(0,(X78)+V79-W79),2) | Y79: =ROUND((AA78)*(IF('Your Debts'!$G$12=0,0,INDEX('Your Debts'!$C$5:$C$12,'Your Debts'!$G$12)/12)),2) | Z79: =MIN((AA78)+Y79,MAX(0,$C79-(E79+H79+K79+N79+Q79+T79+W79))) | AA79: =ROUND(MAX(0,(AA78)+Y79-Z79),2) | AB79: =F79+I79+L79+O79+R79+U79+X79+AA79 | AC79: =AC78+D79+G79+J79+M79+P79+S79+V79+Y79
A80: 75 | B80: =EDATE('Your Debts'!$B$19,74) | C80: ='Your Debts'!$B$18 | D80: =ROUND((F79)*(IF('Your Debts'!$G$5=0,0,INDEX('Your Debts'!$C$5:$C$12,'Your Debts'!$G$5)/12)),2) | E80: =MIN((F79)+D80,MAX(0,$C80-(0))) | F80: =ROUND(MAX(0,(F79)+D80-E80),2) | G80: =ROUND((I79)*(IF('Your Debts'!$G$6=0,0,INDEX('Your Debts'!$C$5:$C$12,'Your Debts'!$G$6)/12)),2) | H80: =MIN((I79)+G80,MAX(0,$C80-(E80))) | I80: =ROUND(MAX(0,(I79)+G80-H80),2) | J80: =ROUND((L79)*(IF('Your Debts'!$G$7=0,0,INDEX('Your Debts'!$C$5:$C$12,'Your Debts'!$G$7)/12)),2) | K80: =MIN((L79)+J80,MAX(0,$C80-(E80+H80))) | L80: =ROUND(MAX(0,(L79)+J80-K80),2) | M80: =ROUND((O79)*(IF('Your Debts'!$G$8=0,0,INDEX('Your Debts'!$C$5:$C$12,'Your Debts'!$G$8)/12)),2) | N80: =MIN((O79)+M80,MAX(0,$C80-(E80+H80+K80))) | O80: =ROUND(MAX(0,(O79)+M80-N80),2) | P80: =ROUND((R79)*(IF('Your Debts'!$G$9=0,0,INDEX('Your Debts'!$C$5:$C$12,'Your Debts'!$G$9)/12)),2) | Q80: =MIN((R79)+P80,MAX(0,$C80-(E80+H80+K80+N80))) | R80: =ROUND(MAX(0,(R79)+P80-Q80),2) | S80: =ROUND((U79)*(IF('Your Debts'!$G$10=0,0,INDEX('Your Debts'!$C$5:$C$12,'Your Debts'!$G$10)/12)),2) | T80: =MIN((U79)+S80,MAX(0,$C80-(E80+H80+K80+N80+Q80))) | U80: =ROUND(MAX(0,(U79)+S80-T80),2) | V80: =ROUND((X79)*(IF('Your Debts'!$G$11=0,0,INDEX('Your Debts'!$C$5:$C$12,'Your Debts'!$G$11)/12)),2) | W80: =MIN((X79)+V80,MAX(0,$C80-(E80+H80+K80+N80+Q80+T80))) | X80: =ROUND(MAX(0,(X79)+V80-W80),2) | Y80: =ROUND((AA79)*(IF('Your Debts'!$G$12=0,0,INDEX('Your Debts'!$C$5:$C$12,'Your Debts'!$G$12)/12)),2) | Z80: =MIN((AA79)+Y80,MAX(0,$C80-(E80+H80+K80+N80+Q80+T80+W80))) | AA80: =ROUND(MAX(0,(AA79)+Y80-Z80),2) | AB80: =F80+I80+L80+O80+R80+U80+X80+AA80 | AC80: =AC79+D80+G80+J80+M80+P80+S80+V80+Y80
A81: 76 | B81: =EDATE('Your Debts'!$B$19,75) | C81: ='Your Debts'!$B$18 | D81: =ROUND((F80)*(IF('Your Debts'!$G$5=0,0,INDEX('Your Debts'!$C$5:$C$12,'Your Debts'!$G$5)/12)),2) | E81: =MIN((F80)+D81,MAX(0,$C81-(0))) | F81: =ROUND(MAX(0,(F80)+D81-E81),2) | G81: =ROUND((I80)*(IF('Your Debts'!$G$6=0,0,INDEX('Your Debts'!$C$5:$C$12,'Your Debts'!$G$6)/12)),2) | H81: =MIN((I80)+G81,MAX(0,$C81-(E81))) | I81: =ROUND(MAX(0,(I80)+G81-H81),2) | J81: =ROUND((L80)*(IF('Your Debts'!$G$7=0,0,INDEX('Your Debts'!$C$5:$C$12,'Your Debts'!$G$7)/12)),2) | K81: =MIN((L80)+J81,MAX(0,$C81-(E81+H81))) | L81: =ROUND(MAX(0,(L80)+J81-K81),2) | M81: =ROUND((O80)*(IF('Your Debts'!$G$8=0,0,INDEX('Your Debts'!$C$5:$C$12,'Your Debts'!$G$8)/12)),2) | N81: =MIN((O80)+M81,MAX(0,$C81-(E81+H81+K81))) | O81: =ROUND(MAX(0,(O80)+M81-N81),2) | P81: =ROUND((R80)*(IF('Your Debts'!$G$9=0,0,INDEX('Your Debts'!$C$5:$C$12,'Your Debts'!$G$9)/12)),2) | Q81: =MIN((R80)+P81,MAX(0,$C81-(E81+H81+K81+N81))) | R81: =ROUND(MAX(0,(R80)+P81-Q81),2) | S81: =ROUND((U80)*(IF('Your Debts'!$G$10=0,0,INDEX('Your Debts'!$C$5:$C$12,'Your Debts'!$G$10)/12)),2) | T81: =MIN((U80)+S81,MAX(0,$C81-(E81+H81+K81+N81+Q81))) | U81: =ROUND(MAX(0,(U80)+S81-T81),2) | V81: =ROUND((X80)*(IF('Your Debts'!$G$11=0,0,INDEX('Your Debts'!$C$5:$C$12,'Your Debts'!$G$11)/12)),2) | W81: =MIN((X80)+V81,MAX(0,$C81-(E81+H81+K81+N81+Q81+T81))) | X81: =ROUND(MAX(0,(X80)+V81-W81),2) | Y81: =ROUND((AA80)*(IF('Your Debts'!$G$12=0,0,INDEX('Your Debts'!$C$5:$C$12,'Your Debts'!$G$12)/12)),2) | Z81: =MIN((AA80)+Y81,MAX(0,$C81-(E81+H81+K81+N81+Q81+T81+W81))) | AA81: =ROUND(MAX(0,(AA80)+Y81-Z81),2) | AB81: =F81+I81+L81+O81+R81+U81+X81+AA81 | AC81: =AC80+D81+G81+J81+M81+P81+S81+V81+Y81
A82: 77 | B82: =EDATE('Your Debts'!$B$19,76) | C82: ='Your Debts'!$B$18 | D82: =ROUND((F81)*(IF('Your Debts'!$G$5=0,0,INDEX('Your Debts'!$C$5:$C$12,'Your Debts'!$G$5)/12)),2) | E82: =MIN((F81)+D82,MAX(0,$C82-(0))) | F82: =ROUND(MAX(0,(F81)+D82-E82),2) | G82: =ROUND((I81)*(IF('Your Debts'!$G$6=0,0,INDEX('Your Debts'!$C$5:$C$12,'Your Debts'!$G$6)/12)),2) | H82: =MIN((I81)+G82,MAX(0,$C82-(E82))) | I82: =ROUND(MAX(0,(I81)+G82-H82),2) | J82: =ROUND((L81)*(IF('Your Debts'!$G$7=0,0,INDEX('Your Debts'!$C$5:$C$12,'Your Debts'!$G$7)/12)),2) | K82: =MIN((L81)+J82,MAX(0,$C82-(E82+H82))) | L82: =ROUND(MAX(0,(L81)+J82-K82),2) | M82: =ROUND((O81)*(IF('Your Debts'!$G$8=0,0,INDEX('Your Debts'!$C$5:$C$12,'Your Debts'!$G$8)/12)),2) | N82: =MIN((O81)+M82,MAX(0,$C82-(E82+H82+K82))) | O82: =ROUND(MAX(0,(O81)+M82-N82),2) | P82: =ROUND((R81)*(IF('Your Debts'!$G$9=0,0,INDEX('Your Debts'!$C$5:$C$12,'Your Debts'!$G$9)/12)),2) | Q82: =MIN((R81)+P82,MAX(0,$C82-(E82+H82+K82+N82))) | R82: =ROUND(MAX(0,(R81)+P82-Q82),2) | S82: =ROUND((U81)*(IF('Your Debts'!$G$10=0,0,INDEX('Your Debts'!$C$5:$C$12,'Your Debts'!$G$10)/12)),2) | T82: =MIN((U81)+S82,MAX(0,$C82-(E82+H82+K82+N82+Q82))) | U82: =ROUND(MAX(0,(U81)+S82-T82),2) | V82: =ROUND((X81)*(IF('Your Debts'!$G$11=0,0,INDEX('Your Debts'!$C$5:$C$12,'Your Debts'!$G$11)/12)),2) | W82: =MIN((X81)+V82,MAX(0,$C82-(E82+H82+K82+N82+Q82+T82))) | X82: =ROUND(MAX(0,(X81)+V82-W82),2) | Y82: =ROUND((AA81)*(IF('Your Debts'!$G$12=0,0,INDEX('Your Debts'!$C$5:$C$12,'Your Debts'!$G$12)/12)),2) | Z82: =MIN((AA81)+Y82,MAX(0,$C82-(E82+H82+K82+N82+Q82+T82+W82))) | AA82: =ROUND(MAX(0,(AA81)+Y82-Z82),2) | AB82: =F82+I82+L82+O82+R82+U82+X82+AA82 | AC82: =AC81+D82+G82+J82+M82+P82+S82+V82+Y82
A83: 78 | B83: =EDATE('Your Debts'!$B$19,77) | C83: ='Your Debts'!$B$18 | D83: =ROUND((F82)*(IF('Your Debts'!$G$5=0,0,INDEX('Your Debts'!$C$5:$C$12,'Your Debts'!$G$5)/12)),2) | E83: =MIN((F82)+D83,MAX(0,$C83-(0))) | F83: =ROUND(MAX(0,(F82)+D83-E83),2) | G83: =ROUND((I82)*(IF('Your Debts'!$G$6=0,0,INDEX('Your Debts'!$C$5:$C$12,'Your Debts'!$G$6)/12)),2) | H83: =MIN((I82)+G83,MAX(0,$C83-(E83))) | I83: =ROUND(MAX(0,(I82)+G83-H83),2) | J83: =ROUND((L82)*(IF('Your Debts'!$G$7=0,0,INDEX('Your Debts'!$C$5:$C$12,'Your Debts'!$G$7)/12)),2) | K83: =MIN((L82)+J83,MAX(0,$C83-(E83+H83))) | L83: =ROUND(MAX(0,(L82)+J83-K83),2) | M83: =ROUND((O82)*(IF('Your Debts'!$G$8=0,0,INDEX('Your Debts'!$C$5:$C$12,'Your Debts'!$G$8)/12)),2) | N83: =MIN((O82)+M83,MAX(0,$C83-(E83+H83+K83))) | O83: =ROUND(MAX(0,(O82)+M83-N83),2) | P83: =ROUND((R82)*(IF('Your Debts'!$G$9=0,0,INDEX('Your Debts'!$C$5:$C$12,'Your Debts'!$G$9)/12)),2) | Q83: =MIN((R82)+P83,MAX(0,$C83-(E83+H83+K83+N83))) | R83: =ROUND(MAX(0,(R82)+P83-Q83),2) | S83: =ROUND((U82)*(IF('Your Debts'!$G$10=0,0,INDEX('Your Debts'!$C$5:$C$12,'Your Debts'!$G$10)/12)),2) | T83: =MIN((U82)+S83,MAX(0,$C83-(E83+H83+K83+N83+Q83))) | U83: =ROUND(MAX(0,(U82)+S83-T83),2) | V83: =ROUND((X82)*(IF('Your Debts'!$G$11=0,0,INDEX('Your Debts'!$C$5:$C$12,'Your Debts'!$G$11)/12)),2) | W83: =MIN((X82)+V83,MAX(0,$C83-(E83+H83+K83+N83+Q83+T83))) | X83: =ROUND(MAX(0,(X82)+V83-W83),2) | Y83: =ROUND((AA82)*(IF('Your Debts'!$G$12=0,0,INDEX('Your Debts'!$C$5:$C$12,'Your Debts'!$G$12)/12)),2) | Z83: =MIN((AA82)+Y83,MAX(0,$C83-(E83+H83+K83+N83+Q83+T83+W83))) | AA83: =ROUND(MAX(0,(AA82)+Y83-Z83),2) | AB83: =F83+I83+L83+O83+R83+U83+X83+AA83 | AC83: =AC82+D83+G83+J83+M83+P83+S83+V83+Y83
A84: 79 | B84: =EDATE('Your Debts'!$B$19,78) | C84: ='Your Debts'!$B$18 | D84: =ROUND((F83)*(IF('Your Debts'!$G$5=0,0,INDEX('Your Debts'!$C$5:$C$12,'Your Debts'!$G$5)/12)),2) | E84: =MIN((F83)+D84,MAX(0,$C84-(0))) | F84: =ROUND(MAX(0,(F83)+D84-E84),2) | G84: =ROUND((I83)*(IF('Your Debts'!$G$6=0,0,INDEX('Your Debts'!$C$5:$C$12,'Your Debts'!$G$6)/12)),2) | H84: =MIN((I83)+G84,MAX(0,$C84-(E84))) | I84: =ROUND(MAX(0,(I83)+G84-H84),2) | J84: =ROUND((L83)*(IF('Your Debts'!$G$7=0,0,INDEX('Your Debts'!$C$5:$C$12,'Your Debts'!$G$7)/12)),2) | K84: =MIN((L83)+J84,MAX(0,$C84-(E84+H84))) | L84: =ROUND(MAX(0,(L83)+J84-K84),2) | M84: =ROUND((O83)*(IF('Your Debts'!$G$8=0,0,INDEX('Your Debts'!$C$5:$C$12,'Your Debts'!$G$8)/12)),2) | N84: =MIN((O83)+M84,MAX(0,$C84-(E84+H84+K84))) | O84: =ROUND(MAX(0,(O83)+M84-N84),2) | P84: =ROUND((R83)*(IF('Your Debts'!$G$9=0,0,INDEX('Your Debts'!$C$5:$C$12,'Your Debts'!$G$9)/12)),2) | Q84: =MIN((R83)+P84,MAX(0,$C84-(E84+H84+K84+N84))) | R84: =ROUND(MAX(0,(R83)+P84-Q84),2) | S84: =ROUND((U83)*(IF('Your Debts'!$G$10=0,0,INDEX('Your Debts'!$C$5:$C$12,'Your Debts'!$G$10)/12)),2) | T84: =MIN((U83)+S84,MAX(0,$C84-(E84+H84+K84+N84+Q84))) | U84: =ROUND(MAX(0,(U83)+S84-T84),2) | V84: =ROUND((X83)*(IF('Your Debts'!$G$11=0,0,INDEX('Your Debts'!$C$5:$C$12,'Your Debts'!$G$11)/12)),2) | W84: =MIN((X83)+V84,MAX(0,$C84-(E84+H84+K84+N84+Q84+T84))) | X84: =ROUND(MAX(0,(X83)+V84-W84),2) | Y84: =ROUND((AA83)*(IF('Your Debts'!$G$12=0,0,INDEX('Your Debts'!$C$5:$C$12,'Your Debts'!$G$12)/12)),2) | Z84: =MIN((AA83)+Y84,MAX(0,$C84-(E84+H84+K84+N84+Q84+T84+W84))) | AA84: =ROUND(MAX(0,(AA83)+Y84-Z84),2) | AB84: =F84+I84+L84+O84+R84+U84+X84+AA84 | AC84: =AC83+D84+G84+J84+M84+P84+S84+V84+Y84
A85: 80 | B85: =EDATE('Your Debts'!$B$19,79) | C85: ='Your Debts'!$B$18 | D85: =ROUND((F84)*(IF('Your Debts'!$G$5=0,0,INDEX('Your Debts'!$C$5:$C$12,'Your Debts'!$G$5)/12)),2) | E85: =MIN((F84)+D85,MAX(0,$C85-(0))) | F85: =ROUND(MAX(0,(F84)+D85-E85),2) | G85: =ROUND((I84)*(IF('Your Debts'!$G$6=0,0,INDEX('Your Debts'!$C$5:$C$12,'Your Debts'!$G$6)/12)),2) | H85: =MIN((I84)+G85,MAX(0,$C85-(E85))) | I85: =ROUND(MAX(0,(I84)+G85-H85),2) | J85: =ROUND((L84)*(IF('Your Debts'!$G$7=0,0,INDEX('Your Debts'!$C$5:$C$12,'Your Debts'!$G$7)/12)),2) | K85: =MIN((L84)+J85,MAX(0,$C85-(E85+H85))) | L85: =ROUND(MAX(0,(L84)+J85-K85),2) | M85: =ROUND((O84)*(IF('Your Debts'!$G$8=0,0,INDEX('Your Debts'!$C$5:$C$12,'Your Debts'!$G$8)/12)),2) | N85: =MIN((O84)+M85,MAX(0,$C85-(E85+H85+K85))) | O85: =ROUND(MAX(0,(O84)+M85-N85),2) | P85: =ROUND((R84)*(IF('Your Debts'!$G$9=0,0,INDEX('Your Debts'!$C$5:$C$12,'Your Debts'!$G$9)/12)),2) | Q85: =MIN((R84)+P85,MAX(0,$C85-(E85+H85+K85+N85))) | R85: =ROUND(MAX(0,(R84)+P85-Q85),2) | S85: =ROUND((U84)*(IF('Your Debts'!$G$10=0,0,INDEX('Your Debts'!$C$5:$C$12,'Your Debts'!$G$10)/12)),2) | T85: =MIN((U84)+S85,MAX(0,$C85-(E85+H85+K85+N85+Q85))) | U85: =ROUND(MAX(0,(U84)+S85-T85),2) | V85: =ROUND((X84)*(IF('Your Debts'!$G$11=0,0,INDEX('Your Debts'!$C$5:$C$12,'Your Debts'!$G$11)/12)),2) | W85: =MIN((X84)+V85,MAX(0,$C85-(E85+H85+K85+N85+Q85+T85))) | X85: =ROUND(MAX(0,(X84)+V85-W85),2) | Y85: =ROUND((AA84)*(IF('Your Debts'!$G$12=0,0,INDEX('Your Debts'!$C$5:$C$12,'Your Debts'!$G$12)/12)),2) | Z85: =MIN((AA84)+Y85,MAX(0,$C85-(E85+H85+K85+N85+Q85+T85+W85))) | AA85: =ROUND(MAX(0,(AA84)+Y85-Z85),2) | AB85: =F85+I85+L85+O85+R85+U85+X85+AA85 | AC85: =AC84+D85+G85+J85+M85+P85+S85+V85+Y85
A86: 81 | B86: =EDATE('Your Debts'!$B$19,80) | C86: ='Your Debts'!$B$18 | D86: =ROUND((F85)*(IF('Your Debts'!$G$5=0,0,INDEX('Your Debts'!$C$5:$C$12,'Your Debts'!$G$5)/12)),2) | E86: =MIN((F85)+D86,MAX(0,$C86-(0))) | F86: =ROUND(MAX(0,(F85)+D86-E86),2) | G86: =ROUND((I85)*(IF('Your Debts'!$G$6=0,0,INDEX('Your Debts'!$C$5:$C$12,'Your Debts'!$G$6)/12)),2) | H86: =MIN((I85)+G86,MAX(0,$C86-(E86))) | I86: =ROUND(MAX(0,(I85)+G86-H86),2) | J86: =ROUND((L85)*(IF('Your Debts'!$G$7=0,0,INDEX('Your Debts'!$C$5:$C$12,'Your Debts'!$G$7)/12)),2) | K86: =MIN((L85)+J86,MAX(0,$C86-(E86+H86))) | L86: =ROUND(MAX(0,(L85)+J86-K86),2) | M86: =ROUND((O85)*(IF('Your Debts'!$G$8=0,0,INDEX('Your Debts'!$C$5:$C$12,'Your Debts'!$G$8)/12)),2) | N86: =MIN((O85)+M86,MAX(0,$C86-(E86+H86+K86))) | O86: =ROUND(MAX(0,(O85)+M86-N86),2) | P86: =ROUND((R85)*(IF('Your Debts'!$G$9=0,0,INDEX('Your Debts'!$C$5:$C$12,'Your Debts'!$G$9)/12)),2) | Q86: =MIN((R85)+P86,MAX(0,$C86-(E86+H86+K86+N86))) | R86: =ROUND(MAX(0,(R85)+P86-Q86),2) | S86: =ROUND((U85)*(IF('Your Debts'!$G$10=0,0,INDEX('Your Debts'!$C$5:$C$12,'Your Debts'!$G$10)/12)),2) | T86: =MIN((U85)+S86,MAX(0,$C86-(E86+H86+K86+N86+Q86))) | U86: =ROUND(MAX(0,(U85)+S86-T86),2) | V86: =ROUND((X85)*(IF('Your Debts'!$G$11=0,0,INDEX('Your Debts'!$C$5:$C$12,'Your Debts'!$G$11)/12)),2) | W86: =MIN((X85)+V86,MAX(0,$C86-(E86+H86+K86+N86+Q86+T86))) | X86: =ROUND(MAX(0,(X85)+V86-W86),2) | Y86: =ROUND((AA85)*(IF('Your Debts'!$G$12=0,0,INDEX('Your Debts'!$C$5:$C$12,'Your Debts'!$G$12)/12)),2) | Z86: =MIN((AA85)+Y86,MAX(0,$C86-(E86+H86+K86+N86+Q86+T86+W86))) | AA86: =ROUND(MAX(0,(AA85)+Y86-Z86),2) | AB86: =F86+I86+L86+O86+R86+U86+X86+AA86 | AC86: =AC85+D86+G86+J86+M86+P86+S86+V86+Y86
A87: 82 | B87: =EDATE('Your Debts'!$B$19,81) | C87: ='Your Debts'!$B$18 | D87: =ROUND((F86)*(IF('Your Debts'!$G$5=0,0,INDEX('Your Debts'!$C$5:$C$12,'Your Debts'!$G$5)/12)),2) | E87: =MIN((F86)+D87,MAX(0,$C87-(0))) | F87: =ROUND(MAX(0,(F86)+D87-E87),2) | G87: =ROUND((I86)*(IF('Your Debts'!$G$6=0,0,INDEX('Your Debts'!$C$5:$C$12,'Your Debts'!$G$6)/12)),2) | H87: =MIN((I86)+G87,MAX(0,$C87-(E87))) | I87: =ROUND(MAX(0,(I86)+G87-H87),2) | J87: =ROUND((L86)*(IF('Your Debts'!$G$7=0,0,INDEX('Your Debts'!$C$5:$C$12,'Your Debts'!$G$7)/12)),2) | K87: =MIN((L86)+J87,MAX(0,$C87-(E87+H87))) | L87: =ROUND(MAX(0,(L86)+J87-K87),2) | M87: =ROUND((O86)*(IF('Your Debts'!$G$8=0,0,INDEX('Your Debts'!$C$5:$C$12,'Your Debts'!$G$8)/12)),2) | N87: =MIN((O86)+M87,MAX(0,$C87-(E87+H87+K87))) | O87: =ROUND(MAX(0,(O86)+M87-N87),2) | P87: =ROUND((R86)*(IF('Your Debts'!$G$9=0,0,INDEX('Your Debts'!$C$5:$C$12,'Your Debts'!$G$9)/12)),2) | Q87: =MIN((R86)+P87,MAX(0,$C87-(E87+H87+K87+N87))) | R87: =ROUND(MAX(0,(R86)+P87-Q87),2) | S87: =ROUND((U86)*(IF('Your Debts'!$G$10=0,0,INDEX('Your Debts'!$C$5:$C$12,'Your Debts'!$G$10)/12)),2) | T87: =MIN((U86)+S87,MAX(0,$C87-(E87+H87+K87+N87+Q87))) | U87: =ROUND(MAX(0,(U86)+S87-T87),2) | V87: =ROUND((X86)*(IF('Your Debts'!$G$11=0,0,INDEX('Your Debts'!$C$5:$C$12,'Your Debts'!$G$11)/12)),2) | W87: =MIN((X86)+V87,MAX(0,$C87-(E87+H87+K87+N87+Q87+T87))) | X87: =ROUND(MAX(0,(X86)+V87-W87),2) | Y87: =ROUND((AA86)*(IF('Your Debts'!$G$12=0,0,INDEX('Your Debts'!$C$5:$C$12,'Your Debts'!$G$12)/12)),2) | Z87: =MIN((AA86)+Y87,MAX(0,$C87-(E87+H87+K87+N87+Q87+T87+W87))) | AA87: =ROUND(MAX(0,(AA86)+Y87-Z87),2) | AB87: =F87+I87+L87+O87+R87+U87+X87+AA87 | AC87: =AC86+D87+G87+J87+M87+P87+S87+V87+Y87
A88: 83 | B88: =EDATE('Your Debts'!$B$19,82) | C88: ='Your Debts'!$B$18 | D88: =ROUND((F87)*(IF('Your Debts'!$G$5=0,0,INDEX('Your Debts'!$C$5:$C$12,'Your Debts'!$G$5)/12)),2) | E88: =MIN((F87)+D88,MAX(0,$C88-(0))) | F88: =ROUND(MAX(0,(F87)+D88-E88),2) | G88: =ROUND((I87)*(IF('Your Debts'!$G$6=0,0,INDEX('Your Debts'!$C$5:$C$12,'Your Debts'!$G$6)/12)),2) | H88: =MIN((I87)+G88,MAX(0,$C88-(E88))) | I88: =ROUND(MAX(0,(I87)+G88-H88),2) | J88: =ROUND((L87)*(IF('Your Debts'!$G$7=0,0,INDEX('Your Debts'!$C$5:$C$12,'Your Debts'!$G$7)/12)),2) | K88: =MIN((L87)+J88,MAX(0,$C88-(E88+H88))) | L88: =ROUND(MAX(0,(L87)+J88-K88),2) | M88: =ROUND((O87)*(IF('Your Debts'!$G$8=0,0,INDEX('Your Debts'!$C$5:$C$12,'Your Debts'!$G$8)/12)),2) | N88: =MIN((O87)+M88,MAX(0,$C88-(E88+H88+K88))) | O88: =ROUND(MAX(0,(O87)+M88-N88),2) | P88: =ROUND((R87)*(IF('Your Debts'!$G$9=0,0,INDEX('Your Debts'!$C$5:$C$12,'Your Debts'!$G$9)/12)),2) | Q88: =MIN((R87)+P88,MAX(0,$C88-(E88+H88+K88+N88))) | R88: =ROUND(MAX(0,(R87)+P88-Q88),2) | S88: =ROUND((U87)*(IF('Your Debts'!$G$10=0,0,INDEX('Your Debts'!$C$5:$C$12,'Your Debts'!$G$10)/12)),2) | T88: =MIN((U87)+S88,MAX(0,$C88-(E88+H88+K88+N88+Q88))) | U88: =ROUND(MAX(0,(U87)+S88-T88),2) | V88: =ROUND((X87)*(IF('Your Debts'!$G$11=0,0,INDEX('Your Debts'!$C$5:$C$12,'Your Debts'!$G$11)/12)),2) | W88: =MIN((X87)+V88,MAX(0,$C88-(E88+H88+K88+N88+Q88+T88))) | X88: =ROUND(MAX(0,(X87)+V88-W88),2) | Y88: =ROUND((AA87)*(IF('Your Debts'!$G$12=0,0,INDEX('Your Debts'!$C$5:$C$12,'Your Debts'!$G$12)/12)),2) | Z88: =MIN((AA87)+Y88,MAX(0,$C88-(E88+H88+K88+N88+Q88+T88+W88))) | AA88: =ROUND(MAX(0,(AA87)+Y88-Z88),2) | AB88: =F88+I88+L88+O88+R88+U88+X88+AA88 | AC88: =AC87+D88+G88+J88+M88+P88+S88+V88+Y88
A89: 84 | B89: =EDATE('Your Debts'!$B$19,83) | C89: ='Your Debts'!$B$18 | D89: =ROUND((F88)*(IF('Your Debts'!$G$5=0,0,INDEX('Your Debts'!$C$5:$C$12,'Your Debts'!$G$5)/12)),2) | E89: =MIN((F88)+D89,MAX(0,$C89-(0))) | F89: =ROUND(MAX(0,(F88)+D89-E89),2) | G89: =ROUND((I88)*(IF('Your Debts'!$G$6=0,0,INDEX('Your Debts'!$C$5:$C$12,'Your Debts'!$G$6)/12)),2) | H89: =MIN((I88)+G89,MAX(0,$C89-(E89))) | I89: =ROUND(MAX(0,(I88)+G89-H89),2) | J89: =ROUND((L88)*(IF('Your Debts'!$G$7=0,0,INDEX('Your Debts'!$C$5:$C$12,'Your Debts'!$G$7)/12)),2) | K89: =MIN((L88)+J89,MAX(0,$C89-(E89+H89))) | L89: =ROUND(MAX(0,(L88)+J89-K89),2) | M89: =ROUND((O88)*(IF('Your Debts'!$G$8=0,0,INDEX('Your Debts'!$C$5:$C$12,'Your Debts'!$G$8)/12)),2) | N89: =MIN((O88)+M89,MAX(0,$C89-(E89+H89+K89))) | O89: =ROUND(MAX(0,(O88)+M89-N89),2) | P89: =ROUND((R88)*(IF('Your Debts'!$G$9=0,0,INDEX('Your Debts'!$C$5:$C$12,'Your Debts'!$G$9)/12)),2) | Q89: =MIN((R88)+P89,MAX(0,$C89-(E89+H89+K89+N89))) | R89: =ROUND(MAX(0,(R88)+P89-Q89),2) | S89: =ROUND((U88)*(IF('Your Debts'!$G$10=0,0,INDEX('Your Debts'!$C$5:$C$12,'Your Debts'!$G$10)/12)),2) | T89: =MIN((U88)+S89,MAX(0,$C89-(E89+H89+K89+N89+Q89))) | U89: =ROUND(MAX(0,(U88)+S89-T89),2) | V89: =ROUND((X88)*(IF('Your Debts'!$G$11=0,0,INDEX('Your Debts'!$C$5:$C$12,'Your Debts'!$G$11)/12)),2) | W89: =MIN((X88)+V89,MAX(0,$C89-(E89+H89+K89+N89+Q89+T89))) | X89: =ROUND(MAX(0,(X88)+V89-W89),2) | Y89: =ROUND((AA88)*(IF('Your Debts'!$G$12=0,0,INDEX('Your Debts'!$C$5:$C$12,'Your Debts'!$G$12)/12)),2) | Z89: =MIN((AA88)+Y89,MAX(0,$C89-(E89+H89+K89+N89+Q89+T89+W89))) | AA89: =ROUND(MAX(0,(AA88)+Y89-Z89),2) | AB89: =F89+I89+L89+O89+R89+U89+X89+AA89 | AC89: =AC88+D89+G89+J89+M89+P89+S89+V89+Y89
A90: 85 | B90: =EDATE('Your Debts'!$B$19,84) | C90: ='Your Debts'!$B$18 | D90: =ROUND((F89)*(IF('Your Debts'!$G$5=0,0,INDEX('Your Debts'!$C$5:$C$12,'Your Debts'!$G$5)/12)),2) | E90: =MIN((F89)+D90,MAX(0,$C90-(0))) | F90: =ROUND(MAX(0,(F89)+D90-E90),2) | G90: =ROUND((I89)*(IF('Your Debts'!$G$6=0,0,INDEX('Your Debts'!$C$5:$C$12,'Your Debts'!$G$6)/12)),2) | H90: =MIN((I89)+G90,MAX(0,$C90-(E90))) | I90: =ROUND(MAX(0,(I89)+G90-H90),2) | J90: =ROUND((L89)*(IF('Your Debts'!$G$7=0,0,INDEX('Your Debts'!$C$5:$C$12,'Your Debts'!$G$7)/12)),2) | K90: =MIN((L89)+J90,MAX(0,$C90-(E90+H90))) | L90: =ROUND(MAX(0,(L89)+J90-K90),2) | M90: =ROUND((O89)*(IF('Your Debts'!$G$8=0,0,INDEX('Your Debts'!$C$5:$C$12,'Your Debts'!$G$8)/12)),2) | N90: =MIN((O89)+M90,MAX(0,$C90-(E90+H90+K90))) | O90: =ROUND(MAX(0,(O89)+M90-N90),2) | P90: =ROUND((R89)*(IF('Your Debts'!$G$9=0,0,INDEX('Your Debts'!$C$5:$C$12,'Your Debts'!$G$9)/12)),2) | Q90: =MIN((R89)+P90,MAX(0,$C90-(E90+H90+K90+N90))) | R90: =ROUND(MAX(0,(R89)+P90-Q90),2) | S90: =ROUND((U89)*(IF('Your Debts'!$G$10=0,0,INDEX('Your Debts'!$C$5:$C$12,'Your Debts'!$G$10)/12)),2) | T90: =MIN((U89)+S90,MAX(0,$C90-(E90+H90+K90+N90+Q90))) | U90: =ROUND(MAX(0,(U89)+S90-T90),2) | V90: =ROUND((X89)*(IF('Your Debts'!$G$11=0,0,INDEX('Your Debts'!$C$5:$C$12,'Your Debts'!$G$11)/12)),2) | W90: =MIN((X89)+V90,MAX(0,$C90-(E90+H90+K90+N90+Q90+T90))) | X90: =ROUND(MAX(0,(X89)+V90-W90),2) | Y90: =ROUND((AA89)*(IF('Your Debts'!$G$12=0,0,INDEX('Your Debts'!$C$5:$C$12,'Your Debts'!$G$12)/12)),2) | Z90: =MIN((AA89)+Y90,MAX(0,$C90-(E90+H90+K90+N90+Q90+T90+W90))) | AA90: =ROUND(MAX(0,(AA89)+Y90-Z90),2) | AB90: =F90+I90+L90+O90+R90+U90+X90+AA90 | AC90: =AC89+D90+G90+J90+M90+P90+S90+V90+Y90
A91: 86 | B91: =EDATE('Your Debts'!$B$19,85) | C91: ='Your Debts'!$B$18 | D91: =ROUND((F90)*(IF('Your Debts'!$G$5=0,0,INDEX('Your Debts'!$C$5:$C$12,'Your Debts'!$G$5)/12)),2) | E91: =MIN((F90)+D91,MAX(0,$C91-(0))) | F91: =ROUND(MAX(0,(F90)+D91-E91),2) | G91: =ROUND((I90)*(IF('Your Debts'!$G$6=0,0,INDEX('Your Debts'!$C$5:$C$12,'Your Debts'!$G$6)/12)),2) | H91: =MIN((I90)+G91,MAX(0,$C91-(E91))) | I91: =ROUND(MAX(0,(I90)+G91-H91),2) | J91: =ROUND((L90)*(IF('Your Debts'!$G$7=0,0,INDEX('Your Debts'!$C$5:$C$12,'Your Debts'!$G$7)/12)),2) | K91: =MIN((L90)+J91,MAX(0,$C91-(E91+H91))) | L91: =ROUND(MAX(0,(L90)+J91-K91),2) | M91: =ROUND((O90)*(IF('Your Debts'!$G$8=0,0,INDEX('Your Debts'!$C$5:$C$12,'Your Debts'!$G$8)/12)),2) | N91: =MIN((O90)+M91,MAX(0,$C91-(E91+H91+K91))) | O91: =ROUND(MAX(0,(O90)+M91-N91),2) | P91: =ROUND((R90)*(IF('Your Debts'!$G$9=0,0,INDEX('Your Debts'!$C$5:$C$12,'Your Debts'!$G$9)/12)),2) | Q91: =MIN((R90)+P91,MAX(0,$C91-(E91+H91+K91+N91))) | R91: =ROUND(MAX(0,(R90)+P91-Q91),2) | S91: =ROUND((U90)*(IF('Your Debts'!$G$10=0,0,INDEX('Your Debts'!$C$5:$C$12,'Your Debts'!$G$10)/12)),2) | T91: =MIN((U90)+S91,MAX(0,$C91-(E91+H91+K91+N91+Q91))) | U91: =ROUND(MAX(0,(U90)+S91-T91),2) | V91: =ROUND((X90)*(IF('Your Debts'!$G$11=0,0,INDEX('Your Debts'!$C$5:$C$12,'Your Debts'!$G$11)/12)),2) | W91: =MIN((X90)+V91,MAX(0,$C91-(E91+H91+K91+N91+Q91+T91))) | X91: =ROUND(MAX(0,(X90)+V91-W91),2) | Y91: =ROUND((AA90)*(IF('Your Debts'!$G$12=0,0,INDEX('Your Debts'!$C$5:$C$12,'Your Debts'!$G$12)/12)),2) | Z91: =MIN((AA90)+Y91,MAX(0,$C91-(E91+H91+K91+N91+Q91+T91+W91))) | AA91: =ROUND(MAX(0,(AA90)+Y91-Z91),2) | AB91: =F91+I91+L91+O91+R91+U91+X91+AA91 | AC91: =AC90+D91+G91+J91+M91+P91+S91+V91+Y91
A92: 87 | B92: =EDATE('Your Debts'!$B$19,86) | C92: ='Your Debts'!$B$18 | D92: =ROUND((F91)*(IF('Your Debts'!$G$5=0,0,INDEX('Your Debts'!$C$5:$C$12,'Your Debts'!$G$5)/12)),2) | E92: =MIN((F91)+D92,MAX(0,$C92-(0))) | F92: =ROUND(MAX(0,(F91)+D92-E92),2) | G92: =ROUND((I91)*(IF('Your Debts'!$G$6=0,0,INDEX('Your Debts'!$C$5:$C$12,'Your Debts'!$G$6)/12)),2) | H92: =MIN((I91)+G92,MAX(0,$C92-(E92))) | I92: =ROUND(MAX(0,(I91)+G92-H92),2) | J92: =ROUND((L91)*(IF('Your Debts'!$G$7=0,0,INDEX('Your Debts'!$C$5:$C$12,'Your Debts'!$G$7)/12)),2) | K92: =MIN((L91)+J92,MAX(0,$C92-(E92+H92))) | L92: =ROUND(MAX(0,(L91)+J92-K92),2) | M92: =ROUND((O91)*(IF('Your Debts'!$G$8=0,0,INDEX('Your Debts'!$C$5:$C$12,'Your Debts'!$G$8)/12)),2) | N92: =MIN((O91)+M92,MAX(0,$C92-(E92+H92+K92))) | O92: =ROUND(MAX(0,(O91)+M92-N92),2) | P92: =ROUND((R91)*(IF('Your Debts'!$G$9=0,0,INDEX('Your Debts'!$C$5:$C$12,'Your Debts'!$G$9)/12)),2) | Q92: =MIN((R91)+P92,MAX(0,$C92-(E92+H92+K92+N92))) | R92: =ROUND(MAX(0,(R91)+P92-Q92),2) | S92: =ROUND((U91)*(IF('Your Debts'!$G$10=0,0,INDEX('Your Debts'!$C$5:$C$12,'Your Debts'!$G$10)/12)),2) | T92: =MIN((U91)+S92,MAX(0,$C92-(E92+H92+K92+N92+Q92))) | U92: =ROUND(MAX(0,(U91)+S92-T92),2) | V92: =ROUND((X91)*(IF('Your Debts'!$G$11=0,0,INDEX('Your Debts'!$C$5:$C$12,'Your Debts'!$G$11)/12)),2) | W92: =MIN((X91)+V92,MAX(0,$C92-(E92+H92+K92+N92+Q92+T92))) | X92: =ROUND(MAX(0,(X91)+V92-W92),2) | Y92: =ROUND((AA91)*(IF('Your Debts'!$G$12=0,0,INDEX('Your Debts'!$C$5:$C$12,'Your Debts'!$G$12)/12)),2) | Z92: =MIN((AA91)+Y92,MAX(0,$C92-(E92+H92+K92+N92+Q92+T92+W92))) | AA92: =ROUND(MAX(0,(AA91)+Y92-Z92),2) | AB92: =F92+I92+L92+O92+R92+U92+X92+AA92 | AC92: =AC91+D92+G92+J92+M92+P92+S92+V92+Y92
A93: 88 | B93: =EDATE('Your Debts'!$B$19,87) | C93: ='Your Debts'!$B$18 | D93: =ROUND((F92)*(IF('Your Debts'!$G$5=0,0,INDEX('Your Debts'!$C$5:$C$12,'Your Debts'!$G$5)/12)),2) | E93: =MIN((F92)+D93,MAX(0,$C93-(0))) | F93: =ROUND(MAX(0,(F92)+D93-E93),2) | G93: =ROUND((I92)*(IF('Your Debts'!$G$6=0,0,INDEX('Your Debts'!$C$5:$C$12,'Your Debts'!$G$6)/12)),2) | H93: =MIN((I92)+G93,MAX(0,$C93-(E93))) | I93: =ROUND(MAX(0,(I92)+G93-H93),2) | J93: =ROUND((L92)*(IF('Your Debts'!$G$7=0,0,INDEX('Your Debts'!$C$5:$C$12,'Your Debts'!$G$7)/12)),2) | K93: =MIN((L92)+J93,MAX(0,$C93-(E93+H93))) | L93: =ROUND(MAX(0,(L92)+J93-K93),2) | M93: =ROUND((O92)*(IF('Your Debts'!$G$8=0,0,INDEX('Your Debts'!$C$5:$C$12,'Your Debts'!$G$8)/12)),2) | N93: =MIN((O92)+M93,MAX(0,$C93-(E93+H93+K93))) | O93: =ROUND(MAX(0,(O92)+M93-N93),2) | P93: =ROUND((R92)*(IF('Your Debts'!$G$9=0,0,INDEX('Your Debts'!$C$5:$C$12,'Your Debts'!$G$9)/12)),2) | Q93: =MIN((R92)+P93,MAX(0,$C93-(E93+H93+K93+N93))) | R93: =ROUND(MAX(0,(R92)+P93-Q93),2) | S93: =ROUND((U92)*(IF('Your Debts'!$G$10=0,0,INDEX('Your Debts'!$C$5:$C$12,'Your Debts'!$G$10)/12)),2) | T93: =MIN((U92)+S93,MAX(0,$C93-(E93+H93+K93+N93+Q93))) | U93: =ROUND(MAX(0,(U92)+S93-T93),2) | V93: =ROUND((X92)*(IF('Your Debts'!$G$11=0,0,INDEX('Your Debts'!$C$5:$C$12,'Your Debts'!$G$11)/12)),2) | W93: =MIN((X92)+V93,MAX(0,$C93-(E93+H93+K93+N93+Q93+T93))) | X93: =ROUND(MAX(0,(X92)+V93-W93),2) | Y93: =ROUND((AA92)*(IF('Your Debts'!$G$12=0,0,INDEX('Your Debts'!$C$5:$C$12,'Your Debts'!$G$12)/12)),2) | Z93: =MIN((AA92)+Y93,MAX(0,$C93-(E93+H93+K93+N93+Q93+T93+W93))) | AA93: =ROUND(MAX(0,(AA92)+Y93-Z93),2) | AB93: =F93+I93+L93+O93+R93+U93+X93+AA93 | AC93: =AC92+D93+G93+J93+M93+P93+S93+V93+Y93
A94: 89 | B94: =EDATE('Your Debts'!$B$19,88) | C94: ='Your Debts'!$B$18 | D94: =ROUND((F93)*(IF('Your Debts'!$G$5=0,0,INDEX('Your Debts'!$C$5:$C$12,'Your Debts'!$G$5)/12)),2) | E94: =MIN((F93)+D94,MAX(0,$C94-(0))) | F94: =ROUND(MAX(0,(F93)+D94-E94),2) | G94: =ROUND((I93)*(IF('Your Debts'!$G$6=0,0,INDEX('Your Debts'!$C$5:$C$12,'Your Debts'!$G$6)/12)),2) | H94: =MIN((I93)+G94,MAX(0,$C94-(E94))) | I94: =ROUND(MAX(0,(I93)+G94-H94),2) | J94: =ROUND((L93)*(IF('Your Debts'!$G$7=0,0,INDEX('Your Debts'!$C$5:$C$12,'Your Debts'!$G$7)/12)),2) | K94: =MIN((L93)+J94,MAX(0,$C94-(E94+H94))) | L94: =ROUND(MAX(0,(L93)+J94-K94),2) | M94: =ROUND((O93)*(IF('Your Debts'!$G$8=0,0,INDEX('Your Debts'!$C$5:$C$12,'Your Debts'!$G$8)/12)),2) | N94: =MIN((O93)+M94,MAX(0,$C94-(E94+H94+K94))) | O94: =ROUND(MAX(0,(O93)+M94-N94),2) | P94: =ROUND((R93)*(IF('Your Debts'!$G$9=0,0,INDEX('Your Debts'!$C$5:$C$12,'Your Debts'!$G$9)/12)),2) | Q94: =MIN((R93)+P94,MAX(0,$C94-(E94+H94+K94+N94))) | R94: =ROUND(MAX(0,(R93)+P94-Q94),2) | S94: =ROUND((U93)*(IF('Your Debts'!$G$10=0,0,INDEX('Your Debts'!$C$5:$C$12,'Your Debts'!$G$10)/12)),2) | T94: =MIN((U93)+S94,MAX(0,$C94-(E94+H94+K94+N94+Q94))) | U94: =ROUND(MAX(0,(U93)+S94-T94),2) | V94: =ROUND((X93)*(IF('Your Debts'!$G$11=0,0,INDEX('Your Debts'!$C$5:$C$12,'Your Debts'!$G$11)/12)),2) | W94: =MIN((X93)+V94,MAX(0,$C94-(E94+H94+K94+N94+Q94+T94))) | X94: =ROUND(MAX(0,(X93)+V94-W94),2) | Y94: =ROUND((AA93)*(IF('Your Debts'!$G$12=0,0,INDEX('Your Debts'!$C$5:$C$12,'Your Debts'!$G$12)/12)),2) | Z94: =MIN((AA93)+Y94,MAX(0,$C94-(E94+H94+K94+N94+Q94+T94+W94))) | AA94: =ROUND(MAX(0,(AA93)+Y94-Z94),2) | AB94: =F94+I94+L94+O94+R94+U94+X94+AA94 | AC94: =AC93+D94+G94+J94+M94+P94+S94+V94+Y94
A95: 90 | B95: =EDATE('Your Debts'!$B$19,89) | C95: ='Your Debts'!$B$18 | D95: =ROUND((F94)*(IF('Your Debts'!$G$5=0,0,INDEX('Your Debts'!$C$5:$C$12,'Your Debts'!$G$5)/12)),2) | E95: =MIN((F94)+D95,MAX(0,$C95-(0))) | F95: =ROUND(MAX(0,(F94)+D95-E95),2) | G95: =ROUND((I94)*(IF('Your Debts'!$G$6=0,0,INDEX('Your Debts'!$C$5:$C$12,'Your Debts'!$G$6)/12)),2) | H95: =MIN((I94)+G95,MAX(0,$C95-(E95))) | I95: =ROUND(MAX(0,(I94)+G95-H95),2) | J95: =ROUND((L94)*(IF('Your Debts'!$G$7=0,0,INDEX('Your Debts'!$C$5:$C$12,'Your Debts'!$G$7)/12)),2) | K95: =MIN((L94)+J95,MAX(0,$C95-(E95+H95))) | L95: =ROUND(MAX(0,(L94)+J95-K95),2) | M95: =ROUND((O94)*(IF('Your Debts'!$G$8=0,0,INDEX('Your Debts'!$C$5:$C$12,'Your Debts'!$G$8)/12)),2) | N95: =MIN((O94)+M95,MAX(0,$C95-(E95+H95+K95))) | O95: =ROUND(MAX(0,(O94)+M95-N95),2) | P95: =ROUND((R94)*(IF('Your Debts'!$G$9=0,0,INDEX('Your Debts'!$C$5:$C$12,'Your Debts'!$G$9)/12)),2) | Q95: =MIN((R94)+P95,MAX(0,$C95-(E95+H95+K95+N95))) | R95: =ROUND(MAX(0,(R94)+P95-Q95),2) | S95: =ROUND((U94)*(IF('Your Debts'!$G$10=0,0,INDEX('Your Debts'!$C$5:$C$12,'Your Debts'!$G$10)/12)),2) | T95: =MIN((U94)+S95,MAX(0,$C95-(E95+H95+K95+N95+Q95))) | U95: =ROUND(MAX(0,(U94)+S95-T95),2) | V95: =ROUND((X94)*(IF('Your Debts'!$G$11=0,0,INDEX('Your Debts'!$C$5:$C$12,'Your Debts'!$G$11)/12)),2) | W95: =MIN((X94)+V95,MAX(0,$C95-(E95+H95+K95+N95+Q95+T95))) | X95: =ROUND(MAX(0,(X94)+V95-W95),2) | Y95: =ROUND((AA94)*(IF('Your Debts'!$G$12=0,0,INDEX('Your Debts'!$C$5:$C$12,'Your Debts'!$G$12)/12)),2) | Z95: =MIN((AA94)+Y95,MAX(0,$C95-(E95+H95+K95+N95+Q95+T95+W95))) | AA95: =ROUND(MAX(0,(AA94)+Y95-Z95),2) | AB95: =F95+I95+L95+O95+R95+U95+X95+AA95 | AC95: =AC94+D95+G95+J95+M95+P95+S95+V95+Y95
A96: 91 | B96: =EDATE('Your Debts'!$B$19,90) | C96: ='Your Debts'!$B$18 | D96: =ROUND((F95)*(IF('Your Debts'!$G$5=0,0,INDEX('Your Debts'!$C$5:$C$12,'Your Debts'!$G$5)/12)),2) | E96: =MIN((F95)+D96,MAX(0,$C96-(0))) | F96: =ROUND(MAX(0,(F95)+D96-E96),2) | G96: =ROUND((I95)*(IF('Your Debts'!$G$6=0,0,INDEX('Your Debts'!$C$5:$C$12,'Your Debts'!$G$6)/12)),2) | H96: =MIN((I95)+G96,MAX(0,$C96-(E96))) | I96: =ROUND(MAX(0,(I95)+G96-H96),2) | J96: =ROUND((L95)*(IF('Your Debts'!$G$7=0,0,INDEX('Your Debts'!$C$5:$C$12,'Your Debts'!$G$7)/12)),2) | K96: =MIN((L95)+J96,MAX(0,$C96-(E96+H96))) | L96: =ROUND(MAX(0,(L95)+J96-K96),2) | M96: =ROUND((O95)*(IF('Your Debts'!$G$8=0,0,INDEX('Your Debts'!$C$5:$C$12,'Your Debts'!$G$8)/12)),2) | N96: =MIN((O95)+M96,MAX(0,$C96-(E96+H96+K96))) | O96: =ROUND(MAX(0,(O95)+M96-N96),2) | P96: =ROUND((R95)*(IF('Your Debts'!$G$9=0,0,INDEX('Your Debts'!$C$5:$C$12,'Your Debts'!$G$9)/12)),2) | Q96: =MIN((R95)+P96,MAX(0,$C96-(E96+H96+K96+N96))) | R96: =ROUND(MAX(0,(R95)+P96-Q96),2) | S96: =ROUND((U95)*(IF('Your Debts'!$G$10=0,0,INDEX('Your Debts'!$C$5:$C$12,'Your Debts'!$G$10)/12)),2) | T96: =MIN((U95)+S96,MAX(0,$C96-(E96+H96+K96+N96+Q96))) | U96: =ROUND(MAX(0,(U95)+S96-T96),2) | V96: =ROUND((X95)*(IF('Your Debts'!$G$11=0,0,INDEX('Your Debts'!$C$5:$C$12,'Your Debts'!$G$11)/12)),2) | W96: =MIN((X95)+V96,MAX(0,$C96-(E96+H96+K96+N96+Q96+T96))) | X96: =ROUND(MAX(0,(X95)+V96-W96),2) | Y96: =ROUND((AA95)*(IF('Your Debts'!$G$12=0,0,INDEX('Your Debts'!$C$5:$C$12,'Your Debts'!$G$12)/12)),2) | Z96: =MIN((AA95)+Y96,MAX(0,$C96-(E96+H96+K96+N96+Q96+T96+W96))) | AA96: =ROUND(MAX(0,(AA95)+Y96-Z96),2) | AB96: =F96+I96+L96+O96+R96+U96+X96+AA96 | AC96: =AC95+D96+G96+J96+M96+P96+S96+V96+Y96
A97: 92 | B97: =EDATE('Your Debts'!$B$19,91) | C97: ='Your Debts'!$B$18 | D97: =ROUND((F96)*(IF('Your Debts'!$G$5=0,0,INDEX('Your Debts'!$C$5:$C$12,'Your Debts'!$G$5)/12)),2) | E97: =MIN((F96)+D97,MAX(0,$C97-(0))) | F97: =ROUND(MAX(0,(F96)+D97-E97),2) | G97: =ROUND((I96)*(IF('Your Debts'!$G$6=0,0,INDEX('Your Debts'!$C$5:$C$12,'Your Debts'!$G$6)/12)),2) | H97: =MIN((I96)+G97,MAX(0,$C97-(E97))) | I97: =ROUND(MAX(0,(I96)+G97-H97),2) | J97: =ROUND((L96)*(IF('Your Debts'!$G$7=0,0,INDEX('Your Debts'!$C$5:$C$12,'Your Debts'!$G$7)/12)),2) | K97: =MIN((L96)+J97,MAX(0,$C97-(E97+H97))) | L97: =ROUND(MAX(0,(L96)+J97-K97),2) | M97: =ROUND((O96)*(IF('Your Debts'!$G$8=0,0,INDEX('Your Debts'!$C$5:$C$12,'Your Debts'!$G$8)/12)),2) | N97: =MIN((O96)+M97,MAX(0,$C97-(E97+H97+K97))) | O97: =ROUND(MAX(0,(O96)+M97-N97),2) | P97: =ROUND((R96)*(IF('Your Debts'!$G$9=0,0,INDEX('Your Debts'!$C$5:$C$12,'Your Debts'!$G$9)/12)),2) | Q97: =MIN((R96)+P97,MAX(0,$C97-(E97+H97+K97+N97))) | R97: =ROUND(MAX(0,(R96)+P97-Q97),2) | S97: =ROUND((U96)*(IF('Your Debts'!$G$10=0,0,INDEX('Your Debts'!$C$5:$C$12,'Your Debts'!$G$10)/12)),2) | T97: =MIN((U96)+S97,MAX(0,$C97-(E97+H97+K97+N97+Q97))) | U97: =ROUND(MAX(0,(U96)+S97-T97),2) | V97: =ROUND((X96)*(IF('Your Debts'!$G$11=0,0,INDEX('Your Debts'!$C$5:$C$12,'Your Debts'!$G$11)/12)),2) | W97: =MIN((X96)+V97,MAX(0,$C97-(E97+H97+K97+N97+Q97+T97))) | X97: =ROUND(MAX(0,(X96)+V97-W97),2) | Y97: =ROUND((AA96)*(IF('Your Debts'!$G$12=0,0,INDEX('Your Debts'!$C$5:$C$12,'Your Debts'!$G$12)/12)),2) | Z97: =MIN((AA96)+Y97,MAX(0,$C97-(E97+H97+K97+N97+Q97+T97+W97))) | AA97: =ROUND(MAX(0,(AA96)+Y97-Z97),2) | AB97: =F97+I97+L97+O97+R97+U97+X97+AA97 | AC97: =AC96+D97+G97+J97+M97+P97+S97+V97+Y97
A98: 93 | B98: =EDATE('Your Debts'!$B$19,92) | C98: ='Your Debts'!$B$18 | D98: =ROUND((F97)*(IF('Your Debts'!$G$5=0,0,INDEX('Your Debts'!$C$5:$C$12,'Your Debts'!$G$5)/12)),2) | E98: =MIN((F97)+D98,MAX(0,$C98-(0))) | F98: =ROUND(MAX(0,(F97)+D98-E98),2) | G98: =ROUND((I97)*(IF('Your Debts'!$G$6=0,0,INDEX('Your Debts'!$C$5:$C$12,'Your Debts'!$G$6)/12)),2) | H98: =MIN((I97)+G98,MAX(0,$C98-(E98))) | I98: =ROUND(MAX(0,(I97)+G98-H98),2) | J98: =ROUND((L97)*(IF('Your Debts'!$G$7=0,0,INDEX('Your Debts'!$C$5:$C$12,'Your Debts'!$G$7)/12)),2) | K98: =MIN((L97)+J98,MAX(0,$C98-(E98+H98))) | L98: =ROUND(MAX(0,(L97)+J98-K98),2) | M98: =ROUND((O97)*(IF('Your Debts'!$G$8=0,0,INDEX('Your Debts'!$C$5:$C$12,'Your Debts'!$G$8)/12)),2) | N98: =MIN((O97)+M98,MAX(0,$C98-(E98+H98+K98))) | O98: =ROUND(MAX(0,(O97)+M98-N98),2) | P98: =ROUND((R97)*(IF('Your Debts'!$G$9=0,0,INDEX('Your Debts'!$C$5:$C$12,'Your Debts'!$G$9)/12)),2) | Q98: =MIN((R97)+P98,MAX(0,$C98-(E98+H98+K98+N98))) | R98: =ROUND(MAX(0,(R97)+P98-Q98),2) | S98: =ROUND((U97)*(IF('Your Debts'!$G$10=0,0,INDEX('Your Debts'!$C$5:$C$12,'Your Debts'!$G$10)/12)),2) | T98: =MIN((U97)+S98,MAX(0,$C98-(E98+H98+K98+N98+Q98))) | U98: =ROUND(MAX(0,(U97)+S98-T98),2) | V98: =ROUND((X97)*(IF('Your Debts'!$G$11=0,0,INDEX('Your Debts'!$C$5:$C$12,'Your Debts'!$G$11)/12)),2) | W98: =MIN((X97)+V98,MAX(0,$C98-(E98+H98+K98+N98+Q98+T98))) | X98: =ROUND(MAX(0,(X97)+V98-W98),2) | Y98: =ROUND((AA97)*(IF('Your Debts'!$G$12=0,0,INDEX('Your Debts'!$C$5:$C$12,'Your Debts'!$G$12)/12)),2) | Z98: =MIN((AA97)+Y98,MAX(0,$C98-(E98+H98+K98+N98+Q98+T98+W98))) | AA98: =ROUND(MAX(0,(AA97)+Y98-Z98),2) | AB98: =F98+I98+L98+O98+R98+U98+X98+AA98 | AC98: =AC97+D98+G98+J98+M98+P98+S98+V98+Y98
A99: 94 | B99: =EDATE('Your Debts'!$B$19,93) | C99: ='Your Debts'!$B$18 | D99: =ROUND((F98)*(IF('Your Debts'!$G$5=0,0,INDEX('Your Debts'!$C$5:$C$12,'Your Debts'!$G$5)/12)),2) | E99: =MIN((F98)+D99,MAX(0,$C99-(0))) | F99: =ROUND(MAX(0,(F98)+D99-E99),2) | G99: =ROUND((I98)*(IF('Your Debts'!$G$6=0,0,INDEX('Your Debts'!$C$5:$C$12,'Your Debts'!$G$6)/12)),2) | H99: =MIN((I98)+G99,MAX(0,$C99-(E99))) | I99: =ROUND(MAX(0,(I98)+G99-H99),2) | J99: =ROUND((L98)*(IF('Your Debts'!$G$7=0,0,INDEX('Your Debts'!$C$5:$C$12,'Your Debts'!$G$7)/12)),2) | K99: =MIN((L98)+J99,MAX(0,$C99-(E99+H99))) | L99: =ROUND(MAX(0,(L98)+J99-K99),2) | M99: =ROUND((O98)*(IF('Your Debts'!$G$8=0,0,INDEX('Your Debts'!$C$5:$C$12,'Your Debts'!$G$8)/12)),2) | N99: =MIN((O98)+M99,MAX(0,$C99-(E99+H99+K99))) | O99: =ROUND(MAX(0,(O98)+M99-N99),2) | P99: =ROUND((R98)*(IF('Your Debts'!$G$9=0,0,INDEX('Your Debts'!$C$5:$C$12,'Your Debts'!$G$9)/12)),2) | Q99: =MIN((R98)+P99,MAX(0,$C99-(E99+H99+K99+N99))) | R99: =ROUND(MAX(0,(R98)+P99-Q99),2) | S99: =ROUND((U98)*(IF('Your Debts'!$G$10=0,0,INDEX('Your Debts'!$C$5:$C$12,'Your Debts'!$G$10)/12)),2) | T99: =MIN((U98)+S99,MAX(0,$C99-(E99+H99+K99+N99+Q99))) | U99: =ROUND(MAX(0,(U98)+S99-T99),2) | V99: =ROUND((X98)*(IF('Your Debts'!$G$11=0,0,INDEX('Your Debts'!$C$5:$C$12,'Your Debts'!$G$11)/12)),2) | W99: =MIN((X98)+V99,MAX(0,$C99-(E99+H99+K99+N99+Q99+T99))) | X99: =ROUND(MAX(0,(X98)+V99-W99),2) | Y99: =ROUND((AA98)*(IF('Your Debts'!$G$12=0,0,INDEX('Your Debts'!$C$5:$C$12,'Your Debts'!$G$12)/12)),2) | Z99: =MIN((AA98)+Y99,MAX(0,$C99-(E99+H99+K99+N99+Q99+T99+W99))) | AA99: =ROUND(MAX(0,(AA98)+Y99-Z99),2) | AB99: =F99+I99+L99+O99+R99+U99+X99+AA99 | AC99: =AC98+D99+G99+J99+M99+P99+S99+V99+Y99
A100: 95 | B100: =EDATE('Your Debts'!$B$19,94) | C100: ='Your Debts'!$B$18 | D100: =ROUND((F99)*(IF('Your Debts'!$G$5=0,0,INDEX('Your Debts'!$C$5:$C$12,'Your Debts'!$G$5)/12)),2) | E100: =MIN((F99)+D100,MAX(0,$C100-(0))) | F100: =ROUND(MAX(0,(F99)+D100-E100),2) | G100: =ROUND((I99)*(IF('Your Debts'!$G$6=0,0,INDEX('Your Debts'!$C$5:$C$12,'Your Debts'!$G$6)/12)),2) | H100: =MIN((I99)+G100,MAX(0,$C100-(E100))) | I100: =ROUND(MAX(0,(I99)+G100-H100),2) | J100: =ROUND((L99)*(IF('Your Debts'!$G$7=0,0,INDEX('Your Debts'!$C$5:$C$12,'Your Debts'!$G$7)/12)),2) | K100: =MIN((L99)+J100,MAX(0,$C100-(E100+H100))) | L100: =ROUND(MAX(0,(L99)+J100-K100),2) | M100: =ROUND((O99)*(IF('Your Debts'!$G$8=0,0,INDEX('Your Debts'!$C$5:$C$12,'Your Debts'!$G$8)/12)),2) | N100: =MIN((O99)+M100,MAX(0,$C100-(E100+H100+K100))) | O100: =ROUND(MAX(0,(O99)+M100-N100),2) | P100: =ROUND((R99)*(IF('Your Debts'!$G$9=0,0,INDEX('Your Debts'!$C$5:$C$12,'Your Debts'!$G$9)/12)),2) | Q100: =MIN((R99)+P100,MAX(0,$C100-(E100+H100+K100+N100))) | R100: =ROUND(MAX(0,(R99)+P100-Q100),2) | S100: =ROUND((U99)*(IF('Your Debts'!$G$10=0,0,INDEX('Your Debts'!$C$5:$C$12,'Your Debts'!$G$10)/12)),2) | T100: =MIN((U99)+S100,MAX(0,$C100-(E100+H100+K100+N100+Q100))) | U100: =ROUND(MAX(0,(U99)+S100-T100),2) | V100: =ROUND((X99)*(IF('Your Debts'!$G$11=0,0,INDEX('Your Debts'!$C$5:$C$12,'Your Debts'!$G$11)/12)),2) | W100: =MIN((X99)+V100,MAX(0,$C100-(E100+H100+K100+N100+Q100+T100))) | X100: =ROUND(MAX(0,(X99)+V100-W100),2) | Y100: =ROUND((AA99)*(IF('Your Debts'!$G$12=0,0,INDEX('Your Debts'!$C$5:$C$12,'Your Debts'!$G$12)/12)),2) | Z100: =MIN((AA99)+Y100,MAX(0,$C100-(E100+H100+K100+N100+Q100+T100+W100))) | AA100: =ROUND(MAX(0,(AA99)+Y100-Z100),2) | AB100: =F100+I100+L100+O100+R100+U100+X100+AA100 | AC100: =AC99+D100+G100+J100+M100+P100+S100+V100+Y100
A101: 96 | B101: =EDATE('Your Debts'!$B$19,95) | C101: ='Your Debts'!$B$18 | D101: =ROUND((F100)*(IF('Your Debts'!$G$5=0,0,INDEX('Your Debts'!$C$5:$C$12,'Your Debts'!$G$5)/12)),2) | E101: =MIN((F100)+D101,MAX(0,$C101-(0))) | F101: =ROUND(MAX(0,(F100)+D101-E101),2) | G101: =ROUND((I100)*(IF('Your Debts'!$G$6=0,0,INDEX('Your Debts'!$C$5:$C$12,'Your Debts'!$G$6)/12)),2) | H101: =MIN((I100)+G101,MAX(0,$C101-(E101))) | I101: =ROUND(MAX(0,(I100)+G101-H101),2) | J101: =ROUND((L100)*(IF('Your Debts'!$G$7=0,0,INDEX('Your Debts'!$C$5:$C$12,'Your Debts'!$G$7)/12)),2) | K101: =MIN((L100)+J101,MAX(0,$C101-(E101+H101))) | L101: =ROUND(MAX(0,(L100)+J101-K101),2) | M101: =ROUND((O100)*(IF('Your Debts'!$G$8=0,0,INDEX('Your Debts'!$C$5:$C$12,'Your Debts'!$G$8)/12)),2) | N101: =MIN((O100)+M101,MAX(0,$C101-(E101+H101+K101))) | O101: =ROUND(MAX(0,(O100)+M101-N101),2) | P101: =ROUND((R100)*(IF('Your Debts'!$G$9=0,0,INDEX('Your Debts'!$C$5:$C$12,'Your Debts'!$G$9)/12)),2) | Q101: =MIN((R100)+P101,MAX(0,$C101-(E101+H101+K101+N101))) | R101: =ROUND(MAX(0,(R100)+P101-Q101),2) | S101: =ROUND((U100)*(IF('Your Debts'!$G$10=0,0,INDEX('Your Debts'!$C$5:$C$12,'Your Debts'!$G$10)/12)),2) | T101: =MIN((U100)+S101,MAX(0,$C101-(E101+H101+K101+N101+Q101))) | U101: =ROUND(MAX(0,(U100)+S101-T101),2) | V101: =ROUND((X100)*(IF('Your Debts'!$G$11=0,0,INDEX('Your Debts'!$C$5:$C$12,'Your Debts'!$G$11)/12)),2) | W101: =MIN((X100)+V101,MAX(0,$C101-(E101+H101+K101+N101+Q101+T101))) | X101: =ROUND(MAX(0,(X100)+V101-W101),2) | Y101: =ROUND((AA100)*(IF('Your Debts'!$G$12=0,0,INDEX('Your Debts'!$C$5:$C$12,'Your Debts'!$G$12)/12)),2) | Z101: =MIN((AA100)+Y101,MAX(0,$C101-(E101+H101+K101+N101+Q101+T101+W101))) | AA101: =ROUND(MAX(0,(AA100)+Y101-Z101),2) | AB101: =F101+I101+L101+O101+R101+U101+X101+AA101 | AC101: =AC100+D101+G101+J101+M101+P101+S101+V101+Y101
...

Sheet Summary
A1: Summary
A2: The two numbers that matter: when you are free, and what it cost.
A4: YOUR RESULT
A6: Method chosen | B6: ='Your Debts'!B16
A7: Total debt today | B7: ='Your Debts'!B13
A8: Monthly budget | B8: ='Your Debts'!$B$18
A9: Months to debt-free | B9: =IF(COUNTIF('Payoff Plan'!$AB$6:$AB$185,">=0.01")=180,"Not paid off in 15 yrs",COUNTIF('Payoff Plan'!$AB$6:$AB$185,">=0.01"))
A10: Years to debt-free | B10: =IF(ISNUMBER(B9),B9/12,"—")
A11: Debt-free date | B11: =IF(ISNUMBER(B9),EDATE('Your Debts'!$B$19,B9-1),"—")
A12: Total interest you will pay | B12: =INDEX('Payoff Plan'!$AC$6:$AC$185,IF(ISNUMBER(B9),B9,180))
A13: Total you will repay | B13: =B7+B12
A15: HOW TO USE THIS
A16: • Change the extra payment on Your Debts and watch the debt-free date move. That is the whole exercise.
A17: • Switch between Snowball and Avalanche to see the trade-off: Snowball clears accounts sooner and keeps you motivated; Avalanche costs less interest.
A18: • Every time a debt hits zero, its payment rolls onto the next one automatically. Do not lower your budget when that happens — that is where the speed comes from.
A19: • If the months-to-debt-free cell says not paid off, your budget is too close to the interest charge. Raise the extra payment or look at consolidating.
