Workbook

Sheet Start Here
A1: Investment Portfolio Tracker (Canada)
A2: TFSA, RRSP, FHSA and non-registered in one place, with drift against your targets.
B4: WHAT'S INSIDE
B5: • Start Here — this page.
B6: • Holdings — 60 positions with book value, market value and gain/loss.
B7: • Contributions — 300-row deposit and withdrawal register.
B8: • Dividend Log — 200-row income tracker with withholding tax.
B9: • Dashboard — totals, allocation vs target with drift, split by account, two charts.
B11: HOW TO USE IT
B12: 1. Enter your positions on the Holdings tab — units, average cost and today's price.
B13: 2. Pick the account and asset class from the drop-downs; the Dashboard groups on them.
B14: 3. Log deposits and withdrawals on Contributions so you can see real money in versus growth.
B15: 4. Record dividends on the Dividend Log — including withholding tax on US names.
B16: 5. Set your target weights on the Dashboard. The drift column tells you what to rebalance.
... B26: Questions or a problem with the file? Message me through Etsy and I will help.

Sheet Holdings
A1: Holdings
A2: One row per position. Update the price column and everything else follows.
A4: Ticker | B4: Name | C4: Account | D4: Asset class | E4: Currency | F4: Units | G4: Avg cost / unit | H4: Book value | I4: Current price | J4: Market value | K4: Gain / loss $ | L4: Gain / loss % | M4: % of portfolio
A5: VFV.TO | B5: Vanguard S&P 500 Index ETF | C5: TFSA | D5: Equity — US | E5: CAD | F5: 120 | G5: 118.4 | H5: =IF($A5="","",N(F5)*N(G5)) | I5: 141.2 | J5: =IF($A5="","",N(F5)*N(I5)) | K5: =IF($A5="","",N(J5)-N(H5)) | L5: =IF(OR($A5="",N(H5)=0),"",N(K5)/N(H5)) | M5: =IF(OR($A5="",$J$65=0),"",N(J5)/$J$65)
A6: XIC.TO | B6: iShares Core S&P/TSX Capped ETF | C6: TFSA | D6: Equity — Canada | E6: CAD | F6: 200 | G6: 34.1 | H6: =IF($A6="","",N(F6)*N(G6)) | I6: 39.85 | J6: =IF($A6="","",N(F6)*N(I6)) | K6: =IF($A6="","",N(J6)-N(H6)) | L6: =IF(OR($A6="",N(H6)=0),"",N(K6)/N(H6)) | M6: =IF(OR($A6="",$J$65=0),"",N(J6)/$J$65)
A7: XAW.TO | B7: iShares Core MSCI All Country ex-Canada | C7: RRSP | D7: Equity — Global | E7: CAD | F7: 150 | G7: 32.75 | H7: =IF($A7="","",N(F7)*N(G7)) | I7: 38.4 | J7: =IF($A7="","",N(F7)*N(I7)) | K7: =IF($A7="","",N(J7)-N(H7)) | L7: =IF(OR($A7="",N(H7)=0),"",N(K7)/N(H7)) | M7: =IF(OR($A7="",$J$65=0),"",N(J7)/$J$65)
A8: ZAG.TO | B8: BMO Aggregate Bond Index ETF | C8: RRSP | D8: Fixed income | E8: CAD | F8: 180 | G8: 15.2 | H8: =IF($A8="","",N(F8)*N(G8)) | I8: 14.6 | J8: =IF($A8="","",N(F8)*N(I8)) | K8: =IF($A8="","",N(J8)-N(H8)) | L8: =IF(OR($A8="",N(H8)=0),"",N(K8)/N(H8)) | M8: =IF(OR($A8="",$J$65=0),"",N(J8)/$J$65)
A9: CASH.TO | B9: High Interest Savings ETF | C9: Non-registered | D9: Cash & equivalents | E9: CAD | F9: 90 | G9: 50.05 | H9: =IF($A9="","",N(F9)*N(G9)) | I9: 50.12 | J9: =IF($A9="","",N(F9)*N(I9)) | K9: =IF($A9="","",N(J9)-N(H9)) | L9: =IF(OR($A9="",N(H9)=0),"",N(K9)/N(H9)) | M9: =IF(OR($A9="",$J$65=0),"",N(J9)/$J$65)
A10: RY.TO | B10: Royal Bank of Canada | C10: Non-registered | D10: Equity — Canada | E10: CAD | F10: 40 | G10: 121.5 | H10: =IF($A10="","",N(F10)*N(G10)) | I10: 168.3 | J10: =IF($A10="","",N(F10)*N(I10)) | K10: =IF($A10="","",N(J10)-N(H10)) | L10: =IF(OR($A10="",N(H10)=0),"",N(K10)/N(H10)) | M10: =IF(OR($A10="",$J$65=0),"",N(J10)/$J$65)
H11: =IF($A11="","",N(F11)*N(G11)) | J11: =IF($A11="","",N(F11)*N(I11)) | K11: =IF($A11="","",N(J11)-N(H11)) | L11: =IF(OR($A11="",N(H11)=0),"",N(K11)/N(H11)) | M11: =IF(OR($A11="",$J$65=0),"",N(J11)/$J$65)
H12: =IF($A12="","",N(F12)*N(G12)) | J12: =IF($A12="","",N(F12)*N(I12)) | K12: =IF($A12="","",N(J12)-N(H12)) | L12: =IF(OR($A12="",N(H12)=0),"",N(K12)/N(H12)) | M12: =IF(OR($A12="",$J$65=0),"",N(J12)/$J$65)
H13: =IF($A13="","",N(F13)*N(G13)) | J13: =IF($A13="","",N(F13)*N(I13)) | K13: =IF($A13="","",N(J13)-N(H13)) | L13: =IF(OR($A13="",N(H13)=0),"",N(K13)/N(H13)) | M13: =IF(OR($A13="",$J$65=0),"",N(J13)/$J$65)
H14: =IF($A14="","",N(F14)*N(G14)) | J14: =IF($A14="","",N(F14)*N(I14)) | K14: =IF($A14="","",N(J14)-N(H14)) | L14: =IF(OR($A14="",N(H14)=0),"",N(K14)/N(H14)) | M14: =IF(OR($A14="",$J$65=0),"",N(J14)/$J$65)
H15: =IF($A15="","",N(F15)*N(G15)) | J15: =IF($A15="","",N(F15)*N(I15)) | K15: =IF($A15="","",N(J15)-N(H15)) | L15: =IF(OR($A15="",N(H15)=0),"",N(K15)/N(H15)) | M15: =IF(OR($A15="",$J$65=0),"",N(J15)/$J$65)
H16: =IF($A16="","",N(F16)*N(G16)) | J16: =IF($A16="","",N(F16)*N(I16)) | K16: =IF($A16="","",N(J16)-N(H16)) | L16: =IF(OR($A16="",N(H16)=0),"",N(K16)/N(H16)) | M16: =IF(OR($A16="",$J$65=0),"",N(J16)/$J$65)
H17: =IF($A17="","",N(F17)*N(G17)) | J17: =IF($A17="","",N(F17)*N(I17)) | K17: =IF($A17="","",N(J17)-N(H17)) | L17: =IF(OR($A17="",N(H17)=0),"",N(K17)/N(H17)) | M17: =IF(OR($A17="",$J$65=0),"",N(J17)/$J$65)
H18: =IF($A18="","",N(F18)*N(G18)) | J18: =IF($A18="","",N(F18)*N(I18)) | K18: =IF($A18="","",N(J18)-N(H18)) | L18: =IF(OR($A18="",N(H18)=0),"",N(K18)/N(H18)) | M18: =IF(OR($A18="",$J$65=0),"",N(J18)/$J$65)
H19: =IF($A19="","",N(F19)*N(G19)) | J19: =IF($A19="","",N(F19)*N(I19)) | K19: =IF($A19="","",N(J19)-N(H19)) | L19: =IF(OR($A19="",N(H19)=0),"",N(K19)/N(H19)) | M19: =IF(OR($A19="",$J$65=0),"",N(J19)/$J$65)
H20: =IF($A20="","",N(F20)*N(G20)) | J20: =IF($A20="","",N(F20)*N(I20)) | K20: =IF($A20="","",N(J20)-N(H20)) | L20: =IF(OR($A20="",N(H20)=0),"",N(K20)/N(H20)) | M20: =IF(OR($A20="",$J$65=0),"",N(J20)/$J$65)
H21: =IF($A21="","",N(F21)*N(G21)) | J21: =IF($A21="","",N(F21)*N(I21)) | K21: =IF($A21="","",N(J21)-N(H21)) | L21: =IF(OR($A21="",N(H21)=0),"",N(K21)/N(H21)) | M21: =IF(OR($A21="",$J$65=0),"",N(J21)/$J$65)
H22: =IF($A22="","",N(F22)*N(G22)) | J22: =IF($A22="","",N(F22)*N(I22)) | K22: =IF($A22="","",N(J22)-N(H22)) | L22: =IF(OR($A22="",N(H22)=0),"",N(K22)/N(H22)) | M22: =IF(OR($A22="",$J$65=0),"",N(J22)/$J$65)
... H64: =IF($A64="","",N(F64)*N(G64)) | J64: =IF($A64="","",N(F64)*N(I64)) | K64: =IF($A64="","",N(J64)-N(H64)) | L64: =IF(OR($A64="",N(H64)=0),"",N(K64)/N(H64)) | M64: =IF(OR($A64="",$J$65=0),"",N(J64)/$J$65)
A65: TOTAL | H65: =SUM(H5:H64) | J65: =SUM(J5:J64) | K65: =SUM(K5:K64) | L65: =IF(H65=0,"",K65/H65)

Sheet Contributions
A1: Contributions
A2: Every deposit and withdrawal, by account. Needed for real return.
A4: Date | B4: Account | C4: Type | D4: Amount | E4: Note

Sheet Dividend Log
A1: Dividend Log
A2: Track income received so you can see your real yield.
A4: Date | B4: Ticker | C4: Account | D4: Amount | E4: Withholding tax | F4: Net received
F5: =IF($A5="","",N(D5)-N(E5))
F6: =IF($A6="","",N(D6)-N(E6))
F7: =IF($A7="","",N(D7)-N(E7))
F8: =IF($A8="","",N(D8)-N(E8))
F9: =IF($A9="","",N(D9)-N(E9))
F10: =IF($A10="","",N(D10)-N(E10))
F11: =IF($A11="","",N(D11)-N(E11))
F12: =IF($A12="","",N(D12)-N(E12))
F13: =IF($A13="","",N(D13)-N(E13))
F14: =IF($A14="","",N(D14)-N(E14))
F15: =IF($A15="","",N(D15)-N(E15))
F16: =IF($A16="","",N(D16)-N(E16))
... F204: =IF($A204="","",N(D204)-N(E204))
A206: TOTAL | D206: =SUM(D5:D205) | E206: =SUM(E5:E205) | F206: =SUM(F5:F205)

Sheet Dashboard
A1: Dashboard
A2: Where you stand, what it cost, and how it is split.
A4: PORTFOLIO AT A GLANCE
A6: Market value | B6: =Holdings!J65
A7: Book value (what you paid) | B7: =Holdings!H65
A8: Unrealised gain / loss | B8: =Holdings!K65
A9: Return on book | B9: =IF(B7=0,"—",B8/B7)
A10: Dividends received (net) | B10: ='Dividend Log'!F206
A11: Net contributions | B11: =SUMIF(Contributions!$C$5:$C$304,"Contribution",Contributions!$D$5:$D$304)-SUMIF(Contributions!$C$5:$C$304,"Withdrawal",Contributions!$D$5:$D$304)
A12: Total gain incl. dividends | B12: =B8+B10
A13: Number of positions | B13: =COUNTA(Holdings!A5:A64)
A15: ASSET ALLOCATION
A16: Asset class | B16: Market value | C16: % of total | D16: Target % | E16: Drift
A17: Equity — Canada | B17: =SUMIF(Holdings!$D$5:$D$64,$A17,Holdings!$J$5:$J$64) | C17: =IF($B$6=0,0,B17/$B$6) | D17: 0.2 | E17: =C17-D17
A18: Equity — US | B18: =SUMIF(Holdings!$D$5:$D$64,$A18,Holdings!$J$5:$J$64) | C18: =IF($B$6=0,0,B18/$B$6) | D18: 0.3 | E18: =C18-D18
A19: Equity — Global | B19: =SUMIF(Holdings!$D$5:$D$64,$A19,Holdings!$J$5:$J$64) | C19: =IF($B$6=0,0,B19/$B$6) | D19: 0.2 | E19: =C19-D19
A20: Fixed income | B20: =SUMIF(Holdings!$D$5:$D$64,$A20,Holdings!$J$5:$J$64) | C20: =IF($B$6=0,0,B20/$B$6) | D20: 0.2 | E20: =C20-D20
A21: Cash & equivalents | B21: =SUMIF(Holdings!$D$5:$D$64,$A21,Holdings!$J$5:$J$64) | C21: =IF($B$6=0,0,B21/$B$6) | D21: 0.05 | E21: =C21-D21
A22: Real assets | B22: =SUMIF(Holdings!$D$5:$D$64,$A22,Holdings!$J$5:$J$64) | C22: =IF($B$6=0,0,B22/$B$6) | D22: 0.03 | E22: =C22-D22
A23: Crypto | B23: =SUMIF(Holdings!$D$5:$D$64,$A23,Holdings!$J$5:$J$64) | C23: =IF($B$6=0,0,B23/$B$6) | D23: 0.02 | E23: =C23-D23
A24: Other | B24: =SUMIF(Holdings!$D$5:$D$64,$A24,Holdings!$J$5:$J$64) | C24: =IF($B$6=0,0,B24/$B$6) | D24: 0 | E24: =C24-D24
A25: TOTAL | B25: =SUM(B17:B24) | C25: =SUM(C17:C24) | D25: =SUM(D17:D24)
A27: BY ACCOUNT
A28: Account | B28: Market value | C28: % of total
A29: TFSA | B29: =SUMIF(Holdings!$C$5:$C$64,$A29,Holdings!$J$5:$J$64) | C29: =IF($B$6=0,0,B29/$B$6)
A30: RRSP | B30: =SUMIF(Holdings!$C$5:$C$64,$A30,Holdings!$J$5:$J$64) | C30: =IF($B$6=0,0,B30/$B$6)
A31: FHSA | B31: =SUMIF(Holdings!$C$5:$C$64,$A31,Holdings!$J$5:$J$64) | C31: =IF($B$6=0,0,B31/$B$6)
A32: RESP | B32: =SUMIF(Holdings!$C$5:$C$64,$A32,Holdings!$J$5:$J$64) | C32: =IF($B$6=0,0,B32/$B$6)
A33: Non-registered | B33: =SUMIF(Holdings!$C$5:$C$64,$A33,Holdings!$J$5:$J$64) | C33: =IF($B$6=0,0,B33/$B$6)
A34: LIRA | B34: =SUMIF(Holdings!$C$5:$C$64,$A34,Holdings!$J$5:$J$64) | C34: =IF($B$6=0,0,B34/$B$6)
A35: Other | B35: =SUMIF(Holdings!$C$5:$C$64,$A35,Holdings!$J$5:$J$64) | C35: =IF($B$6=0,0,B35/$B$6)
