Workbook

Sheet Start Here
A1: Small Business 12-Month Cash Flow Forecast
A2: Profit is an opinion; cash is a fact. This shows you the fact, month by month.
B4: WHAT'S INSIDE
B5: • Start Here — this page.
B6: • Assumptions — one screen that drives the whole model, with built-in sanity checks.
B7: • Revenue — four streams with growth and unit economics.
B8: • Costs — COGS driven off revenue, 14 overhead lines, capital and financing.
B9: • Cash Flow — timing-aware collections, supplier terms, HST remitted net of input tax credits, tax instalments.
B10: • Dashboard — margins, break-even revenue, lowest cash point and two charts.
B12: HOW TO USE IT
B13: 1. Set your start month, opening cash and month-1 revenue on the Assumptions tab.
B14: 2. Set your collection terms, and enter anything customers already owe you as opening receivables.
B15: 3. Adjust the revenue streams and their growth on the Revenue tab.
B16: 4. Type your real overheads on the Costs tab. Add capital spend and loan movements at the bottom.
... B27: Questions or a problem with the file? Message me through Etsy and I will help.

Sheet Assumptions
A1: Assumptions
A2: Change these and the whole forecast moves. Nothing else needs touching.
A4: BUSINESS SETUP
A5: Forecast start month | B5: 2026-01-01
A6: Business name | B6: My Business Inc.
A7: Opening cash balance | B7: 25000
A8: Sales collected in the month of sale | B8: 0.6
A9: Sales collected 30 days later | B9: 0.35
A10: Sales never collected (bad debt) | B10: 0.05
A11: Supplier terms — paid in month | B11: 0.7
A12: Supplier terms — paid 30 days later | B12: 0.3
A13: Cost of goods sold as % of revenue | B13: 0.42
A14: Sales tax collected on revenue (HST) | B14: 0.13
A15: Sales tax remitted quarterly? | B15: Yes
A16: Corporate tax rate on profit | B16: 0.12
A17: Monthly revenue growth | B17: 0.03
A18: Month 1 revenue | B18: 48000
A19: Opening accounts receivable (collected in month 1) | B19: 0
A20: Share of costs that carry HST (for input tax credits) | B20: 0.75
A21: Collection percentages should add to 100%. Supplier terms should add to 100%.
B22: =IF(ROUND(B8+B9+B10,4)=1,"Collections OK","⚠ Collections do not add to 100%")
B23: =IF(ROUND(B11+B12,4)=1,"Supplier terms OK","⚠ Supplier terms do not add to 100%")
A24: Opening accounts receivable is what customers already owe you on day one. It lands in month 1 collections.
A25: Input tax credits: HST you pay on purchases is claimed back, so the model remits sales tax NET, not gross.

Sheet Revenue
A1: Revenue
A2: Build the top line by stream. Growth applies to the base case.
A4: Revenue stream | B4: =TEXT(EDATE(Assumptions!$B$5,0),"mmm yy") | C4: =TEXT(EDATE(Assumptions!$B$5,1),"mmm yy") | D4: =TEXT(EDATE(Assumptions!$B$5,2),"mmm yy") | E4: =TEXT(EDATE(Assumptions!$B$5,3),"mmm yy") | F4: =TEXT(EDATE(Assumptions!$B$5,4),"mmm yy") | G4: =TEXT(EDATE(Assumptions!$B$5,5),"mmm yy") | H4: =TEXT(EDATE(Assumptions!$B$5,6),"mmm yy") | I4: =TEXT(EDATE(Assumptions!$B$5,7),"mmm yy") | J4: =TEXT(EDATE(Assumptions!$B$5,8),"mmm yy") | K4: =TEXT(EDATE(Assumptions!$B$5,9),"mmm yy") | L4: =TEXT(EDATE(Assumptions!$B$5,10),"mmm yy") | M4: =TEXT(EDATE(Assumptions!$B$5,11),"mmm yy") | N4: Total
A5: Core product / service | B5: =Assumptions!$B$18*0.62 | C5: =B5*(1+Assumptions!$B$17) | D5: =C5*(1+Assumptions!$B$17) | E5: =D5*(1+Assumptions!$B$17) | F5: =E5*(1+Assumptions!$B$17) | G5: =F5*(1+Assumptions!$B$17) | H5: =G5*(1+Assumptions!$B$17) | I5: =H5*(1+Assumptions!$B$17) | J5: =I5*(1+Assumptions!$B$17) | ... M5: =L5*(1+Assumptions!$B$17) | N5: =SUM(B5:M5)
A6: Recurring / retainer | B6: =Assumptions!$B$18*0.22 | C6: =B6*(1+Assumptions!$B$17) | D6: =C6*(1+Assumptions!$B$17) | E6: =D6*(1+Assumptions!$B$17) | F6: =E6*(1+Assumptions!$B$17) | G6: =F6*(1+Assumptions!$B$17) | H6: =G6*(1+Assumptions!$B$17) | I6: =H6*(1+Assumptions!$B$17) | J6: =I6*(1+Assumptions!$B$17) | ... M6: =L6*(1+Assumptions!$B$17) | N6: =SUM(B6:M6)
A7: Add-ons & upsells | B7: =Assumptions!$B$18*0.11 | C7: =B7*(1+Assumptions!$B$17) | D7: =C7*(1+Assumptions!$B$17) | E7: =D7*(1+Assumptions!$B$17) | F7: =E7*(1+Assumptions!$B$17) | G7: =F7*(1+Assumptions!$B$17) | H7: =G7*(1+Assumptions!$B$17) | I7: =H7*(1+Assumptions!$B$17) | J7: =I7*(1+Assumptions!$B$17) | ... M7: =L7*(1+Assumptions!$B$17) | N7: =SUM(B7:M7)
A8: Other income | B8: =Assumptions!$B$18*0.05 | C8: =B8*(1+Assumptions!$B$17) | D8: =C8*(1+Assumptions!$B$17) | E8: =D8*(1+Assumptions!$B$17) | F8: =E8*(1+Assumptions!$B$17) | G8: =F8*(1+Assumptions!$B$17) | H8: =G8*(1+Assumptions!$B$17) | I8: =H8*(1+Assumptions!$B$17) | J8: =I8*(1+Assumptions!$B$17) | ... M8: =L8*(1+Assumptions!$B$17) | N8: =SUM(B8:M8)
A9: TOTAL REVENUE | B9: =SUM(B5:B8) | C9: =SUM(C5:C8) | D9: =SUM(D5:D8) | E9: =SUM(E5:E8) | F9: =SUM(F5:F8) | G9: =SUM(G5:G8) | H9: =SUM(H5:H8) | I9: =SUM(I5:I8) | ... N9: =SUM(N5:N8)
A11: UNIT ECONOMICS (OPTIONAL)
A12: Customers served | B12: 40 | C12: 40 | D12: 40 | E12: 40 | F12: 40 | G12: 40 | H12: 40 | I12: 40 | J12: 40 | K12: 40 | L12: 40 | M12: 40
A13: Average revenue per customer | B13: =IF(B12=0,0,B9/B12) | C13: =IF(C12=0,0,C9/C12) | D13: =IF(D12=0,0,D9/D12) | E13: =IF(E12=0,0,E9/E12) | F13: =IF(F12=0,0,F9/F12) | G13: =IF(G12=0,0,G9/G12) | H13: =IF(H12=0,0,H9/H12) | I13: =IF(I12=0,0,I9/I12) | ... M13: =IF(M12=0,0,M9/M12)

Sheet Costs
A1: Costs
A2: Direct costs move with revenue. Overheads are what you type.
A4: Cost line | B4: =TEXT(EDATE(Assumptions!$B$5,0),"mmm yy") | C4: =TEXT(EDATE(Assumptions!$B$5,1),"mmm yy") | D4: =TEXT(EDATE(Assumptions!$B$5,2),"mmm yy") | E4: =TEXT(EDATE(Assumptions!$B$5,3),"mmm yy") | F4: =TEXT(EDATE(Assumptions!$B$5,4),"mmm yy") | G4: =TEXT(EDATE(Assumptions!$B$5,5),"mmm yy") | H4: =TEXT(EDATE(Assumptions!$B$5,6),"mmm yy") | I4: =TEXT(EDATE(Assumptions!$B$5,7),"mmm yy") | J4: =TEXT(EDATE(Assumptions!$B$5,8),"mmm yy") | K4: =TEXT(EDATE(Assumptions!$B$5,9),"mmm yy") | L4: =TEXT(EDATE(Assumptions!$B$5,10),"mmm yy") | M4: =TEXT(EDATE(Assumptions!$B$5,11),"mmm yy") | N4: Total
A5: Cost of goods sold | B5: =Revenue!B9*Assumptions!$B$13 | C5: =Revenue!C9*Assumptions!$B$13 | D5: =Revenue!D9*Assumptions!$B$13 | E5: =Revenue!E9*Assumptions!$B$13 | F5: =Revenue!F9*Assumptions!$B$13 | G5: =Revenue!G9*Assumptions!$B$13 | H5: =Revenue!H9*Assumptions!$B$13 | I5: =Revenue!I9*Assumptions!$B$13 | ... M5: =Revenue!M9*Assumptions!$B$13 | N5: =SUM(B5:M5)
A7: OPERATING EXPENSES
A8: Salaries & wages | B8: 14000 | C8: 14000 | D8: 14000 | E8: 14000 | F8: 14000 | G8: 14000 | H8: 14000 | I8: 14000 | J8: 14000 | K8: 14000 | L8: 14000 | M8: 14000 | N8: =SUM(B8:M8)
A9: Payroll taxes & benefits | B9: 2100 | C9: 2100 | D9: 2100 | E9: 2100 | F9: 2100 | G9: 2100 | H9: 2100 | I9: 2100 | J9: 2100 | K9: 2100 | L9: 2100 | M9: 2100 | N9: =SUM(B9:M9)
A10: Rent | B10: 3200 | C10: 3200 | D10: 3200 | E10: 3200 | F10: 3200 | G10: 3200 | H10: 3200 | I10: 3200 | J10: 3200 | K10: 3200 | L10: 3200 | M10: 3200 | N10: =SUM(B10:M10)
A11: Utilities | B11: 480 | C11: 480 | D11: 480 | E11: 480 | F11: 480 | G11: 480 | H11: 480 | I11: 480 | J11: 480 | K11: 480 | L11: 480 | M11: 480 | N11: =SUM(B11:M11)
A12: Insurance | B12: 390 | C12: 390 | D12: 390 | E12: 390 | F12: 390 | G12: 390 | H12: 390 | I12: 390 | J12: 390 | K12: 390 | L12: 390 | M12: 390 | N12: =SUM(B12:M12)
A13: Software & subscriptions | B13: 620 | C13: 620 | D13: 620 | E13: 620 | F13: 620 | G13: 620 | H13: 620 | I13: 620 | J13: 620 | K13: 620 | L13: 620 | M13: 620 | N13: =SUM(B13:M13)
A14: Marketing & advertising | B14: 2400 | C14: 2400 | D14: 2400 | E14: 2400 | F14: 2400 | G14: 2400 | H14: 2400 | I14: 2400 | J14: 2400 | K14: 2400 | L14: 2400 | M14: 2400 | N14: =SUM(B14:M14)
A15: Professional fees (legal, accounting) | B15: 750 | C15: 750 | D15: 750 | E15: 750 | F15: 750 | G15: 750 | H15: 750 | I15: 750 | J15: 750 | K15: 750 | L15: 750 | M15: 750 | N15: =SUM(B15:M15)
A16: Bank & merchant fees | B16: 540 | C16: 540 | D16: 540 | E16: 540 | F16: 540 | G16: 540 | H16: 540 | I16: 540 | J16: 540 | K16: 540 | L16: 540 | M16: 540 | N16: =SUM(B16:M16)
A17: Repairs & maintenance | B17: 300 | C17: 300 | D17: 300 | E17: 300 | F17: 300 | G17: 300 | H17: 300 | I17: 300 | J17: 300 | K17: 300 | L17: 300 | M17: 300 | N17: =SUM(B17:M17)
A18: Travel & vehicle | B18: 650 | C18: 650 | D18: 650 | E18: 650 | F18: 650 | G18: 650 | H18: 650 | I18: 650 | J18: 650 | K18: 650 | L18: 650 | M18: 650 | N18: =SUM(B18:M18)
A19: Office supplies | B19: 220 | C19: 220 | D19: 220 | E19: 220 | F19: 220 | G19: 220 | H19: 220 | I19: 220 | J19: 220 | K19: 220 | L19: 220 | M19: 220 | N19: =SUM(B19:M19)
... A21: Other overhead | B21: 400 | C21: 400 | D21: 400 | E21: 400 | F21: 400 | G21: 400 | H21: 400 | I21: 400 | J21: 400 | K21: 400 | L21: 400 | M21: 400 | N21: =SUM(B21:M21)
A22: TOTAL OPERATING EXPENSES | B22: =SUM(B8:B21) | C22: =SUM(C8:C21) | D22: =SUM(D8:D21) | E22: =SUM(E8:E21) | F22: =SUM(F8:F21) | G22: =SUM(G8:G21) | H22: =SUM(H8:H21) | I22: =SUM(I8:I21) | ... N22: =SUM(N8:N21)
A24: CAPITAL & FINANCING
A25: Equipment purchases | B25: 0 | C25: 0 | D25: 0 | E25: 0 | F25: 0 | G25: 0 | H25: 0 | I25: 0 | J25: 0 | K25: 0 | L25: 0 | M25: 0 | N25: =SUM(B25:M25)
A26: Loan drawdown (money in) | B26: 0 | C26: 0 | D26: 0 | E26: 0 | F26: 0 | G26: 0 | H26: 0 | I26: 0 | J26: 0 | K26: 0 | L26: 0 | M26: 0 | N26: =SUM(B26:M26)
A27: Loan repayment (money out) | B27: 0 | C27: 0 | D27: 0 | E27: 0 | F27: 0 | G27: 0 | H27: 0 | I27: 0 | J27: 0 | K27: 0 | L27: 0 | M27: 0 | N27: =SUM(B27:M27)
A28: Owner draw / dividends | B28: 0 | C28: 0 | D28: 0 | E28: 0 | F28: 0 | G28: 0 | H28: 0 | I28: 0 | J28: 0 | K28: 0 | L28: 0 | M28: 0 | N28: =SUM(B28:M28)
A29: Owner injection (money in) | B29: 0 | C29: 0 | D29: 0 | E29: 0 | F29: 0 | G29: 0 | H29: 0 | I29: 0 | J29: 0 | K29: 0 | L29: 0 | M29: 0 | N29: =SUM(B29:M29)

Sheet Cash Flow
A1: Cash Flow
A2: The tab that matters: when cash actually lands and leaves.
A4: Cash movement | B4: =TEXT(EDATE(Assumptions!$B$5,0),"mmm yy") | C4: =TEXT(EDATE(Assumptions!$B$5,1),"mmm yy") | D4: =TEXT(EDATE(Assumptions!$B$5,2),"mmm yy") | E4: =TEXT(EDATE(Assumptions!$B$5,3),"mmm yy") | F4: =TEXT(EDATE(Assumptions!$B$5,4),"mmm yy") | G4: =TEXT(EDATE(Assumptions!$B$5,5),"mmm yy") | H4: =TEXT(EDATE(Assumptions!$B$5,6),"mmm yy") | I4: =TEXT(EDATE(Assumptions!$B$5,7),"mmm yy") | J4: =TEXT(EDATE(Assumptions!$B$5,8),"mmm yy") | K4: =TEXT(EDATE(Assumptions!$B$5,9),"mmm yy") | L4: =TEXT(EDATE(Assumptions!$B$5,10),"mmm yy") | M4: =TEXT(EDATE(Assumptions!$B$5,11),"mmm yy") | N4: Total
A5: Opening cash | B5: =Assumptions!$B$7 | C5: =B23 | D5: =C23 | E5: =D23 | F5: =E23 | G5: =F23 | H5: =G23 | I5: =H23 | J5: =I23 | ... M5: =L23
A7: CASH IN
A8: Collections from sales | B8: =Revenue!B9*Assumptions!$B$8+Assumptions!$B$19 | C8: =Revenue!C9*Assumptions!$B$8+Revenue!B9*Assumptions!$B$9 | D8: =Revenue!D9*Assumptions!$B$8+Revenue!C9*Assumptions!$B$9 | E8: =Revenue!E9*Assumptions!$B$8+Revenue!D9*Assumptions!$B$9 | F8: =Revenue!F9*Assumptions!$B$8+Revenue!E9*Assumptions!$B$9 | G8: =Revenue!G9*Assumptions!$B$8+Revenue!F9*Assumptions!$B$9 | H8: =Revenue!H9*Assumptions!$B$8+Revenue!G9*Assumptions!$B$9 | I8: =Revenue!I9*Assumptions!$B$8+Revenue!H9*Assumptions!$B$9 | J8: =Revenue!J9*Assumptions!$B$8+Revenue!I9*Assumptions!$B$9 | ... M8: =Revenue!M9*Assumptions!$B$8+Revenue!L9*Assumptions!$B$9 | N8: =SUM(B8:M8)
A9: Sales tax collected | B9: =Revenue!B9*Assumptions!$B$14 | C9: =Revenue!C9*Assumptions!$B$14 | D9: =Revenue!D9*Assumptions!$B$14 | E9: =Revenue!E9*Assumptions!$B$14 | F9: =Revenue!F9*Assumptions!$B$14 | G9: =Revenue!G9*Assumptions!$B$14 | H9: =Revenue!H9*Assumptions!$B$14 | I9: =Revenue!I9*Assumptions!$B$14 | ... M9: =Revenue!M9*Assumptions!$B$14 | N9: =SUM(B9:M9)
A10: Loan drawdown & owner injections | B10: =Costs!B26+Costs!B29 | C10: =Costs!C26+Costs!C29 | D10: =Costs!D26+Costs!D29 | E10: =Costs!E26+Costs!E29 | F10: =Costs!F26+Costs!F29 | G10: =Costs!G26+Costs!G29 | H10: =Costs!H26+Costs!H29 | I10: =Costs!I26+Costs!I29 | ... M10: =Costs!M26+Costs!M29 | N10: =SUM(B10:M10)
A11: TOTAL CASH IN | B11: =B8+B9+B10 | C11: =C8+C9+C10 | D11: =D8+D9+D10 | E11: =E8+E9+E10 | F11: =F8+F9+F10 | G11: =G8+G9+G10 | H11: =H8+H9+H10 | I11: =I8+I9+I10 | ... M11: =M8+M9+M10 | N11: =SUM(B11:M11)
A13: CASH OUT
A14: Payments to suppliers (COGS) | B14: =Costs!B5*Assumptions!$B$11 | C14: =Costs!C5*Assumptions!$B$11+Costs!B5*Assumptions!$B$12 | D14: =Costs!D5*Assumptions!$B$11+Costs!C5*Assumptions!$B$12 | E14: =Costs!E5*Assumptions!$B$11+Costs!D5*Assumptions!$B$12 | F14: =Costs!F5*Assumptions!$B$11+Costs!E5*Assumptions!$B$12 | G14: =Costs!G5*Assumptions!$B$11+Costs!F5*Assumptions!$B$12 | H14: =Costs!H5*Assumptions!$B$11+Costs!G5*Assumptions!$B$12 | I14: =Costs!I5*Assumptions!$B$11+Costs!H5*Assumptions!$B$12 | J14: =Costs!J5*Assumptions!$B$11+Costs!I5*Assumptions!$B$12 | ... M14: =Costs!M5*Assumptions!$B$11+Costs!L5*Assumptions!$B$12 | N14: =SUM(B14:M14)
A15: Operating expenses | B15: =Costs!B22 | C15: =Costs!C22 | D15: =Costs!D22 | E15: =Costs!E22 | F15: =Costs!F22 | G15: =Costs!G22 | H15: =Costs!H22 | I15: =Costs!I22 | ... M15: =Costs!M22 | N15: =SUM(B15:M15)
A16: Sales tax paid on purchases | B16: =(Costs!B5+Costs!B22+Costs!B25)*Assumptions!$B$20*Assumptions!$B$14 | C16: =(Costs!C5+Costs!C22+Costs!C25)*Assumptions!$B$20*Assumptions!$B$14 | D16: =(Costs!D5+Costs!D22+Costs!D25)*Assumptions!$B$20*Assumptions!$B$14 | E16: =(Costs!E5+Costs!E22+Costs!E25)*Assumptions!$B$20*Assumptions!$B$14 | F16: =(Costs!F5+Costs!F22+Costs!F25)*Assumptions!$B$20*Assumptions!$B$14 | G16: =(Costs!G5+Costs!G22+Costs!G25)*Assumptions!$B$20*Assumptions!$B$14 | H16: =(Costs!H5+Costs!H22+Costs!H25)*Assumptions!$B$20*Assumptions!$B$14 | I16: =(Costs!I5+Costs!I22+Costs!I25)*Assumptions!$B$20*Assumptions!$B$14 | ... M16: =(Costs!M5+Costs!M22+Costs!M25)*Assumptions!$B$20*Assumptions!$B$14 | N16: =SUM(B16:M16)
A17: Sales tax remitted (net of input tax credits) | B17: =IF(Assumptions!$B$14=0,0,IF(Assumptions!$B$15="Yes",IF(MOD(1,3)=0,SUM(B9:B9)-SUM(B16:B16),0),B9-B16)) | C17: =IF(Assumptions!$B$14=0,0,IF(Assumptions!$B$15="Yes",IF(MOD(2,3)=0,SUM(B9:C9)-SUM(B16:C16),0),C9-C16)) | D17: =IF(Assumptions!$B$14=0,0,IF(Assumptions!$B$15="Yes",IF(MOD(3,3)=0,SUM(B9:D9)-SUM(B16:D16),0),D9-D16)) | E17: =IF(Assumptions!$B$14=0,0,IF(Assumptions!$B$15="Yes",IF(MOD(4,3)=0,SUM(C9:E9)-SUM(C16:E16),0),E9-E16)) | F17: =IF(Assumptions!$B$14=0,0,IF(Assumptions!$B$15="Yes",IF(MOD(5,3)=0,SUM(D9:F9)-SUM(D16:F16),0),F9-F16)) | G17: =IF(Assumptions!$B$14=0,0,IF(Assumptions!$B$15="Yes",IF(MOD(6,3)=0,SUM(E9:G9)-SUM(E16:G16),0),G9-G16)) | H17: =IF(Assumptions!$B$14=0,0,IF(Assumptions!$B$15="Yes",IF(MOD(7,3)=0,SUM(F9:H9)-SUM(F16:H16),0),H9-H16)) | I17: =IF(Assumptions!$B$14=0,0,IF(Assumptions!$B$15="Yes",IF(MOD(8,3)=0,SUM(G9:I9)-SUM(G16:I16),0),I9-I16)) | J17: =IF(Assumptions!$B$14=0,0,IF(Assumptions!$B$15="Yes",IF(MOD(9,3)=0,SUM(H9:J9)-SUM(H16:J16),0),J9-J16)) | K17: =IF(Assumptions!$B$14=0,0,IF(Assumptions!$B$15="Yes",IF(MOD(10,3)=0,SUM(I9:K9)-SUM(I16:K16),0),K9-K16)) | L17: =IF(Assumptions!$B$14=0,0,IF(Assumptions!$B$15="Yes",IF(MOD(11,3)=0,SUM(J9:L9)-SUM(J16:L16),0),L9-L16)) | M17: =IF(Assumptions!$B$14=0,0,IF(Assumptions!$B$15="Yes",IF(MOD(12,3)=0,SUM(K9:M9)-SUM(K16:M16),0),M9-M16)) | N17: =SUM(B17:M17)
A18: Equipment, loan repayments & draws | B18: =Costs!B25+Costs!B27+Costs!B28 | C18: =Costs!C25+Costs!C27+Costs!C28 | D18: =Costs!D25+Costs!D27+Costs!D28 | E18: =Costs!E25+Costs!E27+Costs!E28 | F18: =Costs!F25+Costs!F27+Costs!F28 | G18: =Costs!G25+Costs!G27+Costs!G28 | H18: =Costs!H25+Costs!H27+Costs!H28 | I18: =Costs!I25+Costs!I27+Costs!I28 | ... M18: =Costs!M25+Costs!M27+Costs!M28 | N18: =SUM(B18:M18)
A19: Income tax instalment | B19: =MAX(0,(Revenue!B9-Costs!B5-Costs!B22))*Assumptions!$B$16 | C19: =MAX(0,(Revenue!C9-Costs!C5-Costs!C22))*Assumptions!$B$16 | D19: =MAX(0,(Revenue!D9-Costs!D5-Costs!D22))*Assumptions!$B$16 | E19: =MAX(0,(Revenue!E9-Costs!E5-Costs!E22))*Assumptions!$B$16 | F19: =MAX(0,(Revenue!F9-Costs!F5-Costs!F22))*Assumptions!$B$16 | G19: =MAX(0,(Revenue!G9-Costs!G5-Costs!G22))*Assumptions!$B$16 | H19: =MAX(0,(Revenue!H9-Costs!H5-Costs!H22))*Assumptions!$B$16 | I19: =MAX(0,(Revenue!I9-Costs!I5-Costs!I22))*Assumptions!$B$16 | ... M19: =MAX(0,(Revenue!M9-Costs!M5-Costs!M22))*Assumptions!$B$16 | N19: =SUM(B19:M19)
A20: TOTAL CASH OUT | B20: =B14+B15+B16+B17+B18+B19 | C20: =C14+C15+C16+C17+C18+C19 | D20: =D14+D15+D16+D17+D18+D19 | E20: =E14+E15+E16+E17+E18+E19 | F20: =F14+F15+F16+F17+F18+F19 | G20: =G14+G15+G16+G17+G18+G19 | H20: =H14+H15+H16+H17+H18+H19 | I20: =I14+I15+I16+I17+I18+I19 | ... M20: =M14+M15+M16+M17+M18+M19 | N20: =SUM(B20:M20)
A22: NET CASH MOVEMENT | B22: =B11-B20 | C22: =C11-C20 | D22: =D11-D20 | E22: =E11-E20 | F22: =F11-F20 | G22: =G11-G20 | H22: =H11-H20 | I22: =I11-I20 | ... M22: =M11-M20 | N22: =SUM(B22:M22)
A23: CLOSING CASH | B23: =B5+B22 | C23: =C5+C22 | D23: =D5+D22 | E23: =E5+E22 | F23: =F5+F22 | G23: =G5+G22 | H23: =H5+H22 | I23: =I5+I22 | ... M23: =M5+M22 | N23: =SUM(B23:M23)
A25: Cash warning | B25: =IF(B23<0,"⚠ SHORT","OK") | C25: =IF(C23<0,"⚠ SHORT","OK") | D25: =IF(D23<0,"⚠ SHORT","OK") | E25: =IF(E23<0,"⚠ SHORT","OK") | F25: =IF(F23<0,"⚠ SHORT","OK") | G25: =IF(G23<0,"⚠ SHORT","OK") | H25: =IF(H23<0,"⚠ SHORT","OK") | I25: =IF(I23<0,"⚠ SHORT","OK") | ... M25: =IF(M23<0,"⚠ SHORT","OK")

Sheet Dashboard
A1: Dashboard
A2: Twelve months on one screen.
A4: HEADLINES
A6: Total revenue | B6: =Revenue!N9
A7: Gross profit | B7: =Revenue!N9-Costs!N5
A8: Gross margin | B8: =IF(B6=0,"—",B7/B6)
A9: Operating expenses | B9: =Costs!N22
A10: Net operating profit | B10: =B7-B9
A11: Net margin | B11: =IF(B6=0,"—",B10/B6)
A12: Opening cash | B12: =Assumptions!$B$7
A13: Closing cash after 12 months | B13: ='Cash Flow'!M23
A14: Lowest cash balance in the year | B14: =MIN('Cash Flow'!B23:M23)
A15: Months with negative cash | B15: =COUNTIF('Cash Flow'!B23:M23,"<0")
A16: Monthly break-even revenue | B16: =IF(1-Assumptions!$B$13=0,"—",AVERAGE(Costs!B22:M22)/(1-Assumptions!$B$13))
