Workbook

Sheet Start Here
A1: 3-Statement Financial Model Template
A2: Income statement, balance sheet and cash flow — linked, checked, and built the way analysts build them.
B4: WHAT'S INSIDE
B5: • Start Here — this page.
B6: • Assumptions & Drivers — 12 drivers across 5 years plus an opening balance sheet with a balance check.
B7: • Income Statement — revenue to net income with margin lines.
B8: • Balance Sheet — working capital from DSO/DIO/DPO, PP&E roll-forward, retained earnings roll.
B9: • Cash Flow — indirect method, tying back to the balance sheet cash line.
B10: • Ratios & Dashboard — 13 analyst ratios, two integrity checks and a chart.
B12: HOW TO USE IT
B13: 1. Put your Year 0 actuals into the opening balance sheet block on the Assumptions tab.
B14: 2. Set the operating drivers: growth, margins, working-capital days, capex, tax and debt.
B15: 3. Read the three statements. You never type into them — they are entirely formula-driven.
B16: 4. Check the two integrity flags on Ratios & Dashboard: the balance sheet must say BALANCED, cash must say TIES.
... B27: Questions or a problem with the file? Message me through Etsy and I will help.

Sheet Assumptions
A1: Assumptions & Drivers
A2: Every yellow cell here drives all three statements.
A4: OPERATING DRIVERS
A5: Driver | B5: Year 0 (actual) | C5: Year 1 | D5: Year 2 | E5: Year 3 | F5: Year 4 | G5: Year 5
A6: Revenue growth | B6: — | C6: 0.18 | D6: 0.15 | E6: 0.12 | F6: 0.1 | G6: 0.08
A7: Gross margin | B7: 0.55 | C7: 0.56 | D7: 0.57 | E7: 0.57 | F7: 0.58 | G7: 0.58
A8: Operating expenses % of revenue | B8: 0.34 | C8: 0.34 | D8: 0.33 | E8: 0.33 | F8: 0.32 | G8: 0.32
A9: Depreciation % of opening PP&E | B9: 0.12 | C9: 0.12 | D9: 0.12 | E9: 0.12 | F9: 0.12 | G9: 0.12
A10: Capital expenditure % of revenue | B10: 0.05 | C10: 0.06 | D10: 0.05 | E10: 0.05 | F10: 0.04 | G10: 0.04
A11: Interest rate on debt | B11: 0.075 | C11: 0.075 | D11: 0.075 | E11: 0.075 | F11: 0.075 | G11: 0.075
A12: Effective tax rate | B12: 0.26 | C12: 0.26 | D12: 0.26 | E12: 0.26 | F12: 0.26 | G12: 0.26
A13: Dividend payout % of net income | B13: 0 | C13: 0 | D13: 0.1 | E13: 0.15 | F13: 0.2 | G13: 0.25
A14: Days sales outstanding (DSO) | B14: 42 | C14: 40 | D14: 38 | E14: 36 | F14: 35 | G14: 35
A15: Days inventory on hand (DIO) | B15: 58 | C15: 55 | D15: 52 | E15: 50 | F15: 48 | G15: 46
A16: Days payable outstanding (DPO) | B16: 34 | C16: 36 | D16: 38 | E16: 40 | F16: 40 | G16: 40
A17: Debt drawn / (repaid) in the year | B17: 0 | C17: 0 | D17: 0 | E17: -250000 | F17: -250000 | G17: -250000
A19: OPENING BALANCE SHEET (YEAR 0 ACTUALS)
A20: Revenue — Year 0 | B20: 4200000
A21: Cash | B21: 310000
A22: Accounts receivable | B22: 483000
A23: Inventory | B23: 300000
A24: Property, plant & equipment (net) | B24: 1450000
A25: Accounts payable | B25: 176000
A26: Long-term debt | B26: 900000
A27: Share capital | B27: 500000
A28: Retained earnings | B28: 967000
B30: =IF(ROUND(B21+B22+B23+B24-B25-B26-B27-B28,2)=0,"Opening balance sheet balances ✓","⚠ Opening balance sheet is out by "&TEXT(B21+B22+B23+B24-B25-B26-B27-B28,"$#,##0"))

Sheet Income Statement
A1: Income Statement
A2: Driven entirely from the Assumptions tab.
A4: Line item | B4: Year 0 (actual) | C4: Year 1 | D4: Year 2 | E4: Year 3 | F4: Year 4 | G4: Year 5
A5: Revenue | B5: =Assumptions!$B$20 | C5: =B5*(1+Assumptions!C$6) | D5: =C5*(1+Assumptions!D$6) | E5: =D5*(1+Assumptions!E$6) | F5: =E5*(1+Assumptions!F$6) | G5: =F5*(1+Assumptions!G$6)
A6: Cost of goods sold | B6: =-B5*(1-Assumptions!$B$7) | C6: =-C5*(1-Assumptions!C$7) | D6: =-D5*(1-Assumptions!D$7) | E6: =-E5*(1-Assumptions!E$7) | F6: =-F5*(1-Assumptions!F$7) | G6: =-G5*(1-Assumptions!G$7)
A7: Gross profit | B7: =B5+B6 | C7: =C5+C6 | D7: =D5+D6 | E7: =E5+E6 | F7: =F5+F6 | G7: =G5+G6
A8: Operating expenses | B8: =-B5*Assumptions!$B$8 | C8: =-C5*Assumptions!C$8 | D8: =-D5*Assumptions!D$8 | E8: =-E5*Assumptions!E$8 | F8: =-F5*Assumptions!F$8 | G8: =-G5*Assumptions!G$8
A9: EBITDA | B9: =B7+B8 | C9: =C7+C8 | D9: =D7+D8 | E9: =E7+E8 | F9: =F7+F8 | G9: =G7+G8
A10: Depreciation & amortisation | B10: =-Assumptions!$B$24*Assumptions!$B$9 | C10: =-'Balance Sheet'!B10*Assumptions!C$9 | D10: =-'Balance Sheet'!C10*Assumptions!D$9 | E10: =-'Balance Sheet'!D10*Assumptions!E$9 | F10: =-'Balance Sheet'!E10*Assumptions!F$9 | G10: =-'Balance Sheet'!F10*Assumptions!G$9
A11: EBIT (operating profit) | B11: =B9+B10 | C11: =C9+C10 | D11: =D9+D10 | E11: =E9+E10 | F11: =F9+F10 | G11: =G9+G10
A12: Interest expense | B12: =-Assumptions!$B$26*Assumptions!$B$11 | C12: =-'Balance Sheet'!B16*Assumptions!C$11 | D12: =-'Balance Sheet'!C16*Assumptions!D$11 | E12: =-'Balance Sheet'!D16*Assumptions!E$11 | F12: =-'Balance Sheet'!E16*Assumptions!F$11 | G12: =-'Balance Sheet'!F16*Assumptions!G$11
A13: Profit before tax | B13: =B11+B12 | C13: =C11+C12 | D13: =D11+D12 | E13: =E11+E12 | F13: =F11+F12 | G13: =G11+G12
A14: Income tax | B14: =-MAX(0,B13)*Assumptions!$B$12 | C14: =-MAX(0,C13)*Assumptions!C$12 | D14: =-MAX(0,D13)*Assumptions!D$12 | E14: =-MAX(0,E13)*Assumptions!E$12 | F14: =-MAX(0,F13)*Assumptions!F$12 | G14: =-MAX(0,G13)*Assumptions!G$12
A15: NET INCOME | B15: =B13+B14 | C15: =C13+C14 | D15: =D13+D14 | E15: =E13+E14 | F15: =F13+F14 | G15: =G13+G14
A17: Dividends declared | B17: =0 | C17: =-C15*Assumptions!C$13 | D17: =-D15*Assumptions!D$13 | E17: =-E15*Assumptions!E$13 | F17: =-F15*Assumptions!F$13 | G17: =-G15*Assumptions!G$13
A19: Gross margin % | B19: =IFERROR(B7/B5,0) | C19: =IFERROR(C7/C5,0) | D19: =IFERROR(D7/D5,0) | E19: =IFERROR(E7/E5,0) | F19: =IFERROR(F7/F5,0) | G19: =IFERROR(G7/G5,0)
A20: EBITDA margin % | B20: =IFERROR(B9/B5,0) | C20: =IFERROR(C9/C5,0) | D20: =IFERROR(D9/D5,0) | E20: =IFERROR(E9/E5,0) | F20: =IFERROR(F9/F5,0) | G20: =IFERROR(G9/G5,0)
A21: Net margin % | B21: =IFERROR(B15/B5,0) | C21: =IFERROR(C15/C5,0) | D21: =IFERROR(D15/D5,0) | E21: =IFERROR(E15/E5,0) | F21: =IFERROR(F15/F5,0) | G21: =IFERROR(G15/G5,0)

Sheet Balance Sheet
A1: Balance Sheet
A2: Working capital is driven by DSO, DIO and DPO. Cash comes from the cash flow.
A4: Line item | B4: Year 0 (actual) | C4: Year 1 | D4: Year 2 | E4: Year 3 | F4: Year 4 | G4: Year 5
A5: ASSETS
A6: Cash | B6: =Assumptions!$B$21 | C6: =B6+'Cash Flow'!C18 | D6: =C6+'Cash Flow'!D18 | E6: =D6+'Cash Flow'!E18 | F6: =E6+'Cash Flow'!F18 | G6: =F6+'Cash Flow'!G18
A7: Accounts receivable | B7: =Assumptions!$B$22 | C7: ='Income Statement'!C5/365*Assumptions!C$14 | D7: ='Income Statement'!D5/365*Assumptions!D$14 | E7: ='Income Statement'!E5/365*Assumptions!E$14 | F7: ='Income Statement'!F5/365*Assumptions!F$14 | G7: ='Income Statement'!G5/365*Assumptions!G$14
A8: Inventory | B8: =Assumptions!$B$23 | C8: =-'Income Statement'!C6/365*Assumptions!C$15 | D8: =-'Income Statement'!D6/365*Assumptions!D$15 | E8: =-'Income Statement'!E6/365*Assumptions!E$15 | F8: =-'Income Statement'!F6/365*Assumptions!F$15 | G8: =-'Income Statement'!G6/365*Assumptions!G$15
A9: Total current assets | B9: =SUM(B6:B8) | C9: =SUM(C6:C8) | D9: =SUM(D6:D8) | E9: =SUM(E6:E8) | F9: =SUM(F6:F8) | G9: =SUM(G6:G8)
A10: Property, plant & equipment (net) | B10: =Assumptions!$B$24 | C10: =B10+'Cash Flow'!C12*-1+'Income Statement'!C10 | D10: =C10+'Cash Flow'!D12*-1+'Income Statement'!D10 | E10: =D10+'Cash Flow'!E12*-1+'Income Statement'!E10 | F10: =E10+'Cash Flow'!F12*-1+'Income Statement'!F10 | G10: =F10+'Cash Flow'!G12*-1+'Income Statement'!G10
A11: TOTAL ASSETS | B11: =B9+B10 | C11: =C9+C10 | D11: =D9+D10 | E11: =E9+E10 | F11: =F9+F10 | G11: =G9+G10
A13: LIABILITIES & EQUITY
A14: Accounts payable | B14: =Assumptions!$B$25 | C14: =-'Income Statement'!C6/365*Assumptions!C$16 | D14: =-'Income Statement'!D6/365*Assumptions!D$16 | E14: =-'Income Statement'!E6/365*Assumptions!E$16 | F14: =-'Income Statement'!F6/365*Assumptions!F$16 | G14: =-'Income Statement'!G6/365*Assumptions!G$16
A15: Total current liabilities | B15: =B14 | C15: =C14 | D15: =D14 | E15: =E14 | F15: =F14 | G15: =G14
A16: Long-term debt | B16: =Assumptions!$B$26 | C16: =B16+Assumptions!C$17 | D16: =C16+Assumptions!D$17 | E16: =D16+Assumptions!E$17 | F16: =E16+Assumptions!F$17 | G16: =F16+Assumptions!G$17
A17: Total liabilities | B17: =B15+B16 | C17: =C15+C16 | D17: =D15+D16 | E17: =E15+E16 | F17: =F15+F16 | G17: =G15+G16
A18: Share capital | B18: =Assumptions!$B$27 | C18: =B18 | D18: =C18 | E18: =D18 | F18: =E18 | G18: =F18
A19: Retained earnings | B19: =Assumptions!$B$28 | C19: =B19+'Income Statement'!C15+'Income Statement'!C17 | D19: =C19+'Income Statement'!D15+'Income Statement'!D17 | E19: =D19+'Income Statement'!E15+'Income Statement'!E17 | F19: =E19+'Income Statement'!F15+'Income Statement'!F17 | G19: =F19+'Income Statement'!G15+'Income Statement'!G17
A20: Total equity | B20: =B18+B19 | C20: =C18+C19 | D20: =D18+D19 | E20: =E18+E19 | F20: =F18+F19 | G20: =G18+G19
A21: TOTAL LIABILITIES & EQUITY | B21: =B17+B20 | C21: =C17+C20 | D21: =D17+D20 | E21: =E17+E20 | F21: =F17+F20 | G21: =G17+G20
A23: CHECK — assets less liabilities & equity | B23: =ROUND(B11-B21,2) | C23: =ROUND(C11-C21,2) | D23: =ROUND(D11-D21,2) | E23: =ROUND(E11-E21,2) | F23: =ROUND(F11-F21,2) | G23: =ROUND(G11-G21,2)
A24: Status | B24: =IF(ABS(B23)<0.5,"BALANCED ✓","⚠ OUT") | C24: =IF(ABS(C23)<0.5,"BALANCED ✓","⚠ OUT") | D24: =IF(ABS(D23)<0.5,"BALANCED ✓","⚠ OUT") | E24: =IF(ABS(E23)<0.5,"BALANCED ✓","⚠ OUT") | F24: =IF(ABS(F23)<0.5,"BALANCED ✓","⚠ OUT") | G24: =IF(ABS(G23)<0.5,"BALANCED ✓","⚠ OUT")

Sheet Cash Flow
A1: Cash Flow Statement
A2: Indirect method. Ties back to the cash line on the balance sheet.
A4: Line item | B4: Year 0 (actual) | C4: Year 1 | D4: Year 2 | E4: Year 3 | F4: Year 4 | G4: Year 5
A5: OPERATING
A6: Net income | C6: ='Income Statement'!C15 | D6: ='Income Statement'!D15 | E6: ='Income Statement'!E15 | F6: ='Income Statement'!F15 | G6: ='Income Statement'!G15
A7: Add back depreciation & amortisation | C7: =-'Income Statement'!C10 | D7: =-'Income Statement'!D10 | E7: =-'Income Statement'!E10 | F7: =-'Income Statement'!F10 | G7: =-'Income Statement'!G10
A8: (Increase) / decrease in receivables | C8: ='Balance Sheet'!B7-'Balance Sheet'!C7 | D8: ='Balance Sheet'!C7-'Balance Sheet'!D7 | E8: ='Balance Sheet'!D7-'Balance Sheet'!E7 | F8: ='Balance Sheet'!E7-'Balance Sheet'!F7 | G8: ='Balance Sheet'!F7-'Balance Sheet'!G7
A9: (Increase) / decrease in inventory | C9: ='Balance Sheet'!B8-'Balance Sheet'!C8 | D9: ='Balance Sheet'!C8-'Balance Sheet'!D8 | E9: ='Balance Sheet'!D8-'Balance Sheet'!E8 | F9: ='Balance Sheet'!E8-'Balance Sheet'!F8 | G9: ='Balance Sheet'!F8-'Balance Sheet'!G8
A10: Increase / (decrease) in payables | C10: ='Balance Sheet'!C14-'Balance Sheet'!B14 | D10: ='Balance Sheet'!D14-'Balance Sheet'!C14 | E10: ='Balance Sheet'!E14-'Balance Sheet'!D14 | F10: ='Balance Sheet'!F14-'Balance Sheet'!E14 | G10: ='Balance Sheet'!G14-'Balance Sheet'!F14
A11: Cash from operations | C11: =SUM(C6:C10) | D11: =SUM(D6:D10) | E11: =SUM(E6:E10) | F11: =SUM(F6:F10) | G11: =SUM(G6:G10)
A12: Capital expenditure | C12: =-'Income Statement'!C5*Assumptions!C$10 | D12: =-'Income Statement'!D5*Assumptions!D$10 | E12: =-'Income Statement'!E5*Assumptions!E$10 | F12: =-'Income Statement'!F5*Assumptions!F$10 | G12: =-'Income Statement'!G5*Assumptions!G$10
A13: Cash used in investing | C13: =C12 | D13: =D12 | E13: =E12 | F13: =F12 | G13: =G12
A15: Debt drawn / (repaid) | C15: =Assumptions!C$17 | D15: =Assumptions!D$17 | E15: =Assumptions!E$17 | F15: =Assumptions!F$17 | G15: =Assumptions!G$17
A16: Dividends paid | C16: ='Income Statement'!C17 | D16: ='Income Statement'!D17 | E16: ='Income Statement'!E17 | F16: ='Income Statement'!F17 | G16: ='Income Statement'!G17
A17: Cash from financing | C17: =C15+C16 | D17: =D15+D16 | E17: =E15+E16 | F17: =F15+F16 | G17: =G15+G16
A18: NET CHANGE IN CASH | C18: =C11+C13+C17 | D18: =D11+D13+D17 | E18: =E11+E13+E17 | F18: =F11+F13+F17 | G18: =G11+G13+G17
A19: Opening cash | C19: ='Balance Sheet'!B6 | D19: ='Balance Sheet'!C6 | E19: ='Balance Sheet'!D6 | F19: ='Balance Sheet'!E6 | G19: ='Balance Sheet'!F6
A20: CLOSING CASH | C20: =C19+C18 | D20: =D19+D18 | E20: =E19+E18 | F20: =F19+F18 | G20: =G19+G18
A22: Free cash flow (operations less capex) | C22: =C11+C12 | D22: =D11+D12 | E22: =E11+E12 | F22: =F11+F12 | G22: =G11+G12

Sheet Ratios & Dashboard
A1: Ratios & Dashboard
A2: The numbers a credit officer or investor asks for first.
A4: Line item | B4: Year 0 (actual) | C4: Year 1 | D4: Year 2 | E4: Year 3 | F4: Year 4 | G4: Year 5
A5: Revenue growth | B5: — | C5: =IFERROR('Income Statement'!C5/'Income Statement'!B5-1,0) | D5: =IFERROR('Income Statement'!D5/'Income Statement'!C5-1,0) | E5: =IFERROR('Income Statement'!E5/'Income Statement'!D5-1,0) | F5: =IFERROR('Income Statement'!F5/'Income Statement'!E5-1,0) | G5: =IFERROR('Income Statement'!G5/'Income Statement'!F5-1,0)
A6: Gross margin | B6: — | C6: =IFERROR('Income Statement'!C7/'Income Statement'!C5,0) | D6: =IFERROR('Income Statement'!D7/'Income Statement'!D5,0) | E6: =IFERROR('Income Statement'!E7/'Income Statement'!E5,0) | F6: =IFERROR('Income Statement'!F7/'Income Statement'!F5,0) | G6: =IFERROR('Income Statement'!G7/'Income Statement'!G5,0)
A7: EBITDA margin | B7: — | C7: =IFERROR('Income Statement'!C9/'Income Statement'!C5,0) | D7: =IFERROR('Income Statement'!D9/'Income Statement'!D5,0) | E7: =IFERROR('Income Statement'!E9/'Income Statement'!E5,0) | F7: =IFERROR('Income Statement'!F9/'Income Statement'!F5,0) | G7: =IFERROR('Income Statement'!G9/'Income Statement'!G5,0)
A8: Net margin | B8: — | C8: =IFERROR('Income Statement'!C15/'Income Statement'!C5,0) | D8: =IFERROR('Income Statement'!D15/'Income Statement'!D5,0) | E8: =IFERROR('Income Statement'!E15/'Income Statement'!E5,0) | F8: =IFERROR('Income Statement'!F15/'Income Statement'!F5,0) | G8: =IFERROR('Income Statement'!G15/'Income Statement'!G5,0)
A9: Current ratio | B9: — | C9: =IFERROR('Balance Sheet'!C9/'Balance Sheet'!C15,0) | D9: =IFERROR('Balance Sheet'!D9/'Balance Sheet'!D15,0) | E9: =IFERROR('Balance Sheet'!E9/'Balance Sheet'!E15,0) | F9: =IFERROR('Balance Sheet'!F9/'Balance Sheet'!F15,0) | G9: =IFERROR('Balance Sheet'!G9/'Balance Sheet'!G15,0)
A10: Quick ratio | B10: — | C10: =IFERROR(('Balance Sheet'!C6+'Balance Sheet'!C7)/'Balance Sheet'!C15,0) | D10: =IFERROR(('Balance Sheet'!D6+'Balance Sheet'!D7)/'Balance Sheet'!D15,0) | E10: =IFERROR(('Balance Sheet'!E6+'Balance Sheet'!E7)/'Balance Sheet'!E15,0) | F10: =IFERROR(('Balance Sheet'!F6+'Balance Sheet'!F7)/'Balance Sheet'!F15,0) | G10: =IFERROR(('Balance Sheet'!G6+'Balance Sheet'!G7)/'Balance Sheet'!G15,0)
A11: Debt / equity | B11: — | C11: =IFERROR('Balance Sheet'!C16/'Balance Sheet'!C20,0) | D11: =IFERROR('Balance Sheet'!D16/'Balance Sheet'!D20,0) | E11: =IFERROR('Balance Sheet'!E16/'Balance Sheet'!E20,0) | F11: =IFERROR('Balance Sheet'!F16/'Balance Sheet'!F20,0) | G11: =IFERROR('Balance Sheet'!G16/'Balance Sheet'!G20,0)
A12: Debt / EBITDA | B12: — | C12: =IFERROR('Balance Sheet'!C16/'Income Statement'!C9,0) | D12: =IFERROR('Balance Sheet'!D16/'Income Statement'!D9,0) | E12: =IFERROR('Balance Sheet'!E16/'Income Statement'!E9,0) | F12: =IFERROR('Balance Sheet'!F16/'Income Statement'!F9,0) | G12: =IFERROR('Balance Sheet'!G16/'Income Statement'!G9,0)
A13: Interest coverage (EBIT / interest) | B13: — | C13: =IFERROR('Income Statement'!C11/-'Income Statement'!C12,0) | D13: =IFERROR('Income Statement'!D11/-'Income Statement'!D12,0) | E13: =IFERROR('Income Statement'!E11/-'Income Statement'!E12,0) | F13: =IFERROR('Income Statement'!F11/-'Income Statement'!F12,0) | G13: =IFERROR('Income Statement'!G11/-'Income Statement'!G12,0)
A14: Return on equity | B14: — | C14: =IFERROR('Income Statement'!C15/'Balance Sheet'!C20,0) | D14: =IFERROR('Income Statement'!D15/'Balance Sheet'!D20,0) | E14: =IFERROR('Income Statement'!E15/'Balance Sheet'!E20,0) | F14: =IFERROR('Income Statement'!F15/'Balance Sheet'!F20,0) | G14: =IFERROR('Income Statement'!G15/'Balance Sheet'!G20,0)
A15: Return on assets | B15: — | C15: =IFERROR('Income Statement'!C15/'Balance Sheet'!C11,0) | D15: =IFERROR('Income Statement'!D15/'Balance Sheet'!D11,0) | E15: =IFERROR('Income Statement'!E15/'Balance Sheet'!E11,0) | F15: =IFERROR('Income Statement'!F15/'Balance Sheet'!F11,0) | G15: =IFERROR('Income Statement'!G15/'Balance Sheet'!G11,0)
A16: Cash conversion cycle (days) | B16: — | C16: =Assumptions!C$14+Assumptions!C$15-Assumptions!C$16 | D16: =Assumptions!D$14+Assumptions!D$15-Assumptions!D$16 | E16: =Assumptions!E$14+Assumptions!E$15-Assumptions!E$16 | F16: =Assumptions!F$14+Assumptions!F$15-Assumptions!F$16 | G16: =Assumptions!G$14+Assumptions!G$15-Assumptions!G$16
A17: Free cash flow | B17: — | C17: ='Cash Flow'!C22 | D17: ='Cash Flow'!D22 | E17: ='Cash Flow'!E22 | F17: ='Cash Flow'!F22 | G17: ='Cash Flow'!G22
A19: MODEL INTEGRITY
A20: Balance sheet check | C20: ='Balance Sheet'!C24 | D20: ='Balance Sheet'!D24 | E20: ='Balance Sheet'!E24 | F20: ='Balance Sheet'!F24 | G20: ='Balance Sheet'!G24
A21: Cash flow ties to balance sheet | C21: =IF(ABS('Cash Flow'!C20-'Balance Sheet'!C6)<0.5,"TIES ✓","⚠ OUT") | D21: =IF(ABS('Cash Flow'!D20-'Balance Sheet'!D6)<0.5,"TIES ✓","⚠ OUT") | E21: =IF(ABS('Cash Flow'!E20-'Balance Sheet'!E6)<0.5,"TIES ✓","⚠ OUT") | F21: =IF(ABS('Cash Flow'!F20-'Balance Sheet'!F6)<0.5,"TIES ✓","⚠ OUT") | G21: =IF(ABS('Cash Flow'!G20-'Balance Sheet'!G6)<0.5,"TIES ✓","⚠ OUT")
